Workbook

Sheet CONF 
D2: 2
A3: Titular da Reserva:
A4: Data | B4: Passeio | C4: Valor em Pesos Colombianos P/P | D4: Valor Total em Pesos Colombianos TOTAL
A5: 45781 | B5: Aluguel De Moto Elétrica 2 Pessoas | C5: =VLOOKUP(B5,'TARIFAS '!$A$3:$N$239,2,FALSE) -> 180000 | D5: =+C5*$D$2 -> 360000
A6: 45782 | B6: City Tour Panoramico + Catedral de Sal Regular | C6: =VLOOKUP(B6,'TARIFAS '!$A$3:$N$239,2,FALSE) -> 350000 | D6: =+C6*$D$2 -> 700000
A7: 45784 | B7: Bora Bora Bc | C7: =VLOOKUP(B7,'TARIFAS '!$A$3:$N$239,2,FALSE) -> 390000 | D7: =+C7*$D$2 -> 780000
A8: 45785 | B8: Walking Tour + Castillo San Felipe 09:00 1PAX | C8: =VLOOKUP(B8,'TARIFAS '!$A$3:$N$239,2,FALSE) -> 500000 | D8: =+C8*$D$2 -> 1000000
A9: 45786 | B9: Isla Palma | C9: =VLOOKUP(B9,'TARIFAS '!$A$3:$N$239,2,FALSE) -> 530000 | D9: =+C9*$D$2 -> 1060000
A10: 45611 | B10: PAU´E | C10: =VLOOKUP(B10,'TARIFAS '!$A$3:$N$239,2,FALSE) -> 450000 | D10: =+C10*$D$2 -> 900000
A11: 45612 | B11: Bonavida | C11: =VLOOKUP(B11,'TARIFAS '!$A$3:$N$239,2,FALSE) -> 440000 | D11: =+C11*$D$2 -> 880000
A12: 45613 | B12: Bora Bora Vip | C12: =VLOOKUP(B12,'TARIFAS '!$A$3:$N$239,2,FALSE) -> 490000 | D12: =+C12*$D$2 -> 980000
A13: 45614 | B13: Tour en lancha privativa JOE 2024 | C13: =VLOOKUP(B13,'TARIFAS '!$A$3:$N$239,2,FALSE) -> 3700000 | D13: =+C13*$D$2 -> 7400000
A14: 45615 | B14: City Tour + Catedral de Sal Privativo | C14: =VLOOKUP(B14,'TARIFAS '!$A$3:$N$239,2,FALSE) -> 1700000 | D14: =+C14*$D$2 -> 3400000
A15: 45616 | B15: Aluguel De Moto Elétrica 2 Pessoas | C15: =VLOOKUP(B15,'TARIFAS '!$A$3:$N$239,2,FALSE) -> 180000 | D15: =+C15*$D$2 -> 360000
A16: 45617 | B16: City Tour + Catedral de Sal Privativo | C16: =VLOOKUP(B16,'TARIFAS '!$A$3:$N$239,2,FALSE) -> 1700000 | D16: =+C16*$D$2 -> 3400000
... A20: 45621 | B20: PAU´E | C20: =VLOOKUP(B20,'TARIFAS '!$A$3:$N$239,2,FALSE) -> 450000 | D20: =+C20*$D$2 -> 900000
B21: PAU´E | C21: =VLOOKUP(B21,'TARIFAS '!$A$3:$N$239,2,FALSE) -> 450000 | D21: =+C21*$D$2 -> 900000
A22: Valor Total | D22: =SUM(D5:D21) -> 41220000
A23: Desconto | D23: 0 | E23: (*)
A24: Valor Total com Desconto | D24: =+D22-D23 -> 41220000 | E24: (*)
A25: Valor da Entrada | D25: =SUM(Datos!C4:C20)-D23 -> 13880000 | E25: (*)
A26: Valor Saldo | D26: =SUM(Datos!E4:E20) -> 21340000 | E26: (**)
A28: =+D2 -> 2 | C28: =+D25 -> 13880000
A30: ENTRADA : | B30: =+D25 -> 13880000 | C30: no cambio dia | D30: 2222.455
C31: =+TODAY() -> 46067
A32: Dados para depósito Juliana Rotta 3 / Banco Inter Pix CNPJ: 14.909.728.0001/45 Pagamento da entrada e envio do comprovante.
A37: OBS:
A43: Data | B43: Passeio | D43: Valor Saldo
D44: =D2 -> 2
A45: =+A5 -> 45781 | B45: =+B5 -> Aluguel De Moto Elétrica 2 Pessoas | D45: =+Datos!E4 -> 160000
A46: =+A6 -> 45782 | B46: =+B6 -> City Tour Panoramico + Catedral de Sal Regular | D46: =+Datos!E5 -> 0
A47: =+A7 -> 45784 | B47: =+B7 -> Bora Bora Bc | D47: =+Datos!E6 -> 560000
A48: =+A8 -> 45785 | B48: =+B8 -> Walking Tour + Castillo San Felipe 09:00 1PAX | D48: =+Datos!E7 -> 1000000
A49: =+A9 -> 45786 | B49: =+B9 -> Isla Palma | D49: =+Datos!E8 -> 700000
A50: =+A10 -> 45611 | B50: =+B10 -> PAU´E | D50: =+Datos!E9 -> 700000
A51: =+A11 -> 45612 | B51: =+B11 -> Bonavida | D51: =+Datos!E10 -> 740000
A52: =+A12 -> 45613 | B52: =+B12 -> Bora Bora Vip | D52: =+Datos!E11 -> 740000
A53: =+A13 -> 45614 | B53: =+B13 -> Tour en lancha privativa JOE 2024 | D53: =+Datos!E12 -> 2700000
A54: =+A14 -> 45615 | B54: =+B14 -> City Tour + Catedral de Sal Privativo | D54: =+Datos!E13 -> 2360000
A55: =+A15 -> 45616 | B55: =+B15 -> Aluguel De Moto Elétrica 2 Pessoas | D55: =+Datos!E14 -> 160000
A56: =+A16 -> 45617 | B56: =+B16 -> City Tour + Catedral de Sal Privativo | D56: =+Datos!E15 -> 2360000
... A61: =+A21 -> 0 | B61: =+B21 -> PAU´E | D61: =+Datos!E20 -> 700000
C62: Valor do saldo | D62: =SUM(D45:D61) -> 21340000

Sheet Voucher
B5: Voucher The Experience Travel
B9: Titular da Reserva: | D9: ='CONF '!$B$3 -> 0
B11: =+'CONF '!$D$2 -> 2
B13: Data: | C13: =+'CONF '!A5 -> 45781 | F13: Hora: | G13: =+VLOOKUP(C15,'TARIFAS '!$A$3:$O$239,10,FALSE) -> 0
B15: Tour: | C15: =+'CONF '!B5 -> Aluguel De Moto Elétrica 2 Pessoas | I15: Valor a pagar: | J15: =+'CONF '!D45 -> 160000
B17: Local: | C17: =+VLOOKUP(C15,'TARIFAS '!$A$3:$N$239,7,FALSE) -> Apresentar-se na Cidade Amuralhada, Calle 2a de Badillo 36 – 54 - 58 P 1 emabixo do hostal Badillo Diagonal ao Restaurante La Vitrola | I17: =+VLOOKUP(C15,'TARIFAS '!$A$3:$O$239,8,FALSE)*B11 -> 0
I18: =+VLOOKUP(C15,'TARIFAS '!$A$3:$O$239,9,FALSE) -> 0
B24: (+55) 11 981758504
B30: Voucher The Experience Travel
B34: Titular da Reserva: | D34: ='CONF '!$B$3 -> 0
B36: =+'CONF '!$D$2 -> 2
B38: Data: | C38: =+'CONF '!A6 -> 45782 | F38: Hora: | G38: =+VLOOKUP(C40,'TARIFAS '!$A$3:$O$239,10,FALSE) -> 08:55
B40: Tour: | C40: =+'CONF '!B6 -> City Tour Panoramico + Catedral de Sal Regular | I40: Valor a pagar: | J40: =+'CONF '!D46 -> 0
B42: Local: | C42: =+VLOOKUP(C40,'TARIFAS '!$A$3:$N$239,7,FALSE) -> Apresentar-se na Carrera 11A # 93A - 10 em frente do Cafe Juan Valdez | I42: =+VLOOKUP(C40,'TARIFAS '!$A$3:$O$239,8,FALSE)*B36 -> 0
I43: =+VLOOKUP(C40,'TARIFAS '!$A$3:$O$239,9,FALSE) -> 0
B49: (+55) 11 981758504
B55: Voucher The Experience Travel
B59: Titular da Reserva: | D59: ='CONF '!$B$3 -> 0
B61: =+'CONF '!$D$2 -> 2
B63: Data: | C63: =+'CONF '!A7 -> 45784 | F63: Hora: | G63: =+VLOOKUP(C65,'TARIFAS '!$A$3:$O$239,10,FALSE) -> 07:20
B65: Tour: | C65: =+'CONF '!B7 -> Bora Bora Bc | I65: Valor a pagar: | J65: =+'CONF '!D47 -> 560000
B67: Local: | C67: =+VLOOKUP(C65,'TARIFAS '!$A$3:$N$239,7,FALSE) -> Apresentar-se na porta 03 da Marina la Bodeguita. | I67: =+VLOOKUP(C65,'TARIFAS '!$A$3:$O$239,8,FALSE)*B61 -> 68000
I68: =+VLOOKUP(C65,'TARIFAS '!$A$3:$O$239,9,FALSE) -> Pagar a taxas portuárias COP 29.000 + Seguro COP 5.000 (valor por pessoa – somente em dinheiro. Valor sujeito a alterações)
B74: (+55) 11 981758504
B80: Voucher The Experience Travel
B84: Titular da Reserva: | D84: ='CONF '!$B$3 -> 0
B86: =+'CONF '!$D$2 -> 2
B88: Data: | C88: =+'CONF '!A8 -> 45785 | F88: Hora: | G88: =+VLOOKUP(C90,'TARIFAS '!$A$3:$O$239,10,FALSE) -> 09:00
B90: Tour: | C90: =+'CONF '!B8 -> Walking Tour + Castillo San Felipe 09:00 1PAX | I90: Valor a pagar: | J90: =+'CONF '!D48 -> 1000000
B92: Local: | C92: =+VLOOKUP(C90,'TARIFAS '!$A$3:$N$239,7,FALSE) -> Apresentar-se na recepção do hotel | I92: =+VLOOKUP(C90,'TARIFAS '!$A$3:$O$239,8,FALSE)*B86 -> 0
I93: =+VLOOKUP(C90,'TARIFAS '!$A$3:$O$239,9,FALSE) -> 0
B99: (+55) 11 981758504
B105: Voucher The Experience Travel
B109: Titular da Reserva: | D109: ='CONF '!$B$3 -> 0
B111: =+'CONF '!$D$2 -> 2
B113: Data: | C113: =+'CONF '!A9 -> 45786 | F113: Hora: | G113: =+VLOOKUP(C115,'TARIFAS '!$A$3:$O$239,10,FALSE) -> 05:45
B115: Tour: | C115: =+'CONF '!B9 -> Isla Palma | I115: Valor a pagar: | J115: =+'CONF '!D49 -> 700000
B117: Local: | C117: =+VLOOKUP(C115,'TARIFAS '!$A$3:$N$239,7,FALSE) -> Apresentar-se na porta 02 da Marina la Bodeguita, onde a pessoa responsável pelo embarque e dará o suporte no embarque. | I117: =+VLOOKUP(C115,'TARIFAS '!$A$3:$O$239,8,FALSE)*B111 -> 58000
I118: =+VLOOKUP(C115,'TARIFAS '!$A$3:$O$239,9,FALSE) -> Pagar a taxas portuárias COP 29.000 (valor por pessoa– somente em dinheiro) na van para entrar na Marina.
B124: (+55) 11 981758504
B130: Voucher The Experience Travel
B134: Titular da Reserva: | D134: ='CONF '!$B$3 -> 0
B136: =+'CONF '!$D$2 -> 2
B138: Data: | C138: =+'CONF '!A10 -> 45611 | F138: Hora: | G138: =+VLOOKUP(C140,'TARIFAS '!$A$3:$O$239,10,FALSE) -> 07:30
B140: Tour: | C140: =+'CONF '!B10 -> PAU´E | I140: Valor a pagar: | J140: =+'CONF '!D50 -> 700000
B142: Local: | C142: =+VLOOKUP(C140,'TARIFAS '!$A$3:$N$239,7,FALSE) -> Apresentar-se na porta 04 da Marina la Bodeguita. | I142: =+VLOOKUP(C140,'TARIFAS '!$A$3:$O$239,8,FALSE)*B136 -> 69000
I143: =+VLOOKUP(C140,'TARIFAS '!$A$3:$O$239,9,FALSE) -> Pagar a taxas portuárias COP 29.000 + Seguro COP 5.500 (valor por pessoa – somente em dinheiro. Valor sujeito a alterações)
B149: (+55) 11 981758504
B155: Voucher The Experience Travel
B159: Titular da Reserva: | D159: ='CONF '!$B$3 -> 0
B161: =+'CONF '!$D$2 -> 2
B163: Data: | C163: =+'CONF '!A11 -> 45612 | F163: Hora: | G163: =+VLOOKUP(C165,'TARIFAS '!$A$3:$O$239,10,FALSE) -> 08:30
B165: Tour: | C165: =+'CONF '!B11 -> Bonavida | I165: Valor a pagar: | J165: =+'CONF '!D51 -> 740000
B167: Local: | C167: =+VLOOKUP(C165,'TARIFAS '!$A$3:$N$239,7,FALSE) -> Apresentar-se na Marina La Bodeguita porta 3 onde o catamarã Bona Vida estará ancorado. A tripulação dará toda assistência no embarque. Retorno para a Marina Los Pegasos às 16:00. | I167: =+VLOOKUP(C165,'TARIFAS '!$A$3:$O$239,8,FALSE)*B161 -> 53000
I168: =+VLOOKUP(C165,'TARIFAS '!$A$3:$O$239,9,FALSE) -> Pagar a taxas portuárias COP 26.500 (valor por pessoa – somente em dinheiro. Valor sujeito a alterações)
B174: (+55) 11 981758504
B180: Voucher The Experience Travel
B184: Titular da Reserva: | D184: ='CONF '!$B$3 -> 0
B186: =+'CONF '!$D$2 -> 2
B188: Data: | C188: =+'CONF '!A12 -> 45613 | F188: Hora: | G188: =+VLOOKUP(C190,'TARIFAS '!$A$3:$O$239,10,FALSE) -> 07:20
B190: Tour: | C190: =+'CONF '!B12 -> Bora Bora Vip | I190: Valor a pagar: | J190: =+'CONF '!D52 -> 740000
B192: Local: | C192: =+VLOOKUP(C190,'TARIFAS '!$A$3:$N$239,7,FALSE) -> Apresentar-se na porta 03 da Marina la Bodeguita. | I192: =+VLOOKUP(C190,'TARIFAS '!$A$3:$O$239,8,FALSE)*B186 -> 68000
I193: =+VLOOKUP(C190,'TARIFAS '!$A$3:$O$239,9,FALSE) -> Pagar a taxas portuárias COP 29.000 + Seguro COP 5.000 (valor por pessoa – somente em dinheiro. Valor sujeito a alterações)
B199: (+55) 11 981758504
B205: Voucher The Experience Travel
B209: Titular da Reserva: | D209: ='CONF '!$B$3 -> 0
B211: =+'CONF '!$D$2 -> 2
B213: Data: | C213: =+'CONF '!A13 -> 45614 | F213: Hora: | G213: =+VLOOKUP(C215,'TARIFAS '!$A$3:$O$239,10,FALSE) -> 0
B215: Tour: | C215: =+'CONF '!B13 -> Tour en lancha privativa JOE 2024 | I215: Valor a pagar: | J215: =+'CONF '!D53 -> 2700000
B217: Local: | C217: =+VLOOKUP(C215,'TARIFAS '!$A$3:$N$239,7,FALSE) -> 0 | I217: =+VLOOKUP(C215,'TARIFAS '!$A$3:$O$239,8,FALSE)*B211 -> 0
I218: =+VLOOKUP(C215,'TARIFAS '!$A$3:$O$239,9,FALSE) -> 0
B224: (+55) 11 981758504
B230: Voucher The Experience Travel
B234: Titular da Reserva: | D234: ='CONF '!$B$3 -> 0
B236: =+'CONF '!$D$2 -> 2
B238: Data: | C238: =+'CONF '!A14 -> 45615 | F238: Hora: | G238: =+VLOOKUP(C240,'TARIFAS '!$A$3:$O$239,10,FALSE) -> 0
B240: Tour: | C240: =+'CONF '!B14 -> City Tour + Catedral de Sal Privativo | I240: Valor a pagar: | J240: =+'CONF '!D54 -> 2360000
B242: Local: | C242: =+VLOOKUP(C240,'TARIFAS '!$A$3:$N$239,7,FALSE) -> 0 | I242: =+VLOOKUP(C240,'TARIFAS '!$A$3:$O$239,8,FALSE)*B236 -> 0
I243: =+VLOOKUP(C240,'TARIFAS '!$A$3:$O$239,9,FALSE) -> 0
B249: (+55) 11 981758504
B255: Voucher The Experience Travel
B259: Titular da Reserva: | D259: ='CONF '!$B$3 -> 0
B261: =+'CONF '!$D$2 -> 2
B263: Data: | C263: =+'CONF '!A15 -> 45616 | F263: Hora: | G263: =+VLOOKUP(C265,'TARIFAS '!$A$3:$O$239,10,FALSE) -> 0
B265: Tour: | C265: =+'CONF '!B15 -> Aluguel De Moto Elétrica 2 Pessoas | I265: Valor a pagar: | J265: =+'CONF '!D55 -> 160000
B267: Local: | C267: =+VLOOKUP(C265,'TARIFAS '!$A$3:$N$239,7,FALSE) -> Apresentar-se na Cidade Amuralhada, Calle 2a de Badillo 36 – 54 - 58 P 1 emabixo do hostal Badillo Diagonal ao Restaurante La Vitrola | I267: =+VLOOKUP(C265,'TARIFAS '!$A$3:$O$239,8,FALSE)*B261 -> 0
I268: =+VLOOKUP(C265,'TARIFAS '!$A$3:$O$239,9,FALSE) -> 0
B274: (+55) 11 981758504
B280: Voucher The Experience Travel
B284: Titular da Reserva: | D284: ='CONF '!$B$3 -> 0
B286: =+'CONF '!$D$2 -> 2
B288: Data: | C288: =+'CONF '!A16 -> 45617 | F288: Hora: | G288: =+VLOOKUP(C290,'TARIFAS '!$A$3:$O$239,10,FALSE) -> 0
B290: Tour: | C290: =+'CONF '!B16 -> City Tour + Catedral de Sal Privativo | I290: Valor a pagar: | J290: =+'CONF '!D56 -> 2360000
B292: Local: | C292: =+VLOOKUP(C290,'TARIFAS '!$A$3:$N$239,7,FALSE) -> 0 | I292: =+VLOOKUP(C290,'TARIFAS '!$A$3:$O$239,8,FALSE)*B286 -> 0
I293: =+VLOOKUP(C290,'TARIFAS '!$A$3:$O$239,9,FALSE) -> 0
B299: (+55) 11 981758504
B305: Voucher The Experience Travel
B309: Titular da Reserva: | D309: ='CONF '!$B$3 -> 0
B311: =+'CONF '!$D$2 -> 2
B313: Data: | C313: =+'CONF '!A17 -> 45618 | F313: Hora: | G313: =+VLOOKUP(C315,'TARIFAS '!$A$3:$O$239,10,FALSE) -> 0
...

Sheet Voucher OLD
B5: Voucher The Experience Travel
B9: Titular da Reserva: | D9: Luis Domingo Blasini
B11: =+'CONF '!D2 -> 2
B13: Data: | C13: =+'CONF '!A5 -> 45781 | F13: Hora: | G13: 0.61458333
B15: Tour: | C15: =+'CONF '!B5 -> Aluguel De Moto Elétrica 2 Pessoas | I15: Valor a pagar: | J15: =+'CONF '!D45 -> 160000
B17: Local: | C17: =+VLOOKUP(O8,'TARIFAS '!$A$3:$N$239,7,FALSE) -> #N/A | I17: Valor taxas:
B22: (55) 11 981758504
F24: Data: | G24: =+'CONF '!A6 -> 45782
F26: Tour: | G26: =+'CONF '!B6 -> City Tour Panoramico + Catedral de Sal Regular
F28: Embarque: | G28: =+VLOOKUP(G26,'TARIFAS '!$A$3:$N$239,7,FALSE) -> Apresentar-se na Carrera 11A # 93A - 10 em frente do Cafe Juan Valdez
F32: Titular da Reserva: | G32: =+'CONF '!$B$3 -> 0
F33: Nº de pessoas: | G33: =+'CONF '!$D$2 -> 2
F35: Valor a pagar no passeio: | H35: =+'CONF '!D46 -> 0
F36: Valor taxas a pagar no passeio: | H36: =+VLOOKUP(G26,'TARIFAS '!$A$3:$O$239,8,FALSE)*G33 -> 0
F43: Data: | G43: =+'CONF '!A7 -> 45784
F45: Tour: | G45: =+'CONF '!B7 -> Bora Bora Bc
F47: Embarque: | G47: =+VLOOKUP(G45,'TARIFAS '!$A$3:$N$239,7,FALSE) -> Apresentar-se na porta 03 da Marina la Bodeguita.
F51: Titular da Reserva: | G51: =+'CONF '!$B$3 -> 0
F52: Nº de pessoas: | G52: =+'CONF '!$D$2 -> 2
F54: Valor a pagar no passeio: | H54: =+'CONF '!D47 -> 560000
F55: Valor taxas a pagar no passeio: | H55: =+VLOOKUP(G45,'TARIFAS '!$A$3:$O$239,8,FALSE)*G52 -> 68000
F62: Data: | G62: =+'CONF '!A8 -> 45785
F64: Tour: | G64: =+'CONF '!B8 -> Walking Tour + Castillo San Felipe 09:00 1PAX
F66: Embarque: | G66: =+VLOOKUP(G64,'TARIFAS '!$A$3:$N$239,7,FALSE) -> Apresentar-se na recepção do hotel
F70: Titular da Reserva: | G70: =+'CONF '!$B$3 -> 0
F71: Nº de pessoas: | G71: =+'CONF '!$D$2 -> 2
F73: Valor a pagar no passeio: | H73: =+'CONF '!D48 -> 1000000
F74: Valor taxas a pagar no passeio: | H74: =+VLOOKUP(G64,'TARIFAS '!$A$3:$O$239,8,FALSE)*G71 -> 0
F81: Data: | G81: =+'CONF '!A9 -> 45786
F83: Tour: | G83: =+'CONF '!B9 -> Isla Palma
F85: Embarque: | G85: =+VLOOKUP(G83,'TARIFAS '!$A$3:$N$239,7,FALSE) -> Apresentar-se na porta 02 da Marina la Bodeguita, onde a pessoa responsável pelo embarque e dará o suporte no embarque.
F89: Titular da Reserva: | G89: =+'CONF '!$B$3 -> 0
F90: Nº de pessoas: | G90: =+'CONF '!$D$2 -> 2
F92: Valor a pagar no passeio: | H92: =+'CONF '!D49 -> 700000
F93: Valor taxas a pagar no passeio: | H93: =+VLOOKUP(G83,'TARIFAS '!$A$3:$O$239,8,FALSE)*G90 -> 58000
F100: Data: | G100: =+'CONF '!A10 -> 45611
F102: Tour: | G102: =+'CONF '!B10 -> PAU´E
F104: Embarque: | G104: =+VLOOKUP(G102,'TARIFAS '!$A$3:$N$239,7,FALSE) -> Apresentar-se na porta 04 da Marina la Bodeguita.
F108: Titular da Reserva: | G108: =+'CONF '!$B$3 -> 0
F109: Nº de pessoas: | G109: =+'CONF '!$D$2 -> 2
F111: Valor a pagar no passeio: | H111: =+'CONF '!D56 -> 2360000
F112: Valor taxas a pagar no passeio: | H112: =+VLOOKUP(G102,'TARIFAS '!$A$3:$O$239,8,FALSE)*G109 -> 69000
F119: Data: | G119: =+'CONF '!A11 -> 45612
F121: Tour: | G121: =+'CONF '!B11 -> Bonavida
F123: Embarque: | G123: =+VLOOKUP(G121,'TARIFAS '!$A$3:$N$239,7,FALSE) -> Apresentar-se na Marina La Bodeguita porta 3 onde o catamarã Bona Vida estará ancorado. A tripulação dará toda assistência no embarque. Retorno para a Marina Los Pegasos às 16:00.
F127: Titular da Reserva: | G127: =+'CONF '!$B$3 -> 0
F128: Nº de pessoas: | G128: =+'CONF '!$D$2 -> 2
F130: Valor a pagar no passeio: | H130: =+'CONF '!D57 -> 2700000
F131: Valor taxas a pagar no passeio: | H131: =+VLOOKUP(G121,'TARIFAS '!$A$3:$O$239,8,FALSE)*G128 -> 53000
F138: Data: | G138: =+'CONF '!A12 -> 45613
F140: Tour: | G140: =+'CONF '!B12 -> Bora Bora Vip
F142: Embarque: | G142: =+VLOOKUP(G140,'TARIFAS '!$A$3:$N$239,7,FALSE) -> Apresentar-se na porta 03 da Marina la Bodeguita.
F146: Titular da Reserva: | G146: =+'CONF '!$B$3 -> 0
F147: Nº de pessoas: | G147: =+'CONF '!$D$2 -> 2
F149: Valor a pagar no passeio: | H149: =+'CONF '!D58 -> 2360000
F150: Valor taxas a pagar no passeio: | H150: =+VLOOKUP(G140,'TARIFAS '!$A$3:$O$239,8,FALSE)*G147 -> 68000
F157: Data: | G157: =+'CONF '!A13 -> 45614
F159: Tour: | G159: =+'CONF '!B13 -> Tour en lancha privativa JOE 2024
F161: Embarque: | G161: Apresentar-se na recepção de hotel as 05:30 para embarcar na porta 02 da Marina la Bodeguita as 5:50. Pagar a taxas portuárias COP 23.000 (valor por pessoa– somente em dinheiro. Valor sujeito a alterações) na porta 02 para entrar na Marina.
F165: Titular da Reserva: | G165: =+'CONF '!$B$3 -> 0
F166: Nº de pessoas: | G166: =+'CONF '!$D$2 -> 2
F168: Valor a pagar no passeio: | H168: =+'CONF '!D59 -> 2700000
F169: Valor taxas a pagar no passeio: | H169: =+VLOOKUP(G159,'TARIFAS '!$A$3:$O$239,8,FALSE)*G166 -> 0
F176: Data: | G176: =+'CONF '!A14 -> 45615
F178: Tour: | G178: =+'CONF '!B14 -> City Tour + Catedral de Sal Privativo
F180: Embarque: | G180: =+VLOOKUP(G178,'TARIFAS '!$A$3:$N$239,7,FALSE) -> 0
F184: Titular da Reserva: | G184: =+'CONF '!$B$3 -> 0
F185: Nº de pessoas: | G185: =+'CONF '!$D$2 -> 2
F187: Valor a pagar no passeio: | H187: =+'CONF '!D60 -> 700000
F188: Valor taxas a pagar no passeio: | H188: =+VLOOKUP(G178,'TARIFAS '!$A$3:$O$239,8,FALSE)*G185 -> 0

Sheet Datos
B3: Entrada PP | C3: Entrada TOT | D3: Saldo | E3: SaldoTOT
B4: =VLOOKUP('CONF '!B5,'TARIFAS '!$A$3:$N$239,4,FALSE) -> 100000 | C4: =+B4*'CONF '!$D$2 -> 200000 | D4: =VLOOKUP('CONF '!B5,'TARIFAS '!$A$3:$N$239,5,FALSE) -> 80000 | E4: =+D4*'CONF '!$D$2 -> 160000 | G4: =+B4+D4-'CONF '!C5 -> 0
B5: =VLOOKUP('CONF '!B6,'TARIFAS '!$A$3:$N$239,4,FALSE) -> 350000 | C5: =+B5*'CONF '!$D$2 -> 700000 | D5: =VLOOKUP('CONF '!B6,'TARIFAS '!$A$3:$N$239,5,FALSE) -> 0 | E5: =+D5*'CONF '!$D$2 -> 0 | G5: =+B5+D5-'CONF '!C6 -> 0
B6: =VLOOKUP('CONF '!B7,'TARIFAS '!$A$3:$N$239,4,FALSE) -> 110000 | C6: =+B6*'CONF '!$D$2 -> 220000 | D6: =VLOOKUP('CONF '!B7,'TARIFAS '!$A$3:$N$239,5,FALSE) -> 280000 | E6: =+D6*'CONF '!$D$2 -> 560000 | G6: =+B6+D6-'CONF '!C7 -> 0
B7: =VLOOKUP('CONF '!B8,'TARIFAS '!$A$3:$N$239,4,FALSE) -> 0 | C7: =+B7*'CONF '!$D$2 -> 0 | D7: =VLOOKUP('CONF '!B8,'TARIFAS '!$A$3:$N$239,5,FALSE) -> 500000 | E7: =+D7*'CONF '!$D$2 -> 1000000 | G7: =+B7+D7-'CONF '!C8 -> 0
B8: =VLOOKUP('CONF '!B9,'TARIFAS '!$A$3:$N$239,4,FALSE) -> 180000 | C8: =+B8*'CONF '!$D$2 -> 360000 | D8: =VLOOKUP('CONF '!B9,'TARIFAS '!$A$3:$N$239,5,FALSE) -> 350000 | E8: =+D8*'CONF '!$D$2 -> 700000 | G8: =+B8+D8-'CONF '!C9 -> 0
B9: =VLOOKUP('CONF '!B10,'TARIFAS '!$A$3:$N$239,4,FALSE) -> 100000 | C9: =+B9*'CONF '!$D$2 -> 200000 | D9: =VLOOKUP('CONF '!B10,'TARIFAS '!$A$3:$N$239,5,FALSE) -> 350000 | E9: =+D9*'CONF '!$D$2 -> 700000 | G9: =+B9+D9-'CONF '!C10 -> 0
B10: =VLOOKUP('CONF '!B11,'TARIFAS '!$A$3:$N$239,4,FALSE) -> 70000 | C10: =+B10*'CONF '!$D$2 -> 140000 | D10: =VLOOKUP('CONF '!B11,'TARIFAS '!$A$3:$N$239,5,FALSE) -> 370000 | E10: =+D10*'CONF '!$D$2 -> 740000 | G10: =+B10+D10-'CONF '!C11 -> 0
B11: =VLOOKUP('CONF '!B12,'TARIFAS '!$A$3:$N$239,4,FALSE) -> 120000 | C11: =+B11*'CONF '!$D$2 -> 240000 | D11: =VLOOKUP('CONF '!B12,'TARIFAS '!$A$3:$N$239,5,FALSE) -> 370000 | E11: =+D11*'CONF '!$D$2 -> 740000 | G11: =+B11+D11-'CONF '!C12 -> 0
B12: =VLOOKUP('CONF '!B13,'TARIFAS '!$A$3:$N$239,4,FALSE) -> 1350000 | C12: =+B12*'CONF '!$D$2 -> 2700000 | D12: =VLOOKUP('CONF '!B13,'TARIFAS '!$A$3:$N$239,5,FALSE) -> 1350000 | E12: =+D12*'CONF '!$D$2 -> 2700000 | G12: =+B12+D12-'CONF '!C13 -> -1000000
B13: =VLOOKUP('CONF '!B14,'TARIFAS '!$A$3:$N$239,4,FALSE) -> 520000 | C13: =+B13*'CONF '!$D$2 -> 1040000 | D13: =VLOOKUP('CONF '!B14,'TARIFAS '!$A$3:$N$239,5,FALSE) -> 1180000 | E13: =+D13*'CONF '!$D$2 -> 2360000 | G13: =+B13+D13-'CONF '!C14 -> 0
B14: =VLOOKUP('CONF '!B15,'TARIFAS '!$A$3:$N$239,4,FALSE) -> 100000 | C14: =+B14*'CONF '!$D$2 -> 200000 | D14: =VLOOKUP('CONF '!B15,'TARIFAS '!$A$3:$N$239,5,FALSE) -> 80000 | E14: =+D14*'CONF '!$D$2 -> 160000 | G14: =+B14+D14-'CONF '!C15 -> 0
B15: =VLOOKUP('CONF '!B16,'TARIFAS '!$A$3:$N$239,4,FALSE) -> 520000 | C15: =+B15*'CONF '!$D$2 -> 1040000 | D15: =VLOOKUP('CONF '!B16,'TARIFAS '!$A$3:$N$239,5,FALSE) -> 1180000 | E15: =+D15*'CONF '!$D$2 -> 2360000 | G15: =+B15+D15-'CONF '!C16 -> 0
... B20: =VLOOKUP('CONF '!B21,'TARIFAS '!$A$3:$N$239,4,FALSE) -> 100000 | C20: =+B20*'CONF '!$D$2 -> 200000 | D20: =VLOOKUP('CONF '!B21,'TARIFAS '!$A$3:$N$239,5,FALSE) -> 350000 | E20: =+D20*'CONF '!$D$2 -> 700000 | G20: =+B20+D20-'CONF '!C21 -> 0
B21: =52000*7 -> 364000 | D21: =210000+240000+15*27000 -> 855000 | E21: =+D4*7 -> 560000
B24: =+C24-B21 -> -99000 | C24: =160000*7-D21 -> 265000 | D24: =+D21/15 -> 57000
A25: =+'CONF '!D25+'CONF '!D26 -> 35220000 | C25: =+C24-15000*7 -> 160000
A29: Entrada: COP 21.202.000 no cambio 21/08/2024 = R$ 2.222,46 Dados para depósito Banco Inter Juliana Rotta 3 Pix CNPJ: 14.909.728.0001/45
A37: =+CONCATENATE("Entrada: ",TEXT('CONF '!$B$30,"COP #,#")," no cambio ",TEXT('CONF '!$C$31,"dd/mm/yyyy")," = ",TEXT('CONF '!$D$30,"R$ #,#.#0"), " Dados para depósito Banco Inter Juliana Rotta 3 Pix CNPJ: 14.909.728.0001/45") -> Entrada: COP 13880000, no cambio 14/02/2026 = R$ 2222,455 Dados para depósito Banco Inter Juliana Rotta 3 Pix CNPJ: 14.909.728.0001/45

Sheet TARIFAS 
A1: 1 | B1: $ 2 | C1: 3 | D1: $ 4 | E1: 5 | F1: $ 6 | G1: 7 | H1: $ 8 | I1: 9 | J1: $ 10
B2: TET | C2: PVP | D2: ENTRADA | E2: NETO | F2: TEXTOS | G2: LOCAL | H2: VALOR TAXAS | I2: TEXTO TAXAS | J2: HORA | N2: Voucher | O2: taxas
A3: - | B3: 0 | C3: 0 | D3: 0 | E3: 0 | F3: 0 | G3: 0 | H3: 0
A4: Aluguel De Moto Elétrica | B4: 160000 | C4: 70000 | D4: 104000 | E4: 56000 | F4: Para passear sem passar calor e curtir o melhor de Cartagena em grande estilo. Apresentar-se na hora reservada na Cidade Amuralhada, Calle 2a de Badillo 36 – 54 - 58 P 1 emabixo do hostal Badillo Inclui Passeio de 60min Capacete Treinamento – tempo não descontado do tour Hidratação Valor do saldo a pagar: Na hora de realizar o registro em Ecoway realizar o pagamento de COP 56.000 referente ao aluguel para uma pessoa. | G4: Apresentar-se na Cidade Amuralhada, Calle 2a de Badillo 36 – 54 - 58 P 1 emabixo do hostal Badillo Diagonal ao Restaurante La Vitrola | H4: 0
A5: Aluguel De Moto Elétrica 2 Pessoas | B5: 180000 | C5: 100000 | D5: 100000 | E5: 80000 | F5: Para passear sem passar calor e curtir o melhor de Cartagena em grande estilo. Apresentar-se na hora reservada naCidade Amuralhada, Calle 2a de Badillo 36 – 54 - 58 P 1 emabixo do hostal Badillo Inclui Passeio de 60min Capacete Treinamento – tempo não descontado do tour Hidratação Valor do saldo a pagar: Na hora de realizar o registro em Ecoway realizar o pagamento de COP 80.000 referente ao aluguel para duas pessoas. | G5: Apresentar-se na Cidade Amuralhada, Calle 2a de Badillo 36 – 54 - 58 P 1 emabixo do hostal Badillo Diagonal ao Restaurante La Vitrola | H5: 0
A6: Aula De Salsa | B6: 120000 | C6: 250000 | D6: =B6-E6 -> 35000 | E6: 85000 | F6: Aula de salsa para aprender a bailar o ritmo tipico colombiano e conhecer mais da cultura localApresentar-se as 17hs no Lunático Cooking Studio na Calle del Pedregal n 29, no Bairro de Getsemani. Inclui: Garrafa de agua ou Mojito Valor a pagar no passeio No dia da aula realizar o pagamento de COP 85.000 referente ao saldo por pessoa no dinheiro. | G6: Apresentar-se no Lunático Cooking Studio na Calle del Pedregal n 29, no Bairro de Getsemani. | H6: 0 | J6: 17:00
A7: Aula De Salsa Criança | B7: 90000 | C7: 250000 | D7: =B7-E7 -> 47500 | E7: 42500 | F7: Aula de salsa para aprender a bailar o ritmo tipico colombiano e conhecer mais da cultura localApresentar-se as 17hs no Lunático Cooking Studio na Calle del Pedregal n 29, no Bairro de Getsemani. Inclui: Garrafa de agua ou Mojito Valor a pagar no passeio No dia da aula realizar o pagamento de COP 42.500 referente ao saldo por pessoa no dinheiro. | G7: Apresentar-se no Lunático Cooking Studio na Calle del Pedregal n 29, no Bairro de Getsemani. | H7: 0 | J7: 17:00
A8: Bonavida | B8: 440000 | C8: 370000 | D8: =B8-E8 -> 70000 | E8: 370000 | F8: Um passeio de catamarã com paradas para mergulho e snorkel nas águas das baías das Ilhas do Rosário. Ideal para quem gosta de nadar e navegar sem paradas em praias. Apresentar-se 08am na Marina La Bodeguita porta 3 onde o catamarã Bona Vida estará ancorado, e a tripulação dará toda assistência no embarque as 8:30am Aproximadamente às 14h40 iniciaremos nosso retorno ao cais Los Pegasos. desembarcar às 16h00. Inclui: Petiscos (Empanadas, quibbe e palitos de queijo). Open bar de bebidas não alcoólicas (água, refrigerante, limonada natural e suco temperado). Almoço (Arroz com frutos do mar ou arroz com legumes). Máscaras e tubos para mergulho com snorkel (não guiado). Serviço de bar a bordo (Venda de bebidas não alcoólicas). Valor do saldo a pagar: Para garantir a reserva, é necessário pagar o saldo de COP 370.000 (COP 350.000 passeio + COP 23.000 taxas), a través do link de pagamento com cartão de crédito enviado por mensagem, referente ao saldo por pessoa e taxas portuárias no deck de Bonavida. O pagamento é não reembolsável. | G8: Apresentar-se na Marina La Bodeguita porta 3 onde o catamarã Bona Vida estará ancorado. A tripulação dará toda assistência no embarque. Retorno para a Marina Los Pegasos às 16:00. | H8: 26500 | I8: Pagar a taxas portuárias COP 26.500 (valor por pessoa – somente em dinheiro. Valor sujeito a alterações) | J8: 08:30
A9: Bonavida Criança | B9: 290000 | C9: 125000 | D9: 105000 | E9: 185000 | F9: Um passeio de catamarã com paradas para mergulho e snorkel nas águas das baías das Ilhas do Rosário. Ideal para quem gosta de nadar e navegar sem paradas em praias. Apresentar-se no deck de madeira ao lado da Marina La Bodeguita as 08am onde o catamarã Bona Vida estará ancorado e a tripulação dará toda assistência no embarque. Inclui Taxas portuárias Suco de boas vindas Almoço – opção de arroz de marisco, frango ou vegetariano com salada. Acompanha suco Assentos e redes para tomar sol Snorkel e máscaras Valor do saldo a pagar: No dia do passeio, realizar o pagamento de COP 205.000 só em cartão (COP 185.000 passeio + COP 23.000 taxas), referente ao saldo por pessoa e taxas portuárias no deck de Bonavida | G9: Apresentar-se na Marina La Bodeguita porta 3 onde o catamarã Bona Vida estará ancorado. A tripulação dará toda assistência no embarque. Retorno para a Marina Los Pegasos às 16:00. | H9: 26500 | I9: Pagar a taxas portuárias COP 26.500 (valor por pessoa – somente em dinheiro. Valor sujeito a alterações) | J9: 08:30
A10: Bora Bora Bc | B10: 390000 | C10: 370000 | D10: =B10-E10 -> 110000 | E10: 280000 | F10: Excelente opção aproveitar um dia espetacular na Praia ouvindo boa música e com uma paisagem impressionante. Apresentar-se as 07:30 na porta 03 da Marina la Bodeguita. Pagar a taxas portuárias COP 26.500 + Seguro 5.000 = 31.500COP (valor por pessoa – somente em dinheiro. Valor sujeito a alterações) Inclui Ida e volta em lancha rápida Coquetel de boas-vindas Almoço - opção: peixe, frango ou vegetariano, com arroz de coco, salada e banana frita. Acompanha suco Camas de praia e DJ Obs: no caso de ser um passageiro, dependendo da ocupação, poderão ser acomodados em espreguiçadeiras ao inves de camas de praia Nao Inclui: cama da primeira fila e a mesma deve ser contratada na hora do embarque direto com bora (custo de COP 80.000 aproximadamente) Valor do saldo a pagar: Para garantir a reserva, pagamento do saldo de COP 250.000 por pessoa através do link de pagamento com cartão de crédito enviado por mensagem, não reembolsável | G10: Apresentar-se na porta 03 da Marina la Bodeguita. | H10: 34000 | I10: Pagar a taxas portuárias COP 29.000 + Seguro COP 5.000 (valor por pessoa – somente em dinheiro. Valor sujeito a alterações) | J10: 07:20
A11: Bora Bora Vip | B11: 490000 | C11: 470000 | D11: =B11-E11 -> 120000 | E11: 370000 | F11: Excelente opção aproveitar um dia espetacular na praia com boa música e paisagem impressionante. Apresentar-se as 07:20 na porta 03 da Marina la Bodeguita. Pagar a taxas portuárias COP 26.500 + Seguro COP 5.000 = COP 31.500(valor por pessoa – somente em dinheiro. Valor sujeito a alterações) Inclui Ida e volta em lancha rápida Coquetel de boas-vindas Almoço - opções: paella, frango ou vegetariano. Acompanha suco Cama de praia e toalha Lounge com A/C, DJ, praia VIP e acesso ao Bora Bora Beach Club Nao Inclui: cama da primeira fila e a mesma deve ser contratada na hora do embarque direto com bora (custo de COP 80.000 aproximadamente) Valor do saldo a pagar: Para garantir a reserva, pagamento do saldo de COP 330.000 por pessoa através do link de pagamento com cartão de crédito enviado por mensagem, não reembolsável | G11: Apresentar-se na porta 03 da Marina la Bodeguita. | H11: 34000 | I11: Pagar a taxas portuárias COP 29.000 + Seguro COP 5.000 (valor por pessoa – somente em dinheiro. Valor sujeito a alterações) | J11: 07:20
A12: Coralina Isleño | B12: 420000 | C12: 380000 | D12: =B12-E12 -> 130000 | E12: 290000 | F12: Um dia de charme, elegância e atendimento excelente em decks semi privativos com a beleza do Caribe a seus pés. Ideal para quem gosta de nadar e fazer snorkel. Apresentar-se na recepção do hotel para esperar a van de Coralina Island. Para hotéis em Bocagrande a partir de 07:45am e hotéis na cidade amuralhada a partir de 08 Inclui Taxas portuárias Traslado de ida a Marina la Bodeguita Ida e volta em lancha rápida Taça de vinho de boas-vindas Almoço a la carte e sobremesa. Camas de praia e toalha Valor do saldo a pagar: Na ilha no final do passeio realizar o pagamento de COP 270.000 + Pagar as tasas portuarias COP 26.500 + Seguro COP 5.000 (valor sujeito a altearções) = COP 276.000 por pessoa referente ao saldo do passeio e taxas portuárias no dinheiro ou cartão de crédito. | G12: Apresentar-se na recepção do hotel para esperar a van de Coralina Island. Para hotéis em Bocagrande a partir de 07:45am e hotéis na cidade amuralhada a partir de 08am | H12: 34000 | I12: Pagar a taxas portuárias COP 29.000 + Seguro COP 5.000 (valor por pessoa – somente em dinheiro. Valor sujeito a alterações) | J12: 07:45
A13: Coralina VIP | B13: 580000 | C13: 530000 | D13: =B13-E13 -> 150000 | E13: 430000 | F13: Um dia de charme, elegância e atendimento excelente em decks semi privativos com a beleza do Caribe a seus pés. Ideal para quem gosta de nadar e fazer snorkel. Apresentar-se na recepção do hotel para esperar a van de Coralina Island. Para hotéis em Bocagrande a partir de 07:45am e hotéis na cidade amuralhada a partir de 08am na recepção. Inclui Taxas portuárias Traslado de ida a Marina la Bodeguita Ida e volta em lancha rápida Taça de vinho de boas-vindas Almoço a la carte e sobremesa. Camas de praia e toalha Valor do saldo a pagar: Na ilha no final do passeio realizar o pagamento de COP 405.000 + Pagar a taxas portuárias COP 26.500+ Seguro COP 5.000 (valor sujeito a altearções) = COP 426.000 por pessoa referente ao saldo do passeio e taxas portuárias no dinheiro ou cartão de crédito. | G13: Apresentar-se na recepção do hotel para esperar a van de Coralina Island. Para hotéis em Bocagrande a partir de 07:45am e hotéis na cidade amuralhada a partir de 08am na recepção. | H13: 34000 | I13: Pagar a taxas portuárias COP 29.000 + Seguro COP 5.000 (valor por pessoa – somente em dinheiro. Valor sujeito a alterações) | J13: 07:45
A14: Degustação De Cervejas | B14: 250000 | C14: 185000 | D14: 20000 | E14: 230000 | F14: Degustação de cervejas artesanais Colombianas Uma imersão na cena das cervejas colombianas, seus sabores, preparos e produção. Degustação de 10 cervejas diferentes Acompanhada com ceviche e sanduíche Atividade bilíngue (inglês/espanhol) Valor de saldo a pagar por pessoa: .000 pesos Horário das 15 as 16:30h De terça a sábado Mínimo de 2 pessoas – para grupos consultar valores e horarios | G14: 0 | H14: 0
A15: Degustação De Rum Colombiano | B15: 250000 | C15: 185000 | D15: 65000 | E15: 185000 | F15: 0 | G15: 0 | H15: 0
A16: Degustação De Rum Colombiano | B16: 300000 | C16: 185000 | D16: 70000 | E16: 230000 | F16: Aprender sobre o universo do rum colombiano com chocolotes para harmonizar sabores. Degustação de variedade runs colombianos em diferentes preparos e chocolates locais para ressaltar o sabor da bebida nacional Atividade bilíngue (inglês/espanhol) Valor do saldo a pagar: No dia da aula realizar o pagamento de COP 230.000 por pessoa referente ao saldo da atividade no dinheiro. | G16: 0 | H16: 0
A17: Ensaio Fotográfico | B17: 550000 | C17: 400000 | D17: 190000 | E17: 360000 | F17: Cartagena é uma das cidades mais bonitas do mundo, declarada Patrimônio da Unesco desde 1984. Uma sessão de fotos na cidade é a forma perfeita de eternizar os momentos especiais que famílias, casais e amigos passam por aqui. Ponto de encontro as 16:00hs na Iglesia San Pedro Claver. No dia anterior ao passeio, será enviado contato do fotógrafo. Inclui Sessão de duas horas na cidade amuralhada das 4pm as 6pm. Entrega de fotos tiradas em alta resolução e em uma pasta adicional para a Internet As fotografias incluem edição e retoque geral Uma foto impressa, tamanho 20 x30 (como uma amostra da qualidade do trabalho) Envio por We Transfer (alta resolução) e pelo email (baixa resolução) Média de 50 a 60 fotos selecionadas Valor a pagar no passeio: No local do passeio realizar o pagamento de COP 360.000 referente ao saldo do passeio no dinheiro. | G17: Apresentar-se na Iglesia San Pedro Claver. No dia anterior ao passeio, será enviado contato do fotógrafo. | H17: 0
A18: Experiência Culinária | B18: 300000 | C18: 250000 | D18: 50000 | E18: 250000 | F18: Descubra a identidade caribenha da gastronomia de Cartagena preparando uma refeição de quatro tempos com um chef local em um estúdio culinário incrível com uma vista incrível da cidade. Apresentar-se as 10:30am no Lunático Cooking Studio na Calle del Pedregal n 29, no Bairro de Getsemani. Inclui: Suco de boas Vindas Ingredientes e cozinha equipada com chef local Degustação do menu final com cerveja ou vinho Valor do saldo a pagar:No dia da aula realizar o pagamento de COP 250.000 por pessoa referente ao saldo da atividade no dinheiro. | G18: Apresentar-se no Lunático Cooking Studio na Calle del Pedregal n 29, no Bairro de Getsemani. | H18: 0 | J18: 10:30
A19: Experiência Culinária Criança | B19: 240000 | C19: 250000 | D19: 115000 | E19: 125000 | F19: Descubra a identidade caribenha da gastronomia de Cartagena preparando uma refeição de quatro tempos com um chef local em um estúdio culinário incrível com uma vista incrível da cidade. Apresentar-se as 10:30am no Lunático Cooking Studio na Calle del Pedregal n 29, no Bairro de Getsemani. Inclui: Suco de boas Vindas Ingredientes e cozinha equipada com chef local Degustação do menu final com bebida Valor do saldo a pagar:No dia da aula realizar o pagamento de COP 125.000 por pessoa referente ao saldo da atividade no dinheiro. | G19: Apresentar-se no Lunático Cooking Studio na Calle del Pedregal n 29, no Bairro de Getsemani. | H19: 0 | J19: 10:30
A20: Fenix Cena | B20: 290000 | C20: 245000 | D20: 95000 | E20: 195000 | F20: Praia de areia branca, palmeiras e camas de praia com um piscina de frente para o Caribe a só 10 minutos de Cartagena Apresentar-se as 18:40 na Porta 02 da Marina La Bodeguita. Pagar os impostos de COP 14.000 por pessoa . Dentro da marina, a pessoa responsável de Fenix Beach dará assistência para o embarque. Inclui: Bebida de boas vindas Jantar - prato a la carte do menu (exceto Costillas al Whisky, Pago Rojo, Cazuela de Mariscos e a Posta Cartagenera) e sobremesa do dia Dj, fogueira e mesa no bar ou restaurante Valor do saldo a pagar: No Fenix realizar o pagamento de COP 195.000 referente ao saldo do passeio por pessoa no dinheiro ou cartão de crédito. | G20: Apresentar-se na Porta 02 da Marina La Bodeguita. Dentro da marina, a pessoa responsável de Fenix Beach dará assistência para o embarque. | H20: 14000 | I20: Pagar as taxas de COP 14.000 por pessoa | J20: 18:40
A21: Fenix Cena Criança | B21: 300000 | C21: 245000 | D21: 150000 | E21: 150000 | F21: Praia de areia branca, palmeiras e camas de praia com um piscina de frente para o Caribe a só 10 minutos de Cartagena Apresentar-se as 18:40 na Porta 02 da Marina La Bodeguita. Pagar os impostos de COP 14.000 por pessoa . Dentro da marina, a pessoa responsável de Fenix Beach dará assistência para o embarque. Inclui: Bebida de boas vindas Jantar - prato a la carte do menu (exceto Costillas al Whisky, Pago Rojo, Cazuela de Mariscos e a Posta Cartagenera) e sobremesa do dia Dj, fogueira e mesa no bar ou restaurante Valor do saldo a pagar: No Fenix realizar o pagamento de COP 150.000 referente ao saldo do passeio por pessoa no dinheiro ou cartão de crédito. | G21: Apresentar-se na Porta 02 da Marina La Bodeguita. Dentro da marina, a pessoa responsável de Fenix Beach dará assistência para o embarque. | H21: 14000 | I21: Pagar as taxas de COP 14.000 por pessoa | J21: 18:40
A22: Fenix Decoração na praia | B22: 320000 | C22: 100000 | D22: 170000 | E22: 150000 | F22: Para garantir a reserva, pagamento do saldo de COP 150.000 por através do link de pagamento com cartão de crédito enviado por mensagem, não reembolsável | G22: 0 | H22: 0
A23: Fenix Decoração ninho | B23: 320000 | C23: 100000 | D23: 170000 | E23: 150000 | F23: Para garantir a reserva, pagamento do saldo de COP 150.000 por através do link de pagamento com cartão de crédito enviado por mensagem, não reembolsável | G23: 0 | H23: 0
A24: Fenix Decoração ninho 5/10 pax | B24: 450000 | C24: 100000 | D24: 200000 | E24: 250000 | F24: Para garantir a reserva, pagamento do saldo de COP 250.000 por através do link de pagamento com cartão de crédito enviado por mensagem, não reembolsável | G24: 0 | H24: 0
A25: Fenix Pasadia | B25: 390000 | C25: 195000 | D25: 180000 | E25: 210000 | F25: Praia de areia branca, palmeiras e camas de praia com um piscina de frente para o Caribe a só 10 minutos de Cartagena Apresentar-se na porta 01 da Marina la Bodeguita. Pagar a taxas portuárias COP 14.000 (valor por pessoa– somente em dinheiro. Sujeito a alteração) na porta 01 para entrar na Marina. Inclui: Bebida de boas vindas Almoço - opção: peixe, frango ou vegano, com arroz de coco, salada e banana frita. Acompanha suco e sobremesa Camas de praia, piscina, quadra de volêi Valor do saldo a pagar: No guichê de Fenix na hora do registro realizar o pagamento de COP 210.000 referente ao saldo do passeio por pessoa no dinheiro ou cartão de crédito. | G25: Apresentar-se na porta 01 da Marina la Bodeguita. | H25: 14000 | I25: Pagar a taxas portuárias COP 14.000 (valor por pessoa– somente em dinheiro. Sujeito a alteração) na porta 01 para entrar na Marina.
A26: Fenix Pasadia Criança | F26: Praia de areia branca, palmeiras e camas de praia com um piscina de frente para o Caribe a só 10 minutos de Cartagena Apresentar-se na porta 01 da Marina la Bodeguita. Pagar a taxas portuárias COP 14.000 (valor por pessoa– somente em dinheiro. Sujeito a alteração) na porta 01 para entrar na Marina. Inclui: Bebida de boas vindas Almoço - opção: peixe, frango ou vegano, com arroz de coco, salada e banana frita. Acompanha suco e sobremesa Camas de praia, piscina, quadra de volêi Valor do saldo a pagar: No guichê de Fenix na hora do registro realizar o pagamento de COP 210.000 referente ao saldo do passeio por pessoa no dinheiro ou cartão de crédito. | G26: Apresentar-se na porta 01 da Marina la Bodeguita. | H26: 14000 | I26: Pagar a taxas portuárias COP 14.000 (valor por pessoa– somente em dinheiro. Sujeito a alteração) na porta 01 para entrar na Marina.
A27: Fenix Pasadia+Cena | F27: 0 | G27: 0 | H27: 14000
A28: Insta Tour Ciudad Amurallada | B28: 190000 | C28: 0 | D28: 75000 | E28: 115000 | F28: Cada rua na Cidade Amuralhada tem o seu encanto mas os spots mais INSTAGRAMÁVEIS você visita em nosso tour. Apresentar-se as 16:30hs na Iglesia San Pedro Claver para encontrar com o guia. Inclui Guia turístico profissional em português Caminhada nas calles mais Instagramáveis Subida na Cúpula da Igreja Pôr do sol e Drink em rooftop da cidade Tratamento digital de 5 fotos tiradas no celular Valor a pagar no passeio No dia do passeio realizar o pagamento de COP 115.000 referente ao saldo do passeio por pessoa somente em dinheiro | G28: Apresentar-se na Iglesia San Pedro Claver para encontrar com o guia. | H28: 0 | J28: 16:30
A29: Insta Tour Ciudad Amurallada Hotel | B29: 190000 | C29: 0 | D29: 75000 | E29: 115000 | F29: Cada rua na Cidade Amuralhada tem o seu encanto mas os spots mais INSTAGRAMÁVEIS você visita em nosso tour. Apresentar-se as 16:30hs na recepção do hotel para encontrar com o guia. Inclui Guia turístico profissional em português Caminhada nas calles mais Instagramáveis Subida na Cúpula da Igreja Pôr do sol e Drink em rooftop da cidade Tratamento digital de 5 fotos tiradas no celular Valor a pagar no passeio No dia do passeio realizar o pagamento de COP 115.000 referente ao saldo do passeio por pessoa somente em dinheiro | G29: Apresentar-sena recepçâo do hotel para encontrar com o guia. | H29: 0 | J29: 16:30
A30: Isla Bela | B30: 360000 | C30: 310000 | D30: 120000 | E30: 240000 | F30: Um dia no paraíso com boa praia e bela paisagem. Opção ideal para quem quer sossego e gosta de nadar. Apresentar-se as 07:30 na porta 03 da Marina la Bodeguita. Pagar a taxas portuárias + seguro COP 31.500 (valor por pessoa– somente em dinheiro) Inclui Ida e volta em lancha rápida Coquetel de Boas-vindas (não alcoólico) Almoço - opção: peixe, frango ou vegetariano, com arroz de coco, salada e banana frita. Acompanha suco Cadeiras de praia Opcional Visita ao Oceanário (entrada não incluída) – avisar diretamente na lancha na hora do embarque se desejar visitar o Oceanário. Valor do saldo a pagar: Para garantir a reserva, pagamento do saldo de COP 240.000 por pessoa através do link de pagamento com cartão de crédito enviado por mensagem, não reembolsável | G30: Apresentar-se na porta 03 da Marina la Bodeguita. | H30: 31500 | I30: Pagar a taxas portuárias COP 26.500 + Seguro COP 5.000 (valor por pessoa – somente em dinheiro. Valor sujeito a alterações) | J30: 07:30
A31: Isla Bela Criança | B31: 320000 | C31: 150000 | D31: 100000 | E31: 220000 | F31: Um dia no paraíso com boa praia e bela paisagem. Opção ideal para quem quer sossego e gosta de nadar. Apresentar-se as 07:30 na porta 03 da Marina la Bodeguita. Pagar a taxas portuárias+ seguro COP 31.500 (valor por pessoa– somente em dinheiro) Inclui Ida e volta em lancha rápida Coquetel de Boas-vindas (não alcoólico) Almoço - opção: peixe, frango ou vegetariano, com arroz de coco, salada e banana frita. Acompanha suco Cadeiras de praia. Opcional Visita ao Oceanário (entrada não incluída) – avisar diretamente na lancha na hora do embarque se desejar visitar o Oceanário. Valor do saldo a pagar: Para garantir a reserva, pagamento do saldo de COP 220.000 por pessoa através do link de pagamento com cartão de crédito enviado por mensagem, não reembolsável | G31: Apresentar-se na porta 03 da Marina la Bodeguita. | H31: 31500 | I31: Pagar a taxas portuárias COP 26.500 + Seguro COP 5.000 (valor por pessoa – somente em dinheiro. Valor sujeito a alterações) | J31: 07:30
A32: Isla Bela | B32: 390000 | C32: 310000 | D32: =B32-E32 -> 125000 | E32: 265000 | F32: Um dia no paraíso com boa praia e bela paisagem. Opção ideal para quem quer sossego e gosta de nadar. Apresentar-se as 07:30 na porta 03 da Marina la Bodeguita. Pagar a taxas portuárias + seguro COP 31.500 (valor por pessoa– somente em dinheiro) Inclui Ida e volta em lancha rápida Coquetel de Boas-vindas (não alcoólico) Almoço - opção: peixe, frango ou vegetariano, com arroz de coco, salada e banana frita. Acompanha suco Cadeiras de praia Opcional Visita ao Oceanário (entrada não incluída) – avisar diretamente na lancha na hora do embarque se desejar visitar o Oceanário. Valor do saldo a pagar: Para garantir a reserva, pagamento do saldo de COP 240.000 por pessoa através do link de pagamento com cartão de crédito enviado por mensagem, não reembolsável | G32: Apresentar-se na porta 03 da Marina la Bodeguita. | H32: 34000 | I32: Pagar a taxas portuárias COP 29.000 + Seguro COP 5.000 (valor por pessoa – somente em dinheiro. Valor sujeito a alterações) | J32: 07:30
A33: Isla Bela Criança | B33: 300000 | C33: 150000 | D33: =B33-E33 -> 60000 | E33: 240000 | F33: Um dia no paraíso com boa praia e bela paisagem. Opção ideal para quem quer sossego e gosta de nadar. Apresentar-se as 07:30 na porta 03 da Marina la Bodeguita. Pagar a taxas portuárias+ seguro COP 31.500 (valor por pessoa– somente em dinheiro) Inclui Ida e volta em lancha rápida Coquetel de Boas-vindas (não alcoólico) Almoço - opção: peixe, frango ou vegetariano, com arroz de coco, salada e banana frita. Acompanha suco Cadeiras de praia. Opcional Visita ao Oceanário (entrada não incluída) – avisar diretamente na lancha na hora do embarque se desejar visitar o Oceanário. Valor do saldo a pagar: Para garantir a reserva, pagamento do saldo de COP 220.000 por pessoa através do link de pagamento com cartão de crédito enviado por mensagem, não reembolsável | G33: Apresentar-se na porta 03 da Marina la Bodeguita. | H33: 34000 | I33: Pagar a taxas portuárias COP 29.000 + Seguro COP 5.000 (valor por pessoa – somente em dinheiro. Valor sujeito a alterações) | J33: 07:30
A34: Isla Del Encanto | B34: 370000 | C34: 250000 | D34: 138000 | E34: 232000 | F34: Localizada em Baru e com boa estrutura de hotel. Ideal para famílias e com crianças pequenas. Apresentar-se na recepção do hotel para esperar a van a partir das 08:15am. Pagar a taxas portuárias COP 23.000 (valor por pessoa – somente em dinheiro. Valor sujeito a alterações) na van para entrar na Marina. Inclui Ida e volta em lancha rápida Suco de boas-vindas Almoço - opção: peixe, frango ou vegetariano, com arroz de coco, salada e banana frita. Acompanha suco Cadeiras de praia e toalhas Valor do saldo a pagar: No guichê de Isla del Encanto na hora do registro realizar o pagamento de COP 232.000 referente ao saldo do passeio por pessoa no dinheiro ou cartão de crédito. | G34: Apresentar-se na recepção do hotel para esperar a van. | H34: 26500 | I34: Pagar a taxas portuárias COP 26.500(valor por pessoa– somente em dinheiro) na van para entrar na Marina. | J34: 08:15
A35: Isla Del Encanto Criança até 10 anos | B35: 310000 | C35: 140000 | D35: 190000 | E35: 120000 | F35: Localizada em Baru e com boa estrutura de hotel. Ideal para famílias e com crianças pequenas. Apresentar-se na recepção do hotel para esperar a van a partir das 08:15am. Pagar a taxas portuárias COP 23.000 (valor por pessoa – somente em dinheiro. Valor sujeito a alterações) na van para entrar na Marina. Inclui Ida e volta em lancha rápida Suco de boas-vindas Almoço - opção: peixe, frango ou vegetariano, com arroz de coco, salada e banana frita. Acompanha suco Cadeiras de praia e toalhas Valor do saldo a pagar: No guichê de Isla del Encanto na hora do registro realizar o pagamento de COP 120.000 referente ao saldo do passeio por pessoa no dinheiro ou cartão de crédito. | G35: Apresentar-se na recepção do hotel para esperar a van. | H35: 26500 | I35: Pagar a taxas portuárias COP 26.500(valor por pessoa– somente em dinheiro) na van para entrar na Marina. | J35: 08:15
A36: Isla Del Encanto Criança até 4 anos | B36: 270000 | C36: 90000 | D36: 170000 | E36: 100000 | F36: Localizada em Baru e com boa estrutura de hotel. Ideal para famílias e com crianças pequenas. Apresentar-se na recepção do hotel para esperar a van a partir das 08:15am. Pagar a taxas portuárias COP 23.000 (valor por pessoa – somente em dinheiro. Valor sujeito a alterações) na van para entrar na Marina. Inclui Ida e volta em lancha rápida Suco de boas-vindas Almoço - opção: peixe, frango ou vegetariano, com arroz de coco, salada e banana frita. Acompanha suco Cadeiras de praia e toalhas Valor do saldo a pagar: No guichê de Isla del Encanto na hora do registro realizar o pagamento de COP 100.000 referente ao saldo do passeio por pessoa no dinheiro ou cartão de crédito. | G36: Apresentar-se na recepção do hotel para esperar a van. | H36: 26500 | I36: Pagar a taxas portuárias COP 26.500(valor por pessoa– somente em dinheiro) na van para entrar na Marina. | J36: 08:15
A37: Isla Del Encanto TA | E37: 200000 | F37: Localizada em Baru e com boa estrutura de hotel. Ideal para famílias e com crianças pequenas. Apresentar-se na recepção do hotel para esperar a van a partir das 08:15am. Pagar a taxas portuárias COP 23.000 (valor por pessoa – somente em dinheiro. Valor sujeito a alterações) na van para entrar na Marina. Inclui Ida e volta em lancha rápida Suco de boas-vindas Almoço - opção: peixe, frango ou vegetariano, com arroz de coco, salada e banana frita. Acompanha suco Cadeiras de praia e toalhas Valor do saldo a pagar: No guichê de Isla del Encanto na hora do registro realizar o pagamento de COP 200.000 referente ao saldo do passeio por pessoa no dinheiro ou cartão de crédito. | G37: Apresentar-se na recepção do hotel para esperar a van. | H37: 26500 | I37: Pagar a taxas portuárias COP 26.500(valor por pessoa– somente em dinheiro) na van para entrar na Marina. | J37: 08:15
A38: Isla Del Pirata | B38: 330000 | C38: 200000 | D38: 170000 | E38: 160000 | F38: Um beach club para quem gosta de nadar, remar e ficar na água o dia inteiro. Perfeito para casais e amigos. Apresentar-se 08:15 no guichê 01 de Isla del Pirata na Marina la Bodeguita. Pagar a taxas portuárias COP 23.000 (valor por pessoa – somente em dinheiro. Valor sujeito a alterações) para entrar na porta 01 da Marina. Inclui Ida e volta em lancha rápida Coquetel de boas vindas Almoço - opção: peixe com arroz de coco, salada e banana frita. Ou voucher de consumo no restaurante de COP 40.000 Cadeiras de praias e toalhas Valor do saldo a pagar: No guichê de Isla de Pirata na hora do registro realizar o pagamento de COP 160.000 referente ao saldo do passeio por pessoa no dinheiro ou cartão de crédito. | G38: Apresentar-se 08:15 no guichê 01 de Isla del Pirata na Marina la Bodeguita. Pagar a taxas portuárias COP 23.000 (somente em dinheiro – valor por pessoa) para entrar na porta 01 da Marina. | H38: 26500
A39: Isla Del Pirata Criança | B39: 270000 | C39: 160000 | D39: 140000 | E39: 130000 | F39: Um beach club para quem gosta de nadar, remar e ficar na água o dia inteiro. Perfeito para casais e amigos. Apresentar-se 08:15 no guichê 01 de Isla del Pirata na Marina la Bodeguita. Pagar a taxas portuárias COP 23.000 (somente em dinheiro – valor por pessoa) para entrar na porta 01 da Marina. Inclui Ida e volta em lancha rápida Coquetel de boas vindas Almoço - opção: peixe com arroz de coco, salada e banana frita. Ou voucher de consumo no restaurante de COP 40.000 Cadeiras de praias e toalhas Valor do saldo a pagar: No guichê de Isla de Pirata na hora do registro realizar o pagamento de COP 130.000 referente ao saldo do passeio por pessoa no dinheiro ou cartão de crédito. | G39: 0 | H39: 26500
A40: Isla del Sol | B40: 420000 | C40: 370000 | D40: =B40-E40 -> 140000 | E40: 280000 | F40: Isla del Sol é excelente para famílias e casais curtirem o dia com infra estrutura de hotel e piscina Apresentar-se as 07:50 na porta 04 da Marina la Bodeguita onde a pessoa responsável pelo embarque de Isla del Sol dará o suporte no embarque. Pagar a taxas portuárias COP 26.500 (valor por pessoa – somente em dinheiro. Valor sujeito a alterações) Inclui: - Frutas tropicais de boas vindas. - Almoço típico (peixe frito ou frango, arroz com coco, mandioca frita, patacones, salada, bebidas não alcoólicas e sobremesa). - Cadeiras, guarda sol, piscina (com agua salgada), redes para descanso, - Tour panorâmico pelo Parque Nacional Natural Corales del Rosario com ida ao Oceanário (entrada opcional - não incluída) Pagamento do saldo do passeio: Para garantir a reserva, pagamento do saldo de COP 270.000 por pessoa através do link de pagamento com cartão de crédito enviado por mensagem, não reembolsável | G40: Apresentar-sena porta 04 da Marina la Bodeguita onde a pessoa responsável pelo embarque de Isla del Sol dará o suporte no embarque. | H40: 29000 | I40: Pagar a taxas portuárias COP 29.000(valor por pessoa– somente em dinheiro) na van para entrar na Marina. | J40: 07:50
A41: Isla del Sol Criança 4 até 10 anos | B41: 320000 | C41: 230000 | D41: =B41-E41 -> 147000 | E41: 173000 | F41: Isla del Sol é excelente para famílias e casais curtirem o dia com infra estrutura de hotel e piscina Apresentar-se as 07:50 na porta 04 da Marina la Bodeguita onde a pessoa responsável pelo embarque de Isla del Sol dará o suporte no embarque. Pagar a taxas portuárias COP 26.500 (valor por pessoa – somente em dinheiro. Valor sujeito a alterações) Pagar a taxas portuárias COP 26.500 (valor por pessoa – somente em dinheiro. Valor sujeito a alterações) Inclui: - Ida e volta em lancha rápida - Frutas tropicais de boas vindas. - Almoço típico (peixe frito ou frango, arroz com coco, mandioca frita, patacones, salada, bebidas não alcoólicas e sobremesa). - Cadeiras, guarda sol, piscina (com agua salgada), redes para descanso, - Tour panorâmico pelo Parque Nacional Natural Corales del Rosario com ida ao Oceanário (entrada opcional - não incluída) Pagamento do saldo do passeio: Para garantir a reserva, pagamento do saldo de COP 184.000 por pessoa através do link de pagamento com cartão de crédito enviado por mensagem, não reembolsável | G41: Apresentar-sena porta 04 da Marina la Bodeguita onde a pessoa responsável pelo embarque de Isla del Sol dará o suporte no embarque. | H41: 26500 | I41: Pagar a taxas portuárias COP 26.500(valor por pessoa– somente em dinheiro) na van para entrar na Marina. | J41: 07:50
A42: Isla del Sol Criança de 2 até 3 anos | B42: 350000 | C42: 180000 | D42: 230000 | E42: 120000 | F42: Isla del Sol é excelente para famílias e casais curtirem o dia com infra estrutura de hotel e piscina Apresentar-se as 07:50 na porta 04 da Marina la Bodeguita onde a pessoa responsável pelo embarque de Isla del Sol dará o suporte no embarque. Pagar a taxas portuárias COP 26.500 (valor por pessoa – somente em dinheiro. Valor sujeito a alterações) Pagar a taxas portuárias COP 26.500 (valor por pessoa – somente em dinheiro. Valor sujeito a alterações) Inclui: - Ida e volta em lancha rápida - Frutas tropicais de boas vindas. - Almoço típico (peixe frito ou frango, arroz com coco, mandioca frita, patacones, salada, bebidas não alcoólicas e sobremesa). - Cadeiras, guarda sol, piscina (com agua salgada), redes para descanso, - Tour panorâmico pelo Parque Nacional Natural Corales del Rosario com ida ao Oceanário (entrada opcional - não incluída) Pagamento do saldo do passeio: Para garantir a reserva, pagamento do saldo de COP 120.000 por pessoa através do link de pagamento com cartão de crédito enviado por mensagem, não reembolsável | G42: Apresentar-sena porta 04 da Marina la Bodeguita onde a pessoa responsável pelo embarque de Isla del Sol dará o suporte no embarque. | H42: 26500 | I42: Pagar a taxas portuárias COP 26.500(valor por pessoa– somente em dinheiro) na van para entrar na Marina. | J42: 07:50
A43: Isla del Sol parada | C43: 260000 | D43: -234000 | E43: 234000 | F43: Isla del Sol é excelente para famílias e casais curtirem o dia com infra estrutura de hotel e piscina Inclui: - Frutas tropicais de boas vindas. - Almoço típico (peixe frito ou frango, arroz com coco, mandioca frita, patacones, salada, bebidas não alcoólicas e sobremesa). - Cadeiras, guarda sol, piscina (com agua salgada), redes para descanso, - Tour panorâmico pelo Parque Nacional Natural Corales del Rosario com ida ao Oceanário (entrada opcional - não incluída) Pagamento do saldo do passeio: Para garantir a reserva, pagamento do saldo de COP 234.000 por pessoa através do link de pagamento com cartão de crédito enviado por mensagem, não reembolsável | G43: Apresentar-sena porta 04 da Marina la Bodeguita onde a pessoa responsável pelo embarque de Isla del Sol dará o suporte no embarque. | H43: 26500 | I43: Pagar a taxas portuárias COP 26.500(valor por pessoa– somente em dinheiro) na van para entrar na Marina. | J43: 07:50
A44: Isla Palma | B44: 530000 | C44: 250000 | D44: =B44-E44 -> 180000 | E44: 350000 | F44: Mergulhar em um sonho de viagem para conhecer uma das Ilhas da parte de San Bernardo do Arquipélago, vale a pena a longa viagem Apresentar-se as 5:30 na recepção. Pagar a taxas portuárias COP 26.500 (valor por pessoa– somente em dinheiro. Valor sujeito a alterações) na porta 02 para entrar na Marina. Inclui Ida e volta em lancha rápida Sucol de boas-vindas Almoço - opção: peixe, frango ou vegetariano, com arroz de coco, salada e banana frita. Acompanha suco Cadeiras de praia Valor do saldo a pagar: Para garantir a reserva, pagamento de COP 330.000 +5% referente ao saldo do passeio por pessoa no dinheiro ou cartão de crédito. | G44: Apresentar-se na porta 02 da Marina la Bodeguita, onde a pessoa responsável pelo embarque e dará o suporte no embarque. | H44: 29000 | I44: Pagar a taxas portuárias COP 29.000 (valor por pessoa– somente em dinheiro) na van para entrar na Marina. | J44: 05:45
A45: Islabela parada | B45: 150000 | C45: 260000 | D45: 150000 | F45: Um dia no paraíso com boa praia e bela paisagem. Opção ideal para quem quer sossego e gosta de nadar. Inclui 4 espreguiçadeiras duplas e uma individual. Valor do saldo a pagar: Para garantir a reserva, pagamento do saldo de COP 150.000 por pessoa através do link de pagamento com cartão de crédito enviado por mensagem, não reembolsável sendo COP 70.000 consumíveis em comidas ou bebidas. | G45: Apresentar-se na porta 03 da Marina la Bodeguita. | H45: 31500 | I45: Pagar a taxas portuárias COP 26.500 + Seguro COP 5.000 (valor por pessoa – somente em dinheiro. Valor sujeito a alterações) | J45: 07:30
A46: Luxury Criança | B46: 250000 | C46: 145000 | D46: 90000 | E46: 160000 | F46: Perfeito para quem busca areia branca e mar azul. Ideal para grupos de amigos. Apresentar-se as 07:15 na porta 04 da Marina la Bodeguita. Pagar a taxas portuárias COP 23.000 (valor por pessoa– somente em dinheiro. Valor sujeito a alterações)na porta 04 para entrar na Marina. Inclui Ida e volta em lancha rápida Embarque prioritário Almoço - opção: peixe, frango ou vegetariano, com arroz de coco, salada e banana frita. Caiaque, snorkel e quadra de vôlei Camas de praia Valor do saldo a pagar: Para garantir a reserva, pagamento do saldo de COP 125.000 por pessoa através do link de pagamento com cartão de crédito enviado por mensagem, não reembolsável | G46: Apresentar-se as 07:15 na porta 04 da Marina la Bodeguita. Pagar as taxas portuárias COP 23.000 (valor por pessoa – somente em dinheiro) na porta 04 para entrar na Marina | H46: 26500
A47: Luxury Open Bar | B47: 350000 | C47: 300000 | D47: 120000 | E47: 230000 | F47: Perfeito para quem busca areia branca e mar azul. Opção com open bar de bedidas nacionais. Ideal para grupos de amigos. Apresentar-se as 07:15 na porta 04 da Marina la Bodeguita. Pagar a taxas portuárias COP 23.000 (valor por pessoa– somente em dinheiro. Valor sujeito a alterações)na porta 04 para entrar na Marina. Inclui Ida e volta em lancha rápida Embarque prioritário Bebidas não alcoólicas (água, refrigerante, limonada natural), coquetéis com licor nacional (mojito, cuba libre, caipirinha, coquetéis da casa) e cervejas nacionais Almoço - opção: peixe, frango ou vegetariano, com arroz de coco, salada e banana frita. Caiaque, snorkel e quadra de vôlei Camas de praia Obs: no caso de ser um passageiro, dependendo da ocupação, poderão ser acomodados em espreguiçadeiras ao inves de camas de praia Valor do saldo a pagar: Para garantir a reserva, pagamento do saldo de COP 230.000 por pessoa através do link de pagamento com cartão de crédito enviado por mensagem, não reembolsável | G47: Apresentar-se as 07:15 na porta 04 da Marina la Bodeguita. Pagar as taxas portuárias COP 23.000 (valor por pessoa – somente em dinheiro) na porta 04 para entrar na Marina | H47: 26500
A48: Mangata Beach Club | B48: 420000 | C48: 380000 | D48: =B48-E48 -> 130000 | E48: 290000 | F48: Um Beach Club para os amantes da gastronomia, do bom serviço e de experiências exclusivas. Ideal para casais e amigos aproveitarem as belezas naturais com sofisticação e bom gosto. Apresentar-se as 07:20 na porta 04 da Marina la Bodeguita. Pagar a taxas portuárias COP 23.000 (valor por pessoa – somente em dinheiro. Valor sujeito a alterações Inclui Ida e Volta em lancha rápida Bebida de boas-vindas Almoço a la carte – 08 opções de menu Cadeiras de praia, caiaque e snorkel Ducha de água doce e toalha Apresentar-se as 07:20 na porta 04 da Marina la Bodeguita. Pagar a taxas portuárias COP 23.000 (valor por pessoa – somente em dinheiro. Valor sujeito a alterações. Valor a pagar no dia do passeio No dia do tour realizar o pagamento de COP 290.000 por pessoa, referente ao saldo do passeio. | G48: Apresentar-se na porta 04 da Marina la Bodeguita. | H48: 26500 | I48: Pagar a taxas portuárias COP 26.500(valor por pessoa– somente em dinheiro) na van para entrar na Marina. | J48: 07:20
A49: Mangata Beach Club criança | F49: Um Beach Club para os amantes da gastronomia, do bom serviço e de experiências exclusivas. Ideal para casais e amigos aproveitarem as belezas naturais com sofisticação e bom gosto. Apresentar-se as 07:20 na porta 04 da Marina la Bodeguita. Pagar a taxas portuárias COP 23.000 (valor por pessoa – somente em dinheiro. Valor sujeito a alterações Inclui Ida e Volta em lancha rápida Bebida de boas-vindas Almoço a la carte – 08 opções de menu Cadeiras de praia, caiaque e snorkel Ducha de água doce e toalha Apresentar-se as 07:20 na porta 04 da Marina la Bodeguita. Pagar a taxas portuárias COP 23.000 (valor por pessoa – somente em dinheiro. Valor sujeito a alterações. Valor a pagar no dia do passeio No dia do tour realizar o pagamento de COP 270.000 por pessoa, referente ao saldo do passeio. | G49: Apresentar-se na porta 04 da Marina la Bodeguita. | H49: 26500 | I49: Pagar a taxas portuárias COP 26.500(valor por pessoa– somente em dinheiro) na van para entrar na Marina. | J49: 07:20
A50: Mergulho Com Cilindro Padi | B50: 630000 | C50: 390000 | D50: 170000 | E50: 460000 | F50: Para mergulhadores que já possuem uma certificação, oferecemos mergulhos divertidos todos os dias, saindo de Cartagena. Valor do saldo a pagar: Na ilha na hora do registro realizar o pagamento de 224.000 referente ao saldo do passeio por pessoa no dinheiro ou cartão de crédito. certificação, oferecemos mergulhos divertidos todos os dias, saindo de Cartagena. Apresentar-se na hora combinada no Deck de madeira ao lado da Marina La Bodeguita para embarque. Inclui Ida e volta em lancha rápida Day use sem consumação no Blue Apple Beach Club Equipamento de mergulho completo 2 mergulhos na água do mar aberto Acompanhado por um profissional certificado da PADI Água suco, frutas e lanches Fotos mediante solicitação Valor do saldo a pagar: Na ilha na hora do registro realizar o pagamento de COP 351.000 referente ao saldo do passeio por pessoa em dinheiro. | G50: 0 | H50: 0
A51: Mergulho Com Cilindro Padi | B51: 0 | C51: 390000 | D51: 0 | E51: 0 | F51: Para mergulhadores que já possuem uma certificação, oferecemos mergulhos divertidos todos os dias, saindo de Cartagena. Valor do saldo a pagar: Na ilha na hora do registro realizar o pagamento de 224.000 referente ao saldo do passeio por pessoa no dinheiro ou cartão de crédito. certificação, oferecemos mergulhos divertidos todos os dias, saindo de Cartagena. Apresentar-se na hora combinada no Deck de madeira ao lado da Marina La Bodeguita para embarque. Inclui Ida e volta em lancha rápida Day use sem consumação no Blue Apple Beach Club Equipamento de mergulho completo 2 mergulhos na água do mar aberto Acompanhado por um profissional certificado da PADI Água suco, frutas e lanches Fotos mediante solicitação Valor do saldo a pagar: Na ilha na hora do registro realizar o pagamento de COP 351.000 referente ao saldo do passeio por pessoa em dinheiro. | G51: 0 | H51: 0
A52: Mergulho Com Cilindro Primeiro Mergulho | B52: 590000 | C52: 390000 | D52: 100000 | E52: 490000 | F52: Para mergulhadores que não possuem uma certificação, oferecemos mergulhos divertidos todos os dias, saindo de Cartagena. Apresentar-se na hora combinada no Deck de madeira ao lado da Marina La Bodeguita para embarque. Inclui Ida e volta em lancha rápida Day use sem consumação no Blue Apple Beach Club Sessão teórica curta Prática em águas confinadas para se sentir confortável e desenvolver habilidades. Equipamento de mergulho completo Mergulho 100% assistido e guiado em mar aberto com um instrutor profissional da PADI Água suco, frutas e lanches Fotos mediante solicitação Valor do saldo a pagar: Na ilha na hora do registro realizar o pagamento de COP 396.000 referente ao saldo do passeio por pessoa em dinheiro. | G52: 0 | H52: 0
A53: Mergulho Com Cilindro Primeiro Mergulho | B53: 0 | C53: 390000 | D53: 0 | E53: 0 | F53: Para mergulhadores que não possuem uma certificação, oferecemos mergulhos divertidos todos os dias, saindo de Cartagena. Apresentar-se na hora combinada no Deck de madeira ao lado da Marina La Bodeguita para embarque. Inclui Ida e volta em lancha rápida Day use sem consumação no Blue Apple Beach Club Sessão teórica curta Prática em águas confinadas para se sentir confortável e desenvolver habilidades. Equipamento de mergulho completo Mergulho 100% assistido e guiado em mar aberto com um instrutor profissional da PADI Água suco, frutas e lanches Fotos mediante solicitação Valor do saldo a pagar: Na ilha na hora do registro realizar o pagamento de COP 396.000 referente ao saldo do passeio por pessoa em dinheiro. | G53: 0 | H53: 0
A54: Namaste | B54: 250000 | C54: 180000 | D54: 70000 | E54: 180000 | F54: Um dia em um beach club intimista para conexão com a natureza em grande estilo e bem pertinho de Cartagena. Apresentar-se as 08:45 am na Praia de Castillo Grande, atrás do Hospital de Bocagrande onde a pessoa responsável pelo embarque estará esperando no banner de Namastê e dará assistência. O embarque é feito na praia direto na agua, recomendamos ir de shorts e chinelos. Inclui: Ida e volta em lancha rápida Coquetel de boas-vindas Voucher de 40.000 consumível em bebidas ou comida Quiosque e toalha Valor do saldo a pagar: Na ilha na hora do registro realizar o pagamento de COP 144.000 referente ao saldo do passeio por pessoa no dinheiro ou cartão de crédito. | G54: 0 | H54: 0
A55: Namaste Entardecer | B55: 0 | C55: 250000 | D55: 0 | E55: 0 | F55: Um dia em um beach club intimista para conexão com a natureza em grande estilo e bem pertinho de Cartagena. Apresentar-se as 08:45 am na Praia de Castillo Grande, atrás do Hospital de Bocagrande onde a pessoa responsável pelo embarque estará esperando no banner de Namastê e dará assistência. O embarque é feito na praia direto na agua, recomendamos ir de shorts e chinelos. Inclui: Ida às 09 am ou 10am e volta às 09pm em lancha rápida Bebida de boas vindas Voucher de 40.000 consumível em bebidas ou comida Quiosque exclusivo e toalha 2 por 1 em coquetéis de 3pm a 5pm Fogueira na hora do entardecer Valor do saldo a pagar: Na ilha na hora do registro realizar o pagamento de COP 200.000 referente ao saldo do passeio por pessoa no dinheiro ou cartão de crédito. | G55: Apresentar-seam na Praia de Castillo Grande, atrás do Hospital de Bocagrande onde a pessoa responsável pelo embarque estará esperando no banner de Namastê e dará assistência. O embarque é feito na praia direto na agua, recomendamos ir de shorts e chinelos. | H55: 0 | J55: 08:45
A56: Namaste Holistico | B56: 0 | C56: 280000 | D56: 0 | E56: 0 | F56: Um dia em um beach club intimista para conexão com a natureza em grande estilo e bem pertinho de Cartagena. Apresentar-se as 08:45 am na Praia de Castillo Grande, atrás do Hospital de Bocagrande onde a pessoa responsável pelo embarque estará esperando no banner de Namastê e dará assistência. O embarque é feito na praia direto na agua, recomendamos ir de shorts e chinelos. Inclui: Ida e volta em lancha rápida Bebida detox Voucher de 40.000 consumível em bebidas ou comida Quiosque exclusivo, toalha e mat de yoga Massagem relaxante de 30min Atividade de Bem-Estar Valor do saldo a pagar: Na ilha na hora do registro realizar o pagamento de COP 224.000 referente ao saldo do passeio por pessoa no dinheiro ou cartão de crédito. | G56: Apresentar-seam na Praia de Castillo Grande, atrás do Hospital de Bocagrande onde a pessoa responsável pelo embarque estará esperando no banner de Namastê e dará assistência. O embarque é feito na praia direto na agua, recomendamos ir de shorts e chinelos. | H56: 0 | J56: 08:45
A57: Namaste Romantico | B57: 0 | C57: 1000000 | D57: 0 | E57: 0 | F57: Um dia em um beach club intimista para conexão com a natureza em grande estilo e bem pertinho de Cartagena. Apresentar-se as 08:45 am na Praia de Castillo Grande, atrás do Hospital de Bocagrande onde a pessoa responsável pelo embarque estará esperando no banner de Namastê e dará assistência. O embarque é feito na praia direto na agua, recomendamos ir de shorts e chinelos. Inclui: Ida às 09 am ou 10am e volta às 09pm em lancha rápida Bebida de boas vindas Voucher de 40.000 consumível em bebidas ou comida Quiosque exclusivo e toalha 2 por 1 em coquetéis de 3pm a 5pm Fogueira na hora do entardecer Massagem de casal de 40min Jantar romântico na praia com garrafa de vinho e fogueira Valor do saldo a pagar: Na ilha na hora do registro realizar o pagamento de COP 800.000 referente ao saldo do passeio por casal no dinheiro ou cartão de crédito. | G57: Apresentar-seam na Praia de Castillo Grande, atrás do Hospital de Bocagrande onde a pessoa responsável pelo embarque estará esperando no banner de Namastê e dará assistência. O embarque é feito na praia direto na agua, recomendamos ir de shorts e chinelos. | H57: 0 | J57: 08:45
A58: Palenque | B58: 300000 | C58: 130000 | D58: 140000 | E58: 160000 | F58: Passeio no primeiro quilombo da America Latina, conhecer as raizes afro caribenhas e as origens culturais de Cartagena e região. Só domingos. Retorno as 15:00 Apresentar-se as 07:30 am na recepção no hotel para esperar a van do passeio. Inclui Transporte ida e volta Visita etnoturistica a San Basilio de Palenque Almoço típico Guia em espanhol Valor do saldo a pagar: No dia do passeio realizar o pagamento de COP 160.000 referente ao saldo por pessoa | G58: Apresentar-se na recepção no hotel para esperar a van do passeio. | H58: 0 | J58: 07:30
A59: Palmarito | B59: 350000 | C59: 130000 | D59: 215000 | E59: 135000 | F59: Beach Club com infra estrutura de hotel. Lugar divertido para aproveitar com toda a família. Apresentar-se as 09:00 am na Praia de Castillo Grande, atrás do Hospital de Bocagrande onde a pessoa responsável pelo embarque estará esperando. O embarque é feito na praia direto na agua, recomendamos ir de shorts e chinelos. Inclui Ida e volta em lancha rápida Suco de boas-vindas Almoço - opção: peixe, frango ou vegetariano, com arroz de coco, salada e banana frita. Acompanha suco Cadeiras de praia e toalhas Valor do saldo a pagar: Na ilha na hora do registro realizar o pagamento de COP 135.000 referente ao saldo do passeio por pessoa no dinheiro ou cartão de crédito. | G59: Apresentar-se am na Praia de Castillo Grande, atrás do Hospital de Bocagrande onde a pessoa responsável pelo embarque estará esperando. O embarque é feito na praia direto na agua, recomendamos ir de shorts e chinelos. | H59: 0 | J59: 09:00
A60: Palmarito Criança | B60: 210000 | C60: 110000 | D60: 110000 | E60: 100000 | F60: Beach Club com infra estrutura de hotel. Lugar divertido para aproveitar com toda a família. Apresentar-se as 09:00 am na Praia de Castillo Grande, atrás do Hospital de Bocagrande onde a pessoa responsável pelo embarque estará esperando. O embarque é feito na praia direto na agua, recomendamos ir de shorts e chinelos. Inclui Ida e volta em lancha rápida Suco de boas-vindas Almoço - opção: peixe, frango ou vegetariano, com arroz de coco, salada e banana frita. Acompanha suco Cadeiras de praia e toalhas Valor do saldo a pagar: No guichê de Isla del Encanto na hora do registro realizar o pagamento de COP 100.000 referente ao saldo do passeio por pessoa no dinheiro ou cartão de crédito. | G60: Apresentar-se am na Praia de Castillo Grande, atrás do Hospital de Bocagrande onde a pessoa responsável pelo embarque estará esperando. O embarque é feito na praia direto na agua, recomendamos ir de shorts e chinelos. | H60: 0 | J60: 09:00
A61: PAO PAO | B61: 390000 | C61: 370000 | D61: =B61-E61 -> 120000 | E61: 270000 | F61: Beach club descolado para maiores de 12 anos, para curtir boa música com bom clima e excelentes instalações. Apresentar-se as 07:20 na porta 03 da Marina la Bodeguita. Pagar a taxas portuárias COP 26.500 + Seguro COP 5.000 = COP 31.500(valor por pessoa – somente em dinheiro. Valor sujeito a alterações) Inclui Ida e volta em lancha rápida Bebida de boas vindas não alcoólica Almoço: Paella PAO PAO, Macarrão marinara ou Prato Cartagenero: peixe, arroz de coco, salada e banana frita. Cadeiras de praia (para camas/cadeiras da primeira fila há custo adicional e deve ser contratado na hora do embarque) Uso de piscina Não inclui: uso da jacuzzi e de lounges específicos Valor do saldo a pagar: Para garantir a reserva, pagamento do saldo de COP 230.000 por pessoa através do link de pagamento com cartão de crédito enviado por mensagem, não reembolsável | G61: Apresentar-se na porta 03 da Marina la Bodeguita. | H61: 34000 | I61: Pagar a taxas portuárias COP 29.000 + Seguro COP 5.000 (valor por pessoa – somente em dinheiro. Valor sujeito a alterações) | J61: 07:20
A62: Parada em Paue | B62: 200000 | C62: 94500 | D62: 100000 | E62: 100000 | F62: Beach Club novo, para curtir aguas cristalinas, música relax e uma das paisagens mais lindas das Ilhas do Rosario Inclui Valor da entrada por pessoa COP 200.000, sendo COP 100.000 consumíveis em comidas ou bebidas. Valor do saldo a pagar: Na chegada em Pau´e, no dia do passeio fazer o pagamento do saldo restante de COP 50.000 por PAX | G62: 0 | H62: 0 | J62: 0
A63: Parada em Paue Crianças | B63: 150000 | C63: 94500 | D63: 90000 | E63: 60000 | F63: Beach Club novo, para curtir aguas cristalinas, música relax e uma das paisagens mais lindas das Ilhas do Rosario Inclui Valor da entrada por pessoa COP 150.000, sendo COP 60.000 consumíveis em comidas ou bebidas. Valor do saldo a pagar: Na chegada em Pau´e, no dia do passeio fazer o pagamento do saldo restante de COP 30.000 por PAX | G63: 0 | H63: 0 | J63: 0
A64: Parada Pao Pao 1 | B64: 250000 | C64: 300000 | D64: 50000 | E64: 200000 | F64: Beach club descolado para maiores de 18 anos, para curtir boa música com bom clima e excelentes instalações. Inclui 2 guarda-sóis brancos + 1 guarda-sol (Cada guarda-sol tem uma mesa de apoio) Não inclui: uso da jacuzzi e de lounges específicos Valor do saldo a pagar: Para garantir a reserva, pagamento do saldo de COP 200.000 por pessoa através do link de pagamento com cartão de crédito enviado por mensagem, não reembolsável | G64: 0 | H64: 0 | J64: 0
A65: Parada Pao Pao 2 | B65: 0 | C65: 300000 | D65: -250000 | E65: 250000 | F65: Beach club descolado para maiores de 18 anos, para curtir boa música com bom clima e excelentes instalações. Inclui Não inclui: uso da jacuzzi e de lounges específicos Valor do saldo a pagar: Para garantir a reserva, pagamento do saldo de COP 250.000 por pessoa através do link de pagamento com cartão de crédito enviado por mensagem, não reembolsável | G65: 0 | H65: 0 | J65: 0
A66: PAU´E | B66: 450000 | C66: 310000 | D66: =B66-E66 -> 100000 | E66: 350000 | F66: Beach Club novo, para curtir aguas cristalinas, música relax e uma das paisagens mais lindas das Ilhas do Rosario Apresentar-se as 07:30 na porta 04 da Marina la Bodeguita. Pagar a taxas portuárias + seguro COP 32.000 (valor por pessoa – somente em dinheiro. Valor sujeito a alterações) na porta 04 para entrar na Marina. Inclui Ida e volta em lancha rápida Bebida de boas vindas alcoólica ou não alcoólica Almoço: Massa com vegetais, Arroz cremoso de mar ou Prato Cartagenero: peixe (u frango), arroz de coco, salada e banana frita. Camas de praia e espreguiçadeiras Valor do saldo a pagar: Para garantir a reserva, é necessário pagar o saldo de COP 310.000 + 5% por pessoa através do link de pagamento com cartão de crédito enviado por mensagem, ou COP 310.000 nos hotéis de Centro, Getsemani, Bocagrande e El Laguito. O pagamento é não reembolsável e deve ser feito até 2 dias antes do passeio. | G66: Apresentar-se na porta 04 da Marina la Bodeguita. | H66: =29000+5500 -> 34500 | I66: Pagar a taxas portuárias COP 29.000 + Seguro COP 5.500 (valor por pessoa – somente em dinheiro. Valor sujeito a alterações) | J66: 07:30
A67: PAU´E Criança | B67: 370000 | C67: 280000 | D67: =B67-E67 -> 140000 | E67: 230000 | F67: Beach Club novo, para curtir aguas cristalinas, música relax e uma das paisagens mais lindas das Ilhas do Rosario Apresentar-se as 07:30 na porta 04 da Marina la Bodeguita. Pagar a taxas portuárias + seguro COP 32.000 (valor por pessoa – somente em dinheiro. Valor sujeito a alterações) na porta 04 para entrar na Marina. Inclui Ida e volta em lancha rápida Bebida de boas vindas alcoólica ou não alcoólica Almoço: Massa com vegetais, Arroz cremoso de mar ou Prato Cartagenero: peixe (u frango), arroz de coco, salada e banana frita. Camas de praia e espreguiçadeiras Valor do saldo a pagar: Para garantir a reserva, é necessário pagar o saldo de COP 160.000 + 5% por pessoa através do link de pagamento com cartão de crédito enviado por mensagem, ou COP 160.000 nos hotéis de Centro, Getsemani, Bocagrande e El Laguito. O pagamento é não reembolsável e deve ser feito até 2 dias antes do passeio. | G67: Apresentar-se na porta 04 da Marina la Bodeguita. | H67: =29000+5500 -> 34500 | I67: Pagar a taxas portuárias COP 29.000 + Seguro COP 5.500 (valor por pessoa – somente em dinheiro. Valor sujeito a alterações) | J67: 07:30
A68: Rosario de Mar | B68: 420000 | C68: 380000 | D68: =B68-E68 -> 140000 | E68: 280000 | F68: Um paraíso de tranquilidade e conforto, com boa praia, sombra de árvores e infraestrutura perfeita para família, casais e amigos. - Ida e volta em lancha rápida. - Bebidas de boas vindas. - Almoço com opções no cardápio e bebida não alcóolica. - Camas de prais, duchas, toalhas. Valor do saldo a pagar: Para garantir a reserva, pagamento do saldo de COP 250.000 por pessoa através do link de pagamento com cartão de crédito enviado por mensagem, não reembolsável Pagar a taxas portuárias COP 26.500 (valor por pessoa– somente em dinheiro) Saída diárias, ponto de encontro as 7:40hrs no portão 4 da Marina La Bodeguita. Saídas as 08:15am e chegada as 04:15pm | G68: Apresentar-se na porta 04 da Marina la Bodeguita. | H68: 29000 | I68: Pagar a taxas portuárias COP29;000(valor por pessoa – somente em dinheiro. Valor sujeito a alterações) | J68: 08:15
A69: Rosário de Mar Criança | B69: 320000 | C69: 260000 | D69: =B69-E69 -> 120000 | E69: 200000 | F69: Um paraíso de tranquilidade e conforto, com boa praia, sombra de árvores e infraestrutura perfeita para família, casais e amigos. - Ida e volta em lancha rápida. - Bebidas de boas vindas. - Almoço com opções no cardápio e bebida não alcóolica. - Camas de prais, duchas, toalhas. Valor do saldo a pagar: Para garantir a reserva, pagamento do saldo de COP 180.000 por pessoa através do link de pagamento com cartão de crédito enviado por mensagem, não reembolsável Pagar a taxas portuárias COP 26.500 (valor por pessoa– somente em dinheiro) Saída diárias, ponto de encontro as 7:40hrs no portão 4 da Marina La Bodeguita. Saídas as 08:15am e chegada as 04:15pm | G69: Apresentar-se na porta 04 da Marina la Bodeguita. | H69: 29000 | I69: Pagar a taxas portuárias COP29;000(valor por pessoa – somente em dinheiro. Valor sujeito a alterações) | J69: 08:15
A70: Sabai | B70: 500000 | C70: 300000 | D70: =B70-E70 -> 140000 | E70: 360000 | F70: Passar o dia com tranquilidade em uma pequena praia em Baru. Ideal para familias e casais. Horário de saída: 8h00 - Horário de retorno a Cartagena: 15h00. Ponto de encontro: Marina Todomar Bocagrande às 7h45. Inclui Transporte marítimo de ida e volta: viagem de 60 minutos sob sombra total em barco esportivo tipo lounge. * Embarque e saída da marina privada Todomar Bocagrande. * Taxa de embarque. * Água a bordo. * Dois pilotos profissionais + anfitriã/guia bilíngue dedicado. * Passeio pelo Forte Bocachica e Pântano Cholón. * Desembarque em nosso cais privado de 50 metros de comprimento. * Boas-vindas: Paleta de frutas regionais. * Acesso a uma espetacular piscina de 25 metros. * Camas na beira da praia + toalha. * Extensão de 200 metros de frente para a praia sem vendedores ou aglomerações. * Almoço à la carte com bebida. (algumas exceções) * Atividades: Caiaques, Vôlei, jogos de tabuleiro. * Água e café tudo e Valor do saldo a pagar: Para garantir a reserva, é necessário pagar o saldo de COP 330.000 referente ao saldo do passeio por pessoa a través do link de pagamento com cartão de crédito, enviado por mensagem.O pagamento é não reembolsável. | G70: Apresentar-se na Marina Todomar Bocagrande | H70: 0 | J70: 07:45
A71: Sabai Criança | B71: 400000 | C71: 260000 | D71: =B71-E71 -> 70000 | E71: 330000 | F71: Passar o dia com tranquilidade em uma pequena praia em Baru. Ideal para familias e casais. Apresentar-se na marina TodoMar as 07:45Hs Inclui Transporte terrestre (60 min) Ida e volta em lancha rápida (15min) Suco de boas-vindas COP 80.000 para consumo Camas de praia, kayaks, toalhas Tour panoramico em lancha aos manguezais Valor do saldo a pagar: Realizar o pagamento de COP 290.000 referente ao saldo do passeio por pessoa em cartão de crédito. | G71: Apresentar-se na Marina Todomar Bocagrande | H71: 0 | J71: 07:45
A72: Sabai Criança terrestre | B72: 380000 | C72: 260000 | D72: 90000 | E72: 290000 | F72: Passar o dia com tranquilidade em uma pequena praia em Baru. Ideal para familias e casais. Apresentarse na recepção do hotel a partir das7:30hrs. Inclui * Transporte porta a porta de Cartagena ida e volta (90 minutos por via terrestre em vans compartilhadas + 15 minutos de mar em barco compartilhado para 15 pessoas). Cobertura de coleta: Laguito, Castillogrande, Bocagrande, Centro-Getsemani, Manga, Marbella-Crespo, zona norte até hotel Sonesta. * Horário de início da coleta: 7h30. * Durante a rota marítima: Inclui um passeio por Cholon e túnel de mangue. * Boas-vindas: Paleta de frutas regionais. Extensão de 200 metros de frente para a praia sem vendedores ou aglomerações. *Acesso a uma espetacular piscina de 25 metros. *Almoço à la carte com bebida. (algumas exceções) * Camas na beira da praia + toalha. * Atividades: Caiaques, Vôlei, jogos de tabuleiro. * Água e café o dia todo. * Wi-Fi na praia. Valor do saldo a pagar: Para garantir a reserva, é necessário pagar o saldo de COP 290.000 referente ao saldo do passeio por pessoa a través do link de pagamento com cartão de crédito, enviado por mensagem.O pagamento é não reembolsável. | G72: Apresentarse na recepção do hotel | H72: 0 | J72: 07:30
A73: Parada en Sabai | B73: 250000 | C73: 300000 | D73: =B73-E73 -> 41000 | E73: 209000 | F73: Passar o dia com tranquilidade em uma pequena praia em Baru. Ideal para familias e casais. Inclui Suco de boas-vindas COP 80.000 para consumo Camas de praia, kayaks, toalhas Agua e cafe Tour panoramico em lancha aos manguezais Valor do saldo a pagar: Para garantir a reserva, pagamento do saldo de COP 220.000 + 5% por pessoa através do link de pagamento com cartão de crédito enviado por mensagem, não reembolsável | G73: Apresentar-se na Marina Todomar Bocagrande | H73: 0 | J73: 07:45
A74: Sofitel Baru Playa Blanca | B74: 490000 | C74: 350000 | D74: =B74-E74 -> 140000 | E74: 350000 | F74: Un día para relaxar e aproveitar o melhor das Ilhas do Rosario com muito luxo no day use exclusivo do Sofitel Baru Casablanca, com mar azul, piscinas e serviço impecável Apresentar-se na recepção do hotel a as 07:30 Hrs. Retorno as 17:30 Hrs. Inclui Acesso aos restaurantes, uso das cadeiras de praias Piscina, toalhas e duchas Uso cortesia de kaiak, paddle das 11h as 13h Opcional visita ao Oceanário (valores não incluídos) Kids villa a partir de 3 anos das 09am as 5pm com lanche Valor do saldo a pagar: Para garantir a reserva, pagamento do saldo de COP 260.000 por pessoa a através do link de pagamento com cartão de crédito enviado por mensagem, não reembolsável | G74: Apresentarse na recepção do hotel | H74: 0 | J74: 08:00
A75: Sofitel Baru Playa Blanca Criança | B75: 330000 | C75: 260000 | D75: 200000 | E75: 130000 | F75: Un día para relaxar e aproveitar o melhor das Ilhas do Rosario com muito luxo no day use exclusivo do Sofitel Baru Casablanca, com mar azul, piscinas e serviço impecável Apresentar-se na recepção do hotel a as 07:30 Hrs. Retorno as 17:30 Hrs. Inclui Acesso aos restaurantes, uso das cadeiras de praias Piscina, toalhas e duchas Uso cortesia de kaiak, paddle das 11h as 13h Opcional visita ao Oceanário (valores não incluídos) Kids villa a partir de 3 anos das 09am as 5pm com lanche Valor do saldo a pagar: Para garantir a reserva, pagamento do saldo de COP 130.000 por pessoa a através do link de pagamento com cartão de crédito enviado por mensagem, não reembolsável | G75: 0 | H75: 0
A76: Sofitel Casablanca | B76: 500000 | C76: 260000 | D76: 240000 | E76: 260000 | F76: Un día para relaxar e aproveitar o melhor das Ilhas do Rosario com muito luxo no day use exclusivo do Sofitel Baru Casablanca, com mar azul, piscinas e serviço impecável Apresentar-se na recepção do hotel a as 09:00 Hrs. Retorno as 17:00 Hrs. Inclui Acesso aos restaurantes, uso das cadeiras de praias / Piscina e toalhas Uso cortesia de kaiak, paddle das 11h as 13h Opcional visita ao Oceanário (valores não incluídos) Kids villa a partir de 3 anos das 09am as 5pm com lanche Valor do saldo a pagar: Para garantir a reserva, pagamento do saldo de COP 260.000 não reembolsável | G76: Apresentar-se na recepção do hotel as 09:00 Hrs. Retorno as 17:00 Hrs. | H76: 0
A77: Sofitel Casablanca criança | B77: 330000 | C77: 260000 | D77: 330000 | E77: 0 | F77: Un día para relaxar e aproveitar o melhor das Ilhas do Rosario com muito luxo no day use exclusivo do Sofitel Baru Casablanca, com mar azul, piscinas e serviço impecável Apresentar-se na recepção do hotel a as 07:30 Hrs. Retorno as 17:30 Hrs. Inclui Acesso aos restaurantes, uso das cadeiras de praias / Piscina e toalhas Uso cortesia de kaiak, paddle das 11h as 13h Opcional visita ao Oceanário (valores não incluídos) Kids villa a partir de 3 anos das 09am as 5pm com lanche Valor do saldo a pagar: Para garantir a reserva, pagamento do saldo de COP 1.100.000 para 2 adultos e 2 crianças (02 a 11 anos)a através do link de pagamento com cartão de crédito enviado por mensagem, não reembolsável | G77: Apresentar-se na recepção do hotel as 07:30 Hrs. Retorno as 17:30 Hrs. | H77: 0
A78: Sofitel Casablanca Familiar | B78: 0 | C78: 260000 | D78: 0 | E78: 0 | F78: Un día para relaxar e aproveitar o melhor das Ilhas do Rosario com muito luxo no day use exclusivo do Sofitel Baru Casablanca, com mar azul, piscinas e serviço impecável Apresentar-se na recepção do hotel a as 07:30 Hrs. Retorno as 17:30 Hrs. Inclui Habitação para passar o dia com ameneties e 4 bebidas de boas vindas Acesso aos restaurantes, uso das cadeiras de praias / Piscina e toalhas Uso cortesia de kaiak, paddle das 11h as 13h Opcional visita ao Oceanário (valores não incluídos) Kids villa a partir de 3 anos das 09am as 5pm com lanche Valor do saldo a pagar: Para garantir a reserva, pagamento do saldo de COP 1.100.000 para 2 adultos e 2 crianças (02 a 11 anos)a através do link de pagamento com cartão de crédito enviado por mensagem, não reembolsável | G78: 0 | H78: 0
A79: Sofitel Santa Clara Aula de culinária | B79: 0 | C79: 260000 | D79: 0 | E79: 0 | F79: Inclui Aproveite uma aula de culinária com um de nossos chefs e torne-se um verdadeiro especialista em gastronomia caribenha! Valor do saldo a pagar: Para garantir a reserva, pagamento do saldo de COP 3.700.000 para grupo de 6 pessoas a através do link de pagamento com cartão de crédito enviado por mensagem, não reembolsável | G79: Apresentar-se na recepção do hotel as 07:30 Hrs. Retorno as 17:30 Hrs. | H79: 0
A80: Sofitel Santa Clara Cata de Ron y Chocolate | B80: 350000 | C80: 260000 | D80: 145000 | E80: 205000 | F80: Inclui A experiência inclui 3 amostras de rum premium colombiano e chocolate para harmonização, com o acompanhamento do nosso sommelier, que irá guiá-lo(a) na descoberta do processo, história e sabores por trás dessa bebida espirituosa. Valor do saldo a pagar: Para garantir a reserva, pagamento do saldo de COP 205.000 | G80: Apresentar-se na recepção do hotel as 07:30 Hrs. Retorno as 17:30 Hrs. | H80: 0
A81: Sofitel Transfer Van | B81: 1100000 | C81: 60000 | D81: 1100000 | E81: 0 | F81: Apresentar-se na recepção do hotel as 07:30 Hrs para esperar o motorista. Apresentar-se na recepção do Sofitel Baru as 17:30 Hrs para esperar o motorista | G81: Apresentar-se na recepção do hotel as 07:30 Hrs para esperar o motorista. Apresentar-se na recepção do Sofitel Baru as 17:30 Hrs para esperar o motorista | H81: 0
A82: SofitelTransfer Até 03 Pessoas | B82: 700000 | C82: 0 | D82: 700000 | E82: 0 | F82: Apresentar-se na recepção do hotel as 07:30 Hrs para esperar o motorista. Apresentar-se na recepção do Sofitel Baru as 17:30 Hrs para esperar o motorista | G82: Apresentar-se na recepção do hotel as 07:30 Hrs para esperar o motorista. Apresentar-se na recepção do Sofitel Baru as 17:30 Hrs para esperar o motorista | H82: 0
A83: Sunset Sibarita Master Criança | B83: 150000 | C83: 94500 | D83: =B83-E83 -> 95000 | E83: 55000 | F83: Passeio de iate pela Báia de Cartagena para curtir o por do sol com boa música e alto astral. Apresentar-se as 16:20 no portão #4 da Marina La Bodeguita para embarque onde o barco Sibarita Master estará ancorado e a tripulação dará assistência no embarque. Pagar a taxas portuárias COP 14.000 (valor por pessoa – somente em dinheiro. Valor sujeito a alterações) Inclui: Cuba Livre, ponche de rum, limonada, cervejas nacionais, vinho, água e refrigerante Serviços a bordo: banheiros, Mesas e bancos cômodos e serviço de bar com de bebidas e aperitivos (com custo adicional) Valor do saldo a pagar: Na embarcação na hora do registro realizar o pagamento de COP 50.000 referente ao saldo do passeio por pessoa no dinheiro ou cartão de crédito. | G83: Apresentar-se as 16:20 no portão #4 da Marina La Bodeguita para embarque onde o barco Sibarita Master estará ancorado e a tripulação dará assistência no embarque. | H83: 14000 | I83: Pagar a taxas portuárias COP 14.000(valor por pessoa – somente em dinheiro. Valor sujeito a alterações) | J83: 16:20
A84: Sunset Sibarita Master | B84: 230000 | C84: 94500 | D84: =B84-E84 -> 120000 | E84: 110000 | F84: Passeio de iate pela Báia de Cartagena para curtir o por do sol com boa música e alto astral. Apresentar-se as 16:20 no portão #4 da Marina La Bodeguita para embarque onde o barco Sibarita Master estará ancorado e a tripulação dará assistência no embarque. Pagar a taxas portuárias COP 14.000 (valor por pessoa – somente em dinheiro. Valor sujeito a alterações) Inclui: Cuba Livre, ponche de rum, limonada, cervejas nacionais, vinho, água e refrigerante Serviços a bordo: banheiros, Mesas e bancos cômodos e serviço de bar com de bebidas e aperitivos (com custo adicional) Valor do saldo a pagar: Na embarcação na hora do registro realizar o pagamento de COP 100.000 referente ao saldo do passeio por pessoa no dinheiro ou cartão de crédito. | G84: Apresentar-se as 16:20 no portão #4 da Marina La Bodeguita para embarque onde o barco Sibarita Master estará ancorado e a tripulação dará assistência no embarque. | H84: 14000 | I84: Pagar a taxas portuárias COP 14.000(valor por pessoa – somente em dinheiro. Valor sujeito a alterações) | J84: 16:20
A85: TOP 3 Ilhas | B85: 440000 | C85: 300000 | D85: =B85-E85 -> 110000 | E85: 330000 | F85: Um passeio exclusivo para 28 pessoas que oferece um passeio pelas Ilhas do Rosário com parada em Pao Pao, Islabela e Bora Bora Beach Club. Apresentar-se as 08:00 na porta 03 da Marina la Bodeguita. Pagar a taxas portuárias COP 26.500 + Seguro COP 5.000 = COP 31.500(valor por pessoa – somente em dinheiro. Valor sujeito a alterações) O passeio inclui: * Transporte em lancha * Guia bilíngue * Passeio panorâmico pelas Ilhas Rosário * 1 coquetel de boas-vindas em cada ilha * Hidratação no barco (Água, Refrigerante) * 3 opções de almoço + bebida (Islabela) * Espaço exclusivo para o passeio em cada ilha Apenas para adultos +18 Não inclui: •Imposto de doca + seguro •Toalhas •Serviços ou consumos adicionais •Espaços preferenciais •Acesso à área VIP de Bora Bora O horário de saída é às 8h45. Reserva garantida até às 8h30 Horário aproximado de chegada ao cais La Bodeguita 16h30 Valor do saldo a pagar: Para garantir a reserva, pagamento do saldo de COP 280.000 por pessoa através do link de pagamento com cartão de crédito enviado por mensagem, não reembolsável | G85: Apresentar-se na porta 03 da Marina la Bodeguita. | H85: 34000 | I85: Pagar a taxas portuárias COP 29.000 + Seguro COP 5.000 (valor por pessoa – somente em dinheiro. Valor sujeito a alterações) | J85: 08:00
A86: Tour Café Colombiano | B86: 160000 | C86: 0 | D86: 160000 | E86: 0 | F86: O café colombiano é conhecido por ser um dos melhores cafés do mundo! Venha conhecer tudo sobre o Café Colombiano e seus métodos de extração. Apresentar-se as 16:30hs na Iglesia San Pedro Claver para encontrar com o guia. Inclui Guia turístico profissional em português Visita a 3 cafeterias Degustação de 3 cafés | G86: Apresentar-se as 16:30 na Iglesia San Pedro Claver para encontrar com o guia. | H86: 0
A87: Tour Café Colombiano Hotel | B87: 160000 | C87: 0 | D87: 0 | E87: 0 | F87: O café colombiano é conhecido por ser um dos melhores cafés do mundo! Venha conhecer tudo sobre o Café Colombiano e seus métodos de extração. Apresentar-se as 16:30hs na recepçâo do hotel para encontrar com o guia. Inclui Guia turístico profissional em português Visita a 3 cafeterias Degustação de 3 cafés Valor a pagar no passeio No dia do passeio realizar o pagamento de COP 87.000 referente ao saldo do passeio por pessoa somente em dinheiro | G87: Apresentar-se as 16:30 na recepçâo do hotel para encontrar com o guia. | H87: 0
A88: Tour en lancha privativa las Islas del Rosario | B88: 1850000 | C88: 300000 | D88: 725000 | E88: 1125000 | F88: Excelente opção para curtir uma aventura em alto mar, navegando no mar azul e visitando as praias lindas do Caribe Colombiano Apresentar-se a as 08:30am na Marina (a ser definida mais próximo do passeio) onde la tripulação estará esperando para dar assistência na hora del embarque. Inclui: Capitão e tripulação Gelo e Cooler Combustível Sistema de som Banheiro Não Inclui: Toalhas, bebidas ou comidas, mas podem ser levadas. Valor do saldo a pagar: No dia do tour fazer o pagamento do saldo restante de COP 1.125.000 para a pessoa encarregada de recebê-los, seu nombre é Arturo e estará la para dar toda asisstência na hora do embarque. | G88: Apresentar-se as 08:50 na Marina Los Pegasos onde la tripulação da lancha Seawater estará esperando para dar assistência na hora del embarque. | H88: 20000
A89: Tour Moto, Bici Moto, Moto Chopper | B89: 200000 | C89: 140000 | D89: 100000 | E89: 100000 | F89: Conhecer a cidade em duas rodas e passear sem passar calor para curtir o melhor de Cartagena em grande estilo. Apresentar-se na hora reservada na Cidade Amuralhada, Calle 2a de Badillo 36 – 54 - 58 P 1 emabixo do hostal Badillo Inclui Passeio de 60min Capacete Guia em espanhol ou inglês Fotografias Treinamento – tempo não descontado do tour Hidratação Valor do saldo a pagar: Na hora de realizar o registro em Ecoway realizar o pagamento de COP 100.000 referente ao saldo do passeio por pessoa no dinheiro ou cartão de crédito. | G89: Apresentar-se na hora reservada na Cidade Amuralhada, Calle 2a de Badillo 36 – 54 - 58 P 1 emabixo do hostal Badillo | H89: 0
A90: Tour No Mercadão + Aula De Culinária | B90: 440000 | C90: 375000 | D90: 65000 | E90: 375000 | F90: Visita ao mercado municipal Bazurto para explorar e experimentar comidas exóticas. Depois do tour, levar as compras ao restaurante para começar a Experiência de Cozinha Cartagenera. Apresentar-se as 08:00 am no Lunático Cooking Studio na Calle del Pedregal n 29, no Bairro de Getsemani. Inclui: Ingredientes e cozinha equipada com chef local Degustação do menu final Valor do saldo a pagar:No dia da aula realizar o pagamento de COP 375.000 por pessoa referente ao saldo da atividade no dinheiro. | G90: Apresentar-se as 08:00 am no Lunático Cooking Studio na Calle del Pedregal n 29, no Bairro de Getsemani. | H90: 0
A91: Tour No Mercadão + Aula De Culinária Criança | B91: 360000 | C91: 375000 | D91: 172500 | E91: 187500 | F91: Visita ao mercado municipal Bazurto para explorar e experimentar comidas exóticas. Depois do tour, levar as compras ao restaurante para começar a Experiência de Cozinha Cartagenera. Apresentar-se as 08:00 am no Lunático Cooking Studio na Calle del Pedregal n 29, no Bairro de Getsemani. Inclui: Ingredientes e cozinha equipada com chef local Degustação do menu final com bebida Valor do saldo a pagar:No dia da aula realizar o pagamento de COP 187.500 por pessoa referente ao saldo da atividade no dinheiro. | G91: Apresentar-se as 08:00 am no Lunático Cooking Studio na Calle del Pedregal n 29, no Bairro de Getsemani. | H91: 0
A92: Transfer Aeroporto/Hotel Até 03 Pessoas | B92: 130000 | C92: 60000 | D92: 130000 | E92: 0 | F92: O motorista esperará no portão de desembarque as XXX com a plaquinha com nome do passageiro para levar ao hotel. | G92: O motorista esperará no portão de desembarque com a plaquinha com nome do passageiro para levar ao hotel. | H92: 0
A93: Transfer Aeroporto/Hotel Van Até 08 Pessoas | B93: 240000 | C93: 90000 | D93: 240000 | E93: 0 | F93: O motorista esperará no portão de desembarque as XXX com a plaquinha com nome do passageiro para levar ao hotel. | G93: O motorista esperará no portão de desembarque com a plaquinha com nome do passageiro para levar ao hotel. | H93: 0
A94: Transfer Aeroporto/Hotel Van Até 14 Pessoas | B94: 260000 | C94: 110000 | D94: 260000 | E94: 0 | F94: O motorista esperará no portão de desembarque as XXX com a plaquinha com nome do passageiro para levar ao hotel. | G94: O motorista esperará no portão de desembarque com a plaquinha com nome do passageiro para levar ao hotel. | H94: 0
A95: Transfer Aeroporto/Hotel Van Até 17 Pessoas | B95: 400000 | C95: 110000 | D95: 0 | E95: 0 | F95: O motorista esperará no portão de desembarque as XXX com a plaquinha com nome do passageiro para levar ao hotel. | G95: O motorista esperará no portão de desembarque com a plaquinha com nome do passageiro para levar ao hotel. | H95: 0
A96: Transfer City Tour 4 horas + guia até 3 Pessoas | B96: 0 | C96: 110000 | D96: 0 | E96: 0 | F96: Apresentar-se na recepção as para esperar o motorista. | G96: Apresentar-se na recepção para esperar o motorista. | H96: 0
A97: Transfer City Tour 4 horas até 14 Pessoas | B97: 600000 | C97: 110000 | D97: 600000 | E97: 0 | F97: Apresentar-se na recepção as para esperar o motorista. | G97: Apresentar-se na recepção para esperar o motorista. | H97: 0
... A106: Transfer Hotel/Aviario Van Até 14 Pessoas | B106: 900000 | C106: 500000 | D106: 900000 | E106: 0 | F106: Visita ao Aviário de Cartagena para conhecer espécies de aves de exóticas e coloridas que voam pelos arredores do Aviario Nacional da Colômbia Apresentar-se as 08 am na recepção no hotel para esperar a van do passeio. A van passa entre 08 e 08:15hs. Inclui: Transporte Terrestre ida e volta em Van ou Ônibus Espera de duas horas para visitação Não inclui entradas – podem ser adquiridas direto na bilheteria do aviário no local do passeio. Valor do saldo a pagar: No dia do passeio realizar o pagamento de COP 64.000 referente ao saldo por pessoa | G106: Apresentar-se as 08 am na recepção no hotel para esperar a van do passeio. A van passa entre 08 e 08:15hs. | H106: 0
A107: Transfer Hotel/Aviarios Microbus Até 18 Pessoas | B107: 0 | C107: 600000 | D107: 0 | E107: 0 | F107: Visita ao Aviário de Cartagena para conhecer espécies de aves de exóticas e coloridas que voam pelos arredores do Aviario Nacional da Colômbia Apresentar-se as 08 am na recepção no hotel para esperar a van do passeio. A van passa entre 08 e 08:15hs. Inclui: Transporte Terrestre ida e volta em Van ou Ônibus Espera de duas horas para visitação Não inclui entradas – podem ser adquiridas direto na bilheteria do aviário no local do passeio. Valor do saldo a pagar: No dia do passeio realizar o pagamento de COP 64.000 referente ao saldo por pessoa | G107: Apresentar-se na recepção para esperar o motorista. | H107: 0 | J107: 08:00
A108: Transfer Hotel/Marina - Marina/Hotel 8 Pessoas | B108: 480000 | C108: 110000 | D108: 480000 | E108: 0 | F108: Apresentar-se na recepção do hotel as 07:00 para esperar o motorista para levar a Marina La Bodeguita. A van esperará na saída da porta 4 da Marina as 16:30 para levar de volta ao hotel. | G108: Apresentar-se na recepção do hotel para esperar o motorista para levar a Marina La Bodeguita. A van esperará na saída da porta 4 da Marina as 16:30 para levar de volta ao hotel. | H108: 0
...

Sheet Historico TARIFAS 
B1: 45292 | F1: 2024-2025
B2: TET | C2: PVP | D2: ENTRADA | E2: NETO | F2: TET | G2: PVP | H2: ENTRADA | I2: NETO | J2: Activo | K2: Data inicio | L2: Data fim
A3: - | B3: 0 | C3: 0 | D3: 0 | E3: 0 | F3: 0 | G3: 0 | H3: 0 | I3: 0
A4: Aluguel De Moto Elétrica | B4: 160000 | C4: 70000 | D4: 104000 | E4: 56000 | F4: 160000 | G4: 70000 | H4: 104000 | I4: 56000
A5: Adicional noturno das 21:00hs as 06:00hs
A6: Aluguel De Moto Elétrica 2 Pessoas | B6: 180000 | C6: 100000 | D6: 100000 | E6: 80000 | F6: 180000 | G6: 100000 | H6: 100000 | I6: 80000
A7: Aula De Salsa | B7: 120000 | C7: 250000 | D7: 35000 | E7: 85000 | F7: 120000 | G7: 250000 | H7: 35000 | I7: 85000 | J7: OK Geni
A8: Aula De Salsa Criança | B8: 90000 | C8: 250000 | D8: 47500 | E8: 42500 | F8: 90000 | G8: 250000 | H8: 47500 | I8: 42500 | J8: OK Geni
A9: Bonavida | B9: 440000 | C9: 370000 | D9: 123000 | E9: 370000 | F9: 440000 | G9: 370000 | H9: 123000 | I9: 370000 | J9: 2025
A10: Bonavida Criança | B10: 290000 | C10: 125000 | D10: 105000 | E10: 185000 | F10: 290000 | G10: 125000 | H10: 105000 | I10: 185000
A11: Bora Bora Bc | B11: 360000 | C11: 200000 | D11: 110000 | E11: 250000 | F11: 390000 | G11: 200000 | H11: =F11-I11 -> 110000 | I11: 280000 | J11: OK Geni
A12: Bora Bora Vip | B12: 450000 | C12: 300000 | D12: 120000 | E12: 330000 | F12: 470000 | G12: 300000 | H12: =F12-I12 -> 100000 | I12: 370000 | J12: OK Geni
A13: Consultoria Express | B13: 80 | C13: 0 | D13: 80 | F13: 80 | G13: 0 | H13: 80
A14: Coralina Isleño | B14: 390000 | C14: 360000 | D14: 120000 | E14: 270000 | F14: 420000 | G14: 380000 | H14: =F14-I14 -> 130000 | I14: 290000 | J14: OK Geni | K14: 45651 | L14: 45672
A15: Coralina VIP | B15: 540000 | C15: 505000 | D15: 135000 | E15: 405000 | F15: 580000 | G15: 530000 | H15: =G15-I15 -> 100000 | I15: 430000 | J15: OK Geni | K15: 45651 | L15: 45672
A16: Degustação De Cervejas | B16: 250000 | C16: 185000 | D16: 20000 | E16: 230000 | F16: 250000 | G16: 185000 | H16: =F16-I16 -> 20000 | I16: 230000
A17: Degustação De Rum Colombiano | B17: 250000 | C17: 185000 | D17: 65000 | E17: 185000 | F17: 250000 | G17: 185000 | H17: 65000 | I17: 185000
A18: Degustação De Rum Colombiano | B18: 300000 | C18: 185000 | D18: 70000 | E18: 230000 | F18: 300000 | G18: 185000 | H18: 70000 | I18: 230000
A19: Edição Fotografica | B19: 120 | C19: 0 | D19: 50000 | E19: -49880 | F19: 120 | G19: 0 | H19: 50000 | I19: -49880
A20: Ensaio Fotográfico | B20: 550000 | C20: 400000 | D20: 190000 | E20: 360000 | F20: 550000 | G20: 400000 | H20: 190000 | I20: 360000
A21: Experiência Culinária | B21: 300000 | C21: 250000 | D21: 50000 | E21: 250000 | F21: 300000 | G21: 250000 | H21: 50000 | I21: 250000
A22: Experiência Culinária Criança | B22: 240000 | C22: 250000 | D22: 115000 | E22: 125000 | F22: 240000 | G22: 250000 | H22: 115000 | I22: 125000
A23: Fenix Cena com ninho 10 PAX | B23: 330000 | C23: 245000 | D23: 135000 | E23: 195000 | F23: 330000 | G23: 245000 | H23: 135000 | I23: 195000
A24: Fenix Cena com ninho 15 PAX | B24: 330000 | C24: 245000 | D24: 135000 | E24: 195000 | F24: 330000 | G24: 245000 | H24: 135000 | I24: 195000
A25: Fenix Cena | B25: 290000 | C25: 245000 | D25: 95000 | E25: 195000 | F25: 290000 | G25: 245000 | H25: 95000 | I25: 195000
A26: Fenix Cena Criança | B26: 300000 | C26: 245000 | D26: 150000 | E26: 150000 | F26: 300000 | G26: 245000 | H26: 150000 | I26: 150000
A27: Fenix Decoração na praia | B27: 320000 | C27: 100000 | D27: 170000 | E27: 150000 | F27: 320000 | G27: 100000 | H27: 170000 | I27: 150000
A28: Fenix Decoração ninho | B28: 320000 | C28: 100000 | D28: 170000 | E28: 150000 | F28: 320000 | G28: 100000 | H28: 170000 | I28: 150000
... A30: Fenix Pasadia | B30: 390000 | C30: 195000 | D30: 180000 | E30: 210000 | F30: 390000 | G30: 195000 | H30: 180000 | I30: 210000
A31: Fenix Pasadia Criança
A32: Fenix Pasadia+Cena
A33: Insta Tour Ciudad Amurallada | B33: 190000 | C33: 0 | D33: 75000 | E33: 115000 | F33: 190000 | G33: 0 | H33: 75000 | I33: 115000
A34: Insta Tour Ciudad Amurallada Hotel | B34: 190000 | C34: 0 | D34: 75000 | E34: 115000 | F34: 190000 | G34: 0 | H34: 75000 | I34: 115000
A35: Isla Bela | B35: 360000 | C35: 310000 | D35: 120000 | E35: 240000 | F35: 400000 | G35: 310000 | H35: =F35-I35 -> 135000 | I35: 265000 | J35: OK Geni
A36: Isla Bela Criança | B36: 320000 | C36: 150000 | D36: 100000 | E36: 220000 | F36: 300000 | G36: 150000 | H36: =F36-I36 -> 60000 | I36: 240000 | J36: OK Geni
A37: Isla Del Encanto | B37: 370000 | C37: 250000 | D37: 138000 | E37: 232000 | F37: 370000 | G37: 250000 | H37: 138000 | I37: 232000
A38: Isla Del Encanto Criança até 10 anos | B38: 310000 | C38: 140000 | D38: 190000 | E38: 120000 | F38: 310000 | G38: 140000 | H38: 190000 | I38: 120000
A39: Isla Del Encanto Criança até 4 anos | B39: 270000 | C39: 90000 | D39: 170000 | E39: 100000 | F39: 270000 | G39: 90000 | H39: 170000 | I39: 100000
A40: Isla Del Encanto TA | E40: 200000 | I40: 200000
A41: Isla Del Pirata | B41: 330000 | C41: 200000 | D41: 170000 | E41: 160000 | F41: 330000 | G41: 200000 | H41: 170000 | I41: 160000
A42: Isla Del Pirata Criança | B42: 270000 | C42: 160000 | D42: 140000 | E42: 130000 | F42: 270000 | G42: 160000 | H42: 140000 | I42: 130000
A43: Isla del Sol | B43: 390000 | C43: 340000 | D43: 120000 | E43: 270000 | F43: 390000 | G43: 340000 | H43: 120000 | I43: 270000
A44: Isla del Sol Criança 4 até 10 anos | B44: 350000 | C44: 180000 | D44: 166000 | E44: 184000 | F44: 350000 | G44: 180000 | H44: 166000 | I44: 184000
A45: Isla del Sol Criança de 2 até 3 anos | B45: 350000 | C45: 180000 | D45: 230000 | E45: 120000 | F45: 350000 | G45: 180000 | H45: 230000 | I45: 120000
A46: Isla del Sol parada | C46: 260000 | D46: -234000 | E46: 234000 | G46: 260000 | H46: -234000 | I46: 234000
A47: Isla Palma | B47: 500000 | C47: 250000 | D47: 170000 | E47: 330000 | F47: 500000 | G47: 250000 | H47: 170000 | I47: 330000
A48: Isla Palma (Sem transfer) | B48: 550000 | C48: 250000 | D48: 220000 | E48: 330000 | F48: 550000 | G48: 250000 | H48: 220000 | I48: 330000
A49: Isla Palma Terrestre | B49: 400000 | C49: 250000 | D49: 150000 | E49: 250000 | F49: 400000 | G49: 250000 | H49: 150000 | I49: 250000
A50: Islabela parada | B50: 150000 | C50: 260000 | D50: 150000 | F50: 150000 | G50: 260000 | H50: 150000
A51: Jantar Sibarita Express | B51: 165500 | C51: 154500 | D51: 35500 | E51: 130000 | F51: 250000 | G51: 200000 | H51: =F51-I51 -> 95000 | I51: 155000 | J51: Precio definido | K51: 45627
A52: Jantar Sibarita Master | B52: 280000 | C52: 174500 | D52: 95000 | E52: 185000 | F52: 300000 | G52: 275000 | H52: =F52-I52 -> 80000 | I52: 220000 | J52: OK Geni | K52: 45627
A53: Luxury Classic | B53: 300000 | C53: 195000 | D53: 120000 | E53: 180000 | F53: 300000 | G53: 195000 | H53: =F53-I53 -> 120000 | I53: 180000
A54: Luxury Criança | B54: 250000 | C54: 145000 | D54: 90000 | E54: 160000 | F54: 250000 | G54: 145000 | H54: 90000 | I54: 160000
A55: Luxury Open Bar | B55: 350000 | C55: 300000 | D55: 120000 | E55: 230000 | F55: 350000 | G55: 300000 | H55: 120000 | I55: 230000
A56: Mangata Beach Club | B56: 400000 | C56: 380000 | D56: 110000 | E56: 290000 | F56: 400000 | G56: 380000 | H56: 110000 | I56: 290000
A57: Mangata Beach Club criança
A58: Mergulho Com Cilindro Padi | B58: 630000 | C58: 390000 | D58: 170000 | E58: 460000 | F58: 630000 | G58: 390000 | H58: 170000 | I58: 460000
A59: Mergulho Com Cilindro Padi | B59: 0 | C59: 390000 | D59: 0 | E59: 0 | F59: 0 | G59: 390000 | H59: 0 | I59: 0
A60: Mergulho Com Cilindro Primeiro Mergulho | B60: 590000 | C60: 390000 | D60: 100000 | E60: 490000 | F60: 590000 | G60: 390000 | H60: 100000 | I60: 490000
A61: Mergulho Com Cilindro Primeiro Mergulho | B61: 0 | C61: 390000 | D61: 0 | E61: 0 | F61: 0 | G61: 390000 | H61: 0 | I61: 0
A62: Namaste | B62: 250000 | C62: 180000 | D62: 70000 | E62: 180000 | F62: 250000 | G62: 180000 | H62: 70000 | I62: 180000
A63: Namaste Entardecer | B63: 0 | C63: 250000 | D63: 0 | E63: 0 | F63: 0 | G63: 250000 | H63: 0 | I63: 0
A64: Namaste Holistico | B64: 0 | C64: 280000 | D64: 0 | E64: 0 | F64: 0 | G64: 280000 | H64: 0 | I64: 0
A65: Namaste Romantico | B65: 0 | C65: 1000000 | D65: 0 | E65: 0 | F65: 0 | G65: 1000000 | H65: 0 | I65: 0
A66: Palenque | B66: 300000 | C66: 130000 | D66: 140000 | E66: 160000 | F66: 300000 | G66: 130000 | H66: 140000 | I66: 160000
A67: Palmarito | B67: 350000 | C67: 130000 | D67: 215000 | E67: 135000 | F67: 350000 | G67: 130000 | H67: 215000 | I67: 135000
A68: Palmarito Criança | B68: 210000 | C68: 110000 | D68: 110000 | E68: 100000 | F68: 210000 | G68: 110000 | H68: 110000 | I68: 100000
A69: PAO PAO | B69: 360000 | C69: 300000 | D69: 130000 | E69: 230000 | F69: 390000 | G69: 300000 | H69: =F69-I69 -> 120000 | I69: 270000 | J69: OK Geni
A70: Parada em Paue | B70: 200000 | C70: 94500 | D70: 100000 | E70: 100000 | F70: 200000 | G70: 94500 | H70: 100000 | I70: 100000
A71: Parada em Paue Crianças | B71: 150000 | C71: 94500 | D71: 90000 | E71: 60000 | F71: 150000 | G71: 94500 | H71: 90000 | I71: 60000
A72: Parada Pao Pao 1 | B72: 250000 | C72: 300000 | D72: 50000 | E72: 200000 | F72: 250000 | G72: 300000 | H72: 50000 | I72: 200000
A73: Parada Pao Pao 2 | B73: 0 | C73: 300000 | D73: -250000 | E73: 250000 | F73: 0 | G73: 300000 | H73: -250000 | I73: 250000
A74: PAU´E | B74: 420000 | C74: 310000 | D74: 110000 | E74: 310000 | F74: 420000 | G74: 310000 | H74: 110000 | I74: 310000
A75: PAU´E Criança | B75: 350000 | C75: 190000 | D75: 140000 | E75: 210000 | F75: 350000 | G75: 190000 | H75: 140000 | I75: 210000
A76: Revéillon Sibarita Master | B76: 1000000 | C76: 174500 | D76: 1000000 | E76: 0 | F76: 1000000 | G76: 174500 | H76: 1000000 | I76: 0
A77: Réveillon WALA - Cartagena | B77: 0 | C77: 0 | D77: 0 | E77: 0 | F77: 0 | G77: 0 | H77: 0 | I77: 0
A78: Rosario de Mar | B78: 400000 | C78: 310000 | D78: 150000 | E78: 250000 | F78: 400000 | G78: 310000 | H78: 150000 | I78: 250000
A79: Rosario De Mar Abanico | B79: 460000 | C79: 270000 | D79: 130000 | E79: 330000 | F79: 460000 | G79: 270000 | H79: 130000 | I79: 330000
A80: Rosário de Mar Criança | B80: 270000 | C80: 310000 | D80: 90000 | E80: 180000 | F80: 270000 | G80: 310000 | H80: 90000 | I80: 180000
A81: Rosario De Mar Criança abanico | B81: 340000 | C81: 270000 | D81: 100000 | E81: 240000 | F81: 340000 | G81: 270000 | H81: 100000 | I81: 240000
A82: Sabai | B82: 490000 | C82: 300000 | D82: 160000 | E82: 330000 | F82: 490000 | G82: 300000 | H82: 160000 | I82: 330000
A83: Sabai Criança | B83: 380000 | C83: 260000 | D83: 90000 | E83: 290000 | F83: 380000 | G83: 260000 | H83: 90000 | I83: 290000 | J83: OK Geni
A84: Sabai Criança terrestre | B84: 380000 | C84: 260000 | D84: 90000 | E84: 290000 | F84: 380000 | G84: 260000 | H84: 90000 | I84: 290000
A85: Parada en Sabai | B85: 350000 | C85: 300000 | D85: 130000 | E85: 220000 | F85: 250000 | G85: 300000 | H85: =F85-I85 -> 41000 | I85: 209000 | J85: Precio definido
A86: Sabai Dayuse Crianças | B86: 250000 | C86: 300000 | D86: 150000 | E86: 100000 | F86: 250000 | G86: 300000 | H86: 150000 | I86: 100000
A87: Sabai terrestre | B87: 430000 | C87: 300000 | D87: 100000 | E87: 330000 | F87: 430000 | G87: 300000 | H87: 100000 | I87: 330000
A88: Sofitel Baru Playa Blanca | B88: 420000 | C88: 300000 | D88: 160000 | E88: 260000 | F88: 420000 | G88: 300000 | H88: 160000 | I88: 260000
A89: Sofitel Baru Playa Blanca Criança | B89: 330000 | C89: 260000 | D89: 200000 | E89: 130000 | F89: 330000 | G89: 260000 | H89: 200000 | I89: 130000
A90: Sofitel Casablanca | B90: 500000 | C90: 260000 | D90: 240000 | E90: 260000 | F90: 500000 | G90: 260000 | H90: 240000 | I90: 260000
A91: Sofitel Casablanca criança | B91: 330000 | C91: 260000 | D91: 330000 | E91: 0 | F91: 330000 | G91: 260000 | H91: 330000 | I91: 0
A92: Sofitel Casablanca Familiar | B92: 0 | C92: 260000 | D92: 0 | E92: 0 | F92: 0 | G92: 260000 | H92: 0 | I92: 0
A93: Sofitel Santa Clara Aula de culinária | B93: 0 | C93: 260000 | D93: 0 | E93: 0 | F93: 0 | G93: 260000 | H93: 0 | I93: 0
A94: Sofitel Santa Clara Cata de Ron y Chocolate | B94: 350000 | C94: 260000 | D94: 145000 | E94: 205000 | F94: 350000 | G94: 260000 | H94: 145000 | I94: 205000
A95: Sofitel Transfer Van | B95: 1100000 | C95: 60000 | D95: 1100000 | E95: 0 | F95: 1100000 | G95: 60000 | H95: 1100000 | I95: 0
A96: SofitelTransfer Até 03 Pessoas | B96: 700000 | C96: 0 | D96: 700000 | E96: 0 | F96: 700000 | G96: 0 | H96: 700000 | I96: 0
A97: Sol y Papaya Open Bar | B97: 420000 | C97: 430000 | D97: 140000 | E97: 280000 | F97: 420000 | G97: 430000 | H97: 140000 | I97: 280000
A98: Sol y Papaya Pasadia | B98: 360000 | C98: 430000 | D98: 150000 | E98: 210000 | F98: 360000 | G98: 430000 | H98: 150000 | I98: 210000
A99: Sunset Sibarita Express | J99: Por definir precio
A100: Sunset Sibarita Express Crianças | B100: 100000 | C100: 84500 | D100: 55000 | E100: 45000 | F100: 100000 | G100: 84500 | H100: 55000 | I100: 45000 | J100: Por definir precio
A101: Sunset Sibarita Master | B101: 180000 | C101: 94500 | D101: 80000 | E101: 110000 | F101: 230000 | G101: 94500 | H101: =F101-I101 -> 90000 | I101: 140000 | J101: OK Geni | K101: 45627
...
