Workbook

Sheet Precificação Simples Nacional
A1: Pedro Resende | C1: Código | D1: Descrição | E1: Preço custo (COP) | F1: Valor de venda (COP) | G1: Preço custo (BRL) | H1: IOF | I1: Valor após IOF | J1: Valor de IOF Bruto | K1: Cotação COP | L1: Spread | M1: Cotação Real | N1: Valor SPREAD BRUTO | O1: Custo Convertido (US) | P1: Preço de venda | Q1: Simples Nacional (%) | R1: Outros custos diretos (%) | S1: Comissão (R$) | T1: Margem bruta | U1: MARKUP | V1: MARKDOWN | W1: CLD
C2: Lancha-001 | D2: Veleiro 5 pessoas - Lancha | E2: =E45 -> 6395050 | F2: 10703326 | G2: =(E2*M2)*(1+H2) -> 9262.8202 | H2: 0.035 | I2: =G2*(1-H2) -> 8938.6215 | J2: =G2-I2 -> 324.19871 | K2: 0.00137 | L2: 0.0215 | M2: =K2*(1+L2) -> 0.001399455 | N2: =(I2*L2)+15 -> 207.18036 | O2: =(I2*M2)+L20 -> 12.530698 | P2: =(F2*M2)*(1+H2) -> 15503.081 | Q2: 0.06 | S2: =(P2-G2)*0.2 -> 1248.0522 | T2: =P2-(G2+S2)-(P2*R2) -> 4992.2088 | U2: =IFERROR((P2-G2)/G2,"") -> 0.6736891 | V2: =IFERROR((P2-G2)/P2,"") -> 0.40251747 | W2: =IFERROR(T2/P2,"") -> 0.32201398
C3: Lancha-003 | D3: Veleiro 5 pessoas - Regular | E3: 3670000 | G3: =(E3*M3)*(1+H3) -> 5315.7598 | H3: 0.035 | I3: =G3*(1-H3) -> 5129.7082 | J3: =G3-I3 -> 186.05159 | K3: 0.00137 | L3: 0.0215 | M3: =K3*(1+L3) -> 0.001399455 | N3: =(I3*L3)+15 -> 125.28873 | O3: =(I3*M3)+L21 -> 7.2002959 | P3: =G3*1.75 -> 9302.5797 | Q3: 0.06 | S3: =(P3-G3)*0.2 -> 797.36398 | T3: =P3-(G3+S3)-(P3*R3) -> 3189.4559 | U3: =IFERROR((P3-G3)/G3,"") -> 0.75 | V3: =IFERROR((P3-G3)/P3,"") -> 0.42857143 | W3: =IFERROR(T3/P3,"") -> 0.34285714
C4: DEBCAR-001 | D4: 8 pessoas - Debora Carvalho - Regular | E4: 12140000 | G4: =(E4*M4)*(1+H4) -> 17767.297 | H4: 0.035 | I4: =G4*(1-H4) -> 17145.441 | J4: =G4-I4 -> 621.85538 | K4: 0.00138428 | L4: 0.0215 | M4: =K4*(1+L4) -> 0.001414042 | N4: =(I4*L4)+15 -> 383.62699 | O4: =(I4*M4)+L27 -> 24.265874 | P4: =G4*1.5069 -> 26773.539 | Q4: 0.06 | S4: =(P4-G4)*0.2 -> 1801.2485 | T4: =P4-(G4+S4)-(P4*R4) -> 7204.9941 | U4: =IFERROR((P4-G4)/G4,"") -> 0.5069 | V4: =IFERROR((P4-G4)/P4,"") -> 0.33638596 | W4: =IFERROR(T4/P4,"") -> 0.26910877
C5: DEBCAR-003 | D5: 8 pessoas - Debora Carvalho - Lancha | E5: 12840000 | G5: =(E5*M5)*(1+H5) -> 18791.77 | H5: 0.035 | I5: =G5*(1-H5) -> 18134.058 | J5: =G5-I5 -> 657.71195 | K5: 0.00138428 | L5: 0.0215 | M5: =K5*(1+L5) -> 0.001414042 | N5: =(I5*L5)+15 -> 404.88225 | O5: =(I5*M5)+L33 -> 25.66382 | P5: =G5*1.51 -> 28375.573 | Q5: 0.06 | S5: =(P5-G5)*0.2 -> 1916.7605 | T5: =P5-(G5+S5)-(P5*R5) -> 7667.0422 | U5: =IFERROR((P5-G5)/G5,"") -> 0.51 | V5: =IFERROR((P5-G5)/P5,"") -> 0.33774834 | W5: =IFERROR(T5/P5,"") -> 0.27019868
C6: DEBCAR-005 | D6: 5 pessoas - Debora Carvalho - Lancha + Bogota | E6: 9457000 | G6: =(E6*M6)*(1+H6) -> 13697.859 | H6: 0.035 | I6: =G6*(1-H6) -> 13218.433 | J6: =G6-I6 -> 479.42505 | K6: 0.00137 | L6: 0.0215 | M6: =K6*(1+L6) -> 0.001399455 | N6: =(I6*L6)+15 -> 299.19632 | O6: =(I6*M6)+L34 -> 18.498603 | P6: =G6*1.4169 -> 19408.496 | Q6: 0.06 | S6: =(P6-G6)*0.2 -> 1142.1274 | T6: =P6-(G6+S6)-(P6*R6) -> 4568.5098 | U6: =IFERROR((P6-G6)/G6,"") -> 0.4169 | V6: =IFERROR((P6-G6)/P6,"") -> 0.29423389 | W6: =IFERROR(T6/P6,"") -> 0.23538711
C7: DEBCAR-006 | D7: 5 pessoas - Debora Carvalho - Lancha + Bogota | E7: 9457000 | G7: =(E7*M7)*(1+H7) -> 13697.859 | H7: 0.035 | I7: =G7*(1-H7) -> 13218.433 | J7: =G7-I7 -> 479.42505 | K7: 0.00137 | L7: 0.0215 | M7: =K7*(1+L7) -> 0.001399455 | N7: =(I7*L7)+15 -> 299.19632 | O7: =(I7*M7)+L34 -> 18.498603 | P7: =G7*1.4169 -> 19408.496 | Q7: 0.06 | S7: =(P7-G7)*0.2 -> 1142.1274 | T7: =P7-(G7+S7)-(P7*R7) -> 4568.5098 | U7: =IFERROR((P7-G7)/G7,"") -> 0.4169 | V7: =IFERROR((P7-G7)/P7,"") -> 0.29423389 | W7: =IFERROR(T7/P7,"") -> 0.23538711
C8: DEBCAR-007 | D8: 4 pessoas - Debora Carvalho - ctg + bog | E8: =E173 -> 7861600 | F8: =F173 -> 12232000 | G8: =(E8*M8)*(1+H8) -> 11505.715 | H8: 0.035 | I8: =G8*(1-H8) -> 11103.015 | J8: =G8-I8 -> 402.70002 | K8: 0.00137 | L8: 0.0215 | M8: =M4 -> 0.001414042 | N8: =(I8*L8)+15 -> 253.71482 | O8: =(I8*M8)+L35 -> 15.70013 | P8: 18096 | Q8: 0.06 | S8: =(P8-G8)*0.2 -> 1318.057 | T8: =P8-(G8+S8)-(P8*R8) -> 5272.2281 | U8: =IFERROR((P8-G8)/G8,"") -> 0.57278363 | V8: =IFERROR((P8-G8)/P8,"") -> 0.36418463 | W8: =IFERROR(T8/P8,"") -> 0.29134771
C9: DEBCAR-008 | D9: 4 pessoas - Debora Carvalho - ctg + bog | E9: =E187 -> 7648800 | F9: =F187 -> 11632000 | G9: =(E9*M9)*(1+H9) -> 11078.797 | H9: 0.035 | I9: =G9*(1-H9) -> 10691.039 | J9: =G9-I9 -> 387.75788 | K9: 0.00137 | L9: 0.0215 | M9: =K9*(1+L9) -> 0.001399455 | N9: =(I9*L9)+15 -> 244.85733 | O9: =(I9*M9)+L36 -> 14.961628 | P9: 17208 | Q9: 0.06 | S9: =(P9-G9)*0.2 -> 1225.8407 | T9: =P9-(G9+S9)-(P9*R9) -> 4903.3626 | U9: =IFERROR((P9-G9)/G9,"") -> 0.55323727 | V9: =IFERROR((P9-G9)/P9,"") -> 0.35618336 | W9: =IFERROR(T9/P9,"") -> 0.28494669
C10: CLULIV-001 | D10: 12 pessoas - Clube do Livro | E10: 8207280 | G10: =(E10*M10)*(1+H10) -> 12011.629 | H10: 0.035 | I10: =G10*(1-H10) -> 11591.222 | J10: =G10-I10 -> 420.40702 | K10: 0.00138428 | L10: 0.0215 | M10: =K10*(1+L10) -> 0.001414042 | N10: =(I10*L10)+15 -> 264.21128 | O10: =(I10*M10)+L37 -> 16.390475 | P10: =G10*1.7483 -> 20999.931 | Q10: 0.06 | S10: =(P10-G10)*0.2 -> 1797.6604 | T10: =P10-(G10+S10)-(P10*R10) -> 7190.6417 | U10: =IFERROR((P10-G10)/G10,"") -> 0.7483 | V10: =IFERROR((P10-G10)/P10,"") -> 0.42801579 | W10: =IFERROR(T10/P10,"") -> 0.34241263
C11: CLULIV-003 | D11: 12 pessoas - Clube do Livro - Sem Sibarita | E11: 6887280 | G11: =(E11*M11)*(1+H11) -> 10079.765 | H11: 0.035 | I11: =G11*(1-H11) -> 9726.9732 | J11: =G11-I11 -> 352.79177 | K11: 0.00138428 | L11: 0.0215 | M11: =K11*(1+L11) -> 0.001414042 | N11: =(I11*L11)+15 -> 224.12992 | O11: =(I11*M11)+L38 -> 13.754349 | P11: =G11*1.6827 -> 16961.22 | Q11: 0.06 | S11: =(P11-G11)*0.2 -> 1376.2911 | T11: =P11-(G11+S11)-(P11*R11) -> 5505.1644 | U11: =IFERROR((P11-G11)/G11,"") -> 0.6827 | V11: =IFERROR((P11-G11)/P11,"") -> 0.405717 | W11: =IFERROR(T11/P11,"") -> 0.3245736
C12: CLULIV-005 | D12: 12 pessoas - Clube do Livro - Sem Sibarita E LANCHA TOP | E12: 7612000 | G12: =(E12*M12)*(1+H12) -> 11025.494 | H12: 0.035 | I12: =G12*(1-H12) -> 10639.602 | J12: =G12-I12 -> 385.8923 | K12: 0.00137 | L12: 0.0215 | M12: =K12*(1+L12) -> 0.001399455 | N12: =(I12*L12)+15 -> 243.75144 | O12: =(I12*M12)+L39 -> 14.889644 | P12: =G12 -> 11025.494 | Q12: 0.06 | S12: =(P12-G12)*0.2 -> 0 | T12: =P12-(G12+S12)-(P12*R12) -> 0 | U12: =IFERROR((P12-G12)/G12,"") -> 0 | V12: =IFERROR((P12-G12)/P12,"") -> 0 | W12: =IFERROR(T12/P12,"") -> 0
C13: CLULIV-007 | D13: 12 pessoas - Clube do Livro - AZIMUT 55 | E13: 17332000 | G13: =(E13*M13)*(1+H13) -> 25104.291 | H13: 0.035 | I13: =G13*(1-H13) -> 24225.641 | J13: =G13-I13 -> 878.6502 | K13: 0.00137 | L13: 0.0215 | M13: =K13*(1+L13) -> 0.001399455 | N13: =(I13*L13)+15 -> 535.85129 | O13: =(I13*M13)+L40 -> 33.902695 | P13: =G13*1.4476 -> 36340.972 | Q13: 0.06 | S13: =(P13-G13)*0.2 -> 2247.3362 | T13: =P13-(G13+S13)-(P13*R13) -> 8989.3447 | U13: =IFERROR((P13-G13)/G13,"") -> 0.4476 | V13: =IFERROR((P13-G13)/P13,"") -> 0.30920144 | W13: =IFERROR(T13/P13,"") -> 0.24736115
C14: MURCRU-001 | D14: murilo cRUZ | E14: 4100000 | G14: =(E14*M14)*(1+H14) -> 6000.4873 | H14: 0.035 | I14: =G14*(1-H14) -> 5790.4703 | J14: =G14-I14 -> 210.01706 | K14: 0.00138428 | L14: 0.0215 | M14: =K14*(1+L14) -> 0.001414042 | N14: =(I14*L14)+15 -> 139.49511 | O14: =(I14*M14)+L41 -> 8.1879683 | P14: =G14*1.2929 -> 7758.03 | Q14: 0.06 | S14: =(P14-G14)*0.2 -> 351.50855 | T14: =P14-(G14+S14)-(P14*R14) -> 1406.0342 | U14: =IFERROR((P14-G14)/G14,"") -> 0.2929 | V14: =IFERROR((P14-G14)/P14,"") -> 0.22654498 | W14: =IFERROR(T14/P14,"") -> 0.18123598
C15: PATRIG-001 | D15: Patricia Rigotto - renovacao votos | E15: 10145000 | G15: =(E15*M15)*(1+H15) -> 14847.547 | H15: 0.035 | I15: =G15*(1-H15) -> 14327.883 | J15: =G15-I15 -> 519.66415 | K15: 0.00138428 | L15: 0.0215 | M15: =K15*(1+L15) -> 0.001414042 | N15: =(I15*L15)+15 -> 323.04949 | O15: =(I15*M15)+L42 -> 20.260229 | P15: =G15*1.27 -> 18856.385 | Q15: 0.06 | S15: =(P15-G15)*0.2 -> 801.76755 | T15: =P15-(G15+S15)-(P15*R15) -> 3207.0702 | U15: =IFERROR((P15-G15)/G15,"") -> 0.27 | V15: =IFERROR((P15-G15)/P15,"") -> 0.21259843 | W15: =IFERROR(T15/P15,"") -> 0.17007874
C16: SENODA-001 | D16: Senhor Odair | E16: 5624000 | F16: 9864 | G16: =F16*(1+H16) -> 10209.24 | H16: 0.035 | I16: =G16*(1-H16) -> 9851.9166 | J16: =G16-I16 -> 357.3234 | K16: 0.00138428 | L16: 0.0215 | M16: =K16*(1+L16) -> 0.001414042 | N16: =(I16*L16)+15 -> 226.81621 | O16: =(I16*M16)+L43 -> 13.931024 | P16: =G16*1.7539 -> 17905.986 | Q16: 0.06 | S16: =(P16-G16)*0.2 -> 1539.3492 | T16: =P16-(G16+S16)-(P16*R16) -> 6157.3968 | U16: =IFERROR((P16-G16)/G16,"") -> 0.7539 | V16: =IFERROR((P16-G16)/P16,"") -> 0.42984207 | W16: =IFERROR(T16/P16,"") -> 0.34387365
C17: ANETUR-001 | D17: Anetur | E17: 12212000 | G17: =(E17*M17)*(1+H17) -> 17872.671 | H17: 0.035 | I17: =G17*(1-H17) -> 17247.127 | J17: =G17-I17 -> 625.54348 | K17: 0.00138428 | L17: 0.0215 | M17: =K17*(1+L17) -> 0.001414042 | N17: =(I17*L17)+15 -> 385.81324 | O17: =(I17*M17)+L44 -> 24.388163 | P17: =G17*1.51 -> 26987.733 | Q17: 0.06 | S17: =(P17-G17)*0.2 -> 1823.0124 | T17: =P17-(G17+S17)-(P17*R17) -> 7292.0498 | U17: =IFERROR((P17-G17)/G17,"") -> 0.51 | V17: =IFERROR((P17-G17)/P17,"") -> 0.33774834 | W17: =IFERROR(T17/P17,"") -> 0.27019868
C18: AMAANT-001 | D18: Amanda Antunes | E18: 7671000 | F18: 12094000 | G18: =(E18*M18)*(1+H18) -> 11226.765 | H18: 0.035 | I18: =G18*(1-H18) -> 10833.829 | J18: =G18-I18 -> 392.93679 | K18: 0.00138428 | L18: 0.0215 | M18: =K18*(1+L18) -> 0.001414042 | N18: =(I18*L18)+15 -> 247.92732 | O18: =(I18*M18)+L45 -> 15.319489 | P18: 16991 | Q18: 0.06 | S18: =(P18-G18)*0.2 -> 1152.8469 | T18: =P18-(G18+S18)-(P18*R18) -> 4611.3877 | U18: =IFERROR((P18-G18)/G18,"") -> 0.51343681 | V18: =IFERROR((P18-G18)/P18,"") -> 0.33925223 | W18: =IFERROR(T18/P18,"") -> 0.27140178
C19: ANAPIM-001 | D19: Ana Pimentel | E19: 4790000 | F19: 6795000 | G19: =(E19*M19)*(1+H19) -> 7010.3254 | H19: 0.035 | I19: =G19*(1-H19) -> 6764.964 | J19: =G19-I19 -> 245.36139 | K19: 0.00138428 | L19: 0.0215 | M19: =K19*(1+L19) -> 0.001414042 | N19: =(I19*L19)+15 -> 160.44673 | O19: =(I19*M19)+L47 -> 9.5659434 | P19: =(F19*M19)*(1+H19) -> 9944.7101 | Q19: 0.06 | S19: =(P19-G19)*0.2 -> 586.87693 | T19: =P19-(G19+S19)-(P19*R19) -> 2347.5077 | U19: =IFERROR((P19-G19)/G19,"") -> 0.41858038 | V19: =IFERROR((P19-G19)/P19,"") -> 0.2950699 | W19: =IFERROR(T19/P19,"") -> 0.23605592
C20: FERMEN-001 | D20: Fer Mendes | E20: 350000 | F20: 26860000 | G20: =(E20*M20)*(1+H20) -> 512.23672 | H20: 0.035 | I20: =G20*(1-H20) -> 494.30844 | J20: =G20-I20 -> 17.928285 | K20: 0.00138428 | L20: 0.0215 | M20: =K20*(1+L20) -> 0.001414042 | N20: =(I20*L20)+15 -> 25.627631 | O20: =(I20*M20)+L48 -> 0.6989729 | P20: =(F20*M20)*(1+H20) -> 39310.51 | Q20: 0.06 | S20: =(P20-G20)*0.2 -> 7759.6546 | T20: =P20-(G20+S20)-(P20*R20) -> 31038.618 | U20: =IFERROR((P20-G20)/G20,"") -> 75.742857 | V20: =IFERROR((P20-G20)/P20,"") -> 0.98696947 | W20: =IFERROR(T20/P20,"") -> 0.78957558
C21: FABCAS-001 | D21: FABIANA CASTERO | E21: 844000 | F21: 1200000 | G21: =(E21*M21)*(1+H21) -> 1235.2223 | H21: 0.035 | I21: =G21*(1-H21) -> 1191.9895 | J21: =G21-I21 -> 43.232779 | K21: 0.00138428 | L21: 0.0215 | M21: =K21*(1+L21) -> 0.001414042 | N21: =(I21*L21)+15 -> 40.627774 | O21: =(I21*M21)+L49 -> 1.6855232 | P21: =(F21*M21)*(1+H21) -> 1756.2402 | Q21: 0.06 | S21: =(P21-G21)*0.2 -> 104.20358 | T21: =P21-(G21+S21)-(P21*R21) -> 416.81434 | U21: =IFERROR((P21-G21)/G21,"") -> 0.42180095 | V21: =IFERROR((P21-G21)/P21,"") -> 0.29666667 | W21: =IFERROR(T21/P21,"") -> 0.23733333
C22: analuciacardoso001 | D22: ana lucia black friday | E22: 490000 | F22: =F582 -> 650000 | G22: =(E22*M22)*(1+H22) -> 717.13141 | H22: 0.035 | I22: =G22*(1-H22) -> 692.03181 | J22: =G22-I22 -> 25.099599 | K22: 0.00138428 | L22: 0.0215 | M22: =K22*(1+L22) -> 0.001414042 | N22: =(I22*L22)+15 -> 29.878684 | O22: =(I22*M22)+L49 -> 0.97856206 | P22: =(F22*M22)*(1+H22) -> 951.29677 | Q22: 0.06 | S22: =(P22-G22)*0.2 -> 46.833072 | T22: =P22-(G22+S22)-(P22*R22) -> 187.33229 | U22: =IFERROR((P22-G22)/G22,"") -> 0.32653061 | V22: =IFERROR((P22-G22)/P22,"") -> 0.24615385 | W22: =IFERROR(T22/P22,"") -> 0.19692308
C23: DINARY | D23: Dinary | E23: =E563 -> 5650000 | F23: =F563 -> 7710000 | G23: =(E23*M23)*(1+H23) -> 8268.9642 | H23: 0.035 | I23: =G23*(1-H23) -> 7979.5505 | J23: =G23-I23 -> 289.41375 | K23: 0.00138428 | L23: 0.0215 | M23: =K23*(1+L23) -> 0.001414042 | N23: =(I23*L23)+15 -> 186.56034 | O23: =(I23*M23)+L50 -> 11.28342 | P23: =(F23*M23)*(1+H23) -> 11283.843 | Q23: 0.06 | S23: =(P23-G23)*0.2 -> 602.9758 | T23: =P23-(G23+S23)-(P23*R23) -> 2411.9032 | U23: =IFERROR((P23-G23)/G23,"") -> 0.36460177 | V23: =IFERROR((P23-G23)/P23,"") -> 0.26718547 | W23: =IFERROR(T23/P23,"") -> 0.21374838
C24: GIULIA001 | D24: Giulia Morais | E24: 3462000 | F24: 4910000 | G24: =(E24*M24)*(1+H24) -> 5066.7529 | H24: 0.035 | I24: =G24*(1-H24) -> 4889.4166 | J24: =G24-I24 -> 177.33635 | K24: 0.00138428 | L24: 0.0215 | M24: =K24*(1+L24) -> 0.001414042 | N24: =(I24*L24)+15 -> 120.12246 | O24: =(I24*M24)+L50 -> 6.9138405 | P24: =(F24*M24)*(1+H24) -> 7185.9494 | Q24: 0.06 | S24: =(P24-G24)*0.2 -> 423.8393 | T24: =P24-(G24+S24)-(P24*R24) -> 1695.3572 | U24: =IFERROR((P24-G24)/G24,"") -> 0.41825534 | V24: =IFERROR((P24-G24)/P24,"") -> 0.29490835 | W24: =IFERROR(T24/P24,"") -> 0.23592668
C25: cha revelacao | E25: 2230000 | F25: 3700000 | G25: =(E25*M25)*(1+H25) -> 0
C26: FERMEN-001 | E26: 15736000 | F26: 23760000 | G26: =(E26*M26)*(1+H26) -> 23030.163 | H26: 0.035 | I26: =G26*(1-H26) -> 22224.107 | J26: =G26-I26 -> 806.05571 | K26: 0.00138428 | L26: 0.0215 | M26: =K26*(1+L26) -> 0.001414042 | N26: =(I26*L26)+15 -> 492.81831 | O26: =(I26*M26)+L51 -> 31.425822 | P26: =G26*1.664 -> 38322.191 | Q26: 0.06 | S26: =(P26-G26)*0.2 -> 3058.4056 | T26: =P26-(G26+S26)-(P26*R26) -> 12233.623 | U26: =IFERROR((P26-G26)/G26,"") -> 0.664 | V26: =IFERROR((P26-G26)/P26,"") -> 0.39903846 | W26: =IFERROR(T26/P26,"") -> 0.31923077
C27: FERMEN-002 | E27: 142500 | G27: =(E27*M27)*(1+H27) -> 208.55352 | H27: 0.035 | I27: =G27*(1-H27) -> 201.25415 | J27: =G27-I27 -> 7.2993733 | K27: 0.00138428 | L27: 0.0215 | M27: =K27*(1+L27) -> 0.001414042 | N27: =(I27*L27)+15 -> 19.326964 | O27: =(I27*M27)+L52 -> 0.28458182 | P27: =G27*1.664 -> 347.03306 | Q27: 0.06 | S27: =(P27-G27)*0.2 -> 27.695908 | T27: =P27-(G27+S27)-(P27*R27) -> 110.78363 | U27: =IFERROR((P27-G27)/G27,"") -> 0.664 | V27: =IFERROR((P27-G27)/P27,"") -> 0.39903846 | W27: =IFERROR(T27/P27,"") -> 0.31923077
G28: =(E28*M28)*(1+H28) -> 0 | H28: 0.035 | I28: =G28*(1-H28) -> 0 | J28: =G28-I28 -> 0 | K28: 0.00138428 | L28: 0.0215 | M28: =K28*(1+L28) -> 0.001414042 | N28: =(I28*L28)+15 -> 15 | O28: =(I28*M28)+L53 -> 0 | P28: =G28*1.664 -> 0 | Q28: 0.06 | S28: =(P28-G28)*0.2 -> 0 | T28: =P28-(G28+S28)-(P28*R28) -> 0 | U28: =IFERROR((P28-G28)/G28,"") | V28: =IFERROR((P28-G28)/P28,"") | W28: =IFERROR(T28/P28,"")
P29: =G29*1.664 -> 0 | T29: =P29-(G29+S29)-(P29*R29) -> 0 | U29: =IFERROR((P29-G29)/G29,"") | V29: =IFERROR((P29-G29)/P29,"") | W29: =IFERROR(T29/P29,"")
C30: ana caludia | D30: 12 pax | E30: 180000 | F30: 300000 | G30: =(E30*M30)*(1+H30) -> 282.46657 | H30: 0.035 | I30: =G30*(1-H30) -> 272.58024 | J30: =G30-I30 -> 9.8863301 | K30: 0.00148428 | L30: 0.0215 | M30: =K30*(1+L30) -> 0.001516192 | N30: =(I30*L30)+15 -> 20.860475 | O30: =(I30*M30)+L50 -> 0.41328399 | P30: =G30*1.664 -> 470.02438 | Q30: 0.06 | S30: =(P30-G30)*0.2 -> 37.511561 | T30: =P30-(G30+S30)-(P30*R30) -> 150.04624 | U30: =IFERROR((P30-G30)/G30,"") -> 0.664 | V30: =IFERROR((P30-G30)/P30,"") -> 0.39903846 | W30: =IFERROR(T30/P30,"") -> 0.31923077
C31: brielly10 | D31: 12 pax | E31: =E792 -> 6600000 | F31: =F792 -> 9050000 | G31: =(E31*M31)*(1+H31) -> 9659.321 | H31: 0.035 | I31: =G31*(1-H31) -> 9321.2448 | J31: =G31-I31 -> 338.07624 | K31: 0.00138428 | L31: 0.0215 | M31: =K31*(1+L31) -> 0.001414042 | N31: =(I31*L31)+15 -> 215.40676 | O31: =(I31*M31)+L51 -> 13.180632 | P31: =G31*1.664 -> 16073.11 | Q31: 0.06 | S31: =(P31-G31)*0.2 -> 1282.7578 | T31: =P31-(G31+S31)-(P31*R31) -> 5131.0313 | U31: =IFERROR((P31-G31)/G31,"") -> 0.664 | V31: =IFERROR((P31-G31)/P31,"") -> 0.39903846 | W31: =IFERROR(T31/P31,"") -> 0.31923077
C32: alice | D32: Mínimo 15 e máximo 23 pagantes + 1 TC free | E32: 2928400 | F32: 3810000 | G32: =(E32*M32)*(1+H32) -> 4285.8115 | H32: 0.035 | I32: =G32*(1-H32) -> 4135.8081 | J32: =G32-I32 -> 150.0034 | K32: 0.00138428 | L32: 0.0215 | M32: =K32*(1+L32) -> 0.001414042 | N32: =(I32*L32)+15 -> 103.91987 | O32: =(I32*M32)+L52 -> 5.8482064 | P32: =G32*1.664 -> 7131.5903 | Q32: 0.06 | S32: =(P32-G32)*0.2 -> 569.15576 | T32: =P32-(G32+S32)-(P32*R32) -> 2276.6231 | U32: =IFERROR((P32-G32)/G32,"") -> 0.664 | V32: =IFERROR((P32-G32)/P32,"") -> 0.39903846 | W32: =IFERROR(T32/P32,"") -> 0.31923077
C33: giselerodrigues001 | D33: 2 pax | E33: =E618 -> 1648000 | F33: =F618 -> 2360000 | G33: =(E33*M33)*(1+H33) -> 2411.9032 | H33: 0.035 | I33: =G33*(1-H33) -> 2327.4866 | J33: =G33-I33 -> 84.416612 | K33: 0.00138428 | L33: 0.0215 | M33: =K33*(1+L33) -> 0.001414042 | N33: =(I33*L33)+15 -> 65.040961 | O33: =(I33*M33)+L53 -> 3.2911638 | P33: =G33*1.664 -> 4013.4069 | Q33: 0.06 | S33: =(P33-G33)*0.2 -> 320.30074 | T33: =P33-(G33+S33)-(P33*R33) -> 1281.203 | U33: =IFERROR((P33-G33)/G33,"") -> 0.664 | V33: =IFERROR((P33-G33)/P33,"") -> 0.39903846 | W33: =IFERROR(T33/P33,"") -> 0.31923077
T34: =P34-(G34+S34)-(P34*R34) -> 0 | U34: =IFERROR((P34-G34)/G34,"") | V34: =IFERROR((P34-G34)/P34,"") | W34: =IFERROR(T34/P34,"")
E35: Valor de Custo(COP) | F35: Valor de venda(COP) | G35: Markup | H35: comissao | T35: =P35-(G35+S35)-(P35*R35) -> #VALUE! | U35: =IFERROR((P35-G35)/G35,"") | V35: =IFERROR((P35-G35)/P35,"") | W35: =IFERROR(T35/P35,"")
C36: Veleiro 5 pessoas - Lancha | D36: Transfer in | E36: 170000 | F36: 350000 | G36: =F36/E36 -> 2.0588235 | T36: =P36-(G36+S36)-(P36*R36) -> -2.0588235 | U36: =IFERROR((P36-G36)/G36,"") -> -1 | V36: =IFERROR((P36-G36)/P36,"") | W36: =IFERROR(T36/P36,"")
D37: Guia | E37: 600000 | F37: =400000*5 -> 2000000 | G37: =F37/E37 -> 3.3333333 | T37: =P37-(G37+S37)-(P37*R37) -> -3.3333333 | U37: =IFERROR((P37-G37)/G37,"") -> -1 | V37: =IFERROR((P37-G37)/P37,"") | W37: =IFERROR(T37/P37,"")
D38: Castelo | E38: =36000*5 -> 180000 | G38: =F38/E38 -> 0 | T38: =P38-(G38+S38)-(P38*R38) -> 0 | U38: =IFERROR((P38-G38)/G38,"") | V38: =IFERROR((P38-G38)/P38,"") | W38: =IFERROR(T38/P38,"")
D39: Carro 4 horas | E39: 350000 | G39: =F39/E39 -> 0 | T39: =P39-(G39+S39)-(P39*R39) -> 0 | U39: =IFERROR((P39-G39)/G39,"") | V39: =IFERROR((P39-G39)/P39,"") | W39: =IFERROR(T39/P39,"")
D40: água | E40: 50000 | G40: =F40/E40 -> 0 | T40: =P40-(G40+S40)-(P40*R40) -> 0 | U40: =IFERROR((P40-G40)/G40,"") | V40: =IFERROR((P40-G40)/P40,"") | W40: =IFERROR(T40/P40,"")
D41: Lancha | E41: 4075050 | F41: =E41*1.51 -> 6153325.5 | G41: =F41/E41 -> 1.51 | T41: =P41-(G41+S41)-(P41*R41) -> -1.51 | U41: =IFERROR((P41-G41)/G41,"") -> -1 | V41: =IFERROR((P41-G41)/P41,"") | W41: =IFERROR(T41/P41,"")
D42: sibarita | E42: =110000*5 -> 550000 | F42: =250000*5 -> 1250000 | G42: =F42/E42 -> 2.2727273 | T42: =P42-(G42+S42)-(P42*R42) -> -2.2727273 | U42: =IFERROR((P42-G42)/G42,"") -> -1 | V42: =IFERROR((P42-G42)/P42,"") | W42: =IFERROR(T42/P42,"")
D43: Parada Capri | E43: =50000*5 -> 250000 | F43: 600000 | G43: =F43/E43 -> 2.4 | T43: =P43-(G43+S43)-(P43*R43) -> -2.4 | U43: =IFERROR((P43-G43)/G43,"") -> -1 | V43: =IFERROR((P43-G43)/P43,"") | W43: =IFERROR(T43/P43,"")
D44: Transfer out | E44: 170000 | F44: 350000 | G44: =F44/E44 -> 2.0588235 | T44: =P44-(G44+S44)-(P44*R44) -> -2.0588235 | U44: =IFERROR((P44-G44)/G44,"") -> -1 | V44: =IFERROR((P44-G44)/P44,"") | W44: =IFERROR(T44/P44,"")
D45: Total | E45: 6395050 | F45: =SUM(F36,F37,F41,F42,F43,F44) -> 10703326 | G45: =F45/E45 -> 1.6736891 | T45: =P45-(G45+S45)-(P45*R45) -> -1.6736891 | U45: =IFERROR((P45-G45)/G45,"") -> -1 | V45: =IFERROR((P45-G45)/P45,"") | W45: =IFERROR(T45/P45,"")
T46: =P46-(G46+S46)-(P46*R46) -> 0 | U46: =IFERROR((P46-G46)/G46,"") | V46: =IFERROR((P46-G46)/P46,"") | W46: =IFERROR(T46/P46,"")
C47: Veleiro 5 pessoas - capri regular | D47: Transfer in | E47: 170000 | F47: 350000 | G47: =F47/E47 -> 2.0588235 | T47: =P47-(G47+S47)-(P47*R47) -> -2.0588235 | U47: =IFERROR((P47-G47)/G47,"") -> -1 | V47: =IFERROR((P47-G47)/P47,"") | W47: =IFERROR(T47/P47,"")
D48: Guia | E48: 600000 | F48: =400000*5 -> 2000000 | G48: =F48/E48 -> 3.3333333 | T48: =P48-(G48+S48)-(P48*R48) -> -3.3333333 | U48: =IFERROR((P48-G48)/G48,"") -> -1 | V48: =IFERROR((P48-G48)/P48,"") | W48: =IFERROR(T48/P48,"")
D49: Castelo | E49: =36000*5 -> 180000 | G49: =F49/E49 -> 0 | T49: =P49-(G49+S49)-(P49*R49) -> 0 | U49: =IFERROR((P49-G49)/G49,"") | V49: =IFERROR((P49-G49)/P49,"") | W49: =IFERROR(T49/P49,"")
D50: Carro 4 horas | E50: 350000 | G50: =F50/E50 -> 0 | T50: =P50-(G50+S50)-(P50*R50) -> 0 | U50: =IFERROR((P50-G50)/G50,"") | V50: =IFERROR((P50-G50)/P50,"") | W50: =IFERROR(T50/P50,"")
D51: água | E51: 50000 | G51: =F51/E51 -> 0 | T51: =P51-(G51+S51)-(P51*R51) -> 0 | U51: =IFERROR((P51-G51)/G51,"") | V51: =IFERROR((P51-G51)/P51,"") | W51: =IFERROR(T51/P51,"")
D52: Lancha | G52: =F52/E52 -> #DIV/0! | T52: =P52-(G52+S52)-(P52*R52) -> #DIV/0! | U52: =IFERROR((P52-G52)/G52,"") | V52: =IFERROR((P52-G52)/P52,"") | W52: =IFERROR(T52/P52,"")
D53: sibarita | E53: =110000*5 -> 550000 | F53: =250000*5 -> 1250000 | G53: =F53/E53 -> 2.2727273 | T53: =P53-(G53+S53)-(P53*R53) -> -2.2727273 | U53: =IFERROR((P53-G53)/G53,"") -> -1 | V53: =IFERROR((P53-G53)/P53,"") | W53: =IFERROR(T53/P53,"")
D54: Capri | E54: =330000*5 -> 1650000 | F54: =510000*5 -> 2550000 | G54: =F54/E54 -> 1.5454545 | L54: 0.0565 | M54: IOF+ Spread | T54: =P54-(G54+S54)-(P54*R54) -> -1.5454545 | U54: =IFERROR((P54-G54)/G54,"") -> -1 | V54: =IFERROR((P54-G54)/P54,"") | W54: =IFERROR(T54/P54,"")
D55: Transfer out | E55: 170000 | F55: 350000 | G55: =F55/E55 -> 2.0588235 | T55: =P55-(G55+S55)-(P55*R55) -> -2.0588235 | U55: =IFERROR((P55-G55)/G55,"") -> -1 | V55: =IFERROR((P55-G55)/P55,"") | W55: =IFERROR(T55/P55,"")
D56: Total | E56: =SUM(E47:E55) -> 3720000 | F56: =SUM(F47:F55) -> 6500000 | G56: =F56/E56 -> 1.7473118 | L56: 10031.78 | M56: tarifa fixa por transação na Colômbia | T56: =P56-(G56+S56)-(P56*R56) -> -1.7473118 | U56: =IFERROR((P56-G56)/G56,"") -> -1 | V56: =IFERROR((P56-G56)/P56,"") | W56: =IFERROR(T56/P56,"")
L57: INTER>> ITAU>> WISE>> COLÔMBIA | T57: =P57-(G57+S57)-(P57*R57) -> 0 | U57: =IFERROR((P57-G57)/G57,"") | V57: =IFERROR((P57-G57)/P57,"") | W57: =IFERROR(T57/P57,"")
C58: 8 pessoas - Debora Carvalho - Regular | D58: Transfer in e out | E58: =170000*2 -> 340000 | F58: =700000 -> 700000 | G58: =(F58-E58)/E58 -> 1.0588235 | T58: =P58-(G58+S58)-(P58*R58) -> -1.0588235 | U58: =IFERROR((P58-G58)/G58,"") -> -1 | V58: =IFERROR((P58-G58)/P58,"") | W58: =IFERROR(T58/P58,"")
D59: Guia | E59: 1368000 | F59: =E59*1.75 -> 2394000 | G59: =(F59-E59)/E59 -> 0.75 | T59: =P59-(G59+S59)-(P59*R59) -> -0.75 | U59: =IFERROR((P59-G59)/G59,"") -> -1 | V59: =IFERROR((P59-G59)/P59,"") | W59: =IFERROR(T59/P59,"")
D60: Castelo | T60: =P60-(G60+S60)-(P60*R60) -> 0 | U60: =IFERROR((P60-G60)/G60,"") | V60: =IFERROR((P60-G60)/P60,"") | W60: =IFERROR(T60/P60,"")
D61: van 14 pax | T61: =P61-(G61+S61)-(P61*R61) -> 0 | U61: =IFERROR((P61-G61)/G61,"") | V61: =IFERROR((P61-G61)/P61,"") | W61: =IFERROR(T61/P61,"")
D62: água | T62: =P62-(G62+S62)-(P62*R62) -> 0 | U62: =IFERROR((P62-G62)/G62,"") | V62: =IFERROR((P62-G62)/P62,"") | W62: =IFERROR(T62/P62,"")
D63: Sibarita | E63: =110000*8 -> 880000 | F63: =230000*8 -> 1840000 | G63: =(F63-E63)/E63 -> 1.0909091 | T63: =P63-(G63+S63)-(P63*R63) -> -1.0909091 | U63: =IFERROR((P63-G63)/G63,"") -> -1 | V63: =IFERROR((P63-G63)/P63,"") | W63: =IFERROR(T63/P63,"")
D64: Rosário del mar | E64: =280000*8 -> 2240000 | F64: =430000*8 -> 3440000 | G64: =(F64-E64)/E64 -> 0.53571429 | T64: =P64-(G64+S64)-(P64*R64) -> -0.53571429 | U64: =IFERROR((P64-G64)/G64,"") -> -1 | V64: =IFERROR((P64-G64)/P64,"") | W64: =IFERROR(T64/P64,"")
D65: Jantar Ilha | E65: =275000*8 -> 2200000 | F65: =320000*8 -> 2560000 | G65: =(F65-E65)/E65 -> 0.16363636 | T65: =P65-(G65+S65)-(P65*R65) -> -0.16363636 | U65: =IFERROR((P65-G65)/G65,"") -> -1 | V65: =IFERROR((P65-G65)/P65,"") | W65: =IFERROR(T65/P65,"")
D66: Macani | E66: =309000*8 -> 2472000 | F66: =430000*8 -> 3440000 | G66: =(F66-E66)/E66 -> 0.39158576 | T66: =P66-(G66+S66)-(P66*R66) -> -0.39158576 | U66: =IFERROR((P66-G66)/G66,"") -> -1 | V66: =IFERROR((P66-G66)/P66,"") | W66: =IFERROR(T66/P66,"")
D67: Capri | E67: =330000*8 -> 2640000 | F67: =490000*8 -> 3920000 | G67: =(F67-E67)/E67 -> 0.48484848 | T67: =P67-(G67+S67)-(P67*R67) -> -0.48484848 | U67: =IFERROR((P67-G67)/G67,"") -> -1 | V67: =IFERROR((P67-G67)/P67,"") | W67: =IFERROR(T67/P67,"")
D68: total | E68: =SUM(E58:E67) -> 12140000 | F68: =SUM(F58:F67) -> 18294000 | G68: =(F68-E68)/E68 -> 0.50691928 | T68: =P68-(G68+S68)-(P68*R68) -> -0.50691928 | U68: =IFERROR((P68-G68)/G68,"") -> -1 | V68: =IFERROR((P68-G68)/P68,"") | W68: =IFERROR(T68/P68,"")
F69: =IFERROR((#REF!-#REF!)/#REF!,"") | T69: =P69-(G69+S69)-(P69*R69) -> 0 | U69: =IFERROR((P69-G69)/G69,"") | V69: =IFERROR((P69-G69)/P69,"") | W69: =IFERROR(T69/P69,"")
C70: 8 pessoas - Debora Carvalho - Lancha | D70: Transfer in e out | E70: =170000*2 -> 340000 | F70: =700000 -> 700000 | G70: =(F70-E70)/E70 -> 1.0588235 | T70: =P70-(G70+S70)-(P70*R70) -> -1.0588235 | U70: =IFERROR((P70-G70)/G70,"") -> -1 | V70: =IFERROR((P70-G70)/P70,"") | W70: =IFERROR(T70/P70,"")
D71: Guia | E71: 1368000 | F71: =E71*1.75 -> 2394000 | G71: =(F71-E71)/E71 -> 0.75 | T71: =P71-(G71+S71)-(P71*R71) -> -0.75 | U71: =IFERROR((P71-G71)/G71,"") -> -1 | V71: =IFERROR((P71-G71)/P71,"") | W71: =IFERROR(T71/P71,"")
D72: Castelo | T72: =P72-(G72+S72)-(P72*R72) -> 0 | U72: =IFERROR((P72-G72)/G72,"") | V72: =IFERROR((P72-G72)/P72,"") | W72: =IFERROR(T72/P72,"")
D73: van 14 pax | T73: =P73-(G73+S73)-(P73*R73) -> 0 | U73: =IFERROR((P73-G73)/G73,"") | V73: =IFERROR((P73-G73)/P73,"") | W73: =IFERROR(T73/P73,"")
D74: água | T74: =P74-(G74+S74)-(P74*R74) -> 0 | U74: =IFERROR((P74-G74)/G74,"") | V74: =IFERROR((P74-G74)/P74,"") | W74: =IFERROR(T74/P74,"")
D75: Sibarita | E75: =110000*8 -> 880000 | F75: =230000*8 -> 1840000 | G75: =(F75-E75)/E75 -> 1.0909091 | T75: =P75-(G75+S75)-(P75*R75) -> -1.0909091 | U75: =IFERROR((P75-G75)/G75,"") -> -1 | V75: =IFERROR((P75-G75)/P75,"") | W75: =IFERROR(T75/P75,"")
D76: Rosário del mar | E76: =280000*8 -> 2240000 | F76: =430000*8 -> 3440000 | G76: =(F76-E76)/E76 -> 0.53571429 | T76: =P76-(G76+S76)-(P76*R76) -> -0.53571429 | U76: =IFERROR((P76-G76)/G76,"") -> -1 | V76: =IFERROR((P76-G76)/P76,"") | W76: =IFERROR(T76/P76,"")
D77: Jantar Ilha | E77: =275000*8 -> 2200000 | F77: =320000*8 -> 2560000 | G77: =(F77-E77)/E77 -> 0.16363636 | T77: =P77-(G77+S77)-(P77*R77) -> -0.16363636 | U77: =IFERROR((P77-G77)/G77,"") -> -1 | V77: =IFERROR((P77-G77)/P77,"") | W77: =IFERROR(T77/P77,"")
D78: Macani | E78: =309000*8 -> 2472000 | F78: =430000*8 -> 3440000 | G78: =(F78-E78)/E78 -> 0.39158576 | T78: =P78-(G78+S78)-(P78*R78) -> -0.39158576 | U78: =IFERROR((P78-G78)/G78,"") -> -1 | V78: =IFERROR((P78-G78)/P78,"") | W78: =IFERROR(T78/P78,"")
D79: Lancha Privada | E79: 2940000 | F79: =E79*1.5 -> 4410000 | G79: =(F79-E79)/E79 -> 0.5 | T79: =P79-(G79+S79)-(P79*R79) -> -0.5 | U79: =IFERROR((P79-G79)/G79,"") -> -1 | V79: =IFERROR((P79-G79)/P79,"") | W79: =IFERROR(T79/P79,"")
D80: Parada em Capri | E80: =50000*8 -> 400000 | F80: =E80*1.51 -> 604000 | G80: =(F80-E80)/E80 -> 0.51 | T80: =P80-(G80+S80)-(P80*R80) -> -0.51 | U80: =IFERROR((P80-G80)/G80,"") -> -1 | V80: =IFERROR((P80-G80)/P80,"") | W80: =IFERROR(T80/P80,"")
D81: total | E81: =SUM(E70:E80) -> 12840000 | F81: =SUM(F70:F80) -> 19388000 | G81: =(F81-E81)/E81 -> 0.50996885 | T81: =P81-(G81+S81)-(P81*R81) -> -0.50996885 | U81: =IFERROR((P81-G81)/G81,"") -> -1 | V81: =IFERROR((P81-G81)/P81,"") | W81: =IFERROR(T81/P81,"")
H82: comissao tet | I82: valor por pax | T82: =P82-(G82+S82)-(P82*R82) -> 0 | U82: =IFERROR((P82-G82)/G82,"") | V82: =IFERROR((P82-G82)/P82,"") | W82: =IFERROR(T82/P82,"")
D83: Walking tour 1 | E83: =300000+36000+30000+10000 -> 376000 | F83: =E83*1.3 -> 488800 | G83: =(F83-E83)/E83 -> 0.3 | H83: =F83-E83 -> 112800 | I83: 500000 | T83: =P83-(G83+S83)-(P83*R83) -> -0.3 | U83: =IFERROR((P83-G83)/G83,"") -> -1 | V83: =IFERROR((P83-G83)/P83,"") | W83: =IFERROR(T83/P83,"")
D84: Walking tour 2 | E84: =300000+(36000*2)+30000+(10000*2) -> 422000 | F84: =E84*1.5 -> 633000 | G84: =(F84-E84)/E84 -> 0.5 | H84: =F84-E84 -> 211000 | I84: 325000 | T84: =P84-(G84+S84)-(P84*R84) -> -0.5 | U84: =IFERROR((P84-G84)/G84,"") -> -1 | V84: =IFERROR((P84-G84)/P84,"") | W84: =IFERROR(T84/P84,"")
D85: Walking tour 3 | E85: =400000+(36000*3)+30000+(10000*3) -> 568000 | F85: =E85*1.5 -> 852000 | G85: =(F85-E85)/E85 -> 0.5 | H85: =F85-E85 -> 284000 | I85: 300000 | T85: =P85-(G85+S85)-(P85*R85) -> -0.5 | U85: =IFERROR((P85-G85)/G85,"") -> -1 | V85: =IFERROR((P85-G85)/P85,"") | W85: =IFERROR(T85/P85,"")
D86: Walking tour 4 | E86: =600000+(36000*4)+240000+(10000*4) -> 1024000 | F86: =E86*1.3 -> 1331200 | G86: =(F86-E86)/E86 -> 0.3 | H86: =F86-E86 -> 307200 | I86: 330000 | T86: =P86-(G86+S86)-(P86*R86) -> -0.3 | U86: =IFERROR((P86-G86)/G86,"") -> -1 | V86: =IFERROR((P86-G86)/P86,"") | W86: =IFERROR(T86/P86,"")
D87: Walking tour 5 | E87: =600000+(36000*5)+350000+(10000*5) -> 1180000 | F87: =E87*1.3 -> 1534000 | G87: =(F87-E87)/E87 -> 0.3 | H87: =F87-E87 -> 354000 | I87: 310000 | T87: =P87-(G87+S87)-(P87*R87) -> -0.3 | U87: =IFERROR((P87-G87)/G87,"") -> -1 | V87: =IFERROR((P87-G87)/P87,"") | W87: =IFERROR(T87/P87,"")
D88: Walking tour 6 | E88: =600000+(36000*6)+350000+(10000*6) -> 1226000 | F88: =E88*1.5 -> 1839000 | G88: =(F88-E88)/E88 -> 0.5 | H88: =F88-E88 -> 613000 | I88: 310000 | T88: =P88-(G88+S88)-(P88*R88) -> -0.5 | U88: =IFERROR((P88-G88)/G88,"") -> -1 | V88: =IFERROR((P88-G88)/P88,"") | W88: =IFERROR(T88/P88,"")
D89: Walking tour 7 | E89: =600000+(36000*7)+350000+(10000*7) -> 1272000 | F89: =E89*1.51 -> 1920720 | G89: =(F89-E89)/E89 -> 0.51 | H89: =F89-E89 -> 648720 | I89: =F89/7 -> 274388.57 | T89: =P89-(G89+S89)-(P89*R89) -> -0.51 | U89: =IFERROR((P89-G89)/G89,"") -> -1 | V89: =IFERROR((P89-G89)/P89,"") | W89: =IFERROR(T89/P89,"")
D90: Walking tour 8 | E90: =600000+(36000*8)+400000+(10000*8) -> 1368000 | F90: =E90*1.51 -> 2065680 | G90: =(F90-E90)/E90 -> 0.51 | H90: =F90-E90 -> 697680 | I90: =F90/8 -> 258210 | T90: =P90-(G90+S90)-(P90*R90) -> -0.51 | U90: =IFERROR((P90-G90)/G90,"") -> -1 | V90: =IFERROR((P90-G90)/P90,"") | W90: =IFERROR(T90/P90,"")
D91: Walking tour 9 | E91: =600000+(36000*9)+400000+(10000*9) -> 1414000 | F91: =E91*1.51 -> 2135140 | G91: =(F91-E91)/E91 -> 0.51 | H91: =F91-E91 -> 721140 | I91: =F91/9 -> 237237.78 | T91: =P91-(G91+S91)-(P91*R91) -> -0.51 | U91: =IFERROR((P91-G91)/G91,"") -> -1 | V91: =IFERROR((P91-G91)/P91,"") | W91: =IFERROR(T91/P91,"")
D92: Walking tour 10 | E92: =600000+(36000*10)+400000+(10000*10) -> 1460000 | F92: =E92*1.75 -> 2555000 | G92: =(F92-E92)/E92 -> 0.75 | H92: =F92-E92 -> 1095000 | I92: =F92/10 -> 255500 | T92: =P92-(G92+S92)-(P92*R92) -> -0.75 | U92: =IFERROR((P92-G92)/G92,"") -> -1 | V92: =IFERROR((P92-G92)/P92,"") | W92: =IFERROR(T92/P92,"")
D93: Walking tour 11 | E93: =900000+(36000*11)+400000+(10000*11) -> 1806000 | F93: =E93*1.75 -> 3160500 | G93: =(F93-E93)/E93 -> 0.75 | H93: =F93-E93 -> 1354500 | I93: =F93/11 -> 287318.18 | T93: =P93-(G93+S93)-(P93*R93) -> -0.75 | U93: =IFERROR((P93-G93)/G93,"") -> -1 | V93: =IFERROR((P93-G93)/P93,"") | W93: =IFERROR(T93/P93,"")
D94: Walking tour 12 | E94: =900000+(36000*12)+400000+(10000*12) -> 1852000 | F94: =E94*1.75 -> 3241000 | G94: =(F94-E94)/E94 -> 0.75 | H94: =F94-E94 -> 1389000 | I94: =F94/12 -> 270083.33 | T94: =P94-(G94+S94)-(P94*R94) -> -0.75 | U94: =IFERROR((P94-G94)/G94,"") -> -1 | V94: =IFERROR((P94-G94)/P94,"") | W94: =IFERROR(T94/P94,"")
T95: =P95-(G95+S95)-(P95*R95) -> 0 | U95: =IFERROR((P95-G95)/G95,"") | V95: =IFERROR((P95-G95)/P95,"") | W95: =IFERROR(T95/P95,"")
C96: Clube do livro | D96: Transfer in e out | E96: =200000*2 -> 400000 | F96: =1200000 -> 1200000 | G96: =(F96-E96)/E96 -> 2 | T96: =P96-(G96+S96)-(P96*R96) -> -2 | U96: =IFERROR((P96-G96)/G96,"") -> -1 | V96: =IFERROR((P96-G96)/P96,"") | W96: =IFERROR(T96/P96,"")
D97: Guia | E97: =900000+(36000*12)+400000+(10000*12) -> 1852000 | F97: =E97*1.75 -> 3241000 | G97: =(F97-E97)/E97 -> 0.75 | T97: =P97-(G97+S97)-(P97*R97) -> -0.75 | U97: =IFERROR((P97-G97)/G97,"") -> -1 | V97: =IFERROR((P97-G97)/P97,"") | W97: =IFERROR(T97/P97,"")
D98: Passeio | E98: =10000*12+500000 -> 620000 | F98: =E98*1.75 -> 1085000 | G98: =(F98-E98)/E98 -> 0.75 | T98: =P98-(G98+S98)-(P98*R98) -> -0.75 | U98: =IFERROR((P98-G98)/G98,"") -> -1 | V98: =IFERROR((P98-G98)/P98,"") | W98: =IFERROR(T98/P98,"")
D99: Sibarita | E99: =110000*12 -> 1320000 | F99: =230000*12 -> 2760000 | G99: =(F99-E99)/E99 -> 1.0909091 | T99: =P99-(G99+S99)-(P99*R99) -> -1.0909091 | U99: =IFERROR((P99-G99)/G99,"") -> -1 | V99: =IFERROR((P99-G99)/P99,"") | W99: =IFERROR(T99/P99,"")
D100: Lancha Privada | E100: 3415280 | F100: =E100*1.51 -> 5157072.8 | G100: =(F100-E100)/E100 -> 0.51 | T100: =P100-(G100+S100)-(P100*R100) -> -0.51 | U100: =IFERROR((P100-G100)/G100,"") -> -1 | V100: =IFERROR((P100-G100)/P100,"") | W100: =IFERROR(T100/P100,"")
...

Sheet Precificação por Produto
E2: Precificação | X2: Formatos de visualização | AA2: Pesquisa | AE2: Histórico de vendas
A3: DATA da Cotação | B3: Código | C3: Passeio | D3: Descrição | E3: Preço custo (COP) | F3: Valor de venda (COP) | G3: Quantidade de pessoas | H3: Preço custo (BRL) | I3: IOF | J3: Valor após IOF | K3: Valor de IOF Bruto | L3: Cotação COP | M3: Spread | N3: Cotação Real | O3: Valor SPREAD BRUTO | P3: Custo Convertido (US) | Q3: Preço de venda | R3: Simples Nacional (%) | S3: Outros custos diretos (%) | T3: ENTRADA | V3: Comissão Jadhe (R$) | W3: Margem bruta | X3: MARKUP | Y3: MARKDOWN | Z3: CLD | AA3: Pesquisa 1 | AB3: Pesquisa 2 | AC3: Pesquisa 3 | AD3: Estabelecimento | AE3: Custo 2025 | AF3: Mês 2 | AG3: Mês 3 | AH3: Média venda mensal | AI3: Vendas acumuladas
A4: Bogotá BOG PASS | T4: =F4-E4 -> 0
T5: =F5-E5 -> 0
A6: 2026 | C6: city tour imperdíveis - manhã | D6: Regular | E6: 119200 | F6: 300000 | G6: 1 | H6: =((E6*N6)*(1+I6))*G6 -> 176.05622 | I6: 0.035 | J6: =H6*(1-I6) -> 169.89426 | K6: =H6-J6 -> 6.1619678 | L6: 0.001397 | M6: 0.0215 | N6: =L6*(1+M6) -> 0.0014270355 | O6: =(J6*M6)+15 -> 18.652726 | P6: =(J6*N6)+M6 -> 0.26394513 | Q6: =((F6*N6)*(1+I6))*G6 -> 443.09452 | R6: 0.06 | T6: =F6-E6 -> 180800 | U6: =T6*(1-I6-M6) -> 170584.8 | V6: =(F6-E6)*0.2 -> 36160 | W6: =(F6*(1-I6-M6)-(E6+V6)-(F6*S6)-(F6*R6)) -> 109690 | X6: =IFERROR((F6-E6)/E6,"") -> 1.5167785 | Y6: =IFERROR((Q6-H6)/Q6,"") -> 0.60266667 | Z6: =IFERROR(W6/F6,"") -> 0.36563333
A7: 2026 | C7: city tour bairros inconicos - tarde | D7: Regular | E7: 119200 | F7: 300000 | G7: 1 | H7: =((E7*N7)*(1+I7))*G7 -> 176.05622 | I7: 0.035 | J7: =H7*(1-I7) -> 169.89426 | K7: =H7-J7 -> 6.1619678 | L7: 0.001397 | M7: 0.0215 | N7: =L7*(1+M7) -> 0.0014270355 | O7: =(J7*M7)+15 -> 18.652726 | P7: =(J7*N7)+M7 -> 0.26394513 | Q7: =((F7*N7)*(1+I7))*G7 -> 443.09452 | R7: 0.06 | T7: =F7-E7 -> 180800 | U7: =T7*(1-I7-M7) -> 170584.8 | V7: =(F7-E7)*0.2 -> 36160 | W7: =F7-(E7+V7)-(F7*S7)-(F7*R7) -> 126640 | X7: =IFERROR((F7-E7)/E7,"") -> 1.5167785 | Y7: =IFERROR((Q7-H7)/Q7,"") -> 0.60266667 | Z7: =IFERROR(W7/F7,"") -> 0.42213333
A8: 2026 | C8: Catedral de Sal (BOG PASS) | D8: Regular | E8: 263200 | F8: 380000 | G8: 1 | H8: =((E8*N8)*(1+I8))*G8 -> 388.74159 | I8: 0.035 | J8: =H8*(1-I8) -> 375.13564 | K8: =H8-J8 -> 13.605956 | L8: 0.001397 | M8: 0.0215 | N8: =L8*(1+M8) -> 0.0014270355 | O8: =(J8*M8)+15 -> 23.065416 | P8: =(J8*N8)+M8 -> 0.55683187 | Q8: =((F8*N8)*(1+I8))*G8 -> 561.25306 | R8: 0.06 | T8: =F8-E8 -> 116800 | U8: =T8*(1-I8-M8) -> 110200.8 | V8: =(F8-E8)*0.2 -> 23360 | W8: =F8-(E8+V8)-(F8*S8)-(F8*R8) -> 70640 | X8: =IFERROR((F8-E8)/E8,"") -> 0.443769 | Y8: =IFERROR((Q8-H8)/Q8,"") -> 0.30736842 | Z8: =IFERROR(W8/F8,"") -> 0.18589474
A9: 2026 | C9: Catedral de Sal + Guatavita (BOG PASS) | D9: Regular | E9: 343200 | F9: 600000 | G9: 1 | H9: =((E9*N9)*(1+I9))*G9 -> 506.90013 | I9: 0.035 | J9: =H9*(1-I9) -> 489.15863 | K9: =H9-J9 -> 17.741505 | L9: 0.001397 | M9: 0.0215 | N9: =L9*(1+M9) -> 0.0014270355 | O9: =(J9*M9)+15 -> 25.516911 | P9: =(J9*N9)+M9 -> 0.71954673 | Q9: =((F9*N9)*(1+I9))*G9 -> 886.18905 | R9: 0.06 | T9: =F9-E9 -> 256800 | U9: =T9*(1-I9-M9) -> 242290.8 | V9: =(F9-E9)*0.2 -> 51360 | W9: =F9-(E9+V9)-(F9*S9)-(F9*R9) -> 169440 | X9: =IFERROR((F9-E9)/E9,"") -> 0.74825175 | Y9: =IFERROR((Q9-H9)/Q9,"") -> 0.428 | Z9: =IFERROR(W9/F9,"") -> 0.2824
A10: 2026 | C10: Finca Cafeteira (Grupal) (BOG PASS) | D10: Regular | E10: 343200 | F10: 650000 | G10: 1 | H10: =((E10*N10)*(1+I10))*G10 -> 506.90013 | I10: 0.035 | J10: =H10*(1-I10) -> 489.15863 | K10: =H10-J10 -> 17.741505 | L10: 0.001397 | M10: 0.0215 | N10: =L10*(1+M10) -> 0.0014270355 | O10: =(J10*M10)+15 -> 25.516911 | P10: =(J10*N10)+M10 -> 0.71954673 | Q10: =((F10*N10)*(1+I10))*G10 -> 960.03813 | R10: 0.06 | T10: =F10-E10 -> 306800 | U10: =T10*(1-I10-M10) -> 289465.8 | V10: =(F10-E10)*0.2 -> 61360 | W10: =F10-(E10+V10)-(F10*S10)-(F10*R10) -> 206440 | X10: =IFERROR((F10-E10)/E10,"") -> 0.89393939 | Y10: =IFERROR((Q10-H10)/Q10,"") -> 0.472 | Z10: =IFERROR(W10/F10,"") -> 0.3176
A11: 2026 | C11: Transfer in - DIURNO - 06am -09pm (bog pass) | D11: Carro 3 Pessoas | E11: 112000 | F11: 360000 | G11: 1 | H11: =((E11*N11)*(1+I11))*G11 -> 165.42196 | I11: 0.035 | J11: =H11*(1-I11) -> 159.63219 | K11: =H11-J11 -> 5.7897684 | L11: 0.001397 | M11: 0.0215 | N11: =L11*(1+M11) -> 0.0014270355 | O11: =(J11*M11)+15 -> 18.432092 | P11: =(J11*N11)+M11 -> 0.2493008 | Q11: =((F11*N11)*(1+I11))*G11 -> 531.71343 | R11: 0.06 | T11: =F11-E11 -> 248000 | U11: =T11*(1-I11-M11) -> 233988 | V11: =(F11-E11)*0.2 -> 49600 | W11: =F11-(E11+V11)-(F11*S11)-(F11*R11) -> 176800 | X11: =IFERROR((F11-E11)/E11,"") -> 2.2142857 | Y11: =IFERROR((Q11-H11)/Q11,"") -> 0.68888889 | Z11: =IFERROR(W11/F11,"") -> 0.49111111
A12: 2026 | C12: Transfer in - DIURNO - 06am -09pm (bog pass) | D12: VAN 4-6 PAX | E12: 173600 | F12: 550000 | G12: 1 | H12: =((E12*N12)*(1+I12))*G12 -> 256.40403 | I12: 0.035 | J12: =H12*(1-I12) -> 247.42989 | K12: =H12-J12 -> 8.9741411 | L12: 0.001397 | M12: 0.0215 | N12: =L12*(1+M12) -> 0.0014270355 | O12: =(J12*M12)+15 -> 20.319743 | P12: =(J12*N12)+M12 -> 0.37459124 | Q12: =((F12*N12)*(1+I12))*G12 -> 812.33996 | R12: 0.06 | T12: =F12-E12 -> 376400 | U12: =T12*(1-I12-M12) -> 355133.4 | V12: =(F12-E12)*0.2 -> 75280 | W12: =F12-(E12+V12)-(F12*S12)-(F12*R12) -> 268120 | X12: =IFERROR((F12-E12)/E12,"") -> 2.1682028 | Y12: =IFERROR((Q12-H12)/Q12,"") -> 0.68436364 | Z12: =IFERROR(W12/F12,"") -> 0.48749091
A13: 2026 | C13: Transfer in - DIURNO - 06am - 09pm (bog pass) | D13: VAN 7-10 Pax | E13: 260800 | F13: 770000 | G13: 1 | H13: =((E13*N13)*(1+I13))*G13 -> 385.19684 | I13: 0.035 | J13: =H13*(1-I13) -> 371.71495 | K13: =H13-J13 -> 13.481889 | L13: 0.001397 | M13: 0.0215 | N13: =L13*(1+M13) -> 0.0014270355 | O13: =(J13*M13)+15 -> 22.991871 | P13: =(J13*N13)+M13 -> 0.55195043 | Q13: =((F13*N13)*(1+I13))*G13 -> 1137.2759 | R13: 0.06 | T13: =F13-E13 -> 509200 | U13: =T13*(1-I13-M13) -> 480430.2 | V13: =(F13-E13)*0.2 -> 101840 | W13: =F13-(E13+V13)-(F13*S13)-(F13*R13) -> 361160 | X13: =IFERROR((F13-E13)/E13,"") -> 1.952454 | Y13: =IFERROR((Q13-H13)/Q13,"") -> 0.6612987 | Z13: =IFERROR(W13/F13,"") -> 0.46903896
A14: 2026 | C14: Transfer in - NOTURNO - 06am - 09pm (bog pass) | D14: Carro 3 Pessoas | E14: 127200 | F14: 360000 | G14: 1 | H14: =((E14*N14)*(1+I14))*G14 -> 187.87208 | I14: 0.035 | J14: =H14*(1-I14) -> 181.29655 | K14: =H14-J14 -> 6.5755227 | L14: 0.001397 | M14: 0.0215 | N14: =L14*(1+M14) -> 0.0014270355 | O14: =(J14*M14)+15 -> 18.897876 | P14: =(J14*N14)+M14 -> 0.28021662 | Q14: =((F14*N14)*(1+I14))*G14 -> 531.71343 | R14: 0.06 | T14: =F14-E14 -> 232800 | U14: =T14*(1-I14-M14) -> 219646.8 | V14: =(F14-E14)*0.2 -> 46560 | W14: =F14-(E14+V14)-(F14*S14)-(F14*R14) -> 164640 | X14: =IFERROR((F14-E14)/E14,"") -> 1.8301887 | Y14: =IFERROR((Q14-H14)/Q14,"") -> 0.64666667 | Z14: =IFERROR(W14/F14,"") -> 0.45733333
A15: 2026 | C15: Transfer in - NOTURNIO - 06am - 09pm (bog pass) | D15: VAN 4-6 PAX | E15: 216800 | F15: 550000 | G15: 1 | H15: =((E15*N15)*(1+I15))*G15 -> 320.20964 | I15: 0.035 | J15: =H15*(1-I15) -> 309.0023 | K15: =H15-J15 -> 11.207337 | L15: 0.001397 | M15: 0.0215 | N15: =L15*(1+M15) -> 0.0014270355 | O15: =(J15*M15)+15 -> 21.64355 | P15: =(J15*N15)+M15 -> 0.46245726 | Q15: =((F15*N15)*(1+I15))*G15 -> 812.33996 | R15: 0.06 | T15: =F15-E15 -> 333200 | U15: =T15*(1-I15-M15) -> 314374.2 | V15: =(F15-E15)*0.2 -> 66640 | W15: =F15-(E15+V15)-(F15*S15)-(F15*R15) -> 233560 | X15: =IFERROR((F15-E15)/E15,"") -> 1.5369004 | Y15: =IFERROR((Q15-H15)/Q15,"") -> 0.60581818 | Z15: =IFERROR(W15/F15,"") -> 0.42465455
A16: 2026 | C16: Transfer in - NOTURNO - 06am - 09pm (bog pass) | D16: VAN 7-10 Pax | E16: 292000 | F16: 770000 | G16: 1 | H16: =((E16*N16)*(1+I16))*G16 -> 431.27867 | I16: 0.035 | J16: =H16*(1-I16) -> 416.18392 | K16: =H16-J16 -> 15.094753 | L16: 0.001397 | M16: 0.0215 | N16: =L16*(1+M16) -> 0.0014270355 | O16: =(J16*M16)+15 -> 23.947954 | P16: =(J16*N16)+M16 -> 0.61540922 | Q16: =((F16*N16)*(1+I16))*G16 -> 1137.2759 | R16: 0.06 | T16: =F16-E16 -> 478000 | U16: =T16*(1-I16-M16) -> 450993 | V16: =(F16-E16)*0.2 -> 95600 | W16: =F16-(E16+V16)-(F16*S16)-(F16*R16) -> 336200 | X16: =IFERROR((F16-E16)/E16,"") -> 1.6369863 | Y16: =IFERROR((Q16-H16)/Q16,"") -> 0.62077922 | Z16: =IFERROR(W16/F16,"") -> 0.43662338
A17: 2026 | C17: Transfer OUT - DIURNO - 06am -09pm (bog pass) | D17: Carro 3 Pessoas | E17: 80000 | F17: 360000 | G17: 1 | H17: =((E17*N17)*(1+I17))*G17 -> 118.15854 | I17: 0.035 | J17: =H17*(1-I17) -> 114.02299 | K17: =H17-J17 -> 4.1355489 | L17: 0.001397 | M17: 0.0215 | N17: =L17*(1+M17) -> 0.0014270355 | O17: =(J17*M17)+15 -> 17.451494 | P17: =(J17*N17)+M17 -> 0.18421486 | Q17: =((F17*N17)*(1+I17))*G17 -> 531.71343 | R17: 0.06 | T17: =F17-E17 -> 280000 | U17: =T17*(1-I17-M17) -> 264180 | V17: =(F17-E17)*0.2 -> 56000 | W17: =F17-(E17+V17)-(F17*S17)-(F17*R17) -> 202400 | X17: =IFERROR((F17-E17)/E17,"") -> 3.5 | Y17: =IFERROR((Q17-H17)/Q17,"") -> 0.77777778 | Z17: =IFERROR(W17/F17,"") -> 0.56222222
A18: 2026 | C18: Transfer OUT - DIURNO - 06am -09pm (bog pass) | D18: VAN 4-6 PAX | E18: 140000 | F18: 550000 | G18: 1 | H18: =((E18*N18)*(1+I18))*G18 -> 206.77744 | I18: 0.035 | J18: =H18*(1-I18) -> 199.54023 | K18: =H18-J18 -> 7.2372105 | L18: 0.001397 | M18: 0.0215 | N18: =L18*(1+M18) -> 0.0014270355 | O18: =(J18*M18)+15 -> 19.290115 | P18: =(J18*N18)+M18 -> 0.306251 | Q18: =((F18*N18)*(1+I18))*G18 -> 812.33996 | R18: 0.06 | T18: =F18-E18 -> 410000 | U18: =T18*(1-I18-M18) -> 386835 | V18: =(F18-E18)*0.2 -> 82000 | W18: =F18-(E18+V18)-(F18*S18)-(F18*R18) -> 295000 | X18: =IFERROR((F18-E18)/E18,"") -> 2.9285714 | Y18: =IFERROR((Q18-H18)/Q18,"") -> 0.74545455 | Z18: =IFERROR(W18/F18,"") -> 0.53636364
... A22: 2026 | C22: Transfer OUT - NOTURNO - 06am - 09pm (bog pass) | D22: VAN 7-10 Pax | E22: 244000 | F22: 770000 | G22: 1 | H22: =((E22*N22)*(1+I22))*G22 -> 360.38355 | I22: 0.035 | J22: =H22*(1-I22) -> 347.77012 | K22: =H22-J22 -> 12.613424 | L22: 0.001397 | M22: 0.0215 | N22: =L22*(1+M22) -> 0.0014270355 | O22: =(J22*M22)+15 -> 22.477058 | P22: =(J22*N22)+M22 -> 0.51778031 | Q22: =((F22*N22)*(1+I22))*G22 -> 1137.2759 | R22: 0.06 | T22: =F22-E22 -> 526000 | U22: =T22*(1-I22-M22) -> 496281 | V22: =(F22-E22)*0.2 -> 105200 | W22: =F22-(E22+V22)-(F22*S22)-(F22*R22) -> 374600 | X22: =IFERROR((F22-E22)/E22,"") -> 2.1557377 | Y22: =IFERROR((Q22-H22)/Q22,"") -> 0.68311688 | Z22: =IFERROR(W22/F22,"") -> 0.48649351
T23: =F23-E23 -> 0 | U23: =T23*(1-I23-M23) -> 0 | V23: =(F23-E23)*0.2 -> 0 | W23: =F23-(E23+V23)-(F23*S23)-(F23*R23) -> 0 | X23: =IFERROR((F23-E23)/E23,"") | Z23: =IFERROR(W23/F23,"")
A24: Cartagena | T24: =F24-E24 -> 0 | U24: =T24*(1-I24-M24) -> 0 | V24: =(F24-E24)*0.2 -> 0 | W24: =F24-(E24+V24)-(F24*S24)-(F24*R24) -> 0 | X24: =IFERROR((F24-E24)/E24,"") | Z24: =IFERROR(W24/F24,"")
A25: 2026 | C25: Jantar Fenix Beach | E25: 225000 | F25: 370000 | G25: 1 | H25: =((E25*N25)*(1+I25))*G25 -> 332.32089 | I25: 0.035 | J25: =H25*(1-I25) -> 320.68966 | K25: =H25-J25 -> 11.631231 | L25: 0.001397 | M25: 0.0215 | N25: =L25*(1+M25) -> 0.0014270355 | O25: =(J25*M25)+15 -> 21.894828 | P25: =(J25*N25)+M25 -> 0.47913553 | Q25: =((F25*N25)*(1+I25))*G25 -> 546.48324 | R25: 0.06 | T25: =F25-E25 -> 145000 | U25: =T25*(1-I25-M25) -> 136807.5 | V25: =(F25-E25)*0.2 -> 29000 | W25: =F25-(E25+V25)-(F25*S25)-(F25*R25) -> 93800 | X25: =IFERROR((F25-E25)/E25,"") -> 0.64444444 | Y25: =IFERROR((Q25-H25)/Q25,"") -> 0.39189189 | Z25: =IFERROR(W25/F25,"") -> 0.25351351 | AH25: =IFERROR(AVERAGE(AE25:AG25),"") | AI25: =AE25+AF25+AG25 -> 0
A26: 2026 | C26: Jantar Fenix Beach | E26: 150000 | F26: 300000 | G26: 1 | H26: =((E26*N26)*(1+I26))*G26 -> 221.54726 | I26: 0.035 | J26: =H26*(1-I26) -> 213.79311 | K26: =H26-J26 -> 7.7541541 | L26: 0.001397 | M26: 0.0215 | N26: =L26*(1+M26) -> 0.0014270355 | O26: =(J26*M26)+15 -> 19.596552 | P26: =(J26*N26)+M26 -> 0.32659035 | Q26: =((F26*N26)*(1+I26))*G26 -> 443.09452 | R26: 0.06 | T26: =F26-E26 -> 150000 | U26: =T26*(1-I26-M26) -> 141525 | V26: =(F26-E26)*0.2 -> 30000 | W26: =F26-(E26+V26)-(F26*S26)-(F26*R26) -> 102000 | X26: =IFERROR((F26-E26)/E26,"") -> 1 | Y26: =IFERROR((Q26-H26)/Q26,"") -> 0.5 | Z26: =IFERROR(W26/F26,"") -> 0.34 | AH26: =IFERROR(AVERAGE(AE26:AG26),"") | AI26: =AE26+AF26+AG26 -> 0
H27: =((E27*N27)*(1+I27))*G27 -> 0 | Q27: =((F27*N27)*(1+I27))*G27 -> 0 | R27: 0.06 | T27: =F27-E27 -> 0 | U27: =T27*(1-I27-M27) -> 0 | V27: =(F27-E27)*0.2 -> 0 | W27: =F27-(E27+V27)-(F27*S27)-(F27*R27) -> 0 | X27: =IFERROR((F27-E27)/E27,"") | Z27: =IFERROR(W27/F27,"")
A28: 2026 | C28: Corona Island | E28: 633000 | F28: 850000 | G28: 1 | H28: =((E28*N28)*(1+I28))*G28 -> 934.92944 | I28: 0.035 | J28: =H28*(1-I28) -> 902.20691 | K28: =H28-J28 -> 32.722531 | L28: 0.001397 | M28: 0.0215 | N28: =L28*(1+M28) -> 0.0014270355 | O28: =(J28*M28)+15 -> 34.397449 | P28: =(J28*N28)+M28 -> 1.3089813 | Q28: =((F28*N28)*(1+I28))*G28 -> 1255.4345 | R28: 0.06 | T28: =F28-E28 -> 217000 | U28: =T28*(1-I28-M28) -> 204739.5 | V28: =(F28-E28)*0.2 -> 43400 | W28: =F28-(E28+V28)-(F28*S28)-(F28*R28) -> 122600 | X28: =IFERROR((F28-E28)/E28,"") -> 0.34281201 | Y28: =IFERROR((Q28-H28)/Q28,"") -> 0.25529412 | Z28: =IFERROR(W28/F28,"") -> 0.14423529 | AH28: =IFERROR(AVERAGE(AE28:AG28),"") | AI28: =AE28+AF28+AG28 -> 0
T29: =F29-E29 -> 0 | U29: =T29*(1-I29-M29) -> 0 | V29: =(F29-E29)*0.2 -> 0 | W29: =F29-(E29+V29)-(F29*S29)-(F29*R29) -> 0 | X29: =IFERROR((F29-E29)/E29,"") | Z29: =IFERROR(W29/F29,"")
A30: 2026 | C30: Capri Premium | E30: 390000 | F30: 610000 | G30: 1 | H30: =((E30*N30)*(1+I30))*G30 -> 576.02288 | I30: 0.035 | J30: =H30*(1-I30) -> 555.86208 | K30: =H30-J30 -> 20.160801 | L30: 0.001397 | M30: 0.0215 | N30: =L30*(1+M30) -> 0.0014270355 | O30: =(J30*M30)+15 -> 26.951035 | P30: =(J30*N30)+M30 -> 0.81473492 | Q30: =((F30*N30)*(1+I30))*G30 -> 900.95886 | R30: 0.06 | T30: =F30-E30 -> 220000 | U30: =T30*(1-I30-M30) -> 207570 | V30: =(F30-E30)*0.2 -> 44000 | W30: =F30-(E30+V30)-(F30*S30)-(F30*R30) -> 139400 | X30: =IFERROR((F30-E30)/E30,"") -> 0.56410256 | Y30: =IFERROR((Q30-H30)/Q30,"") -> 0.36065574 | Z30: =IFERROR(W30/F30,"") -> 0.22852459 | AH30: =IFERROR(AVERAGE(AE30:AG30),"") | AI30: =AE30+AF30+AG30 -> 0
A31: 2026 | C31: Capri Classic | E31: 330000 | F31: 510000 | G31: 1 | H31: =((E31*N31)*(1+I31))*G31 -> 487.40398 | I31: 0.035 | J31: =H31*(1-I31) -> 470.34484 | K31: =H31-J31 -> 17.059139 | L31: 0.001397 | M31: 0.0215 | N31: =L31*(1+M31) -> 0.0014270355 | O31: =(J31*M31)+15 -> 25.112414 | P31: =(J31*N31)+M31 -> 0.69269878 | Q31: =((F31*N31)*(1+I31))*G31 -> 753.26069 | R31: 0.06 | T31: =F31-E31 -> 180000 | U31: =T31*(1-I31-M31) -> 169830 | V31: =(F31-E31)*0.2 -> 36000 | W31: =F31-(E31+V31)-(F31*S31)-(F31*R31) -> 113400 | X31: =IFERROR((F31-E31)/E31,"") -> 0.54545455 | Y31: =IFERROR((Q31-H31)/Q31,"") -> 0.35294118 | Z31: =IFERROR(W31/F31,"") -> 0.22235294 | AH31: =IFERROR(AVERAGE(AE31:AG31),"") | AI31: =AE31+AF31+AG31 -> 0
T32: =F32-E32 -> 0 | U32: =T32*(1-I32-M32) -> 0 | V32: =(F32-E32)*0.2 -> 0 | W32: =F32-(E32+V32)-(F32*S32)-(F32*R32) -> 0 | X32: =IFERROR((F32-E32)/E32,"") | Z32: =IFERROR(W32/F32,"")
A33: 2026 | C33: Isla Bela | E33: 300000 | F33: 490000 | G33: 1 | H33: =((E33*N33)*(1+I33))*G33 -> 443.09452 | I33: 0.035 | J33: =H33*(1-I33) -> 427.58621 | K33: =H33-J33 -> 15.508308 | L33: 0.001397 | M33: 0.0215 | N33: =L33*(1+M33) -> 0.0014270355 | O33: =(J33*M33)+15 -> 24.193104 | P33: =(J33*N33)+M33 -> 0.63168071 | Q33: =((F33*N33)*(1+I33))*G33 -> 723.72105 | R33: 0.06 | T33: =F33-E33 -> 190000 | U33: =T33*(1-I33-M33) -> 179265 | V33: =(F33-E33)*0.2 -> 38000 | W33: =F33-(E33+V33)-(F33*S33)-(F33*R33) -> 122600 | X33: =IFERROR((F33-E33)/E33,"") -> 0.63333333 | Y33: =IFERROR((Q33-H33)/Q33,"") -> 0.3877551 | Z33: =IFERROR(W33/F33,"") -> 0.25020408 | AH33: =IFERROR(AVERAGE(AE33:AG33),"") | AI33: =AE33+AF33+AG33 -> 0
A34: 2026 | C34: Isla Bela chd - 03 a 10 anos | E34: 260000 | F34: 390000 | G34: 1 | H34: =((E34*N34)*(1+I34))*G34 -> 384.01525 | I34: 0.035 | J34: =H34*(1-I34) -> 370.57472 | K34: =H34-J34 -> 13.440534 | L34: 0.001397 | M34: 0.0215 | N34: =L34*(1+M34) -> 0.0014270355 | O34: =(J34*M34)+15 -> 22.967356 | P34: =(J34*N34)+M34 -> 0.55032328 | Q34: =((F34*N34)*(1+I34))*G34 -> 576.02288 | R34: 0.06 | T34: =F34-E34 -> 130000 | U34: =T34*(1-I34-M34) -> 122655 | V34: =(F34-E34)*0.2 -> 26000 | W34: =F34-(E34+V34)-(F34*S34)-(F34*R34) -> 80600 | X34: =IFERROR((F34-E34)/E34,"") -> 0.5 | Y34: =IFERROR((Q34-H34)/Q34,"") -> 0.33333333 | Z34: =IFERROR(W34/F34,"") -> 0.20666667 | AH34: =IFERROR(AVERAGE(AE34:AG34),"") | AI34: =AE34+AF34+AG34 -> 0
T35: =F35-E35 -> 0 | U35: =T35*(1-I35-M35) -> 0 | V35: =(F35-E35)*0.2 -> 0 | W35: =F35-(E35+V35)-(F35*S35)-(F35*R35) -> 0 | X35: =IFERROR((F35-E35)/E35,"") | Z35: =IFERROR(W35/F35,"")
A36: 2026 | C36: Mergulho iniciante | E36: 620000 | F36: 890000 | G36: 1 | H36: =((E36*N36)*(1+I36))*G36 -> 915.72868 | I36: 0.035 | J36: =H36*(1-I36) -> 883.67818 | K36: =H36-J36 -> 32.050504 | L36: 0.001397 | M36: 0.0215 | N36: =L36*(1+M36) -> 0.0014270355 | O36: =(J36*M36)+15 -> 33.999081 | P36: =(J36*N36)+M36 -> 1.2825401 | Q36: =((F36*N36)*(1+I36))*G36 -> 1314.5138 | R36: 0.06 | T36: =F36-E36 -> 270000 | U36: =T36*(1-I36-M36) -> 254745 | V36: =(F36-E36)*0.2 -> 54000 | W36: =F36-(E36+V36)-(F36*S36)-(F36*R36) -> 162600 | X36: =IFERROR((F36-E36)/E36,"") -> 0.43548387 | Y36: =IFERROR((Q36-H36)/Q36,"") -> 0.30337079 | Z36: =IFERROR(W36/F36,"") -> 0.18269663 | AH36: =IFERROR(AVERAGE(AE36:AG36),"") | AI36: =AE36+AF36+AG36 -> 0
A37: 2026 | C37: Mergulho para certificados | E37: 570000 | F37: 800000 | G37: 1 | H37: =((E37*N37)*(1+I37))*G37 -> 841.87959 | I37: 0.035 | J37: =H37*(1-I37) -> 812.41381 | K37: =H37-J37 -> 29.465786 | L37: 0.001397 | M37: 0.0215 | N37: =L37*(1+M37) -> 0.0014270355 | O37: =(J37*M37)+15 -> 32.466897 | P37: =(J37*N37)+M37 -> 1.1808433 | Q37: =((F37*N37)*(1+I37))*G37 -> 1181.5854 | R37: 0.06 | T37: =F37-E37 -> 230000 | U37: =T37*(1-I37-M37) -> 217005 | V37: =(F37-E37)*0.2 -> 46000 | W37: =F37-(E37+V37)-(F37*S37)-(F37*R37) -> 136000 | X37: =IFERROR((F37-E37)/E37,"") -> 0.40350877 | Y37: =IFERROR((Q37-H37)/Q37,"") -> 0.2875 | Z37: =IFERROR(W37/F37,"") -> 0.17 | AH37: =IFERROR(AVERAGE(AE37:AG37),"") | AI37: =AE37+AF37+AG37 -> 0
T38: =F38-E38 -> 0 | U38: =T38*(1-I38-M38) -> 0 | V38: =(F38-E38)*0.2 -> 0 | W38: =F38-(E38+V38)-(F38*S38)-(F38*R38) -> 0 | X38: =IFERROR((F38-E38)/E38,"") | Z38: =IFERROR(W38/F38,"")
A39: 2026 | C39: Bona Vida Sunset Adulto | E39: 134000 | F39: 230000 | G39: 1 | H39: =((E39*N39)*(1+I39))*G39 -> 197.91555 | I39: 0.035 | J39: =H39*(1-I39) -> 190.98851 | K39: =H39-J39 -> 6.9270444 | L39: 0.001397 | M39: 0.0215 | N39: =L39*(1+M39) -> 0.0014270355 | O39: =(J39*M39)+15 -> 19.106253 | P39: =(J39*N39)+M39 -> 0.29404738 | Q39: =((F39*N39)*(1+I39))*G39 -> 339.7058 | R39: 0.06 | T39: =F39-E39 -> 96000 | U39: =T39*(1-I39-M39) -> 90576 | V39: =(F39-E39)*0.2 -> 19200 | W39: =F39-(E39+V39)-(F39*S39)-(F39*R39) -> 63000 | X39: =IFERROR((F39-E39)/E39,"") -> 0.71641791 | Y39: =IFERROR((Q39-H39)/Q39,"") -> 0.4173913 | Z39: =IFERROR(W39/F39,"") -> 0.27391304 | AH39: =IFERROR(AVERAGE(AE39:AG39),"") | AI39: =AE39+AF39+AG39 -> 0
A40: 2026 | C40: Bona Vida Sunset CHD - 7 a 14 anos | E40: 67000 | F40: 190000 | G40: 1 | H40: =((E40*N40)*(1+I40))*G40 -> 98.957777 | I40: 0.035 | J40: =H40*(1-I40) -> 95.494255 | K40: =H40-J40 -> 3.4635222 | L40: 0.001397 | M40: 0.0215 | N40: =L40*(1+M40) -> 0.0014270355 | O40: =(J40*M40)+15 -> 17.053126 | P40: =(J40*N40)+M40 -> 0.15777369 | Q40: =((F40*N40)*(1+I40))*G40 -> 280.62653 | R40: 0.06 | T40: =F40-E40 -> 123000 | U40: =T40*(1-I40-M40) -> 116050.5 | V40: =(F40-E40)*0.2 -> 24600 | W40: =F40-(E40+V40)-(F40*S40)-(F40*R40) -> 87000 | X40: =IFERROR((F40-E40)/E40,"") -> 1.8358209 | Y40: =IFERROR((Q40-H40)/Q40,"") -> 0.64736842 | Z40: =IFERROR(W40/F40,"") -> 0.45789474 | AH40: =IFERROR(AVERAGE(AE40:AG40),"") | AI40: =AE40+AF40+AG40 -> 0
T41: =F41-E41 -> 0 | U41: =T41*(1-I41-M41) -> 0 | V41: =(F41-E41)*0.2 -> 0 | W41: =F41-(E41+V41)-(F41*S41)-(F41*R41) -> 0 | X41: =IFERROR((F41-E41)/E41,"") | Z41: =IFERROR(W41/F41,"")
A42: 2026 | C42: Bona Vida Islas Adulto | E42: 390000 | F42: 510000 | G42: 1 | H42: =((E42*N42)*(1+I42))*G42 -> 576.02288 | I42: 0.035 | J42: =H42*(1-I42) -> 555.86208 | K42: =H42-J42 -> 20.160801 | L42: 0.001397 | M42: 0.0215 | N42: =L42*(1+M42) -> 0.0014270355 | O42: =(J42*M42)+15 -> 26.951035 | P42: =(J42*N42)+M42 -> 0.81473492 | Q42: =((F42*N42)*(1+I42))*G42 -> 753.26069 | R42: 0.06 | T42: =F42-E42 -> 120000 | U42: =T42*(1-I42-M42) -> 113220 | V42: =(F42-E42)*0.2 -> 24000 | W42: =F42-(E42+V42)-(F42*S42)-(F42*R42) -> 65400 | X42: =IFERROR((F42-E42)/E42,"") -> 0.30769231 | Y42: =IFERROR((Q42-H42)/Q42,"") -> 0.23529412 | Z42: =IFERROR(W42/F42,"") -> 0.12823529 | AH42: =IFERROR(AVERAGE(AE42:AG42),"") | AI42: =AE42+AF42+AG42 -> 0
A43: 2026 | C43: Bona Vida Islas CHD - 7 a 14 anos | E43: 67000 | F43: 190000 | G43: 1 | H43: =((E43*N43)*(1+I43))*G43 -> 98.957777 | I43: 0.035 | J43: =H43*(1-I43) -> 95.494255 | K43: =H43-J43 -> 3.4635222 | L43: 0.001397 | M43: 0.0215 | N43: =L43*(1+M43) -> 0.0014270355 | O43: =(J43*M43)+15 -> 17.053126 | P43: =(J43*N43)+M43 -> 0.15777369 | Q43: =((F43*N43)*(1+I43))*G43 -> 280.62653 | R43: 0.06 | T43: =F43-E43 -> 123000 | U43: =T43*(1-I43-M43) -> 116050.5 | V43: =(F43-E43)*0.2 -> 24600 | W43: =F43-(E43+V43)-(F43*S43)-(F43*R43) -> 87000 | X43: =IFERROR((F43-E43)/E43,"") -> 1.8358209 | Y43: =IFERROR((Q43-H43)/Q43,"") -> 0.64736842 | Z43: =IFERROR(W43/F43,"") -> 0.45789474 | AH43: =IFERROR(AVERAGE(AE43:AG43),"") | AI43: =AE43+AF43+AG43 -> 0
T44: =F44-E44 -> 0 | U44: =T44*(1-I44-M44) -> 0 | V44: =(F44-E44)*0.2 -> 0 | W44: =F44-(E44+V44)-(F44*S44)-(F44*R44) -> 0 | X44: =IFERROR((F44-E44)/E44,"") | Z44: =IFERROR(W44/F44,"")
A45: 2026 | C45: BORA BORA CLUB | E45: 290000 | F45: 450000 | G45: 1 | H45: =((E45*N45)*(1+I45))*G45 -> 428.32471 | I45: 0.035 | J45: =H45*(1-I45) -> 413.33334 | K45: =H45-J45 -> 14.991365 | L45: 0.001397 | M45: 0.0215 | N45: =L45*(1+M45) -> 0.0014270355 | O45: =(J45*M45)+15 -> 23.886667 | P45: =(J45*N45)+M45 -> 0.61134135 | Q45: =((F45*N45)*(1+I45))*G45 -> 664.64178 | R45: 0.06 | T45: =F45-E45 -> 160000 | U45: =T45*(1-I45-M45) -> 150960 | V45: =(F45-E45)*0.2 -> 32000 | W45: =F45-(E45+V45)-(F45*S45)-(F45*R45) -> 101000 | X45: =IFERROR((F45-E45)/E45,"") -> 0.55172414 | Y45: =IFERROR((Q45-H45)/Q45,"") -> 0.35555556 | Z45: =IFERROR(W45/F45,"") -> 0.22444444 | AH45: =IFERROR(AVERAGE(AE45:AG45),"") | AI45: =AE45+AF45+AG45 -> 0
A46: 2026 | C46: BORA VIP | E46: 380000 | F46: 540000 | G46: 1 | H46: =((E46*N46)*(1+I46))*G46 -> 561.25306 | I46: 0.035 | J46: =H46*(1-I46) -> 541.6092 | K46: =H46-J46 -> 19.643857 | L46: 0.001397 | M46: 0.0215 | N46: =L46*(1+M46) -> 0.0014270355 | O46: =(J46*M46)+15 -> 26.644598 | P46: =(J46*N46)+M46 -> 0.79439556 | Q46: =((F46*N46)*(1+I46))*G46 -> 797.57014 | R46: 0.06 | T46: =F46-E46 -> 160000 | U46: =T46*(1-I46-M46) -> 150960 | V46: =(F46-E46)*0.2 -> 32000 | W46: =F46-(E46+V46)-(F46*S46)-(F46*R46) -> 95600 | X46: =IFERROR((F46-E46)/E46,"") -> 0.42105263 | Y46: =IFERROR((Q46-H46)/Q46,"") -> 0.2962963 | Z46: =IFERROR(W46/F46,"") -> 0.17703704 | AH46: =IFERROR(AVERAGE(AE46:AG46),"") | AI46: =AE46+AF46+AG46 -> 0
A47: 2026 | C47: TOP 3 | E47: 360000 | F47: 500000 | G47: 1 | H47: =((E47*N47)*(1+I47))*G47 -> 531.71343 | I47: 0.035 | J47: =H47*(1-I47) -> 513.10346 | K47: =H47-J47 -> 18.60997 | L47: 0.001397 | M47: 0.0215 | N47: =L47*(1+M47) -> 0.0014270355 | O47: =(J47*M47)+15 -> 26.031724 | P47: =(J47*N47)+M47 -> 0.75371685 | Q47: =((F47*N47)*(1+I47))*G47 -> 738.49087 | R47: 0.06 | T47: =F47-E47 -> 140000 | U47: =T47*(1-I47-M47) -> 132090 | V47: =(F47-E47)*0.2 -> 28000 | W47: =F47-(E47+V47)-(F47*S47)-(F47*R47) -> 82000 | X47: =IFERROR((F47-E47)/E47,"") -> 0.38888889 | Y47: =IFERROR((Q47-H47)/Q47,"") -> 0.28 | Z47: =IFERROR(W47/F47,"") -> 0.164 | AH47: =IFERROR(AVERAGE(AE47:AG47),"") | AI47: =AE47+AF47+AG47 -> 0
A48: 2026 | C48: PAO PAO | E48: 280000 | F48: 450000 | G48: 1 | H48: =((E48*N48)*(1+I48))*G48 -> 413.55489 | I48: 0.035 | J48: =H48*(1-I48) -> 399.08047 | K48: =H48-J48 -> 14.474421 | L48: 0.001397 | M48: 0.0215 | N48: =L48*(1+M48) -> 0.0014270355 | O48: =(J48*M48)+15 -> 23.58023 | P48: =(J48*N48)+M48 -> 0.59100199 | Q48: =((F48*N48)*(1+I48))*G48 -> 664.64178 | R48: 0.06 | T48: =F48-E48 -> 170000 | U48: =T48*(1-I48-M48) -> 160395 | V48: =(F48-E48)*0.2 -> 34000 | W48: =F48-(E48+V48)-(F48*S48)-(F48*R48) -> 109000 | X48: =IFERROR((F48-E48)/E48,"") -> 0.60714286 | Y48: =IFERROR((Q48-H48)/Q48,"") -> 0.37777778 | Z48: =IFERROR(W48/F48,"") -> 0.24222222 | AH48: =IFERROR(AVERAGE(AE48:AG48),"") | AI48: =AE48+AF48+AG48 -> 0
T49: =F49-E49 -> 0 | U49: =T49*(1-I49-M49) -> 0 | V49: =(F49-E49)*0.2 -> 0 | W49: =F49-(E49+V49)-(F49*S49)-(F49*R49) -> 0 | X49: =IFERROR((F49-E49)/E49,"") | Z49: =IFERROR(W49/F49,"")
A50: 2026 | C50: Paue | E50: 370000 | F50: 520000 | G50: 1 | H50: =((E50*N50)*(1+I50))*G50 -> 546.48324 | I50: 0.035 | J50: =H50*(1-I50) -> 527.35633 | K50: =H50-J50 -> 19.126914 | L50: 0.001397 | M50: 0.0215 | N50: =L50*(1+M50) -> 0.0014270355 | O50: =(J50*M50)+15 -> 26.338161 | P50: =(J50*N50)+M50 -> 0.77405621 | Q50: =((F50*N50)*(1+I50))*G50 -> 768.03051 | R50: 0.06 | T50: =F50-E50 -> 150000 | U50: =T50*(1-I50-M50) -> 141525 | V50: =(F50-E50)*0.2 -> 30000 | W50: =F50-(E50+V50)-(F50*S50)-(F50*R50) -> 88800 | X50: =IFERROR((F50-E50)/E50,"") -> 0.40540541 | Y50: =IFERROR((Q50-H50)/Q50,"") -> 0.28846154 | Z50: =IFERROR(W50/F50,"") -> 0.17076923 | AH50: =IFERROR(AVERAGE(AE50:AG50),"") | AI50: =AE50+AF50+AG50 -> 0
A51: 2026 | C51: Paue CHD 04 A 07 ANOS | E51: 250000 | F51: 370000 | G51: 1 | H51: =((E51*N51)*(1+I51))*G51 -> 369.24544 | I51: 0.035 | J51: =H51*(1-I51) -> 356.32185 | K51: =H51-J51 -> 12.92359 | L51: 0.001397 | M51: 0.0215 | N51: =L51*(1+M51) -> 0.0014270355 | O51: =(J51*M51)+15 -> 22.66092 | P51: =(J51*N51)+M51 -> 0.52998392 | Q51: =((F51*N51)*(1+I51))*G51 -> 546.48324 | R51: 0.06 | T51: =F51-E51 -> 120000 | U51: =T51*(1-I51-M51) -> 113220 | V51: =(F51-E51)*0.2 -> 24000 | W51: =F51-(E51+V51)-(F51*S51)-(F51*R51) -> 73800 | X51: =IFERROR((F51-E51)/E51,"") -> 0.48 | Y51: =IFERROR((Q51-H51)/Q51,"") -> 0.32432432 | Z51: =IFERROR(W51/F51,"") -> 0.19945946 | AH51: =IFERROR(AVERAGE(AE51:AG51),"") | AI51: =AE51+AF51+AG51 -> 0
T52: =F52-E52 -> 0 | U52: =T52*(1-I52-M52) -> 0 | V52: =(F52-E52)*0.2 -> 0 | W52: =F52-(E52+V52)-(F52*S52)-(F52*R52) -> 0 | X52: =IFERROR((F52-E52)/E52,"") | Z52: =IFERROR(W52/F52,"")
A53: 2026 | C53: Rosario de Mar plan arrecife | E53: 300000 | F53: 450000 | G53: 1 | H53: =((E53*N53)*(1+I53))*G53 -> 443.09452 | I53: 0.035 | J53: =H53*(1-I53) -> 427.58621 | K53: =H53-J53 -> 15.508308 | L53: 0.001397 | M53: 0.0215 | N53: =L53*(1+M53) -> 0.0014270355 | O53: =(J53*M53)+15 -> 24.193104 | P53: =(J53*N53)+M53 -> 0.63168071 | Q53: =((F53*N53)*(1+I53))*G53 -> 664.64178 | R53: 0.06 | T53: =F53-E53 -> 150000 | U53: =T53*(1-I53-M53) -> 141525 | V53: =(F53-E53)*0.2 -> 30000 | W53: =F53-(E53+V53)-(F53*S53)-(F53*R53) -> 93000 | X53: =IFERROR((F53-E53)/E53,"") -> 0.5 | Y53: =IFERROR((Q53-H53)/Q53,"") -> 0.33333333 | Z53: =IFERROR(W53/F53,"") -> 0.20666667 | AH53: =IFERROR(AVERAGE(AE53:AG53),"") | AI53: =AE53+AF53+AG53 -> 0
A54: 2026 | C54: rosario de mar CHD 04 a 07 anos plan arrecife | E54: 220000 | F54: 370000 | G54: 1 | H54: =((E54*N54)*(1+I54))*G54 -> 324.93598 | I54: 0.035 | J54: =H54*(1-I54) -> 313.56322 | K54: =H54-J54 -> 11.372759 | L54: 0.001397 | M54: 0.0215 | N54: =L54*(1+M54) -> 0.0014270355 | O54: =(J54*M54)+15 -> 21.741609 | P54: =(J54*N54)+M54 -> 0.46896585 | Q54: =((F54*N54)*(1+I54))*G54 -> 546.48324 | R54: 0.06 | T54: =F54-E54 -> 150000 | U54: =T54*(1-I54-M54) -> 141525 | V54: =(F54-E54)*0.2 -> 30000 | W54: =F54-(E54+V54)-(F54*S54)-(F54*R54) -> 97800 | X54: =IFERROR((F54-E54)/E54,"") -> 0.68181818 | Y54: =IFERROR((Q54-H54)/Q54,"") -> 0.40540541 | Z54: =IFERROR(W54/F54,"") -> 0.26432432 | AH54: =IFERROR(AVERAGE(AE54:AG54),"") | AI54: =AE54+AF54+AG54 -> 0
T55: =F55-E55 -> 0 | U55: =T55*(1-I55-M55) -> 0 | V55: =(F55-E55)*0.2 -> 0 | W55: =F55-(E55+V55)-(F55*S55)-(F55*R55) -> 0 | X55: =IFERROR((F55-E55)/E55,"") | Z55: =IFERROR(W55/F55,"")
A56: 2026 | C56: Rosario de Mar plan abanico (open bar) | E56: 400000 | F56: 580000 | G56: 1 | H56: =((E56*N56)*(1+I56))*G56 -> 590.7927 | I56: 0.035 | J56: =H56*(1-I56) -> 570.11495 | K56: =H56-J56 -> 20.677744 | L56: 0.001397 | M56: 0.0215 | N56: =L56*(1+M56) -> 0.0014270355 | O56: =(J56*M56)+15 -> 27.257471 | P56: =(J56*N56)+M56 -> 0.83507428 | Q56: =((F56*N56)*(1+I56))*G56 -> 856.64941 | R56: 0.06 | T56: =F56-E56 -> 180000 | U56: =T56*(1-I56-M56) -> 169830 | V56: =(F56-E56)*0.2 -> 36000 | W56: =F56-(E56+V56)-(F56*S56)-(F56*R56) -> 109200 | X56: =IFERROR((F56-E56)/E56,"") -> 0.45 | Y56: =IFERROR((Q56-H56)/Q56,"") -> 0.31034483 | Z56: =IFERROR(W56/F56,"") -> 0.18827586 | AH56: =IFERROR(AVERAGE(AE56:AG56),"") | AI56: =AE56+AF56+AG56 -> 0
T57: =F57-E57 -> 0 | U57: =T57*(1-I57-M57) -> 0 | V57: =(F57-E57)*0.2 -> 0 | W57: =F57-(E57+V57)-(F57*S57)-(F57*R57) -> 0 | X57: =IFERROR((F57-E57)/E57,"") | Z57: =IFERROR(W57/F57,"")
A58: 2026 | C58: Sabai | E58: 390000 | F58: 520000 | G58: 1 | H58: =((E58*N58)*(1+I58))*G58 -> 576.02288 | I58: 0.035 | J58: =H58*(1-I58) -> 555.86208 | K58: =H58-J58 -> 20.160801 | L58: 0.001397 | M58: 0.0215 | N58: =L58*(1+M58) -> 0.0014270355 | O58: =(J58*M58)+15 -> 26.951035 | P58: =(J58*N58)+M58 -> 0.81473492 | Q58: =((F58*N58)*(1+I58))*G58 -> 768.03051 | R58: 0.06 | T58: =F58-E58 -> 130000 | U58: =T58*(1-I58-M58) -> 122655 | V58: =(F58-E58)*0.2 -> 26000 | W58: =F58-(E58+V58)-(F58*S58)-(F58*R58) -> 72800 | X58: =IFERROR((F58-E58)/E58,"") -> 0.33333333 | Y58: =IFERROR((Q58-H58)/Q58,"") -> 0.25 | Z58: =IFERROR(W58/F58,"") -> 0.14 | AH58: =IFERROR(AVERAGE(AE58:AG58),"") | AI58: =AE58+AF58+AG58 -> 0
A59: 2026 | C59: sabai chd 5 a 09 anos | E59: 130000 | F59: 380000 | G59: 1 | H59: =((E59*N59)*(1+I59))*G59 -> 192.00763 | I59: 0.035 | J59: =H59*(1-I59) -> 185.28736 | K59: =H59-J59 -> 6.7202669 | L59: 0.001397 | M59: 0.0215 | N59: =L59*(1+M59) -> 0.0014270355 | O59: =(J59*M59)+15 -> 18.983678 | P59: =(J59*N59)+M59 -> 0.28591164 | Q59: =((F59*N59)*(1+I59))*G59 -> 561.25306 | R59: 0.06 | T59: =F59-E59 -> 250000 | U59: =T59*(1-I59-M59) -> 235875 | V59: =(F59-E59)*0.2 -> 50000 | W59: =F59-(E59+V59)-(F59*S59)-(F59*R59) -> 177200 | X59: =IFERROR((F59-E59)/E59,"") -> 1.9230769 | Y59: =IFERROR((Q59-H59)/Q59,"") -> 0.65789474 | Z59: =IFERROR(W59/F59,"") -> 0.46631579 | AH59: =IFERROR(AVERAGE(AE59:AG59),"") | AI59: =AE59+AF59+AG59 -> 0
T60: =F60-E60 -> 0 | U60: =T60*(1-I60-M60) -> 0 | V60: =(F60-E60)*0.2 -> 0 | W60: =F60-(E60+V60)-(F60*S60)-(F60*R60) -> 0 | X60: =IFERROR((F60-E60)/E60,"") | Z60: =IFERROR(W60/F60,"")
A61: 2026 | C61: alondra in | E61: 61000 | F61: 160000 | G61: 1 | H61: =((E61*N61)*(1+I61))*G61 -> 90.095886 | I61: 0.035 | J61: =H61*(1-I61) -> 86.94253 | K61: =H61-J61 -> 3.153356 | L61: 0.001397 | M61: 0.0215 | N61: =L61*(1+M61) -> 0.0014270355 | O61: =(J61*M61)+15 -> 16.869264 | P61: =(J61*N61)+M61 -> 0.14557008 | Q61: =((F61*N61)*(1+I61))*G61 -> 236.31708 | R61: 0.06 | T61: =F61-E61 -> 99000 | U61: =T61*(1-I61-M61) -> 93406.5 | V61: =(F61-E61)*0.2 -> 19800 | W61: =F61-(E61+V61)-(F61*S61)-(F61*R61) -> 69600 | X61: =IFERROR((F61-E61)/E61,"") -> 1.6229508 | Y61: =IFERROR((Q61-H61)/Q61,"") -> 0.61875 | Z61: =IFERROR(W61/F61,"") -> 0.435 | AH61: =IFERROR(AVERAGE(AE61:AG61),"") | AI61: =AE61+AF61+AG61 -> 0
A62: 2026 | C62: alondra out | E62: 61000 | F62: 140000 | G62: 1 | H62: =((E62*N62)*(1+I62))*G62 -> 90.095886 | I62: 0.035 | J62: =H62*(1-I62) -> 86.94253 | K62: =H62-J62 -> 3.153356 | L62: 0.001397 | M62: 0.0215 | N62: =L62*(1+M62) -> 0.0014270355 | O62: =(J62*M62)+15 -> 16.869264 | P62: =(J62*N62)+M62 -> 0.14557008 | Q62: =((F62*N62)*(1+I62))*G62 -> 206.77744 | R62: 0.06 | T62: =F62-E62 -> 79000 | U62: =T62*(1-I62-M62) -> 74536.5 | V62: =(F62-E62)*0.2 -> 15800 | W62: =F62-(E62+V62)-(F62*S62)-(F62*R62) -> 54800 | X62: =IFERROR((F62-E62)/E62,"") -> 1.295082 | Y62: =IFERROR((Q62-H62)/Q62,"") -> 0.56428571 | Z62: =IFERROR(W62/F62,"") -> 0.39142857 | AH62: =IFERROR(AVERAGE(AE62:AG62),"") | AI62: =AE62+AF62+AG62 -> 0
A63: 2026 | C63: alondra in out | E63: =E61+E62 -> 122000 | F63: 250000 | G63: 1 | H63: =((E63*N63)*(1+I63))*G63 -> 180.19177 | I63: 0.035 | J63: =H63*(1-I63) -> 173.88506 | K63: =H63-J63 -> 6.306712 | L63: 0.001397 | M63: 0.0215 | N63: =L63*(1+M63) -> 0.0014270355 | O63: =(J63*M63)+15 -> 18.738529 | P63: =(J63*N63)+M63 -> 0.26964015 | Q63: =((F63*N63)*(1+I63))*G63 -> 369.24544 | R63: 0.06 | T63: =F63-E63 -> 128000 | U63: =T63*(1-I63-M63) -> 120768 | V63: =(F63-E63)*0.2 -> 25600 | W63: =F63-(E63+V63)-(F63*S63)-(F63*R63) -> 87400 | X63: =IFERROR((F63-E63)/E63,"") -> 1.0491803 | Y63: =IFERROR((Q63-H63)/Q63,"") -> 0.512 | Z63: =IFERROR(W63/F63,"") -> 0.3496 | AH63: =IFERROR(AVERAGE(AE63:AG63),"") | AI63: =AE63+AF63+AG63 -> 0
A64: 2026 | C64: alondra in van 8 pax | E64: 160000 | F64: 300000 | G64: 1 | H64: =((E64*N64)*(1+I64))*G64 -> 236.31708 | I64: 0.035 | J64: =H64*(1-I64) -> 228.04598 | K64: =H64-J64 -> 8.2710978 | L64: 0.001397 | M64: 0.0215 | N64: =L64*(1+M64) -> 0.0014270355 | O64: =(J64*M64)+15 -> 19.902989 | P64: =(J64*N64)+M64 -> 0.34692971 | Q64: =((F64*N64)*(1+I64))*G64 -> 443.09452 | R64: 0.06 | T64: =F64-E64 -> 140000 | U64: =T64*(1-I64-M64) -> 132090 | V64: =(F64-E64)*0.2 -> 28000 | W64: =F64-(E64+V64)-(F64*S64)-(F64*R64) -> 94000 | X64: =IFERROR((F64-E64)/E64,"") -> 0.875 | Y64: =IFERROR((Q64-H64)/Q64,"") -> 0.46666667 | Z64: =IFERROR(W64/F64,"") -> 0.31333333 | AH64: =IFERROR(AVERAGE(AE64:AG64),"") | AI64: =AE64+AF64+AG64 -> 0
A65: 2026 | C65: alondra out van 8 pax | E65: 160000 | F65: 340000 | G65: 1 | H65: =((E65*N65)*(1+I65))*G65 -> 236.31708 | I65: 0.035 | J65: =H65*(1-I65) -> 228.04598 | K65: =H65-J65 -> 8.2710978 | L65: 0.001397 | M65: 0.0215 | N65: =L65*(1+M65) -> 0.0014270355 | O65: =(J65*M65)+15 -> 19.902989 | P65: =(J65*N65)+M65 -> 0.34692971 | Q65: =((F65*N65)*(1+I65))*G65 -> 502.17379 | R65: 0.06 | T65: =F65-E65 -> 180000 | U65: =T65*(1-I65-M65) -> 169830 | V65: =(F65-E65)*0.2 -> 36000 | W65: =F65-(E65+V65)-(F65*S65)-(F65*R65) -> 123600 | X65: =IFERROR((F65-E65)/E65,"") -> 1.125 | Y65: =IFERROR((Q65-H65)/Q65,"") -> 0.52941176 | Z65: =IFERROR(W65/F65,"") -> 0.36352941 | AH65: =IFERROR(AVERAGE(AE65:AG65),"") | AI65: =AE65+AF65+AG65 -> 0
A66: 2026 | C66: alondra in e out van 8 pax | E66: =160000*2 -> 320000 | F66: 580000 | G66: 1 | H66: =((E66*N66)*(1+I66))*G66 -> 472.63416 | I66: 0.035 | J66: =H66*(1-I66) -> 456.09196 | K66: =H66-J66 -> 16.542196 | L66: 0.001397 | M66: 0.0215 | N66: =L66*(1+M66) -> 0.0014270355 | O66: =(J66*M66)+15 -> 24.805977 | P66: =(J66*N66)+M66 -> 0.67235942 | Q66: =((F66*N66)*(1+I66))*G66 -> 856.64941 | R66: 0.06 | T66: =F66-E66 -> 260000 | U66: =T66*(1-I66-M66) -> 245310 | V66: =(F66-E66)*0.2 -> 52000 | W66: =F66-(E66+V66)-(F66*S66)-(F66*R66) -> 173200 | X66: =IFERROR((F66-E66)/E66,"") -> 0.8125 | Y66: =IFERROR((Q66-H66)/Q66,"") -> 0.44827586 | Z66: =IFERROR(W66/F66,"") -> 0.29862069 | AH66: =IFERROR(AVERAGE(AE66:AG66),"") | AI66: =AE66+AF66+AG66 -> 0
A67: 2026 | C67: alondra in van 14pax | E67: 160000 | F67: 300000 | G67: 1 | H67: =((E67*N67)*(1+I67))*G67 -> 236.31708 | I67: 0.035 | J67: =H67*(1-I67) -> 228.04598 | K67: =H67-J67 -> 8.2710978 | L67: 0.001397 | M67: 0.0215 | N67: =L67*(1+M67) -> 0.0014270355 | O67: =(J67*M67)+15 -> 19.902989 | P67: =(J67*N67)+M67 -> 0.34692971 | Q67: =((F67*N67)*(1+I67))*G67 -> 443.09452 | R67: 0.06 | T67: =F67-E67 -> 140000 | U67: =T67*(1-I67-M67) -> 132090 | V67: =(F67-E67)*0.2 -> 28000 | W67: =F67-(E67+V67)-(F67*S67)-(F67*R67) -> 94000 | X67: =IFERROR((F67-E67)/E67,"") -> 0.875 | Y67: =IFERROR((Q67-H67)/Q67,"") -> 0.46666667 | Z67: =IFERROR(W67/F67,"") -> 0.31333333 | AH67: =IFERROR(AVERAGE(AE67:AG67),"") | AI67: =AE67+AF67+AG67 -> 0
A68: 2026 | C68: alondra out van 14 pax | E68: 160000 | F68: 340000 | G68: 1 | H68: =((E68*N68)*(1+I68))*G68 -> 236.31708 | I68: 0.035 | J68: =H68*(1-I68) -> 228.04598 | K68: =H68-J68 -> 8.2710978 | L68: 0.001397 | M68: 0.0215 | N68: =L68*(1+M68) -> 0.0014270355 | O68: =(J68*M68)+15 -> 19.902989 | P68: =(J68*N68)+M68 -> 0.34692971 | Q68: =((F68*N68)*(1+I68))*G68 -> 502.17379 | R68: 0.06 | T68: =F68-E68 -> 180000 | U68: =T68*(1-I68-M68) -> 169830 | V68: =(F68-E68)*0.2 -> 36000 | W68: =F68-(E68+V68)-(F68*S68)-(F68*R68) -> 123600 | X68: =IFERROR((F68-E68)/E68,"") -> 1.125 | Y68: =IFERROR((Q68-H68)/Q68,"") -> 0.52941176 | Z68: =IFERROR(W68/F68,"") -> 0.36352941 | AH68: =IFERROR(AVERAGE(AE68:AG68),"") | AI68: =AE68+AF68+AG68 -> 0
A69: 2026 | C69: alondra in e out van 14 pax | E69: =160000*2 -> 320000 | F69: 580000 | G69: 1 | H69: =((E69*N69)*(1+I69))*G69 -> 472.63416 | I69: 0.035 | J69: =H69*(1-I69) -> 456.09196 | K69: =H69-J69 -> 16.542196 | L69: 0.001397 | M69: 0.0215 | N69: =L69*(1+M69) -> 0.0014270355 | O69: =(J69*M69)+15 -> 24.805977 | P69: =(J69*N69)+M69 -> 0.67235942 | Q69: =((F69*N69)*(1+I69))*G69 -> 856.64941 | R69: 0.06 | T69: =F69-E69 -> 260000 | U69: =T69*(1-I69-M69) -> 245310 | V69: =(F69-E69)*0.2 -> 52000 | W69: =F69-(E69+V69)-(F69*S69)-(F69*R69) -> 173200 | X69: =IFERROR((F69-E69)/E69,"") -> 0.8125 | Y69: =IFERROR((Q69-H69)/Q69,"") -> 0.44827586 | Z69: =IFERROR(W69/F69,"") -> 0.29862069 | AH69: =IFERROR(AVERAGE(AE69:AG69),"") | AI69: =AE69+AF69+AG69 -> 0
A71: 2026 | C71: alondra aviario ate 3 pax | E71: 385000 | F71: 580000 | G71: 1 | H71: =((E71*N71)*(1+I71))*G71 -> 568.63797 | I71: 0.035 | J71: =H71*(1-I71) -> 548.73564 | K71: =H71-J71 -> 19.902329 | L71: 0.001397 | M71: 0.0215 | N71: =L71*(1+M71) -> 0.0014270355 | O71: =(J71*M71)+15 -> 26.797816 | P71: =(J71*N71)+M71 -> 0.80456524 | Q71: =((F71*N71)*(1+I71))*G71 -> 856.64941 | R71: 0.06 | T71: =F71-E71 -> 195000 | U71: =T71*(1-I71-M71) -> 183982.5 | V71: =(F71-E71)*0.2 -> 39000 | W71: =F71-(E71+V71)-(F71*S71)-(F71*R71) -> 121200 | X71: =IFERROR((F71-E71)/E71,"") -> 0.50649351 | Y71: =IFERROR((Q71-H71)/Q71,"") -> 0.3362069 | Z71: =IFERROR(W71/F71,"") -> 0.20896552 | AH71: =IFERROR(AVERAGE(AE71:AG71),"") | AI71: =AE71+AF71+AG71 -> 0
A72: 2026 | C72: alondra aviario ate 8 pax | E72: 555000 | F72: 780000 | G72: 1 | H72: =((E72*N72)*(1+I72))*G72 -> 819.72487 | I72: 0.035 | J72: =H72*(1-I72) -> 791.0345 | K72: =H72-J72 -> 28.69037 | L72: 0.001397 | M72: 0.0215 | N72: =L72*(1+M72) -> 0.0014270355 | O72: =(J72*M72)+15 -> 32.007242 | P72: =(J72*N72)+M72 -> 1.1503343 | Q72: =((F72*N72)*(1+I72))*G72 -> 1152.0458 | R72: 0.06 | T72: =F72-E72 -> 225000 | U72: =T72*(1-I72-M72) -> 212287.5 | V72: =(F72-E72)*0.2 -> 45000 | W72: =F72-(E72+V72)-(F72*S72)-(F72*R72) -> 133200 | X72: =IFERROR((F72-E72)/E72,"") -> 0.40540541 | Y72: =IFERROR((Q72-H72)/Q72,"") -> 0.28846154 | Z72: =IFERROR(W72/F72,"") -> 0.17076923 | AH72: =IFERROR(AVERAGE(AE72:AG72),"") | AI72: =AE72+AF72+AG72 -> 0
A73: 2026 | C73: alondra aviario ate 14 pax | E73: 660000 | F73: 900000 | G73: 1 | H73: =((E73*N73)*(1+I73))*G73 -> 974.80795 | I73: 0.035 | J73: =H73*(1-I73) -> 940.68967 | K73: =H73-J73 -> 34.118278 | L73: 0.001397 | M73: 0.0215 | N73: =L73*(1+M73) -> 0.0014270355 | O73: =(J73*M73)+15 -> 35.224828 | P73: =(J73*N73)+M73 -> 1.3638976 | Q73: =((F73*N73)*(1+I73))*G73 -> 1329.2836 | R73: 0.06 | T73: =F73-E73 -> 240000 | U73: =T73*(1-I73-M73) -> 226440 | V73: =(F73-E73)*0.2 -> 48000 | W73: =F73-(E73+V73)-(F73*S73)-(F73*R73) -> 138000 | X73: =IFERROR((F73-E73)/E73,"") -> 0.36363636 | Y73: =IFERROR((Q73-H73)/Q73,"") -> 0.26666667 | Z73: =IFERROR(W73/F73,"") -> 0.15333333 | AH73: =IFERROR(AVERAGE(AE73:AG73),"") | AI73: =AE73+AF73+AG73 -> 0
A75: 2026 | C75: Corona Island | E75: 633000 | F75: 850000 | G75: 1 | H75: =((E75*N75)*(1+I75))*G75 -> 934.92944 | I75: 0.035 | J75: =H75*(1-I75) -> 902.20691 | K75: =H75-J75 -> 32.722531 | L75: 0.001397 | M75: 0.0215 | N75: =L75*(1+M75) -> 0.0014270355 | O75: =(J75*M75)+15 -> 34.397449 | P75: =(J75*N75)+M75 -> 1.3089813 | Q75: =((F75*N75)*(1+I75))*G75 -> 1255.4345 | R75: 0.06 | T75: =F75-E75 -> 217000 | U75: =T75*(1-I75-M75) -> 204739.5 | V75: =(F75-E75)*0.2 -> 43400 | W75: =F75-(E75+V75)-(F75*S75)-(F75*R75) -> 122600 | X75: =IFERROR((F75-E75)/E75,"") -> 0.34281201 | Y75: =IFERROR((Q75-H75)/Q75,"") -> 0.25529412 | Z75: =IFERROR(W75/F75,"") -> 0.14423529 | AH75: =IFERROR(AVERAGE(AE75:AG75),"") | AI75: =AE75+AF75+AG75 -> 0
T76: =F76-E76 -> 0 | U76: =T76*(1-I76-M76) -> 0 | V76: =(F76-E76)*0.2 -> 0 | W76: =F76-(E76+V76)-(F76*S76)-(F76*R76) -> 0 | X76: =IFERROR((F76-E76)/E76,"") | Z76: =IFERROR(W76/F76,"")
A77: 2026 | C77: isla palma | E77: 420000 | F77: 550000 | G77: 1 | H77: =((E77*N77)*(1+I77))*G77 -> 620.33233 | I77: 0.035 | J77: =H77*(1-I77) -> 598.6207 | K77: =H77-J77 -> 21.711632 | L77: 0.001397 | M77: 0.0215 | N77: =L77*(1+M77) -> 0.0014270355 | O77: =(J77*M77)+15 -> 27.870345 | P77: =(J77*N77)+M77 -> 0.87575299 | Q77: =((F77*N77)*(1+I77))*G77 -> 812.33996 | R77: 0.06 | T77: =F77-E77 -> 130000 | U77: =T77*(1-I77-M77) -> 122655 | V77: =(F77-E77)*0.2 -> 26000 | W77: =F77-(E77+V77)-(F77*S77)-(F77*R77) -> 71000 | X77: =IFERROR((F77-E77)/E77,"") -> 0.30952381 | Y77: =IFERROR((Q77-H77)/Q77,"") -> 0.23636364 | Z77: =IFERROR(W77/F77,"") -> 0.12909091 | AH77: =IFERROR(AVERAGE(AE77:AG77),"") | AI77: =AE77+AF77+AG77 -> 0
A78: 2026 | C78: isla palma CHD 04 a 06 anos | E78: 350000 | F78: 420000 | G78: 1 | H78: =((E78*N78)*(1+I78))*G78 -> 516.94361 | I78: 0.035 | J78: =H78*(1-I78) -> 498.85058 | K78: =H78-J78 -> 18.093026 | L78: 0.001397 | M78: 0.0215 | N78: =L78*(1+M78) -> 0.0014270355 | O78: =(J78*M78)+15 -> 25.725288 | P78: =(J78*N78)+M78 -> 0.73337749 | Q78: =((F78*N78)*(1+I78))*G78 -> 620.33233 | R78: 0.06 | T78: =F78-E78 -> 70000 | U78: =T78*(1-I78-M78) -> 66045 | V78: =(F78-E78)*0.2 -> 14000 | W78: =F78-(E78+V78)-(F78*S78)-(F78*R78) -> 30800 | X78: =IFERROR((F78-E78)/E78,"") -> 0.2 | Y78: =IFERROR((Q78-H78)/Q78,"") -> 0.16666667 | Z78: =IFERROR(W78/F78,"") -> 0.073333333 | AH78: =IFERROR(AVERAGE(AE78:AG78),"") | AI78: =AE78+AF78+AG78 -> 0
T79: =F79-E79 -> 0 | U79: =T79*(1-I79-M79) -> 0 | V79: =(F79-E79)*0.2 -> 0 | W79: =F79-(E79+V79)-(F79*S79)-(F79*R79) -> 0 | X79: =IFERROR((F79-E79)/E79,"") | Z79: =IFERROR(W79/F79,"")
A80: 2025 | B80: CTY102-BOG | C80: Candelaria + Museu (Básico) (BOG PASS) | D80: 2 Pessoas | E80: =((418000*0.8)*1.1)+(110000/G80) -> 422840 | F80: =E80*1.6 -> 676544 | G80: 2 | H80: =((E80*N80)*(1+I80))*G80 -> 1249.0539 | I80: 0.035 | J80: =H80*(1-I80) -> 1205.337 | K80: =H80-J80 -> 43.716887 | L80: 0.001397 | M80: 0.0215 | N80: =L80*(1+M80) -> 0.0014270355 | O80: =(J80*M80)+15 -> 40.914746 | P80: =(J80*N80)+M80 -> 1.7415587 | Q80: =((F80*N80)*(1+I80))*G80 -> 1998.4863 | R80: 0.06 | T80: =F80-E80 -> 253704 | U80: =T80*(1-I80-M80) -> 239369.72 | V80: =(F80-E80)*0.2 -> 50740.8 | W80: =F80-(E80+V80)-(F80*S80)-(F80*R80) -> 162370.56 | X80: =IFERROR((F80-E80)/E80,"") -> 0.6 | Y80: =IFERROR((Q80-H80)/Q80,"") -> 0.375 | Z80: =IFERROR(W80/F80,"") -> 0.24 | AH80: =IFERROR(AVERAGE(AE80:AG80),"") | AI80: =AE80+AF80+AG80 -> 0
A81: 2025 | B81: CTY103-BOG | C81: Candelaria + Museu (Básico) (BOG PASS) | D81: 3 Pessoas | E81: =((368000*0.8)*1.1)+(110000/G81) -> 360506.67 | F81: =E81*1.6 -> 576810.67 | G81: 3 | H81: =((E81*N81)*(1+I81))*G81 -> 1597.3853 | I81: 0.035 | J81: =H81*(1-I81) -> 1541.4768 | K81: =H81-J81 -> 55.908485 | L81: 0.001397 | M81: 0.0215 | N81: =L81*(1+M81) -> 0.0014270355 | O81: =(J81*M81)+15 -> 48.141751 | P81: =(J81*N81)+M81 -> 2.2212421 | Q81: =((F81*N81)*(1+I81))*G81 -> 2555.8165 | R81: 0.06 | T81: =F81-E81 -> 216304 | U81: =T81*(1-I81-M81) -> 204082.82 | V81: =(F81-E81)*0.2 -> 43260.8 | W81: =F81-(E81+V81)-(F81*S81)-(F81*R81) -> 138434.56 | X81: =IFERROR((F81-E81)/E81,"") -> 0.6 | Y81: =IFERROR((Q81-H81)/Q81,"") -> 0.375 | Z81: =IFERROR(W81/F81,"") -> 0.24 | AH81: =IFERROR(AVERAGE(AE81:AG81),"") | AI81: =AE81+AF81+AG81 -> 0
A82: 2025 | B82: CTY104-BOG | C82: Candelaria + Museu (Básico) (BOG PASS) | D82: 4 Pessoas | E82: =((289000*0.8)*1.1)+(110000/G82) -> 281820 | F82: =E82*1.7 -> 479094 | G82: 4 | H82: =((E82*N82)*(1+I82))*G82 -> 1664.972 | I82: 0.035 | J82: =H82*(1-I82) -> 1606.698 | K82: =H82-J82 -> 58.274019 | L82: 0.001397 | M82: 0.0215 | N82: =L82*(1+M82) -> 0.0014270355 | O82: =(J82*M82)+15 -> 49.544006 | P82: =(J82*N82)+M82 -> 2.314315 | Q82: =((F82*N82)*(1+I82))*G82 -> 2830.4524 | R82: 0.06 | T82: =F82-E82 -> 197274 | U82: =T82*(1-I82-M82) -> 186128.02 | V82: =(F82-E82)*0.2 -> 39454.8 | W82: =F82-(E82+V82)-(F82*S82)-(F82*R82) -> 129073.56 | X82: =IFERROR((F82-E82)/E82,"") -> 0.7 | Y82: =IFERROR((Q82-H82)/Q82,"") -> 0.41176471 | Z82: =IFERROR(W82/F82,"") -> 0.26941176 | AH82: =IFERROR(AVERAGE(AE82:AG82),"") | AI82: =AE82+AF82+AG82 -> 0
A83: 2025 | B83: CTY101-BOG | C83: Candelaria + Museu (Básico) (BOG PASS) | D83: 1 Pessoa | E83: =(880000*0.8)+100000 -> 804000 | F83: =E83*1.4 -> 1125600 | G83: 1 | H83: =((E83*N83)*(1+I83))*G83 -> 1187.4933 | I83: 0.035 | J83: =H83*(1-I83) -> 1145.9311 | K83: =H83-J83 -> 41.562266 | L83: 0.001397 | M83: 0.0215 | N83: =L83*(1+M83) -> 0.0014270355 | O83: =(J83*M83)+15 -> 39.637518 | P83: =(J83*N83)+M83 -> 1.6567843 | Q83: =((F83*N83)*(1+I83))*G83 -> 1662.4906 | R83: 0.06 | T83: =F83-E83 -> 321600 | U83: =T83*(1-I83-M83) -> 303429.6 | V83: =(F83-E83)*0.2 -> 64320 | W83: =F83-(E83+V83)-(F83*S83)-(F83*R83) -> 189744 | X83: =IFERROR((F83-E83)/E83,"") -> 0.4 | Y83: =IFERROR((Q83-H83)/Q83,"") -> 0.28571429 | Z83: =IFERROR(W83/F83,"") -> 0.16857143 | AH83: =IFERROR(AVERAGE(AE83:AG83),"") | AI83: =AE83+AF83+AG83 -> 0
A84: 2025 | B84: CTY102-BOG | C84: Candelaria + Museu (Básico) (BOG PASS) | D84: 2 Pessoas | E84: 359400 | F84: 485000 | G84: 2 | H84: =((E84*N84)*(1+I84))*G84 -> 1061.6545 | I84: 0.035 | J84: =H84*(1-I84) -> 1024.4966 | K84: =H84-J84 -> 37.157907 | L84: 0.001397 | M84: 0.0215 | N84: =L84*(1+M84) -> 0.0014270355 | O84: =(J84*M84)+15 -> 37.026676 | P84: =(J84*N84)+M84 -> 1.483493 | Q84: =((F84*N84)*(1+I84))*G84 -> 1432.6723 | R84: 0.06 | T84: =F84-E84 -> 125600 | U84: =T84*(1-I84-M84) -> 118503.6 | V84: =(F84-E84)*0.2 -> 25120 | W84: =F84-(E84+V84)-(F84*S84)-(F84*R84) -> 71380 | X84: =IFERROR((F84-E84)/E84,"") -> 0.34947134 | Y84: =IFERROR((Q84-H84)/Q84,"") -> 0.25896907 | Z84: =IFERROR(W84/F84,"") -> 0.14717526 | AH84: =IFERROR(AVERAGE(AE84:AG84),"") | AI84: =AE84+AF84+AG84 -> 0
A85: 2025 | B85: CTY103-BOG | C85: Candelaria + Museu (Básico) (BOG PASS) | D85: 3 Pessoas | E85: 305511 | F85: 435000 | G85: 3 | H85: =((E85*N85)*(1+I85))*G85 -> 1353.7025 | I85: 0.035 | J85: =H85*(1-I85) -> 1306.3229 | K85: =H85-J85 -> 47.379588 | L85: 0.001397 | M85: 0.0215 | N85: =L85*(1+M85) -> 0.0014270355 | O85: =(J85*M85)+15 -> 43.085943 | P85: =(J85*N85)+M85 -> 1.8856692 | Q85: =((F85*N85)*(1+I85))*G85 -> 1927.4612 | R85: 0.06 | T85: =F85-E85 -> 129489 | U85: =T85*(1-I85-M85) -> 122172.87 | V85: =(F85-E85)*0.2 -> 25897.8 | W85: =F85-(E85+V85)-(F85*S85)-(F85*R85) -> 77491.2 | X85: =IFERROR((F85-E85)/E85,"") -> 0.42384399 | Y85: =IFERROR((Q85-H85)/Q85,"") -> 0.29767586 | Z85: =IFERROR(W85/F85,"") -> 0.17814069 | AH85: =IFERROR(AVERAGE(AE85:AG85),"") | AI85: =AE85+AF85+AG85 -> 0
A86: 2025 | B86: CTY104-BOG | C86: Candelaria + Museu (Básico) (BOG PASS) | D86: 4 Pessoas | E86: 237450 | F86: 453000 | G86: 4 | H86: =((E86*N86)*(1+I86))*G86 -> 1402.8373 | I86: 0.035 | J86: =H86*(1-I86) -> 1353.738 | K86: =H86-J86 -> 49.099304 | L86: 0.001397 | M86: 0.0215 | N86: =L86*(1+M86) -> 0.0014270355 | O86: =(J86*M86)+15 -> 44.105366 | P86: =(J86*N86)+M86 -> 1.9533321 | Q86: =((F86*N86)*(1+I86))*G86 -> 2676.2909 | R86: 0.06 | T86: =F86-E86 -> 215550 | U86: =T86*(1-I86-M86) -> 203371.42 | V86: =(F86-E86)*0.2 -> 43110 | W86: =F86-(E86+V86)-(F86*S86)-(F86*R86) -> 145260 | X86: =IFERROR((F86-E86)/E86,"") -> 0.90777006 | Y86: =IFERROR((Q86-H86)/Q86,"") -> 0.47582781 | Z86: =IFERROR(W86/F86,"") -> 0.32066225 | AH86: =IFERROR(AVERAGE(AE86:AG86),"") | AI86: =AE86+AF86+AG86 -> 0
A87: 2025 | B87: CTY105-BOG | C87: Candelaria + Museu + Monserrate (BOG PASS) | D87: 1 Pessoa | E87: =((926000)*1.1)+(110000/G87) -> 1128600 | F87: 1500000 | G87: 1 | H87: =((E87*N87)*(1+I87))*G87 -> 1666.9216 | I87: 0.035 | J87: =H87*(1-I87) -> 1608.5793 | K87: =H87-J87 -> 58.342256 | L87: 0.001397 | M87: 0.0215 | N87: =L87*(1+M87) -> 0.0014270355 | O87: =(J87*M87)+15 -> 49.584456 | P87: =(J87*N87)+M87 -> 2.3169998 | Q87: =((F87*N87)*(1+I87))*G87 -> 2215.4726 | R87: 0.06 | T87: =F87-E87 -> 371400 | U87: =T87*(1-I87-M87) -> 350415.9 | V87: =(F87-E87)*0.2 -> 74280 | W87: =F87-(E87+V87)-(F87*S87)-(F87*R87) -> 207120 | X87: =IFERROR((F87-E87)/E87,"") -> 0.32908028 | Y87: =IFERROR((Q87-H87)/Q87,"") -> 0.2476 | Z87: =IFERROR(W87/F87,"") -> 0.13808 | AH87: =IFERROR(AVERAGE(AE87:AG87),"") | AI87: =AE87+AF87+AG87 -> 0
A88: 2025 | B88: CTY106-BOG | C88: Candelaria + Museu + Monserrate (BOG PASS) | D88: 2 Pessoas | E88: =((508000)*1.1)+(110000/G88) -> 613800 | F88: =E88*1.6 -> 982080 | G88: 2 | H88: =((E88*N88)*(1+I88))*G88 -> 1813.1428 | I88: 0.035 | J88: =H88*(1-I88) -> 1749.6828 | K88: =H88-J88 -> 63.459998 | L88: 0.001397 | M88: 0.0215 | N88: =L88*(1+M88) -> 0.0014270355 | O88: =(J88*M88)+15 -> 52.61818 | P88: =(J88*N88)+M88 -> 2.5183595 | Q88: =((F88*N88)*(1+I88))*G88 -> 2901.0285 | R88: 0.06 | T88: =F88-E88 -> 368280 | U88: =T88*(1-I88-M88) -> 347472.18 | V88: =(F88-E88)*0.2 -> 73656 | W88: =F88-(E88+V88)-(F88*S88)-(F88*R88) -> 235699.2 | X88: =IFERROR((F88-E88)/E88,"") -> 0.6 | Y88: =IFERROR((Q88-H88)/Q88,"") -> 0.375 | Z88: =IFERROR(W88/F88,"") -> 0.24 | AH88: =IFERROR(AVERAGE(AE88:AG88),"") | AI88: =AE88+AF88+AG88 -> 0
A89: 2025 | B89: CTY107-BOG | C89: Candelaria + Museu + Monserrate (BOG PASS) | D89: 3 Pessoas | E89: =((454400)*1.1)+(110000/G89) -> 536506.67 | F89: =E89*1.6 -> 858410.67 | G89: 3 | H89: =((E89*N89)*(1+I89))*G89 -> 2377.2317 | I89: 0.035 | J89: =H89*(1-I89) -> 2294.0285 | K89: =H89-J89 -> 83.203108 | L89: 0.001397 | M89: 0.0215 | N89: =L89*(1+M89) -> 0.0014270355 | O89: =(J89*M89)+15 -> 64.321614 | P89: =(J89*N89)+M89 -> 3.2951602 | Q89: =((F89*N89)*(1+I89))*G89 -> 3803.5706 | R89: 0.06 | T89: =F89-E89 -> 321904 | U89: =T89*(1-I89-M89) -> 303716.42 | V89: =(F89-E89)*0.2 -> 64380.8 | W89: =F89-(E89+V89)-(F89*S89)-(F89*R89) -> 206018.56 | X89: =IFERROR((F89-E89)/E89,"") -> 0.6 | Y89: =IFERROR((Q89-H89)/Q89,"") -> 0.375 | Z89: =IFERROR(W89/F89,"") -> 0.24 | AH89: =IFERROR(AVERAGE(AE89:AG89),"") | AI89: =AE89+AF89+AG89 -> 0
A90: 2025 | B90: CTY108-BOG | C90: Candelaria + Museu + Monserrate (BOG PASS) | D90: 4 Pessoas | E90: =((362400)*1.1)+(110000/G90) -> 426140 | F90: =E90*1.6 -> 681824 | G90: 4 | H90: =((E90*N90)*(1+I90))*G90 -> 2517.604 | I90: 0.035 | J90: =H90*(1-I90) -> 2429.4879 | K90: =H90-J90 -> 88.11614 | L90: 0.001397 | M90: 0.0215 | N90: =L90*(1+M90) -> 0.0014270355 | O90: =(J90*M90)+15 -> 67.233989 | P90: =(J90*N90)+M90 -> 3.4884654 | Q90: =((F90*N90)*(1+I90))*G90 -> 4028.1664 | R90: 0.06 | T90: =F90-E90 -> 255684 | U90: =T90*(1-I90-M90) -> 241237.85 | V90: =(F90-E90)*0.2 -> 51136.8 | W90: =F90-(E90+V90)-(F90*S90)-(F90*R90) -> 163637.76 | X90: =IFERROR((F90-E90)/E90,"") -> 0.6 | Y90: =IFERROR((Q90-H90)/Q90,"") -> 0.375 | Z90: =IFERROR(W90/F90,"") -> 0.24 | AH90: =IFERROR(AVERAGE(AE90:AG90),"") | AI90: =AE90+AF90+AG90 -> 0
A91: 2025 | B91: CTY109-BOG | C91: Candelaria + Museu + Monserrate (BOG PASS) | D91: 5 Pessoas | E91: =((307200)*1.1)+(110000/G91) -> 359920 | F91: =E91*1.6 -> 575872 | G91: 5 | H91: =((E91*N91)*(1+I91))*G91 -> 2657.9763 | I91: 0.035 | J91: =H91*(1-I91) -> 2564.9472 | K91: =H91-J91 -> 93.029172 | L91: 0.001397 | M91: 0.0215 | N91: =L91*(1+M91) -> 0.0014270355 | O91: =(J91*M91)+15 -> 70.146364 | P91: =(J91*N91)+M91 -> 3.6817707 | Q91: =((F91*N91)*(1+I91))*G91 -> 4252.7621 | R91: 0.06 | T91: =F91-E91 -> 215952 | U91: =T91*(1-I91-M91) -> 203750.71 | V91: =(F91-E91)*0.2 -> 43190.4 | W91: =F91-(E91+V91)-(F91*S91)-(F91*R91) -> 138209.28 | X91: =IFERROR((F91-E91)/E91,"") -> 0.6 | Y91: =IFERROR((Q91-H91)/Q91,"") -> 0.375 | Z91: =IFERROR(W91/F91,"") -> 0.24 | AH91: =IFERROR(AVERAGE(AE91:AG91),"") | AI91: =AE91+AF91+AG91 -> 0
A92: 2025 | B92: CTY105-BOG | C92: Candelaria + Museu + Monserrate (BOG PASS) | D92: 1 Pessoa | E92: 1029600 | F92: 1150000 | G92: 1 | H92: =((E92*N92)*(1+I92))*G92 -> 1520.7004 | I92: 0.035 | J92: =H92*(1-I92) -> 1467.4759 | K92: =H92-J92 -> 53.224514 | L92: 0.001397 | M92: 0.0215 | N92: =L92*(1+M92) -> 0.0014270355 | O92: =(J92*M92)+15 -> 46.550732 | P92: =(J92*N92)+M92 -> 2.1156402 | Q92: =((F92*N92)*(1+I92))*G92 -> 1698.529 | R92: 0.06 | T92: =F92-E92 -> 120400 | U92: =T92*(1-I92-M92) -> 113597.4 | V92: =(F92-E92)*0.2 -> 24080 | W92: =F92-(E92+V92)-(F92*S92)-(F92*R92) -> 27320 | X92: =IFERROR((F92-E92)/E92,"") -> 0.11693862 | Y92: =IFERROR((Q92-H92)/Q92,"") -> 0.10469565 | Z92: =IFERROR(W92/F92,"") -> 0.023756522 | AH92: =IFERROR(AVERAGE(AE92:AG92),"") | AI92: =AE92+AF92+AG92 -> 0
A93: 2025 | B93: CTY106-BOG | C93: Candelaria + Museu + Monserrate (BOG PASS) | D93: 2 Pessoas | E93: =1191200/2 -> 595600 | F93: 680000 | G93: 2 | H93: =((E93*N93)*(1+I93))*G93 -> 1759.3807 | I93: 0.035 | J93: =H93*(1-I93) -> 1697.8023 | K93: =H93-J93 -> 61.578323 | L93: 0.001397 | M93: 0.0215 | N93: =L93*(1+M93) -> 0.0014270355 | O93: =(J93*M93)+15 -> 51.50275 | P93: =(J93*N93)+M93 -> 2.4443242 | Q93: =((F93*N93)*(1+I93))*G93 -> 2008.6952 | R93: 0.06 | T93: =F93-E93 -> 84400 | U93: =T93*(1-I93-M93) -> 79631.4 | V93: =(F93-E93)*0.2 -> 16880 | W93: =F93-(E93+V93)-(F93*S93)-(F93*R93) -> 26720 | X93: =IFERROR((F93-E93)/E93,"") -> 0.14170584 | Y93: =IFERROR((Q93-H93)/Q93,"") -> 0.12411765 | Z93: =IFERROR(W93/F93,"") -> 0.039294118 | AH93: =IFERROR(AVERAGE(AE93:AG93),"") | AI93: =AE93+AF93+AG93 -> 0
A94: 2025 | B94: CTY107-BOG | C94: Candelaria + Museu + Monserrate (BOG PASS) | D94: 3 Pessoas | E94: 487733 | F94: 625000 | G94: 3 | H94: =((E94*N94)*(1+I94))*G94 -> 2161.1182 | I94: 0.035 | J94: =H94*(1-I94) -> 2085.4791 | K94: =H94-J94 -> 75.639137 | L94: 0.001397 | M94: 0.0215 | N94: =L94*(1+M94) -> 0.0014270355 | O94: =(J94*M94)+15 -> 59.8378 | P94: =(J94*N94)+M94 -> 2.9975527 | Q94: =((F94*N94)*(1+I94))*G94 -> 2769.3408 | R94: 0.06 | T94: =F94-E94 -> 137267 | U94: =T94*(1-I94-M94) -> 129511.41 | V94: =(F94-E94)*0.2 -> 27453.4 | W94: =F94-(E94+V94)-(F94*S94)-(F94*R94) -> 72313.6 | X94: =IFERROR((F94-E94)/E94,"") -> 0.28143882 | Y94: =IFERROR((Q94-H94)/Q94,"") -> 0.2196272 | Z94: =IFERROR(W94/F94,"") -> 0.11570176 | AH94: =IFERROR(AVERAGE(AE94:AG94),"") | AI94: =AE94+AF94+AG94 -> 0
A95: 2025 | B95: CTY108-BOG | C95: Candelaria + Museu + Monserrate (BOG PASS) | D95: 4 Pessoas | E95: 387400 | F95: 510000 | G95: 4 | H95: =((E95*N95)*(1+I95))*G95 -> 2288.7309 | I95: 0.035 | J95: =H95*(1-I95) -> 2208.6253 | K95: =H95-J95 -> 80.105582 | L95: 0.001397 | M95: 0.0215 | N95: =L95*(1+M95) -> 0.0014270355 | O95: =(J95*M95)+15 -> 62.485445 | P95: =(J95*N95)+M95 -> 3.1732867 | Q95: =((F95*N95)*(1+I95))*G95 -> 3013.0428 | R95: 0.06 | T95: =F95-E95 -> 122600 | U95: =T95*(1-I95-M95) -> 115673.1 | V95: =(F95-E95)*0.2 -> 24520 | W95: =F95-(E95+V95)-(F95*S95)-(F95*R95) -> 67480 | X95: =IFERROR((F95-E95)/E95,"") -> 0.31646877 | Y95: =IFERROR((Q95-H95)/Q95,"") -> 0.24039216 | Z95: =IFERROR(W95/F95,"") -> 0.13231373 | AH95: =IFERROR(AVERAGE(AE95:AG95),"") | AI95: =AE95+AF95+AG95 -> 0
A96: 2025 | B96: CTY109-BOG | C96: Candelaria + Museu + Monserrate (BOG PASS) | D96: 5 Pessoas | E96: 329200 | F96: 460000 | G96: 5 | H96: =((E96*N96)*(1+I96))*G96 -> 2431.1119 | I96: 0.035 | J96: =H96*(1-I96) -> 2346.023 | K96: =H96-J96 -> 85.088918 | L96: 0.001397 | M96: 0.0215 | N96: =L96*(1+M96) -> 0.0014270355 | O96: =(J96*M96)+15 -> 65.439495 | P96: =(J96*N96)+M96 -> 3.3693581 | Q96: =((F96*N96)*(1+I96))*G96 -> 3397.058 | R96: 0.06 | T96: =F96-E96 -> 130800 | U96: =T96*(1-I96-M96) -> 123409.8 | V96: =(F96-E96)*0.2 -> 26160 | W96: =F96-(E96+V96)-(F96*S96)-(F96*R96) -> 77040 | X96: =IFERROR((F96-E96)/E96,"") -> 0.39732685 | Y96: =IFERROR((Q96-H96)/Q96,"") -> 0.28434783 | Z96: =IFERROR(W96/F96,"") -> 0.16747826 | AH96: =IFERROR(AVERAGE(AE96:AG96),"") | AI96: =AE96+AF96+AG96 -> 0
A97: 2025 | B97: ESP110-BOG | C97: Candelaria walking tour (Grupal) (BOG PASS) | D97: Regular | E97: =120615*1.1 -> 132676.5 | F97: 320000 | G97: 1 | H97: =((E97*N97)*(1+I97))*G97 -> 195.96077 | I97: 0.035 | J97: =H97*(1-I97) -> 189.10214 | K97: =H97-J97 -> 6.8586269 | L97: 0.001397 | M97: 0.0215 | N97: =L97*(1+M97) -> 0.0014270355 | O97: =(J97*M97)+15 -> 19.065696 | P97: =(J97*N97)+M97 -> 0.29135547 | Q97: =((F97*N97)*(1+I97))*G97 -> 472.63416 | R97: 0.06 | T97: =F97-E97 -> 187323.5 | U97: =T97*(1-I97-M97) -> 176739.72 | V97: =(F97-E97)*0.2 -> 37464.7 | W97: =F97-(E97+V97)-(F97*S97)-(F97*R97) -> 130658.8 | X97: =IFERROR((F97-E97)/E97,"") -> 1.4118815 | Y97: =IFERROR((Q97-H97)/Q97,"") -> 0.58538594 | Z97: =IFERROR(W97/F97,"") -> 0.40830875 | AH97: =IFERROR(AVERAGE(AE97:AG97),"") | AI97: =AE97+AF97+AG97 -> 0
A98: 2025 | B98: ESP205-LUN | C98: Cata de Ron y Chocolate (Lunatico) | D98: Por Pessoa | E98: =E308*1.1 -> 0 | F98: 300000 | G98: 1 | H98: =((E98*N98)*(1+I98))*G98 -> 0 | I98: 0.035 | J98: =H98*(1-I98) -> 0 | K98: =H98-J98 -> 0 | L98: 0.001397 | M98: 0.0215 | N98: =L98*(1+M98) -> 0.0014270355 | O98: =(J98*M98)+15 -> 15 | P98: =(J98*N98)+M98 -> 0.0215 | Q98: =((F98*N98)*(1+I98))*G98 -> 443.09452 | R98: 0.06 | T98: =F98-E98 -> 300000 | U98: =T98*(1-I98-M98) -> 283050 | V98: =(F98-E98)*0.2 -> 60000 | W98: =F98-(E98+V98)-(F98*S98)-(F98*R98) -> 222000 | X98: =IFERROR((F98-E98)/E98,"") | Y98: =IFERROR((Q98-H98)/Q98,"") -> 1 | Z98: =IFERROR(W98/F98,"") -> 0.74 | AH98: =IFERROR(AVERAGE(AE98:AG98),"") | AI98: =AE98+AF98+AG98 -> 0
A99: 2026 | B99: ESP205-LUN | C99: Cata de Ron y Chocolate (Lunatico) | D99: Por Pessoa | E99: =E309*1.1 -> 0 | F99: 400000 | G99: 1 | H99: =((E99*N99)*(1+I99))*G99 -> 0 | I99: 0.035 | J99: =H99*(1-I99) -> 0 | K99: =H99-J99 -> 0 | L99: 0.001397 | M99: 0.0215 | N99: =L99*(1+M99) -> 0.0014270355 | O99: =(J99*M99)+15 -> 15 | P99: =(J99*N99)+M99 -> 0.0215 | Q99: =((F99*N99)*(1+I99))*G99 -> 590.7927 | R99: 0.06 | T99: =F99-E99 -> 400000 | U99: =T99*(1-I99-M99) -> 377400 | V99: =(F99-E99)*0.2 -> 80000 | W99: =F99-(E99+V99)-(F99*S99)-(F99*R99) -> 296000 | X99: =IFERROR((F99-E99)/E99,"") | Y99: =IFERROR((Q99-H99)/Q99,"") -> 1 | Z99: =IFERROR(W99/F99,"") -> 0.74 | AH99: =IFERROR(AVERAGE(AE99:AG99),"") | AI99: =AE99+AF99+AG99 -> 0
A100: 2025 | B100: TUR101-BOG | C100: Catedral de Sal (Básico 8h) (BOG PASS) | D100: 1 Pessoa | E100: =((797600)*1.1) -> 877360 | F100: =E100*1.4 -> 1228304 | G100: 1 | H100: =((E100*N100)*(1+I100))*G100 -> 1295.8447 | I100: 0.035 | J100: =H100*(1-I100) -> 1250.4901 | K100: =H100-J100 -> 45.354565 | L100: 0.001397 | M100: 0.0215 | N100: =L100*(1+M100) -> 0.0014270355 | O100: =(J100*M100)+15 -> 41.885538 | P100: =(J100*N100)+M100 -> 1.8059938 | Q100: =((F100*N100)*(1+I100))*G100 -> 1814.1826 | R100: 0.06 | T100: =F100-E100 -> 350944 | U100: =T100*(1-I100-M100) -> 331115.66 | V100: =(F100-E100)*0.2 -> 70188.8 | W100: =F100-(E100+V100)-(F100*S100)-(F100*R100) -> 207056.96 | X100: =IFERROR((F100-E100)/E100,"") -> 0.4 | Y100: =IFERROR((Q100-H100)/Q100,"") -> 0.28571429 | Z100: =IFERROR(W100/F100,"") -> 0.16857143 | AH100: =IFERROR(AVERAGE(AE100:AG100),"") | AI100: =AE100+AF100+AG100 -> 0
A101: 2025 | B101: TUR102-BOG | C101: Catedral de Sal (Básico 8h) (BOG PASS) | D101: 2 Pessoas | E101: =((483200)*1.1) -> 531520 | F101: =E101*1.6 -> 850432 | G101: 2 | H101: =((E101*N101)*(1+I101))*G101 -> 1570.0907 | I101: 0.035 | J101: =H101*(1-I101) -> 1515.1375 | K101: =H101-J101 -> 54.953173 | L101: 0.001397 | M101: 0.0215 | N101: =L101*(1+M101) -> 0.0014270355 | O101: =(J101*M101)+15 -> 47.575456 | P101: =(J101*N101)+M101 -> 2.183655 | Q101: =((F101*N101)*(1+I101))*G101 -> 2512.1451 | R101: 0.06 | T101: =F101-E101 -> 318912 | U101: =T101*(1-I101-M101) -> 300893.47 | V101: =(F101-E101)*0.2 -> 63782.4 | W101: =F101-(E101+V101)-(F101*S101)-(F101*R101) -> 204103.68 | X101: =IFERROR((F101-E101)/E101,"") -> 0.6 | Y101: =IFERROR((Q101-H101)/Q101,"") -> 0.375 | Z101: =IFERROR(W101/F101,"") -> 0.24 | AH101: =IFERROR(AVERAGE(AE101:AG101),"") | AI101: =AE101+AF101+AG101 -> 0
A102: 2025 | B102: TUR103-BOG | C102: Catedral de Sal (Básico 8h) (BOG PASS) | D102: 3 Pessoas | E102: =((456800)*1.1) -> 502480 | F102: =E102*1.6 -> 803968 | G102: 3 | H102: =((E102*N102)*(1+I102))*G102 -> 2226.4614 | I102: 0.035 | J102: =H102*(1-I102) -> 2148.5352 | K102: =H102-J102 -> 77.926148 | L102: 0.001397 | M102: 0.0215 | N102: =L102*(1+M102) -> 0.0014270355 | O102: =(J102*M102)+15 -> 61.193507 | P102: =(J102*N102)+M102 -> 3.087536 | Q102: =((F102*N102)*(1+I102))*G102 -> 3562.3382 | R102: 0.06 | T102: =F102-E102 -> 301488 | U102: =T102*(1-I102-M102) -> 284453.93 | V102: =(F102-E102)*0.2 -> 60297.6 | W102: =F102-(E102+V102)-(F102*S102)-(F102*R102) -> 192952.32 | X102: =IFERROR((F102-E102)/E102,"") -> 0.6 | Y102: =IFERROR((Q102-H102)/Q102,"") -> 0.375 | Z102: =IFERROR(W102/F102,"") -> 0.24 | AH102: =IFERROR(AVERAGE(AE102:AG102),"") | AI102: =AE102+AF102+AG102 -> 0
A103: 2025 | B103: TUR104-BOG | C103: Catedral de Sal (Básico 8h) (BOG PASS) | D103: 4 Pessoas | E103: =((481000*0.8)*1.1) -> 423280 | F103: =E103*1.6 -> 677248 | G103: 4 | H103: =((E103*N103)*(1+I103))*G103 -> 2500.7073 | I103: 0.035 | J103: =H103*(1-I103) -> 2413.1826 | K103: =H103-J103 -> 87.524756 | L103: 0.001397 | M103: 0.0215 | N103: =L103*(1+M103) -> 0.0014270355 | O103: =(J103*M103)+15 -> 66.883425 | P103: =(J103*N103)+M103 -> 3.4651972 | Q103: =((F103*N103)*(1+I103))*G103 -> 4001.1317 | R103: 0.06 | T103: =F103-E103 -> 253968 | U103: =T103*(1-I103-M103) -> 239618.81 | V103: =(F103-E103)*0.2 -> 50793.6 | W103: =F103-(E103+V103)-(F103*S103)-(F103*R103) -> 162539.52 | X103: =IFERROR((F103-E103)/E103,"") -> 0.6 | Y103: =IFERROR((Q103-H103)/Q103,"") -> 0.375 | Z103: =IFERROR(W103/F103,"") -> 0.24 | AH103: =IFERROR(AVERAGE(AE103:AG103),"") | AI103: =AE103+AF103+AG103 -> 0
A104: 2025 | B104: TUR103-BOG | C104: Catedral de Sal (Básico 8h) (BOG PASS) | D104: 3 Pessoas | E104: 456800 | F104: 595000 | G104: 3 | H104: =((E104*N104)*(1+I104))*G104 -> 2024.0558 | I104: 0.035 | J104: =H104*(1-I104) -> 1953.2138 | K104: =H104-J104 -> 70.841952 | L104: 0.001397 | M104: 0.0215 | N104: =L104*(1+M104) -> 0.0014270355 | O104: =(J104*M104)+15 -> 56.994097 | P104: =(J104*N104)+M104 -> 2.8088055 | Q104: =((F104*N104)*(1+I104))*G104 -> 2636.4124 | R104: 0.06 | T104: =F104-E104 -> 138200 | U104: =T104*(1-I104-M104) -> 130391.7 | V104: =(F104-E104)*0.2 -> 27640 | W104: =F104-(E104+V104)-(F104*S104)-(F104*R104) -> 74860 | X104: =IFERROR((F104-E104)/E104,"") -> 0.3025394 | Y104: =IFERROR((Q104-H104)/Q104,"") -> 0.23226891 | Z104: =IFERROR(W104/F104,"") -> 0.12581513 | AH104: =IFERROR(AVERAGE(AE104:AG104),"") | AI104: =AE104+AF104+AG104 -> 0
A105: 2025 | B105: TUR104-BOG | C105: Catedral de Sal (Básico 8h) (BOG PASS) | D105: 4 Pessoas | E105: 461000 | F105: 585000 | G105: 4 | H105: =((E105*N105)*(1+I105))*G105 -> 2723.5543 | I105: 0.035 | J105: =H105*(1-I105) -> 2628.2299 | K105: =H105-J105 -> 95.324402 | L105: 0.001397 | M105: 0.0215 | N105: =L105*(1+M105) -> 0.0014270355 | O105: =(J105*M105)+15 -> 71.506944 | P105: =(J105*N105)+M105 -> 3.7720774 | Q105: =((F105*N105)*(1+I105))*G105 -> 3456.1373 | R105: 0.06 | T105: =F105-E105 -> 124000 | U105: =T105*(1-I105-M105) -> 116994 | V105: =(F105-E105)*0.2 -> 24800 | W105: =F105-(E105+V105)-(F105*S105)-(F105*R105) -> 64100 | X105: =IFERROR((F105-E105)/E105,"") -> 0.26898048 | Y105: =IFERROR((Q105-H105)/Q105,"") -> 0.21196581 | Z105: =IFERROR(W105/F105,"") -> 0.10957265 | AH105: =IFERROR(AVERAGE(AE105:AG105),"") | AI105: =AE105+AF105+AG105 -> 0
A106: 2025 | B106: TUR105-BOG | C106: Catedral de Sal c/ Guia (8h) (BOG PASS) | D106: 1 Pessoa | E106: =((1098400)*1.1)+(110000/G106) -> 1318240 | F106: =E106*1.4 -> 1845536 | G106: 1 | H106: =((E106*N106)*(1+I106))*G106 -> 1947.0164 | I106: 0.035 | J106: =H106*(1-I106) -> 1878.8708 | K106: =H106-J106 -> 68.145574 | L106: 0.001397 | M106: 0.0215 | N106: =L106*(1+M106) -> 0.0014270355 | O106: =(J106*M106)+15 -> 55.395723 | P106: =(J106*N106)+M106 -> 2.7027154 | Q106: =((F106*N106)*(1+I106))*G106 -> 2725.823 | R106: 0.06 | T106: =F106-E106 -> 527296 | U106: =T106*(1-I106-M106) -> 497503.78 | V106: =(F106-E106)*0.2 -> 105459.2 | W106: =F106-(E106+V106)-(F106*S106)-(F106*R106) -> 311104.64 | X106: =IFERROR((F106-E106)/E106,"") -> 0.4 | Y106: =IFERROR((Q106-H106)/Q106,"") -> 0.28571429 | Z106: =IFERROR(W106/F106,"") -> 0.16857143 | AH106: =IFERROR(AVERAGE(AE106:AG106),"") | AI106: =AE106+AF106+AG106 -> 0
...

Sheet Saldos e Devoluções Ju
A2: inte | D2: DEZEMBRO | E2: STATUS | F2: CONSULTORA | G2: camnbio dia venda | H2: camnbio dia pgto
A3: Data | B3: Nombre | C3: Passeio | D3: Valor Total em Pesos Colombianos TOTAL | E3: Pagamento
A4: 45266 | B4: Silvana Rigolino | C4: Walking Tour + Casti VIP 14:00 2PAX | D4: 310000 | E4: PAGO | F4: Jadhe/ Ju paga Saldo/ Pax Pagou por pix
A5: 45267 | B5: Silvana Rigolino | C5: PAO PAO (Con oceanario) 2 pax | D5: 420000 | E5: PAGO | F5: Jadhe/ Ju paga Saldo/ Pax Pagou por pix
A6: 45269 | B6: Tatiane Moura | C6: Welcome Tour 2 PAX 14:00 | D6: 265000 | E6: PAGO | F6: Jadhe/ Ju paga Saldo/ Pax Pagou por pix
A7: 45270 | B7: Tatiane Moura | C7: Mangata 2 pax | D7: 540000 | E7: PAGO | F7: Jadhe/ Ju paga Saldo/ Pax Pagou por pix
A8: 45275 | B8: Isabela Portilho | C8: Walking Tour + Casti VIP 14:00 2PAX | D8: 310000 | E8: PAGO | F8: Alessandra/ Ju paga Saldo /Pax pagou por pix
A9: 45278 | B9: Amanda Nobrega | C9: Walking Tour + Castillo Andres 09:00 2 PAX | D9: 50000 | E9: PAGO | F9: Alessandra/ Só pago da diferença do saldo total
A10: 45282 | B10: João Neto | C10: Walking Tour + Casti VIP 14:00 8PAX | D10: 600000 | E10: PAGO | F10: Jadhe/ Ju paga Saldo/ Pax Pagou por pix
A11: 45283 | B11: Marcela Nogueira | C11: Paue 2 pax | D11: 540000 | E11: PAGO | F11: Alessandra/ Ju paga Saldo /Pax pagou por pix
A12: 45287 | C12: Tour Escala 5 pax | D12: 850000 | E12: PAGO | F12: Agencia/ Ju paga saldo
A13: 45287 | B13: Karla Bueno | C13: SABAI 10 pax adultos, 6 adult y 4 CHILD | D13: 2850000 | E13: PAGO | F13: SI HIZO EL PAGO 2850 Y ERA 2560 - SALDO 290
A14: 45289 | B14: Anne Mello | C14: Bora Bora VIP 2 pax | D14: 40000 | E14: PAGO | F14: Jadhe/ Ju paga Saldo/ Pax Pagou por link
A15: 45294 | B15: Anita Varela | C15: Parada 4 asoleadoras | D15: 400000 | E15: PAGO | F15: Jadhe/ Ju paga Saldo/ Pax Pagou por pix
A16: 12/24/2023 | B16: Sandra Domenico | C16: Islabela 3 pax | D16: 60000 | E16: PAGO | F16: Jadhe/ Só pago da diferença do saldo total
A17: 12/28/2023 | B17: Diandra Ribas | C17: Walking Tour + Cast 1PAX - Andrés | D17: 155000 | E17: PAGO | F17: Jadhe/ Ju paga Saldo/ Pax Pagou por pix
A18: 12/29/2023 | B18: Daniela Fiori | C18: Walking Tour + Castillo San Felipe Andres 2024 | D18: 620000 | E18: PAGO | F18: Jadhe/ Ju paga Saldo/ Pax Pagou por pix
A19: 12/29/2023 | B19: Jaqueline Ornellas | C19: Walking Tour + Castillo Andres 09:00 2 PAX | D19: 50000 | E19: PAGO | F19: Alessandra/ Só pago da diferença do saldo total
A20: 12/30/2023 | B20: Carmen Meneses | C20: Walking Tour + Cast 6 PAX - Andrés | D20: 520000 | E20: PAGO | F20: Jadhe/ Ju paga Saldo/ Pax Pagou por pix
A21: 12/31/2023 | B21: Carmen Meneses | C21: Aviario 6 PAX - Andrés | D21: 340000 | E21: PAGO | F21: Jadhe/ Ju paga Saldo/ Pax Pagou por pix
A22: 12/31/2023 | B22: Julia Castanheira | C22: Sabai 2 pax | D22: 660000- 290.000= 370.000 | E22: PAGO | F22: Alessandra/ Ju paga Saldo /Pax pagou por pix
A31: SALDOS PENDENTES JU | D31: JANEIRO | E31: STATUS | F31: CONSULTORA
A32: Data | B32: Nombre | C32: Passeio | D32: Valor Total em Pesos Colombianos TOTAL | E32: Pagamento
A33: 45297 | B33: Ana Tunher | C33: Walking Tour + Castillo San Felipe VIP 14:00 3PAX 2024 | D33: 355.000COP | E33: PAGO | F33: Jadhe/ Ju paga Saldo/ Pax Pagou por pix
A34: 45298 | B34: Iara Malan | C34: Walking Tour + Cast 3PAX - Hernán | D34: 400000 | E34: PAGO | F34: Jadhe/ Ju paga Saldo/ Pax Pagou por pix
A35: 45301 | B35: Camila Recoliano | C35: Walking Tour + Castillo San Felipe Andres 09:00 2PAX 2024 | D35: 310000 | E35: PAGO | F35: Jadhe/ Ju paga Saldo/ Pax Pagou por pix
A36: 45302 | B36: Regina Sartore | C36: Walking Tour + Castillo San Felipe VIP 09:00 2PAX 2024 | D36: 310000 | E36: PAGO | F36: Jadhe/ Ju paga Saldo/ Pax Pagou por pix
A37: 45303 | B37: Priscilla Bezerra | C37: Isla del sol 2 pax | D37: 544000 | E37: PAGO | F37: Alessandra/ Ju paga Saldo /Pax pagou por pix
A38: 45303 | B38: Marcos Ribeiro | C38: Walking + Cast 2 PAX 14:00hrs- Andrés | D38: 310000 | E38: PAGO | F38: Jadhe/ Ju paga Saldo/ Pax Pagou por pix
A39: 45444 | B39: Carmen Meneses | C39: Boats 4 u | D39: 4347000 | E39: PAGO | F39: Jadhe/ Ju pagou 15% e incluimos transfers nos demais dias
A40: 01/18/2024 | B40: Ivanda Marques | C40: Mangata 4 pax | D40: 1160000 | E40: PAGO | F40: Alessandra/ Ju paga Saldo /Pax pagou por pix
A41: 45444 | B41: Carmen Meneses | C41: Parada Paue | D41: 600000 | E41: PAGO | F41: Jadhe/ Ju paga Saldo/ Pax Pagou por pix
A42: 45383 | B42: Guilherme Schasiepen | C42: Walking Tour + Castillo San Felipe 09:00 7PAX 2024 | D42: 580000 | E42: PAGO | F42: Jadhe/ Ju paga Saldo/ Pax Pagou por pix
A43: 45303 | B43: Gabriel de Souza | C43: Fenix jantar 2 pax | D43: 400000 | E43: PAGO | F43: Alessandra/ Ju paga Saldo /Pax pagou por pix
A44: 45352 | B44: Silvana Brito | C44: Walking Tour + Castillo San Felipe Andres 09:00 2 PAX | D44: 310000 | E44: PAGO | F44: Jadhe/ Ju paga Saldo/ Pax Pagou por pix
A45: 45413 | B45: Juliana Custodio | C45: Walking Tour + Castillo San Felipe Andres 14:00 2 PAX | D45: 310000 | E45: PAGO | F45: Alessandra/ Ju paga Saldo /Pax pagou por pix
A46: 45444 | B46: Ana Tunher | C46: Walking Tour + Castillo San Felipe VIP 14:00 3PAX 2024 | D46: 355000 | E46: PAGO | F46: Jadhe/ Ju paga Saldo/ Pax Pagou por pix
A47: 45303 | B47: Gabriel de Souza | C47: Bora vip 2 pax | D47: 660000 | E47: PAGO | F47: Alessandra/ Ju paga Saldo /Pax pagou por pix
A48: 45304 | B48: Gustavo Mestriner | C48: Walking Tour + Castillo San Felipe Andres 14:00 4 PAX 2024 | D48: 485000 | E48: PAGO | F48: Jadhe/ Ju paga Saldo/ Pax Pagou por pix
A49: 45304 | B49: Gabriel de Souza | C49: Isla Palma 2 pax | D49: 700000 | E49: PAGO | F49: Alessandra/ Ju paga Saldo /Pax pagou por pix
A50: 45305 | B50: Daniella Oliveira | C50: Walking + Cast y convento en la popa 5 PAX - Andrés | D50: 775000 | E50: PAGO | F50: Jadhe/ Ju paga Saldo/ Pax Pagou por pix
A51: 45305 | B51: Marcos Ribeiro | C51: Bora Bora Vip 2 pax | D51: 660000 | E51: PAGO | F51: Jadhe/ Ju paga Saldo/ Pax Pagou por pix
A52: 45352 | B52: Juliana Nogueira | C52: Walking Tour + Castillo San Felipe 09:00 2PAX 2024 | D52: 310000 | E52: PAGO | F52: Jadhe/ Ju paga Saldo/ Pax Pagou por pix
A53: 45308 | B53: Ivanda Marques | C53: Walking Tour + Castillo San Felipe VIP 09:00 3PAX/4PAX 2024 | D53: 620000 | E53: PAGO | F53: Alessandra/ Ju paga Saldo /Pax pagou por pix
A54: 45323 | B54: Heloísa Amaral | C54: City tour Panorâmico, regular 3 pax | D54: 612.000COP | E54: PAGO | F54: Alessandra/ Passeio cancelado (No show)
A55: 45444 | B55: Tobias Lanb | C55: Paue 3 PAX | D55: 930.000COP | E55: PAGO | F55: Jadhe/ Ju paga Saldo/ Pax Pagou por pix
A56: 45383 | B56: Renata Angelo | C56: Walking + Cast 3PAX - Andrés | D56: 385.000COP | E56: PAGO | F56: Jadhe/ Ju paga Saldo/ Pax Pagou por pix
A57: 45309 | B57: Giovanna Costa | C57: Walking Tour + Castillo San Felipe Andres 09:00 1PAX 2024 | D57: 265000 | E57: PAGO | F57: Jadhe/ Ju paga Saldo/ Pax Pagou por pix
A58: 45310 | B58: Ivanda Marques | C58: Isla Palma 4 pax | D58: 1400000 | E58: PAGO | F58: Alessandra/ Ju paga Saldo /Pax pagou por pix
A59: 45310 | B59: Giovanna Costa | C59: Sunset Sibarita Master 2024 1 pax | D59: 100000 | E59: PAGO | F59: Jadhe/ Ju paga Saldo/ Pax Pagou por pix
A60: 45310 | B60: Mariana Bhering | C60: Isla del sol 2 pax | D60: 540000 | E60: PAGO | F60: Alessandra/ Ju paga Saldo /Pax pagou por pix
A61: 45312 | B61: Gabriella Lima | C61: Walking + Cast 2 PAX 14:00hrs- Andrés | D61: 310000 | E61: PAGO | F61: Jadhe/ Ju paga Saldo/ Pax Pagou por pix
A62: 45312 | B62: Giovanna Costa | C62: Bora Bora Bc 2024 1 pax | D62: 250000 | E62: PAGO | F62: Jadhe/ Ju paga Saldo/ Pax Pagou por pix
A63: 45312 | B63: Giovanna Costa | C63: Bonavida 1 pax | D63: 370000 | E63: PAGO | F63: Jadhe/ Ju paga Saldo/ Pax Pagou por pix
A64: 45314 | B64: Luciana Morais | C64: Transfer Aeroporto/Hotel Bogotá até 02 pessoas 2024 | D64: Mismo fornecedor (Deissy) | E64: PAGO | F64: Agencia/ Ju paga saldo
A65: 45315 | B65: Luciana Morais | C65: Walking Tour Centro Historico Privativo + Monserrat Privativo | D65: 1266000 | E65: PAGO | F65: Agencia/ Ju paga saldo
A66: 45315 | B66: Luciana Morais | C66: Transfer Hotel/Aeroporto Bogotá até 02 pessoas 2024 | D66: Mismo fornecedor (Deissy) | E66: PAGO | F66: Agencia/ Ju paga saldo
A67: 45316 | B67: Isabela Gaspar | C67: Jantar fenix | D67: 320000 | E67: PAGO | F67: Jadhe/ Ju paga Saldo/ Pax Pagou por pix
A68: 45317 | B68: Luciana Morais | C68: Walking Tour + Castillo San Felipe VIP 09:00 2PAX 2024 | D68: 310000 | E68: PAGO | F68: Jadhe/ Ju paga Saldo/ Pax Pagou por pix
A69: 45318 | B69: Luciana Morais | C69: Experiência Culinária 2024 | D69: 500000 | E69: PAGO | F69: Agencia/ Ju paga saldo
A70: 45318 | B70: Isabela Gaspar | C70: Walking Tour + Cast 2PAX - Hernán | D70: 340000 | E70: PAGO | F70: Jadhe/ Ju paga Saldo/ Pax Pagou por pix
A74: Data | B74: Nombre | C74: Passeio | D74: Fevereiro | E74: Pagamento
A75: 45325 | B75: Diego da Silva | C75: Mangata 2 pax | D75: 580000 | E75: PAGO | F75: Alessandra/ Ju paga Saldo /Pax pagou por pix
A76: 45326 | B76: Ana Ojeda | C76: Bora vip 2 pax | D76: 660000 | E76: PAGO | F76: Jadhe/ Ju paga diferença do saldo / pagou por pix
A77: 45331 | B77: Rosangela Rocha | C77: Paue 1 pax | D77: 310000 | E77: PAGO | F77: Jadhe/ Ju paga Saldo/ Pax Pagou por pix
A78: 45332 | B78: Danusa Silva | C78: Bora Bora VIP 2 pax | D78: 40000 | E78: PAGO | F78: Jadhe/ Ju paga diferença do saldo / pax pagou
A79: 45332 | B79: Claudia Gregory | C79: Walking Tour + Castillo San Felipe 09:00 4 PAX 2024 | D79: 485000 | E79: PAGO | F79: Jadhe/ Ju paga diferença do saldo / pagou por pix
A80: 45334 | B80: Camila Andrade | C80: Walking Tour + Castillo San Felipe 14:00 2PAX 2024 | D80: 310000 | E80: PAGO | F80: Alessandra/ Ju paga Saldo /Pax pagou por pix
A81: 45334 | B81: Robeiro Arruda | C81: Lancha boasta 4 u | D81: 2760000 | E81: PAGO | F81: Alessandra/ Ju paga Saldo /Pax fiz pago por pix
A82: 45336 | B82: Silvana Rigolino | C82: Bora Bora VIP 2 pax | D82: 620000 | E82: PAGO | F82: Jadhe/ Ju paga Saldo/ Pax Pagou por pix
A83: 45344 | B83: Pamela Silva | C83: Walking Tour + Castillo San Felipe 09:00 2PAX 2024 | D83: 310000 | E83: PAGO | F83: Alessandra/ Ju paga Saldo /Pax pagou por pix
A84: 45344 | B84: Kelly Cristina | C84: Pao Pao 2 pax | D84: 460000 | E84: PAGO | F84: Alessandra/ Ju paga Saldo /Pax pagou por pix
A85: 45338 | B85: Gizely Lima | C85: Walking Tour + Castillo San Felipe 09:00 2PAX ANDRES | D85: 195.000COP | E85: SALDO PENDIENTE | F85: Jadhe/ Ju paga diferença do saldo / pax pagou
A86: 45345 | B86: Emerson Fraga | C86: Walking Tour + Castillo San Felipe 09:00 2PAX 2024 | D86: 310000 | E86: PAGO | F86: Jadhe/ Ju paga diferença do saldo / pax pagou
A87: 45345 | B87: Elaine Gonçalves | C87: Walking Tour + Castillo San Felipe Andres 14:00 3 PAX | D87: 445.000COP | E87: PAGO | F87: Jadhe/ Ju paga saldo / pax pagou
A88: 45347 | B88: Elaine Gonçalves | C88: Sunset sibarita master 2 Pax | D88: 200.000COP | E88: PAGO | F88: Jadhe/ Ju paga saldo / pax pagou
A94: SALDOS PENDENTES JU | D94: MARÇO | E94: STATUS | F94: CONSULTORA
A95: Data | B95: Nombre | C95: Passeio | D95: Valor Total em Pesos Colombianos TOTAL | E95: Pagamento
A96: 45355 | B96: Paola Costa | C96: Paue 2 pax | D96: 620.000COP | E96: PAGO | F96: Alessandra/ Ju paga Saldo /Pax pagou por pix
A97: 45359 | B97: Natalia Neves | C97: Isla Palma | D97: 660.000COP | E97: PAGO | F97: Jadhe/ Ju paga saldo / pax pagou
A98: 45361 | B98: Mônica Mandelli | C98: Walking Tour + Cast 2PAX - 09:00hrs | D98: 466.000COP- 310.000= 156.000COP | E98: PAGO | F98: Jadhe/ Ju paga Saldo/ Pax Pagou por pix -SE PAGO 310.000COP
A99: 45362 | B99: Erika Oliveira | C99: Paue 1 pax | D99: 310.000COP | E99: PAGO | F99: Alessandra/ Ju paga Saldo /Pax pagou por pix
A100: 45364 | B100: Mônica Mandelli | C100: Sofitel Baru Casablanca 2 pax | D100: 520.000COP | E100: PAGO | F100: Jadhe/ Ju paga saldo / pax pagou
A101: 45370 | B101: Tiago Farah | C101: Walking Tour + Castillo San Felipe VIP 09:00 2PAX 2024 | D101: 310.000COP | E101: PAGO | F101: Jadhe/ Ju paga saldo / pax pagou
A102: 45371 | B102: Maria Lara | C102: Walking Tour + Castillo San Felipe VIP 09:00 3PAX 2024 | D102: 609.00COP | E102: PAGO | F102: Jadhe/ Ju paga saldo / pax pagou
A103: 45373 | B103: Igor Magalhães | C103: Sunset Sibarita Master 2 pax | D103: 200.000COP | E103: PAGO | F103: Ju/ Pax pagou por pix
A104: 45374 | B104: Igor Magalhães | C104: Isla Bela 2 pax | D104: 480.000COP | E104: PAGO | F104: Ju/ Pax pagou por pix
A105: 45380 | B105: Beatriz Miranda | C105: Isla del sol 2 pax | D105: 540.000COP | E105: PAGO | F105: Jadhe/ Ju paga saldo / pax pagou
A108: SALDOS PENDENTES JU | D108: ABRIL | E108: STATUS | F108: CONSULTORA
A109: Data | B109: Nombre | C109: Passeio | D109: Valor Total em Pesos Colombianos TOTAL | E109: Pagamento
A110: 45384 | B110: Augusto Lobo | C110: Paue 3 pax | D110: 930.000COP | E110: PAGO | F110: Jadhe/ Ju paga Saldo/ Pax Pagou por pix
A111: 45385 | B111: Augusto Lobo | C111: Sabai 3 pax | D111: 990.000COP | E111: PAGO | F111: Jadhe/ Ju paga Saldo/ Pax Pagou por pix
A112: 45355 | B112: Raquel Varela | C112: Bora Vip 2 pax | D112: 660.000COP | E112: PAGO | F112: Jadhe/ Ju paga Saldo/ Pax Pagou por pix
A113: 45355 | B113: Ana Paula Ceregato | C113: Walking Tour + Castillo San Felipe VIP 09:00 2PAX 2024 | D113: 466.000COP | E113: PAGO | F113: Alessandra/ Ju paga Saldo /Pax pagou por pix
A114: 45387 | B114: Juliana Simoes | C114: Bora Bora Vip 1 pax | D114: 330.000COP | E114: PAGO | F114: Jadhe/ Ju paga Saldo/ Pax Pagou por pix
A115: 45387 | B115: Ana Paula Ceregato | C115: SABAI 2pax | D115: 660.000COP | E115: PAGO | F115: Alessandra/ Ju paga Saldo /Pax pagou por pix
A116: 45391 | B116: Geórgia Carvalho | C116: Walking Tour + Castillo San Felipe VIP 09:00 2PAX 2024 | D116: 466.000COP | E116: PAGO | F116: Jadhe/ Ju paga Saldo/ Pax Pagou por pix
A117: 45392 | B117: Danielle Oliveira | C117: Isla Bela 2 pax | D117: 480.000COP | E117: PAGO | F117: Ju/ Ju paga saldo a pax pagou por pix
A118: 45394 | B118: Geórgia Carvalho | C118: Sunset sibarita Master 2 pax | D118: 200.000COP | E118: PAGO | F118: Jadhe/ Ju paga Saldo/ Pax Pagou por pix
A119: 45399 | B119: Ana Carolina Souza | C119: Isla Palma 2 pax | D119: 660.000COP | E119: PAGO | F119: Alessandra/ Ju paga Saldo /Pax pagou por pix
...

Sheet Grupo Bora
A1: GRUPO BORA BORA
A4: Bora Bora BC
B5: 45748 | C5: 45925 | D5: 2026 | E5: 46023
A6: Precio venta | B6: 390000 | C6: 430000 | D6: 450000 | E6: 450000
A7: Saldo | B7: 280000 | C7: =B7 -> 280000 | D7: =C7 -> 280000 | E7: 290000
A8: Comision | B8: =B6-B7 -> 110000 | C8: =C6-C7 -> 150000 | D8: =D6-D7 -> 170000 | E8: =E6-E7 -> 160000
A10: Bora Bora VIP
B11: 45748 | C11: 2026 | D11: 45925 | E11: 46023
A12: Precio venta | B12: 490000 | C12: 510000 | D12: 510000 | E12: 550000
A13: Saldo | B13: 370000 | C13: =B13 -> 370000 | D13: =B13 -> 370000 | E13: 380000
A14: Comision | B14: =B12-B13 -> 120000 | C14: =C12-C13 -> 140000 | D14: =D12-D13 -> 140000 | E14: =E12-E13 -> 170000
A16: Pao Pao
B17: 45748 | C17: 45925 | D17: 2026 | E17: 46023
A18: Precio venta | B18: 390000 | C18: 430000 | D18: 450000 | E18: 450000
A19: Saldo | B19: 270000 | C19: =B19 -> 270000 | D19: =C19 -> 270000 | E19: 280000
A20: Comision | B20: =B18-B19 -> 120000 | C20: =C18-C19 -> 160000 | D20: =D18-D21 -> 450000 | E20: =E18-E19 -> 170000
A22: Top 3 Ilhas
B23: 45748 | C23: 45925 | D23: 2026
A24: Precio venta | B24: 440000 | C24: 430000 | D24: 450000 | E24: 500000
A25: Saldo | B25: 330000 | C25: =B25 -> 330000 | D25: =C25 -> 330000 | E25: 360000
A26: Comision | B26: =B24-B25 -> 110000 | C26: =C24-C25 -> 100000 | D26: =D24-D25 -> 120000 | E26: =E24-E25 -> 140000

Sheet Cópia de Precificação por Produ
E2: Precificação | X2: Formatos de visualização | AA2: Pesquisa | AE2: Histórico de vendas
A3: DATA da Cotação | B3: Código | C3: Passeio | D3: Descrição | E3: Preço custo (COP) | F3: Valor de venda (COP) | G3: Quantidade de pessoas | H3: Preço custo (BRL) | I3: IOF | J3: Valor após IOF | K3: Valor de IOF Bruto | L3: Cotação COP | M3: Spread | N3: Cotação Real | O3: Valor SPREAD BRUTO | P3: Custo Convertido (US) | Q3: Preço de venda | R3: Simples Nacional (%) | S3: Outros custos diretos (%) | T3: ENTRADA | V3: Comissão Jadhe (R$) | W3: Margem bruta | X3: MARKUP | Y3: MARKDOWN | Z3: CLD | AA3: Pesquisa 1 | AB3: Pesquisa 2 | AC3: Pesquisa 3 | AD3: Estabelecimento | AE3: Custo 2025 | AF3: Mês 2 | AG3: Mês 3 | AH3: Média venda mensal | AI3: Vendas acumuladas
A4: Bogotá BOG PASS | T4: =F4-E4 -> 0
T5: =F5-E5 -> 0
A6: 2026 | C6: city tour imperdíveis - manhã | D6: Regular | E6: 119200 | F6: 300000 | G6: 1 | H6: =((E6*N6)*(1+I6))*G6 -> 176.05622 | I6: 0.035 | J6: =H6*(1-I6) -> 169.89426 | K6: =H6-J6 -> 6.1619678 | L6: 0.001397 | M6: 0.0215 | N6: =L6*(1+M6) -> 0.0014270355 | O6: =(J6*M6)+15 -> 18.652726 | P6: =(J6*N6)+M6 -> 0.26394513 | Q6: =((F6*N6)*(1+I6))*G6 -> 443.09452 | R6: 0.06 | T6: =F6-E6 -> 180800 | U6: =T6*(1-I6-M6) -> 170584.8 | V6: =(F6-E6)*0.2 -> 36160 | W6: =(F6*(1-I6-M6)-(E6+V6)-(F6*S6)-(F6*R6)) -> 109690 | X6: =IFERROR((F6-E6)/E6,"") -> 1.5167785 | Y6: =IFERROR((Q6-H6)/Q6,"") -> 0.60266667 | Z6: =IFERROR(W6/F6,"") -> 0.36563333
A7: 2026 | C7: city tour bairros inconicos - tarde | D7: Regular | E7: 119200 | F7: 300000 | G7: 1 | H7: =((E7*N7)*(1+I7))*G7 -> 176.05622 | I7: 0.035 | J7: =H7*(1-I7) -> 169.89426 | K7: =H7-J7 -> 6.1619678 | L7: 0.001397 | M7: 0.0215 | N7: =L7*(1+M7) -> 0.0014270355 | O7: =(J7*M7)+15 -> 18.652726 | P7: =(J7*N7)+M7 -> 0.26394513 | Q7: =((F7*N7)*(1+I7))*G7 -> 443.09452 | R7: 0.06 | T7: =F7-E7 -> 180800 | U7: =T7*(1-I7-M7) -> 170584.8 | V7: =(F7-E7)*0.2 -> 36160 | W7: =F7-(E7+V7)-(F7*S7)-(F7*R7) -> 126640 | X7: =IFERROR((F7-E7)/E7,"") -> 1.5167785 | Y7: =IFERROR((Q7-H7)/Q7,"") -> 0.60266667 | Z7: =IFERROR(W7/F7,"") -> 0.42213333
A8: 2026 | C8: Catedral de Sal (BOG PASS) | D8: Regular | E8: 263200 | F8: 380000 | G8: 1 | H8: =((E8*N8)*(1+I8))*G8 -> 388.74159 | I8: 0.035 | J8: =H8*(1-I8) -> 375.13564 | K8: =H8-J8 -> 13.605956 | L8: 0.001397 | M8: 0.0215 | N8: =L8*(1+M8) -> 0.0014270355 | O8: =(J8*M8)+15 -> 23.065416 | P8: =(J8*N8)+M8 -> 0.55683187 | Q8: =((F8*N8)*(1+I8))*G8 -> 561.25306 | R8: 0.06 | T8: =F8-E8 -> 116800 | U8: =T8*(1-I8-M8) -> 110200.8 | V8: =(F8-E8)*0.2 -> 23360 | W8: =F8-(E8+V8)-(F8*S8)-(F8*R8) -> 70640 | X8: =IFERROR((F8-E8)/E8,"") -> 0.443769 | Y8: =IFERROR((Q8-H8)/Q8,"") -> 0.30736842 | Z8: =IFERROR(W8/F8,"") -> 0.18589474
A9: 2026 | C9: Catedral de Sal + Guatavita (BOG PASS) | D9: Regular | E9: 343200 | F9: 600000 | G9: 1 | H9: =((E9*N9)*(1+I9))*G9 -> 506.90013 | I9: 0.035 | J9: =H9*(1-I9) -> 489.15863 | K9: =H9-J9 -> 17.741505 | L9: 0.001397 | M9: 0.0215 | N9: =L9*(1+M9) -> 0.0014270355 | O9: =(J9*M9)+15 -> 25.516911 | P9: =(J9*N9)+M9 -> 0.71954673 | Q9: =((F9*N9)*(1+I9))*G9 -> 886.18905 | R9: 0.06 | T9: =F9-E9 -> 256800 | U9: =T9*(1-I9-M9) -> 242290.8 | V9: =(F9-E9)*0.2 -> 51360 | W9: =F9-(E9+V9)-(F9*S9)-(F9*R9) -> 169440 | X9: =IFERROR((F9-E9)/E9,"") -> 0.74825175 | Y9: =IFERROR((Q9-H9)/Q9,"") -> 0.428 | Z9: =IFERROR(W9/F9,"") -> 0.2824
A10: 2026 | C10: Finca Cafeteira (Grupal) (BOG PASS) | D10: Regular | E10: 343200 | F10: 650000 | G10: 1 | H10: =((E10*N10)*(1+I10))*G10 -> 506.90013 | I10: 0.035 | J10: =H10*(1-I10) -> 489.15863 | K10: =H10-J10 -> 17.741505 | L10: 0.001397 | M10: 0.0215 | N10: =L10*(1+M10) -> 0.0014270355 | O10: =(J10*M10)+15 -> 25.516911 | P10: =(J10*N10)+M10 -> 0.71954673 | Q10: =((F10*N10)*(1+I10))*G10 -> 960.03813 | R10: 0.06 | T10: =F10-E10 -> 306800 | U10: =T10*(1-I10-M10) -> 289465.8 | V10: =(F10-E10)*0.2 -> 61360 | W10: =F10-(E10+V10)-(F10*S10)-(F10*R10) -> 206440 | X10: =IFERROR((F10-E10)/E10,"") -> 0.89393939 | Y10: =IFERROR((Q10-H10)/Q10,"") -> 0.472 | Z10: =IFERROR(W10/F10,"") -> 0.3176
A11: 2026 | C11: Transfer in - DIURNO - 06am -09pm (bog pass) | D11: Carro 3 Pessoas | E11: 112000 | F11: 360000 | G11: 1 | H11: =((E11*N11)*(1+I11))*G11 -> 165.42196 | I11: 0.035 | J11: =H11*(1-I11) -> 159.63219 | K11: =H11-J11 -> 5.7897684 | L11: 0.001397 | M11: 0.0215 | N11: =L11*(1+M11) -> 0.0014270355 | O11: =(J11*M11)+15 -> 18.432092 | P11: =(J11*N11)+M11 -> 0.2493008 | Q11: =((F11*N11)*(1+I11))*G11 -> 531.71343 | R11: 0.06 | T11: =F11-E11 -> 248000 | U11: =T11*(1-I11-M11) -> 233988 | V11: =(F11-E11)*0.2 -> 49600 | W11: =F11-(E11+V11)-(F11*S11)-(F11*R11) -> 176800 | X11: =IFERROR((F11-E11)/E11,"") -> 2.2142857 | Y11: =IFERROR((Q11-H11)/Q11,"") -> 0.68888889 | Z11: =IFERROR(W11/F11,"") -> 0.49111111
A12: 2026 | C12: Transfer in - DIURNO - 06am -09pm (bog pass) | D12: VAN 4-6 PAX | E12: 173600 | F12: 550000 | G12: 1 | H12: =((E12*N12)*(1+I12))*G12 -> 256.40403 | I12: 0.035 | J12: =H12*(1-I12) -> 247.42989 | K12: =H12-J12 -> 8.9741411 | L12: 0.001397 | M12: 0.0215 | N12: =L12*(1+M12) -> 0.0014270355 | O12: =(J12*M12)+15 -> 20.319743 | P12: =(J12*N12)+M12 -> 0.37459124 | Q12: =((F12*N12)*(1+I12))*G12 -> 812.33996 | R12: 0.06 | T12: =F12-E12 -> 376400 | U12: =T12*(1-I12-M12) -> 355133.4 | V12: =(F12-E12)*0.2 -> 75280 | W12: =F12-(E12+V12)-(F12*S12)-(F12*R12) -> 268120 | X12: =IFERROR((F12-E12)/E12,"") -> 2.1682028 | Y12: =IFERROR((Q12-H12)/Q12,"") -> 0.68436364 | Z12: =IFERROR(W12/F12,"") -> 0.48749091
A13: 2026 | C13: Transfer in - DIURNO - 06am - 09pm (bog pass) | D13: VAN 7-10 Pax | E13: 260800 | F13: 770000 | G13: 1 | H13: =((E13*N13)*(1+I13))*G13 -> 385.19684 | I13: 0.035 | J13: =H13*(1-I13) -> 371.71495 | K13: =H13-J13 -> 13.481889 | L13: 0.001397 | M13: 0.0215 | N13: =L13*(1+M13) -> 0.0014270355 | O13: =(J13*M13)+15 -> 22.991871 | P13: =(J13*N13)+M13 -> 0.55195043 | Q13: =((F13*N13)*(1+I13))*G13 -> 1137.2759 | R13: 0.06 | T13: =F13-E13 -> 509200 | U13: =T13*(1-I13-M13) -> 480430.2 | V13: =(F13-E13)*0.2 -> 101840 | W13: =F13-(E13+V13)-(F13*S13)-(F13*R13) -> 361160 | X13: =IFERROR((F13-E13)/E13,"") -> 1.952454 | Y13: =IFERROR((Q13-H13)/Q13,"") -> 0.6612987 | Z13: =IFERROR(W13/F13,"") -> 0.46903896
A14: 2026 | C14: Transfer in - NOTURNO - 06am - 09pm (bog pass) | D14: Carro 3 Pessoas | E14: 127200 | F14: 360000 | G14: 1 | H14: =((E14*N14)*(1+I14))*G14 -> 187.87208 | I14: 0.035 | J14: =H14*(1-I14) -> 181.29655 | K14: =H14-J14 -> 6.5755227 | L14: 0.001397 | M14: 0.0215 | N14: =L14*(1+M14) -> 0.0014270355 | O14: =(J14*M14)+15 -> 18.897876 | P14: =(J14*N14)+M14 -> 0.28021662 | Q14: =((F14*N14)*(1+I14))*G14 -> 531.71343 | R14: 0.06 | T14: =F14-E14 -> 232800 | U14: =T14*(1-I14-M14) -> 219646.8 | V14: =(F14-E14)*0.2 -> 46560 | W14: =F14-(E14+V14)-(F14*S14)-(F14*R14) -> 164640 | X14: =IFERROR((F14-E14)/E14,"") -> 1.8301887 | Y14: =IFERROR((Q14-H14)/Q14,"") -> 0.64666667 | Z14: =IFERROR(W14/F14,"") -> 0.45733333
A15: 2026 | C15: Transfer in - NOTURNIO - 06am - 09pm (bog pass) | D15: VAN 4-6 PAX | E15: 216800 | F15: 550000 | G15: 1 | H15: =((E15*N15)*(1+I15))*G15 -> 320.20964 | I15: 0.035 | J15: =H15*(1-I15) -> 309.0023 | K15: =H15-J15 -> 11.207337 | L15: 0.001397 | M15: 0.0215 | N15: =L15*(1+M15) -> 0.0014270355 | O15: =(J15*M15)+15 -> 21.64355 | P15: =(J15*N15)+M15 -> 0.46245726 | Q15: =((F15*N15)*(1+I15))*G15 -> 812.33996 | R15: 0.06 | T15: =F15-E15 -> 333200 | U15: =T15*(1-I15-M15) -> 314374.2 | V15: =(F15-E15)*0.2 -> 66640 | W15: =F15-(E15+V15)-(F15*S15)-(F15*R15) -> 233560 | X15: =IFERROR((F15-E15)/E15,"") -> 1.5369004 | Y15: =IFERROR((Q15-H15)/Q15,"") -> 0.60581818 | Z15: =IFERROR(W15/F15,"") -> 0.42465455
A16: 2026 | C16: Transfer in - NOTURNO - 06am - 09pm (bog pass) | D16: VAN 7-10 Pax | E16: 292000 | F16: 770000 | G16: 1 | H16: =((E16*N16)*(1+I16))*G16 -> 431.27867 | I16: 0.035 | J16: =H16*(1-I16) -> 416.18392 | K16: =H16-J16 -> 15.094753 | L16: 0.001397 | M16: 0.0215 | N16: =L16*(1+M16) -> 0.0014270355 | O16: =(J16*M16)+15 -> 23.947954 | P16: =(J16*N16)+M16 -> 0.61540922 | Q16: =((F16*N16)*(1+I16))*G16 -> 1137.2759 | R16: 0.06 | T16: =F16-E16 -> 478000 | U16: =T16*(1-I16-M16) -> 450993 | V16: =(F16-E16)*0.2 -> 95600 | W16: =F16-(E16+V16)-(F16*S16)-(F16*R16) -> 336200 | X16: =IFERROR((F16-E16)/E16,"") -> 1.6369863 | Y16: =IFERROR((Q16-H16)/Q16,"") -> 0.62077922 | Z16: =IFERROR(W16/F16,"") -> 0.43662338
A17: 2026 | C17: Transfer OUT - DIURNO - 06am -09pm (bog pass) | D17: Carro 3 Pessoas | E17: 80000 | F17: 360000 | G17: 1 | H17: =((E17*N17)*(1+I17))*G17 -> 118.15854 | I17: 0.035 | J17: =H17*(1-I17) -> 114.02299 | K17: =H17-J17 -> 4.1355489 | L17: 0.001397 | M17: 0.0215 | N17: =L17*(1+M17) -> 0.0014270355 | O17: =(J17*M17)+15 -> 17.451494 | P17: =(J17*N17)+M17 -> 0.18421486 | Q17: =((F17*N17)*(1+I17))*G17 -> 531.71343 | R17: 0.06 | T17: =F17-E17 -> 280000 | U17: =T17*(1-I17-M17) -> 264180 | V17: =(F17-E17)*0.2 -> 56000 | W17: =F17-(E17+V17)-(F17*S17)-(F17*R17) -> 202400 | X17: =IFERROR((F17-E17)/E17,"") -> 3.5 | Y17: =IFERROR((Q17-H17)/Q17,"") -> 0.77777778 | Z17: =IFERROR(W17/F17,"") -> 0.56222222
A18: 2026 | C18: Transfer OUT - DIURNO - 06am -09pm (bog pass) | D18: VAN 4-6 PAX | E18: 140000 | F18: 550000 | G18: 1 | H18: =((E18*N18)*(1+I18))*G18 -> 206.77744 | I18: 0.035 | J18: =H18*(1-I18) -> 199.54023 | K18: =H18-J18 -> 7.2372105 | L18: 0.001397 | M18: 0.0215 | N18: =L18*(1+M18) -> 0.0014270355 | O18: =(J18*M18)+15 -> 19.290115 | P18: =(J18*N18)+M18 -> 0.306251 | Q18: =((F18*N18)*(1+I18))*G18 -> 812.33996 | R18: 0.06 | T18: =F18-E18 -> 410000 | U18: =T18*(1-I18-M18) -> 386835 | V18: =(F18-E18)*0.2 -> 82000 | W18: =F18-(E18+V18)-(F18*S18)-(F18*R18) -> 295000 | X18: =IFERROR((F18-E18)/E18,"") -> 2.9285714 | Y18: =IFERROR((Q18-H18)/Q18,"") -> 0.74545455 | Z18: =IFERROR(W18/F18,"") -> 0.53636364
... A22: 2026 | C22: Transfer OUT - NOTURNO - 06am - 09pm (bog pass) | D22: VAN 7-10 Pax | E22: 244000 | F22: 770000 | G22: 1 | H22: =((E22*N22)*(1+I22))*G22 -> 360.38355 | I22: 0.035 | J22: =H22*(1-I22) -> 347.77012 | K22: =H22-J22 -> 12.613424 | L22: 0.001397 | M22: 0.0215 | N22: =L22*(1+M22) -> 0.0014270355 | O22: =(J22*M22)+15 -> 22.477058 | P22: =(J22*N22)+M22 -> 0.51778031 | Q22: =((F22*N22)*(1+I22))*G22 -> 1137.2759 | R22: 0.06 | T22: =F22-E22 -> 526000 | U22: =T22*(1-I22-M22) -> 496281 | V22: =(F22-E22)*0.2 -> 105200 | W22: =F22-(E22+V22)-(F22*S22)-(F22*R22) -> 374600 | X22: =IFERROR((F22-E22)/E22,"") -> 2.1557377 | Y22: =IFERROR((Q22-H22)/Q22,"") -> 0.68311688 | Z22: =IFERROR(W22/F22,"") -> 0.48649351
T23: =F23-E23 -> 0 | U23: =T23*(1-I23-M23) -> 0 | V23: =(F23-E23)*0.2 -> 0 | W23: =F23-(E23+V23)-(F23*S23)-(F23*R23) -> 0 | X23: =IFERROR((F23-E23)/E23,"") | Z23: =IFERROR(W23/F23,"")
A24: Cartagena | T24: =F24-E24 -> 0 | U24: =T24*(1-I24-M24) -> 0 | V24: =(F24-E24)*0.2 -> 0 | W24: =F24-(E24+V24)-(F24*S24)-(F24*R24) -> 0 | X24: =IFERROR((F24-E24)/E24,"") | Z24: =IFERROR(W24/F24,"")
A25: 2026 | C25: Jantar Fenix Beach | E25: 225000 | F25: 370000 | G25: 1 | H25: =((E25*N25)*(1+I25))*G25 -> 332.32089 | I25: 0.035 | J25: =H25*(1-I25) -> 320.68966 | K25: =H25-J25 -> 11.631231 | L25: 0.001397 | M25: 0.0215 | N25: =L25*(1+M25) -> 0.0014270355 | O25: =(J25*M25)+15 -> 21.894828 | P25: =(J25*N25)+M25 -> 0.47913553 | Q25: =((F25*N25)*(1+I25))*G25 -> 546.48324 | R25: 0.06 | T25: =F25-E25 -> 145000 | U25: =T25*(1-I25-M25) -> 136807.5 | V25: =(F25-E25)*0.2 -> 29000 | W25: =F25-(E25+V25)-(F25*S25)-(F25*R25) -> 93800 | X25: =IFERROR((F25-E25)/E25,"") -> 0.64444444 | Y25: =IFERROR((Q25-H25)/Q25,"") -> 0.39189189 | Z25: =IFERROR(W25/F25,"") -> 0.25351351 | AH25: =IFERROR(AVERAGE(AE25:AG25),"") | AI25: =AE25+AF25+AG25 -> 0
A26: 2026 | C26: Jantar Fenix Beach | E26: 150000 | F26: 300000 | G26: 1 | H26: =((E26*N26)*(1+I26))*G26 -> 221.54726 | I26: 0.035 | J26: =H26*(1-I26) -> 213.79311 | K26: =H26-J26 -> 7.7541541 | L26: 0.001397 | M26: 0.0215 | N26: =L26*(1+M26) -> 0.0014270355 | O26: =(J26*M26)+15 -> 19.596552 | P26: =(J26*N26)+M26 -> 0.32659035 | Q26: =((F26*N26)*(1+I26))*G26 -> 443.09452 | R26: 0.06 | T26: =F26-E26 -> 150000 | U26: =T26*(1-I26-M26) -> 141525 | V26: =(F26-E26)*0.2 -> 30000 | W26: =F26-(E26+V26)-(F26*S26)-(F26*R26) -> 102000 | X26: =IFERROR((F26-E26)/E26,"") -> 1 | Y26: =IFERROR((Q26-H26)/Q26,"") -> 0.5 | Z26: =IFERROR(W26/F26,"") -> 0.34 | AH26: =IFERROR(AVERAGE(AE26:AG26),"") | AI26: =AE26+AF26+AG26 -> 0
A27: 2026 | C27: Corona Island | E27: 633000 | F27: 850000 | G27: 1 | H27: =((E27*N27)*(1+I27))*G27 -> 934.92944 | I27: 0.035 | J27: =H27*(1-I27) -> 902.20691 | K27: =H27-J27 -> 32.722531 | L27: 0.001397 | M27: 0.0215 | N27: =L27*(1+M27) -> 0.0014270355 | O27: =(J27*M27)+15 -> 34.397449 | P27: =(J27*N27)+M27 -> 1.3089813 | Q27: =((F27*N27)*(1+I27))*G27 -> 1255.4345 | R27: 0.06 | T27: =F27-E27 -> 217000 | U27: =T27*(1-I27-M27) -> 204739.5 | V27: =(F27-E27)*0.2 -> 43400 | W27: =F27-(E27+V27)-(F27*S27)-(F27*R27) -> 122600 | X27: =IFERROR((F27-E27)/E27,"") -> 0.34281201 | Y27: =IFERROR((Q27-H27)/Q27,"") -> 0.25529412 | Z27: =IFERROR(W27/F27,"") -> 0.14423529 | AH27: =IFERROR(AVERAGE(AE27:AG27),"") | AI27: =AE27+AF27+AG27 -> 0
A28: 2026 | C28: Capri Premium | E28: 390000 | F28: 610000 | G28: 1 | H28: =((E28*N28)*(1+I28))*G28 -> 576.02288 | I28: 0.035 | J28: =H28*(1-I28) -> 555.86208 | K28: =H28-J28 -> 20.160801 | L28: 0.001397 | M28: 0.0215 | N28: =L28*(1+M28) -> 0.0014270355 | O28: =(J28*M28)+15 -> 26.951035 | P28: =(J28*N28)+M28 -> 0.81473492 | Q28: =((F28*N28)*(1+I28))*G28 -> 900.95886 | R28: 0.06 | T28: =F28-E28 -> 220000 | U28: =T28*(1-I28-M28) -> 207570 | V28: =(F28-E28)*0.2 -> 44000 | W28: =F28-(E28+V28)-(F28*S28)-(F28*R28) -> 139400 | X28: =IFERROR((F28-E28)/E28,"") -> 0.56410256 | Y28: =IFERROR((Q28-H28)/Q28,"") -> 0.36065574 | Z28: =IFERROR(W28/F28,"") -> 0.22852459 | AH28: =IFERROR(AVERAGE(AE28:AG28),"") | AI28: =AE28+AF28+AG28 -> 0
A29: 2026 | C29: Capri Classic | E29: 330000 | F29: 510000 | G29: 1 | H29: =((E29*N29)*(1+I29))*G29 -> 487.40398 | I29: 0.035 | J29: =H29*(1-I29) -> 470.34484 | K29: =H29-J29 -> 17.059139 | L29: 0.001397 | M29: 0.0215 | N29: =L29*(1+M29) -> 0.0014270355 | O29: =(J29*M29)+15 -> 25.112414 | P29: =(J29*N29)+M29 -> 0.69269878 | Q29: =((F29*N29)*(1+I29))*G29 -> 753.26069 | R29: 0.06 | T29: =F29-E29 -> 180000 | U29: =T29*(1-I29-M29) -> 169830 | V29: =(F29-E29)*0.2 -> 36000 | W29: =F29-(E29+V29)-(F29*S29)-(F29*R29) -> 113400 | X29: =IFERROR((F29-E29)/E29,"") -> 0.54545455 | Y29: =IFERROR((Q29-H29)/Q29,"") -> 0.35294118 | Z29: =IFERROR(W29/F29,"") -> 0.22235294 | AH29: =IFERROR(AVERAGE(AE29:AG29),"") | AI29: =AE29+AF29+AG29 -> 0
A30: 2026 | C30: Isla Bela | E30: 300000 | F30: 490000 | G30: 1 | H30: =((E30*N30)*(1+I30))*G30 -> 443.09452 | I30: 0.035 | J30: =H30*(1-I30) -> 427.58621 | K30: =H30-J30 -> 15.508308 | L30: 0.001397 | M30: 0.0215 | N30: =L30*(1+M30) -> 0.0014270355 | O30: =(J30*M30)+15 -> 24.193104 | P30: =(J30*N30)+M30 -> 0.63168071 | Q30: =((F30*N30)*(1+I30))*G30 -> 723.72105 | R30: 0.06 | T30: =F30-E30 -> 190000 | U30: =T30*(1-I30-M30) -> 179265 | V30: =(F30-E30)*0.2 -> 38000 | W30: =F30-(E30+V30)-(F30*S30)-(F30*R30) -> 122600 | X30: =IFERROR((F30-E30)/E30,"") -> 0.63333333 | Y30: =IFERROR((Q30-H30)/Q30,"") -> 0.3877551 | Z30: =IFERROR(W30/F30,"") -> 0.25020408 | AH30: =IFERROR(AVERAGE(AE30:AG30),"") | AI30: =AE30+AF30+AG30 -> 0
A31: 2026 | C31: Isla Bela chd - 03 a 10 anos | E31: 260000 | F31: 390000 | G31: 1 | H31: =((E31*N31)*(1+I31))*G31 -> 384.01525 | I31: 0.035 | J31: =H31*(1-I31) -> 370.57472 | K31: =H31-J31 -> 13.440534 | L31: 0.001397 | M31: 0.0215 | N31: =L31*(1+M31) -> 0.0014270355 | O31: =(J31*M31)+15 -> 22.967356 | P31: =(J31*N31)+M31 -> 0.55032328 | Q31: =((F31*N31)*(1+I31))*G31 -> 576.02288 | R31: 0.06 | T31: =F31-E31 -> 130000 | U31: =T31*(1-I31-M31) -> 122655 | V31: =(F31-E31)*0.2 -> 26000 | W31: =F31-(E31+V31)-(F31*S31)-(F31*R31) -> 80600 | X31: =IFERROR((F31-E31)/E31,"") -> 0.5 | Y31: =IFERROR((Q31-H31)/Q31,"") -> 0.33333333 | Z31: =IFERROR(W31/F31,"") -> 0.20666667 | AH31: =IFERROR(AVERAGE(AE31:AG31),"") | AI31: =AE31+AF31+AG31 -> 0
A32: 2026 | C32: Mergulho iniciante | E32: 620000 | F32: 890000 | G32: 1 | H32: =((E32*N32)*(1+I32))*G32 -> 915.72868 | I32: 0.035 | J32: =H32*(1-I32) -> 883.67818 | K32: =H32-J32 -> 32.050504 | L32: 0.001397 | M32: 0.0215 | N32: =L32*(1+M32) -> 0.0014270355 | O32: =(J32*M32)+15 -> 33.999081 | P32: =(J32*N32)+M32 -> 1.2825401 | Q32: =((F32*N32)*(1+I32))*G32 -> 1314.5138 | R32: 0.06 | T32: =F32-E32 -> 270000 | U32: =T32*(1-I32-M32) -> 254745 | V32: =(F32-E32)*0.2 -> 54000 | W32: =F32-(E32+V32)-(F32*S32)-(F32*R32) -> 162600 | X32: =IFERROR((F32-E32)/E32,"") -> 0.43548387 | Y32: =IFERROR((Q32-H32)/Q32,"") -> 0.30337079 | Z32: =IFERROR(W32/F32,"") -> 0.18269663 | AH32: =IFERROR(AVERAGE(AE32:AG32),"") | AI32: =AE32+AF32+AG32 -> 0
A33: 2026 | C33: Mergulho para certificados | E33: 570000 | F33: 800000 | G33: 1 | H33: =((E33*N33)*(1+I33))*G33 -> 841.87959 | I33: 0.035 | J33: =H33*(1-I33) -> 812.41381 | K33: =H33-J33 -> 29.465786 | L33: 0.001397 | M33: 0.0215 | N33: =L33*(1+M33) -> 0.0014270355 | O33: =(J33*M33)+15 -> 32.466897 | P33: =(J33*N33)+M33 -> 1.1808433 | Q33: =((F33*N33)*(1+I33))*G33 -> 1181.5854 | R33: 0.06 | T33: =F33-E33 -> 230000 | U33: =T33*(1-I33-M33) -> 217005 | V33: =(F33-E33)*0.2 -> 46000 | W33: =F33-(E33+V33)-(F33*S33)-(F33*R33) -> 136000 | X33: =IFERROR((F33-E33)/E33,"") -> 0.40350877 | Y33: =IFERROR((Q33-H33)/Q33,"") -> 0.2875 | Z33: =IFERROR(W33/F33,"") -> 0.17 | AH33: =IFERROR(AVERAGE(AE33:AG33),"") | AI33: =AE33+AF33+AG33 -> 0
A34: 2026 | C34: Bona Vida Sunset Adulto | E34: 134000 | F34: 230000 | G34: 1 | H34: =((E34*N34)*(1+I34))*G34 -> 197.91555 | I34: 0.035 | J34: =H34*(1-I34) -> 190.98851 | K34: =H34-J34 -> 6.9270444 | L34: 0.001397 | M34: 0.0215 | N34: =L34*(1+M34) -> 0.0014270355 | O34: =(J34*M34)+15 -> 19.106253 | P34: =(J34*N34)+M34 -> 0.29404738 | Q34: =((F34*N34)*(1+I34))*G34 -> 339.7058 | R34: 0.06 | T34: =F34-E34 -> 96000 | U34: =T34*(1-I34-M34) -> 90576 | V34: =(F34-E34)*0.2 -> 19200 | W34: =F34-(E34+V34)-(F34*S34)-(F34*R34) -> 63000 | X34: =IFERROR((F34-E34)/E34,"") -> 0.71641791 | Y34: =IFERROR((Q34-H34)/Q34,"") -> 0.4173913 | Z34: =IFERROR(W34/F34,"") -> 0.27391304 | AH34: =IFERROR(AVERAGE(AE34:AG34),"") | AI34: =AE34+AF34+AG34 -> 0
A35: 2026 | C35: Bona Vida Sunset CHD - 7 a 14 anos | E35: 67000 | F35: 190000 | G35: 1 | H35: =((E35*N35)*(1+I35))*G35 -> 98.957777 | I35: 0.035 | J35: =H35*(1-I35) -> 95.494255 | K35: =H35-J35 -> 3.4635222 | L35: 0.001397 | M35: 0.0215 | N35: =L35*(1+M35) -> 0.0014270355 | O35: =(J35*M35)+15 -> 17.053126 | P35: =(J35*N35)+M35 -> 0.15777369 | Q35: =((F35*N35)*(1+I35))*G35 -> 280.62653 | R35: 0.06 | T35: =F35-E35 -> 123000 | U35: =T35*(1-I35-M35) -> 116050.5 | V35: =(F35-E35)*0.2 -> 24600 | W35: =F35-(E35+V35)-(F35*S35)-(F35*R35) -> 87000 | X35: =IFERROR((F35-E35)/E35,"") -> 1.8358209 | Y35: =IFERROR((Q35-H35)/Q35,"") -> 0.64736842 | Z35: =IFERROR(W35/F35,"") -> 0.45789474 | AH35: =IFERROR(AVERAGE(AE35:AG35),"") | AI35: =AE35+AF35+AG35 -> 0
A36: 2026 | C36: Bona Vida Islas Adulto | E36: 390000 | F36: 510000 | G36: 1 | H36: =((E36*N36)*(1+I36))*G36 -> 576.02288 | I36: 0.035 | J36: =H36*(1-I36) -> 555.86208 | K36: =H36-J36 -> 20.160801 | L36: 0.001397 | M36: 0.0215 | N36: =L36*(1+M36) -> 0.0014270355 | O36: =(J36*M36)+15 -> 26.951035 | P36: =(J36*N36)+M36 -> 0.81473492 | Q36: =((F36*N36)*(1+I36))*G36 -> 753.26069 | R36: 0.06 | T36: =F36-E36 -> 120000 | U36: =T36*(1-I36-M36) -> 113220 | V36: =(F36-E36)*0.2 -> 24000 | W36: =F36-(E36+V36)-(F36*S36)-(F36*R36) -> 65400 | X36: =IFERROR((F36-E36)/E36,"") -> 0.30769231 | Y36: =IFERROR((Q36-H36)/Q36,"") -> 0.23529412 | Z36: =IFERROR(W36/F36,"") -> 0.12823529 | AH36: =IFERROR(AVERAGE(AE36:AG36),"") | AI36: =AE36+AF36+AG36 -> 0
A37: 2026 | C37: Bona Vida Islas CHD - 7 a 14 anos | E37: 67000 | F37: 190000 | G37: 1 | H37: =((E37*N37)*(1+I37))*G37 -> 98.957777 | I37: 0.035 | J37: =H37*(1-I37) -> 95.494255 | K37: =H37-J37 -> 3.4635222 | L37: 0.001397 | M37: 0.0215 | N37: =L37*(1+M37) -> 0.0014270355 | O37: =(J37*M37)+15 -> 17.053126 | P37: =(J37*N37)+M37 -> 0.15777369 | Q37: =((F37*N37)*(1+I37))*G37 -> 280.62653 | R37: 0.06 | T37: =F37-E37 -> 123000 | U37: =T37*(1-I37-M37) -> 116050.5 | V37: =(F37-E37)*0.2 -> 24600 | W37: =F37-(E37+V37)-(F37*S37)-(F37*R37) -> 87000 | X37: =IFERROR((F37-E37)/E37,"") -> 1.8358209 | Y37: =IFERROR((Q37-H37)/Q37,"") -> 0.64736842 | Z37: =IFERROR(W37/F37,"") -> 0.45789474 | AH37: =IFERROR(AVERAGE(AE37:AG37),"") | AI37: =AE37+AF37+AG37 -> 0
T38: =F38-E38 -> 0 | U38: =T38*(1-I38-M38) -> 0 | V38: =(F38-E38)*0.2 -> 0 | W38: =F38-(E38+V38)-(F38*S38)-(F38*R38) -> 0 | X38: =IFERROR((F38-E38)/E38,"") | Z38: =IFERROR(W38/F38,"")
A39: 2026 | C39: BORA BORA CLUB | E39: 290000 | F39: 450000 | G39: 1 | H39: =((E39*N39)*(1+I39))*G39 -> 428.32471 | I39: 0.035 | J39: =H39*(1-I39) -> 413.33334 | K39: =H39-J39 -> 14.991365 | L39: 0.001397 | M39: 0.0215 | N39: =L39*(1+M39) -> 0.0014270355 | O39: =(J39*M39)+15 -> 23.886667 | P39: =(J39*N39)+M39 -> 0.61134135 | Q39: =((F39*N39)*(1+I39))*G39 -> 664.64178 | R39: 0.06 | T39: =F39-E39 -> 160000 | U39: =T39*(1-I39-M39) -> 150960 | V39: =(F39-E39)*0.2 -> 32000 | W39: =F39-(E39+V39)-(F39*S39)-(F39*R39) -> 101000 | X39: =IFERROR((F39-E39)/E39,"") -> 0.55172414 | Y39: =IFERROR((Q39-H39)/Q39,"") -> 0.35555556 | Z39: =IFERROR(W39/F39,"") -> 0.22444444 | AH39: =IFERROR(AVERAGE(AE39:AG39),"") | AI39: =AE39+AF39+AG39 -> 0
A40: 2026 | C40: BORA VIP | E40: 380000 | F40: 540000 | G40: 1 | H40: =((E40*N40)*(1+I40))*G40 -> 561.25306 | I40: 0.035 | J40: =H40*(1-I40) -> 541.6092 | K40: =H40-J40 -> 19.643857 | L40: 0.001397 | M40: 0.0215 | N40: =L40*(1+M40) -> 0.0014270355 | O40: =(J40*M40)+15 -> 26.644598 | P40: =(J40*N40)+M40 -> 0.79439556 | Q40: =((F40*N40)*(1+I40))*G40 -> 797.57014 | R40: 0.06 | T40: =F40-E40 -> 160000 | U40: =T40*(1-I40-M40) -> 150960 | V40: =(F40-E40)*0.2 -> 32000 | W40: =F40-(E40+V40)-(F40*S40)-(F40*R40) -> 95600 | X40: =IFERROR((F40-E40)/E40,"") -> 0.42105263 | Y40: =IFERROR((Q40-H40)/Q40,"") -> 0.2962963 | Z40: =IFERROR(W40/F40,"") -> 0.17703704 | AH40: =IFERROR(AVERAGE(AE40:AG40),"") | AI40: =AE40+AF40+AG40 -> 0
A41: 2026 | C41: TOP 3 | E41: 360000 | F41: 500000 | G41: 1 | H41: =((E41*N41)*(1+I41))*G41 -> 531.71343 | I41: 0.035 | J41: =H41*(1-I41) -> 513.10346 | K41: =H41-J41 -> 18.60997 | L41: 0.001397 | M41: 0.0215 | N41: =L41*(1+M41) -> 0.0014270355 | O41: =(J41*M41)+15 -> 26.031724 | P41: =(J41*N41)+M41 -> 0.75371685 | Q41: =((F41*N41)*(1+I41))*G41 -> 738.49087 | R41: 0.06 | T41: =F41-E41 -> 140000 | U41: =T41*(1-I41-M41) -> 132090 | V41: =(F41-E41)*0.2 -> 28000 | W41: =F41-(E41+V41)-(F41*S41)-(F41*R41) -> 82000 | X41: =IFERROR((F41-E41)/E41,"") -> 0.38888889 | Y41: =IFERROR((Q41-H41)/Q41,"") -> 0.28 | Z41: =IFERROR(W41/F41,"") -> 0.164 | AH41: =IFERROR(AVERAGE(AE41:AG41),"") | AI41: =AE41+AF41+AG41 -> 0
A42: 2026 | C42: PAO PAO | E42: 280000 | F42: 450000 | G42: 1 | H42: =((E42*N42)*(1+I42))*G42 -> 413.55489 | I42: 0.035 | J42: =H42*(1-I42) -> 399.08047 | K42: =H42-J42 -> 14.474421 | L42: 0.001397 | M42: 0.0215 | N42: =L42*(1+M42) -> 0.0014270355 | O42: =(J42*M42)+15 -> 23.58023 | P42: =(J42*N42)+M42 -> 0.59100199 | Q42: =((F42*N42)*(1+I42))*G42 -> 664.64178 | R42: 0.06 | T42: =F42-E42 -> 170000 | U42: =T42*(1-I42-M42) -> 160395 | V42: =(F42-E42)*0.2 -> 34000 | W42: =F42-(E42+V42)-(F42*S42)-(F42*R42) -> 109000 | X42: =IFERROR((F42-E42)/E42,"") -> 0.60714286 | Y42: =IFERROR((Q42-H42)/Q42,"") -> 0.37777778 | Z42: =IFERROR(W42/F42,"") -> 0.24222222 | AH42: =IFERROR(AVERAGE(AE42:AG42),"") | AI42: =AE42+AF42+AG42 -> 0
T43: =F43-E43 -> 0 | U43: =T43*(1-I43-M43) -> 0 | V43: =(F43-E43)*0.2 -> 0 | W43: =F43-(E43+V43)-(F43*S43)-(F43*R43) -> 0 | X43: =IFERROR((F43-E43)/E43,"") | Z43: =IFERROR(W43/F43,"")
A44: 2026 | C44: Paue | E44: 370000 | F44: 520000 | G44: 1 | H44: =((E44*N44)*(1+I44))*G44 -> 546.48324 | I44: 0.035 | J44: =H44*(1-I44) -> 527.35633 | K44: =H44-J44 -> 19.126914 | L44: 0.001397 | M44: 0.0215 | N44: =L44*(1+M44) -> 0.0014270355 | O44: =(J44*M44)+15 -> 26.338161 | P44: =(J44*N44)+M44 -> 0.77405621 | Q44: =((F44*N44)*(1+I44))*G44 -> 768.03051 | R44: 0.06 | T44: =F44-E44 -> 150000 | U44: =T44*(1-I44-M44) -> 141525 | V44: =(F44-E44)*0.2 -> 30000 | W44: =F44-(E44+V44)-(F44*S44)-(F44*R44) -> 88800 | X44: =IFERROR((F44-E44)/E44,"") -> 0.40540541 | Y44: =IFERROR((Q44-H44)/Q44,"") -> 0.28846154 | Z44: =IFERROR(W44/F44,"") -> 0.17076923 | AH44: =IFERROR(AVERAGE(AE44:AG44),"") | AI44: =AE44+AF44+AG44 -> 0
A45: 2026 | C45: Paue CHD 04 A 07 ANOS | E45: 250000 | F45: 370000 | G45: 1 | H45: =((E45*N45)*(1+I45))*G45 -> 369.24544 | I45: 0.035 | J45: =H45*(1-I45) -> 356.32185 | K45: =H45-J45 -> 12.92359 | L45: 0.001397 | M45: 0.0215 | N45: =L45*(1+M45) -> 0.0014270355 | O45: =(J45*M45)+15 -> 22.66092 | P45: =(J45*N45)+M45 -> 0.52998392 | Q45: =((F45*N45)*(1+I45))*G45 -> 546.48324 | R45: 0.06 | T45: =F45-E45 -> 120000 | U45: =T45*(1-I45-M45) -> 113220 | V45: =(F45-E45)*0.2 -> 24000 | W45: =F45-(E45+V45)-(F45*S45)-(F45*R45) -> 73800 | X45: =IFERROR((F45-E45)/E45,"") -> 0.48 | Y45: =IFERROR((Q45-H45)/Q45,"") -> 0.32432432 | Z45: =IFERROR(W45/F45,"") -> 0.19945946 | AH45: =IFERROR(AVERAGE(AE45:AG45),"") | AI45: =AE45+AF45+AG45 -> 0
T46: =F46-E46 -> 0 | U46: =T46*(1-I46-M46) -> 0 | V46: =(F46-E46)*0.2 -> 0 | W46: =F46-(E46+V46)-(F46*S46)-(F46*R46) -> 0 | X46: =IFERROR((F46-E46)/E46,"") | Z46: =IFERROR(W46/F46,"")
A47: 2026 | C47: Rosario de Mar plan arrecife | E47: 300000 | F47: 450000 | G47: 1 | H47: =((E47*N47)*(1+I47))*G47 -> 443.09452 | I47: 0.035 | J47: =H47*(1-I47) -> 427.58621 | K47: =H47-J47 -> 15.508308 | L47: 0.001397 | M47: 0.0215 | N47: =L47*(1+M47) -> 0.0014270355 | O47: =(J47*M47)+15 -> 24.193104 | P47: =(J47*N47)+M47 -> 0.63168071 | Q47: =((F47*N47)*(1+I47))*G47 -> 664.64178 | R47: 0.06 | T47: =F47-E47 -> 150000 | U47: =T47*(1-I47-M47) -> 141525 | V47: =(F47-E47)*0.2 -> 30000 | W47: =F47-(E47+V47)-(F47*S47)-(F47*R47) -> 93000 | X47: =IFERROR((F47-E47)/E47,"") -> 0.5 | Y47: =IFERROR((Q47-H47)/Q47,"") -> 0.33333333 | Z47: =IFERROR(W47/F47,"") -> 0.20666667 | AH47: =IFERROR(AVERAGE(AE47:AG47),"") | AI47: =AE47+AF47+AG47 -> 0
A48: 2026 | C48: rosario de mar CHD 04 a 07 anos plan arrecife | E48: 220000 | F48: 370000 | G48: 1 | H48: =((E48*N48)*(1+I48))*G48 -> 324.93598 | I48: 0.035 | J48: =H48*(1-I48) -> 313.56322 | K48: =H48-J48 -> 11.372759 | L48: 0.001397 | M48: 0.0215 | N48: =L48*(1+M48) -> 0.0014270355 | O48: =(J48*M48)+15 -> 21.741609 | P48: =(J48*N48)+M48 -> 0.46896585 | Q48: =((F48*N48)*(1+I48))*G48 -> 546.48324 | R48: 0.06 | T48: =F48-E48 -> 150000 | U48: =T48*(1-I48-M48) -> 141525 | V48: =(F48-E48)*0.2 -> 30000 | W48: =F48-(E48+V48)-(F48*S48)-(F48*R48) -> 97800 | X48: =IFERROR((F48-E48)/E48,"") -> 0.68181818 | Y48: =IFERROR((Q48-H48)/Q48,"") -> 0.40540541 | Z48: =IFERROR(W48/F48,"") -> 0.26432432 | AH48: =IFERROR(AVERAGE(AE48:AG48),"") | AI48: =AE48+AF48+AG48 -> 0
T49: =F49-E49 -> 0 | U49: =T49*(1-I49-M49) -> 0 | V49: =(F49-E49)*0.2 -> 0 | W49: =F49-(E49+V49)-(F49*S49)-(F49*R49) -> 0 | X49: =IFERROR((F49-E49)/E49,"") | Z49: =IFERROR(W49/F49,"")
A50: 2026 | C50: Rosario de Mar plan abanico (open bar) | E50: 400000 | F50: 580000 | G50: 1 | H50: =((E50*N50)*(1+I50))*G50 -> 590.7927 | I50: 0.035 | J50: =H50*(1-I50) -> 570.11495 | K50: =H50-J50 -> 20.677744 | L50: 0.001397 | M50: 0.0215 | N50: =L50*(1+M50) -> 0.0014270355 | O50: =(J50*M50)+15 -> 27.257471 | P50: =(J50*N50)+M50 -> 0.83507428 | Q50: =((F50*N50)*(1+I50))*G50 -> 856.64941 | R50: 0.06 | T50: =F50-E50 -> 180000 | U50: =T50*(1-I50-M50) -> 169830 | V50: =(F50-E50)*0.2 -> 36000 | W50: =F50-(E50+V50)-(F50*S50)-(F50*R50) -> 109200 | X50: =IFERROR((F50-E50)/E50,"") -> 0.45 | Y50: =IFERROR((Q50-H50)/Q50,"") -> 0.31034483 | Z50: =IFERROR(W50/F50,"") -> 0.18827586 | AH50: =IFERROR(AVERAGE(AE50:AG50),"") | AI50: =AE50+AF50+AG50 -> 0
T51: =F51-E51 -> 0 | U51: =T51*(1-I51-M51) -> 0 | V51: =(F51-E51)*0.2 -> 0 | W51: =F51-(E51+V51)-(F51*S51)-(F51*R51) -> 0 | X51: =IFERROR((F51-E51)/E51,"") | Z51: =IFERROR(W51/F51,"")
A52: 2026 | C52: Sabai | E52: 390000 | F52: 520000 | G52: 1 | H52: =((E52*N52)*(1+I52))*G52 -> 576.02288 | I52: 0.035 | J52: =H52*(1-I52) -> 555.86208 | K52: =H52-J52 -> 20.160801 | L52: 0.001397 | M52: 0.0215 | N52: =L52*(1+M52) -> 0.0014270355 | O52: =(J52*M52)+15 -> 26.951035 | P52: =(J52*N52)+M52 -> 0.81473492 | Q52: =((F52*N52)*(1+I52))*G52 -> 768.03051 | R52: 0.06 | T52: =F52-E52 -> 130000 | U52: =T52*(1-I52-M52) -> 122655 | V52: =(F52-E52)*0.2 -> 26000 | W52: =F52-(E52+V52)-(F52*S52)-(F52*R52) -> 72800 | X52: =IFERROR((F52-E52)/E52,"") -> 0.33333333 | Y52: =IFERROR((Q52-H52)/Q52,"") -> 0.25 | Z52: =IFERROR(W52/F52,"") -> 0.14 | AH52: =IFERROR(AVERAGE(AE52:AG52),"") | AI52: =AE52+AF52+AG52 -> 0
A53: 2026 | C53: sabai chd 5 a 09 anos | E53: 130000 | F53: 380000 | G53: 1 | H53: =((E53*N53)*(1+I53))*G53 -> 192.00763 | I53: 0.035 | J53: =H53*(1-I53) -> 185.28736 | K53: =H53-J53 -> 6.7202669 | L53: 0.001397 | M53: 0.0215 | N53: =L53*(1+M53) -> 0.0014270355 | O53: =(J53*M53)+15 -> 18.983678 | P53: =(J53*N53)+M53 -> 0.28591164 | Q53: =((F53*N53)*(1+I53))*G53 -> 561.25306 | R53: 0.06 | T53: =F53-E53 -> 250000 | U53: =T53*(1-I53-M53) -> 235875 | V53: =(F53-E53)*0.2 -> 50000 | W53: =F53-(E53+V53)-(F53*S53)-(F53*R53) -> 177200 | X53: =IFERROR((F53-E53)/E53,"") -> 1.9230769 | Y53: =IFERROR((Q53-H53)/Q53,"") -> 0.65789474 | Z53: =IFERROR(W53/F53,"") -> 0.46631579 | AH53: =IFERROR(AVERAGE(AE53:AG53),"") | AI53: =AE53+AF53+AG53 -> 0
T54: =F54-E54 -> 0 | U54: =T54*(1-I54-M54) -> 0 | V54: =(F54-E54)*0.2 -> 0 | W54: =F54-(E54+V54)-(F54*S54)-(F54*R54) -> 0 | X54: =IFERROR((F54-E54)/E54,"") | Z54: =IFERROR(W54/F54,"")
A55: 2026 | C55: alondra in | E55: 61000 | F55: 160000 | G55: 1 | H55: =((E55*N55)*(1+I55))*G55 -> 90.095886 | I55: 0.035 | J55: =H55*(1-I55) -> 86.94253 | K55: =H55-J55 -> 3.153356 | L55: 0.001397 | M55: 0.0215 | N55: =L55*(1+M55) -> 0.0014270355 | O55: =(J55*M55)+15 -> 16.869264 | P55: =(J55*N55)+M55 -> 0.14557008 | Q55: =((F55*N55)*(1+I55))*G55 -> 236.31708 | R55: 0.06 | T55: =F55-E55 -> 99000 | U55: =T55*(1-I55-M55) -> 93406.5 | V55: =(F55-E55)*0.2 -> 19800 | W55: =F55-(E55+V55)-(F55*S55)-(F55*R55) -> 69600 | X55: =IFERROR((F55-E55)/E55,"") -> 1.6229508 | Y55: =IFERROR((Q55-H55)/Q55,"") -> 0.61875 | Z55: =IFERROR(W55/F55,"") -> 0.435 | AH55: =IFERROR(AVERAGE(AE55:AG55),"") | AI55: =AE55+AF55+AG55 -> 0
A56: 2026 | C56: alondra out | E56: 61000 | F56: 140000 | G56: 1 | H56: =((E56*N56)*(1+I56))*G56 -> 90.095886 | I56: 0.035 | J56: =H56*(1-I56) -> 86.94253 | K56: =H56-J56 -> 3.153356 | L56: 0.001397 | M56: 0.0215 | N56: =L56*(1+M56) -> 0.0014270355 | O56: =(J56*M56)+15 -> 16.869264 | P56: =(J56*N56)+M56 -> 0.14557008 | Q56: =((F56*N56)*(1+I56))*G56 -> 206.77744 | R56: 0.06 | T56: =F56-E56 -> 79000 | U56: =T56*(1-I56-M56) -> 74536.5 | V56: =(F56-E56)*0.2 -> 15800 | W56: =F56-(E56+V56)-(F56*S56)-(F56*R56) -> 54800 | X56: =IFERROR((F56-E56)/E56,"") -> 1.295082 | Y56: =IFERROR((Q56-H56)/Q56,"") -> 0.56428571 | Z56: =IFERROR(W56/F56,"") -> 0.39142857 | AH56: =IFERROR(AVERAGE(AE56:AG56),"") | AI56: =AE56+AF56+AG56 -> 0
A57: 2026 | C57: alondra in out | E57: =E55+E56 -> 122000 | F57: 250000 | G57: 1 | H57: =((E57*N57)*(1+I57))*G57 -> 180.19177 | I57: 0.035 | J57: =H57*(1-I57) -> 173.88506 | K57: =H57-J57 -> 6.306712 | L57: 0.001397 | M57: 0.0215 | N57: =L57*(1+M57) -> 0.0014270355 | O57: =(J57*M57)+15 -> 18.738529 | P57: =(J57*N57)+M57 -> 0.26964015 | Q57: =((F57*N57)*(1+I57))*G57 -> 369.24544 | R57: 0.06 | T57: =F57-E57 -> 128000 | U57: =T57*(1-I57-M57) -> 120768 | V57: =(F57-E57)*0.2 -> 25600 | W57: =F57-(E57+V57)-(F57*S57)-(F57*R57) -> 87400 | X57: =IFERROR((F57-E57)/E57,"") -> 1.0491803 | Y57: =IFERROR((Q57-H57)/Q57,"") -> 0.512 | Z57: =IFERROR(W57/F57,"") -> 0.3496 | AH57: =IFERROR(AVERAGE(AE57:AG57),"") | AI57: =AE57+AF57+AG57 -> 0
A58: 2026 | C58: alondra in van 8 pax | E58: 160000 | F58: 300000 | G58: 1 | H58: =((E58*N58)*(1+I58))*G58 -> 236.31708 | I58: 0.035 | J58: =H58*(1-I58) -> 228.04598 | K58: =H58-J58 -> 8.2710978 | L58: 0.001397 | M58: 0.0215 | N58: =L58*(1+M58) -> 0.0014270355 | O58: =(J58*M58)+15 -> 19.902989 | P58: =(J58*N58)+M58 -> 0.34692971 | Q58: =((F58*N58)*(1+I58))*G58 -> 443.09452 | R58: 0.06 | T58: =F58-E58 -> 140000 | U58: =T58*(1-I58-M58) -> 132090 | V58: =(F58-E58)*0.2 -> 28000 | W58: =F58-(E58+V58)-(F58*S58)-(F58*R58) -> 94000 | X58: =IFERROR((F58-E58)/E58,"") -> 0.875 | Y58: =IFERROR((Q58-H58)/Q58,"") -> 0.46666667 | Z58: =IFERROR(W58/F58,"") -> 0.31333333 | AH58: =IFERROR(AVERAGE(AE58:AG58),"") | AI58: =AE58+AF58+AG58 -> 0
A59: 2026 | C59: alondra out van 8 pax | E59: 160000 | F59: 340000 | G59: 1 | H59: =((E59*N59)*(1+I59))*G59 -> 236.31708 | I59: 0.035 | J59: =H59*(1-I59) -> 228.04598 | K59: =H59-J59 -> 8.2710978 | L59: 0.001397 | M59: 0.0215 | N59: =L59*(1+M59) -> 0.0014270355 | O59: =(J59*M59)+15 -> 19.902989 | P59: =(J59*N59)+M59 -> 0.34692971 | Q59: =((F59*N59)*(1+I59))*G59 -> 502.17379 | R59: 0.06 | T59: =F59-E59 -> 180000 | U59: =T59*(1-I59-M59) -> 169830 | V59: =(F59-E59)*0.2 -> 36000 | W59: =F59-(E59+V59)-(F59*S59)-(F59*R59) -> 123600 | X59: =IFERROR((F59-E59)/E59,"") -> 1.125 | Y59: =IFERROR((Q59-H59)/Q59,"") -> 0.52941176 | Z59: =IFERROR(W59/F59,"") -> 0.36352941 | AH59: =IFERROR(AVERAGE(AE59:AG59),"") | AI59: =AE59+AF59+AG59 -> 0
A60: 2026 | C60: alondra in e out van 8 pax | E60: =160000*2 -> 320000 | F60: 580000 | G60: 1 | H60: =((E60*N60)*(1+I60))*G60 -> 472.63416 | I60: 0.035 | J60: =H60*(1-I60) -> 456.09196 | K60: =H60-J60 -> 16.542196 | L60: 0.001397 | M60: 0.0215 | N60: =L60*(1+M60) -> 0.0014270355 | O60: =(J60*M60)+15 -> 24.805977 | P60: =(J60*N60)+M60 -> 0.67235942 | Q60: =((F60*N60)*(1+I60))*G60 -> 856.64941 | R60: 0.06 | T60: =F60-E60 -> 260000 | U60: =T60*(1-I60-M60) -> 245310 | V60: =(F60-E60)*0.2 -> 52000 | W60: =F60-(E60+V60)-(F60*S60)-(F60*R60) -> 173200 | X60: =IFERROR((F60-E60)/E60,"") -> 0.8125 | Y60: =IFERROR((Q60-H60)/Q60,"") -> 0.44827586 | Z60: =IFERROR(W60/F60,"") -> 0.29862069 | AH60: =IFERROR(AVERAGE(AE60:AG60),"") | AI60: =AE60+AF60+AG60 -> 0
A61: 2026 | C61: alondra in van 14pax | E61: 160000 | F61: 300000 | G61: 1 | H61: =((E61*N61)*(1+I61))*G61 -> 236.31708 | I61: 0.035 | J61: =H61*(1-I61) -> 228.04598 | K61: =H61-J61 -> 8.2710978 | L61: 0.001397 | M61: 0.0215 | N61: =L61*(1+M61) -> 0.0014270355 | O61: =(J61*M61)+15 -> 19.902989 | P61: =(J61*N61)+M61 -> 0.34692971 | Q61: =((F61*N61)*(1+I61))*G61 -> 443.09452 | R61: 0.06 | T61: =F61-E61 -> 140000 | U61: =T61*(1-I61-M61) -> 132090 | V61: =(F61-E61)*0.2 -> 28000 | W61: =F61-(E61+V61)-(F61*S61)-(F61*R61) -> 94000 | X61: =IFERROR((F61-E61)/E61,"") -> 0.875 | Y61: =IFERROR((Q61-H61)/Q61,"") -> 0.46666667 | Z61: =IFERROR(W61/F61,"") -> 0.31333333 | AH61: =IFERROR(AVERAGE(AE61:AG61),"") | AI61: =AE61+AF61+AG61 -> 0
A62: 2026 | C62: alondra out van 14 pax | E62: 160000 | F62: 340000 | G62: 1 | H62: =((E62*N62)*(1+I62))*G62 -> 236.31708 | I62: 0.035 | J62: =H62*(1-I62) -> 228.04598 | K62: =H62-J62 -> 8.2710978 | L62: 0.001397 | M62: 0.0215 | N62: =L62*(1+M62) -> 0.0014270355 | O62: =(J62*M62)+15 -> 19.902989 | P62: =(J62*N62)+M62 -> 0.34692971 | Q62: =((F62*N62)*(1+I62))*G62 -> 502.17379 | R62: 0.06 | T62: =F62-E62 -> 180000 | U62: =T62*(1-I62-M62) -> 169830 | V62: =(F62-E62)*0.2 -> 36000 | W62: =F62-(E62+V62)-(F62*S62)-(F62*R62) -> 123600 | X62: =IFERROR((F62-E62)/E62,"") -> 1.125 | Y62: =IFERROR((Q62-H62)/Q62,"") -> 0.52941176 | Z62: =IFERROR(W62/F62,"") -> 0.36352941 | AH62: =IFERROR(AVERAGE(AE62:AG62),"") | AI62: =AE62+AF62+AG62 -> 0
A63: 2026 | C63: alondra in e out van 14 pax | E63: =160000*2 -> 320000 | F63: 580000 | G63: 1 | H63: =((E63*N63)*(1+I63))*G63 -> 472.63416 | I63: 0.035 | J63: =H63*(1-I63) -> 456.09196 | K63: =H63-J63 -> 16.542196 | L63: 0.001397 | M63: 0.0215 | N63: =L63*(1+M63) -> 0.0014270355 | O63: =(J63*M63)+15 -> 24.805977 | P63: =(J63*N63)+M63 -> 0.67235942 | Q63: =((F63*N63)*(1+I63))*G63 -> 856.64941 | R63: 0.06 | T63: =F63-E63 -> 260000 | U63: =T63*(1-I63-M63) -> 245310 | V63: =(F63-E63)*0.2 -> 52000 | W63: =F63-(E63+V63)-(F63*S63)-(F63*R63) -> 173200 | X63: =IFERROR((F63-E63)/E63,"") -> 0.8125 | Y63: =IFERROR((Q63-H63)/Q63,"") -> 0.44827586 | Z63: =IFERROR(W63/F63,"") -> 0.29862069 | AH63: =IFERROR(AVERAGE(AE63:AG63),"") | AI63: =AE63+AF63+AG63 -> 0
A65: 2026 | C65: alondra aviario ate 3 pax | E65: 385000 | F65: 580000 | G65: 1 | H65: =((E65*N65)*(1+I65))*G65 -> 568.63797 | I65: 0.035 | J65: =H65*(1-I65) -> 548.73564 | K65: =H65-J65 -> 19.902329 | L65: 0.001397 | M65: 0.0215 | N65: =L65*(1+M65) -> 0.0014270355 | O65: =(J65*M65)+15 -> 26.797816 | P65: =(J65*N65)+M65 -> 0.80456524 | Q65: =((F65*N65)*(1+I65))*G65 -> 856.64941 | R65: 0.06 | T65: =F65-E65 -> 195000 | U65: =T65*(1-I65-M65) -> 183982.5 | V65: =(F65-E65)*0.2 -> 39000 | W65: =F65-(E65+V65)-(F65*S65)-(F65*R65) -> 121200 | X65: =IFERROR((F65-E65)/E65,"") -> 0.50649351 | Y65: =IFERROR((Q65-H65)/Q65,"") -> 0.3362069 | Z65: =IFERROR(W65/F65,"") -> 0.20896552 | AH65: =IFERROR(AVERAGE(AE65:AG65),"") | AI65: =AE65+AF65+AG65 -> 0
A66: 2026 | C66: alondra aviario ate 8 pax | E66: 555000 | F66: 780000 | G66: 1 | H66: =((E66*N66)*(1+I66))*G66 -> 819.72487 | I66: 0.035 | J66: =H66*(1-I66) -> 791.0345 | K66: =H66-J66 -> 28.69037 | L66: 0.001397 | M66: 0.0215 | N66: =L66*(1+M66) -> 0.0014270355 | O66: =(J66*M66)+15 -> 32.007242 | P66: =(J66*N66)+M66 -> 1.1503343 | Q66: =((F66*N66)*(1+I66))*G66 -> 1152.0458 | R66: 0.06 | T66: =F66-E66 -> 225000 | U66: =T66*(1-I66-M66) -> 212287.5 | V66: =(F66-E66)*0.2 -> 45000 | W66: =F66-(E66+V66)-(F66*S66)-(F66*R66) -> 133200 | X66: =IFERROR((F66-E66)/E66,"") -> 0.40540541 | Y66: =IFERROR((Q66-H66)/Q66,"") -> 0.28846154 | Z66: =IFERROR(W66/F66,"") -> 0.17076923 | AH66: =IFERROR(AVERAGE(AE66:AG66),"") | AI66: =AE66+AF66+AG66 -> 0
A67: 2026 | C67: alondra aviario ate 14 pax | E67: 660000 | F67: 900000 | G67: 1 | H67: =((E67*N67)*(1+I67))*G67 -> 974.80795 | I67: 0.035 | J67: =H67*(1-I67) -> 940.68967 | K67: =H67-J67 -> 34.118278 | L67: 0.001397 | M67: 0.0215 | N67: =L67*(1+M67) -> 0.0014270355 | O67: =(J67*M67)+15 -> 35.224828 | P67: =(J67*N67)+M67 -> 1.3638976 | Q67: =((F67*N67)*(1+I67))*G67 -> 1329.2836 | R67: 0.06 | T67: =F67-E67 -> 240000 | U67: =T67*(1-I67-M67) -> 226440 | V67: =(F67-E67)*0.2 -> 48000 | W67: =F67-(E67+V67)-(F67*S67)-(F67*R67) -> 138000 | X67: =IFERROR((F67-E67)/E67,"") -> 0.36363636 | Y67: =IFERROR((Q67-H67)/Q67,"") -> 0.26666667 | Z67: =IFERROR(W67/F67,"") -> 0.15333333 | AH67: =IFERROR(AVERAGE(AE67:AG67),"") | AI67: =AE67+AF67+AG67 -> 0
A69: 2026 | C69: Corona Island | E69: 633000 | F69: 850000 | G69: 1 | H69: =((E69*N69)*(1+I69))*G69 -> 934.92944 | I69: 0.035 | J69: =H69*(1-I69) -> 902.20691 | K69: =H69-J69 -> 32.722531 | L69: 0.001397 | M69: 0.0215 | N69: =L69*(1+M69) -> 0.0014270355 | O69: =(J69*M69)+15 -> 34.397449 | P69: =(J69*N69)+M69 -> 1.3089813 | Q69: =((F69*N69)*(1+I69))*G69 -> 1255.4345 | R69: 0.06 | T69: =F69-E69 -> 217000 | U69: =T69*(1-I69-M69) -> 204739.5 | V69: =(F69-E69)*0.2 -> 43400 | W69: =F69-(E69+V69)-(F69*S69)-(F69*R69) -> 122600 | X69: =IFERROR((F69-E69)/E69,"") -> 0.34281201 | Y69: =IFERROR((Q69-H69)/Q69,"") -> 0.25529412 | Z69: =IFERROR(W69/F69,"") -> 0.14423529 | AH69: =IFERROR(AVERAGE(AE69:AG69),"") | AI69: =AE69+AF69+AG69 -> 0
T70: =F70-E70 -> 0 | U70: =T70*(1-I70-M70) -> 0 | V70: =(F70-E70)*0.2 -> 0 | W70: =F70-(E70+V70)-(F70*S70)-(F70*R70) -> 0 | X70: =IFERROR((F70-E70)/E70,"") | Z70: =IFERROR(W70/F70,"")
A71: 2026 | C71: isla palma | E71: 420000 | F71: 550000 | G71: 1 | H71: =((E71*N71)*(1+I71))*G71 -> 620.33233 | I71: 0.035 | J71: =H71*(1-I71) -> 598.6207 | K71: =H71-J71 -> 21.711632 | L71: 0.001397 | M71: 0.0215 | N71: =L71*(1+M71) -> 0.0014270355 | O71: =(J71*M71)+15 -> 27.870345 | P71: =(J71*N71)+M71 -> 0.87575299 | Q71: =((F71*N71)*(1+I71))*G71 -> 812.33996 | R71: 0.06 | T71: =F71-E71 -> 130000 | U71: =T71*(1-I71-M71) -> 122655 | V71: =(F71-E71)*0.2 -> 26000 | W71: =F71-(E71+V71)-(F71*S71)-(F71*R71) -> 71000 | X71: =IFERROR((F71-E71)/E71,"") -> 0.30952381 | Y71: =IFERROR((Q71-H71)/Q71,"") -> 0.23636364 | Z71: =IFERROR(W71/F71,"") -> 0.12909091 | AH71: =IFERROR(AVERAGE(AE71:AG71),"") | AI71: =AE71+AF71+AG71 -> 0
A72: 2026 | C72: isla palma CHD 04 a 06 anos | E72: 350000 | F72: 420000 | G72: 1 | H72: =((E72*N72)*(1+I72))*G72 -> 516.94361 | I72: 0.035 | J72: =H72*(1-I72) -> 498.85058 | K72: =H72-J72 -> 18.093026 | L72: 0.001397 | M72: 0.0215 | N72: =L72*(1+M72) -> 0.0014270355 | O72: =(J72*M72)+15 -> 25.725288 | P72: =(J72*N72)+M72 -> 0.73337749 | Q72: =((F72*N72)*(1+I72))*G72 -> 620.33233 | R72: 0.06 | T72: =F72-E72 -> 70000 | U72: =T72*(1-I72-M72) -> 66045 | V72: =(F72-E72)*0.2 -> 14000 | W72: =F72-(E72+V72)-(F72*S72)-(F72*R72) -> 30800 | X72: =IFERROR((F72-E72)/E72,"") -> 0.2 | Y72: =IFERROR((Q72-H72)/Q72,"") -> 0.16666667 | Z72: =IFERROR(W72/F72,"") -> 0.073333333 | AH72: =IFERROR(AVERAGE(AE72:AG72),"") | AI72: =AE72+AF72+AG72 -> 0
T73: =F73-E73 -> 0 | U73: =T73*(1-I73-M73) -> 0 | V73: =(F73-E73)*0.2 -> 0 | W73: =F73-(E73+V73)-(F73*S73)-(F73*R73) -> 0 | X73: =IFERROR((F73-E73)/E73,"") | Z73: =IFERROR(W73/F73,"")
H295: =((E295*N295)*(1+I295))*G295 -> 0 | I295: 0.035 | J295: =H295*(1-I295) -> 0 | K295: =H295-J295 -> 0 | L295: 0.001397 | M295: 0.0215 | N295: =L295*(1+M295) -> 0.0014270355 | O295: =(J295*M295)+15 -> 15 | P295: =(J295*N295)+M295 -> 0.0215 | Q295: =((F295*N295)*(1+I295))*G295 -> 0 | R295: 0.06 | T295: =F295-E295 -> 0 | U295: =T295*(1-I295-M295) -> 0 | V295: =(F295-E295)*0.2 -> 0 | W295: =F295-(E295+V295)-(F295*S295)-(F295*R295) -> 0 | X295: =IFERROR((F295-E295)/E295,"") | Y295: =IFERROR((Q295-H295)/Q295,"") | Z295: =IFERROR(W295/F295,"") | AH295: =IFERROR(AVERAGE(AE295:AG295),"") | AI295: =AE295+AF295+AG295 -> 0
H296: =((E296*N296)*(1+I296))*G296 -> 0 | I296: 0.035 | J296: =H296*(1-I296) -> 0 | K296: =H296-J296 -> 0 | L296: 0.001397 | M296: 0.0215 | N296: =L296*(1+M296) -> 0.0014270355 | O296: =(J296*M296)+15 -> 15 | P296: =(J296*N296)+M296 -> 0.0215 | Q296: =((F296*N296)*(1+I296))*G296 -> 0 | R296: 0.06 | T296: =F296-E296 -> 0 | U296: =T296*(1-I296-M296) -> 0 | V296: =(F296-E296)*0.2 -> 0 | W296: =F296-(E296+V296)-(F296*S296)-(F296*R296) -> 0 | X296: =IFERROR((F296-E296)/E296,"") | Y296: =IFERROR((Q296-H296)/Q296,"") | Z296: =IFERROR(W296/F296,"") | AH296: =IFERROR(AVERAGE(AE296:AG296),"") | AI296: =AE296+AF296+AG296 -> 0
L297: 0.001397 | Q297: =((F297*N297)*(1+I297))*G297 -> 0 | T297: =F297-E297 -> 0 | U297: =T297*(1-I297-M297) -> 0 | V297: =(F297-E297)*0.2 -> 0 | W297: =F297-(E297+V297)-(F297*S297)-(F297*R297) -> 0 | X297: =IFERROR((F297-E297)/E297,"") | Z297: =IFERROR(W297/F297,"")
H298: =((E298*N298)*(1+I298))*G298 -> 0 | I298: 0.035 | J298: =H298*(1-I298) -> 0 | K298: =H298-J298 -> 0 | L298: 0.001397 | M298: 0.0215 | N298: =L298*(1+M298) -> 0.0014270355 | O298: =(J298*M298)+15 -> 15 | P298: =(J298*N298)+M298 -> 0.0215 | Q298: =((F298*N298)*(1+I298))*G298 -> 0 | R298: 0.06 | T298: =F298-E298 -> 0 | U298: =T298*(1-I298-M298) -> 0 | V298: =(F298-E298)*0.2 -> 0 | W298: =F298-(E298+V298)-(F298*S298)-(F298*R298) -> 0 | X298: =IFERROR((F298-E298)/E298,"") | Y298: =IFERROR((Q298-H298)/Q298,"") | Z298: =IFERROR(W298/F298,"") | AH298: =IFERROR(AVERAGE(AE298:AG298),"") | AI298: =AE298+AF298+AG298 -> 0
H299: =((E299*N299)*(1+I299))*G299 -> 0 | I299: 0.035 | J299: =H299*(1-I299) -> 0 | K299: =H299-J299 -> 0 | L299: 0.001397 | M299: 0.0215 | N299: =L299*(1+M299) -> 0.0014270355 | O299: =(J299*M299)+15 -> 15 | P299: =(J299*N299)+M299 -> 0.0215 | Q299: =((F299*N299)*(1+I299))*G299 -> 0 | R299: 0.06 | T299: =F299-E299 -> 0 | U299: =T299*(1-I299-M299) -> 0 | V299: =(F299-E299)*0.2 -> 0 | W299: =F299-(E299+V299)-(F299*S299)-(F299*R299) -> 0 | X299: =IFERROR((F299-E299)/E299,"") | Y299: =IFERROR((Q299-H299)/Q299,"") | Z299: =IFERROR(W299/F299,"") | AH299: =IFERROR(AVERAGE(AE299:AG299),"") | AI299: =AE299+AF299+AG299 -> 0
H300: =((E300*N300)*(1+I300))*G300 -> 0 | I300: 0.035 | J300: =H300*(1-I300) -> 0 | K300: =H300-J300 -> 0 | L300: 0.001397 | M300: 0.0215 | N300: =L300*(1+M300) -> 0.0014270355 | O300: =(J300*M300)+15 -> 15 | P300: =(J300*N300)+M300 -> 0.0215 | Q300: =((F300*N300)*(1+I300))*G300 -> 0 | R300: 0.06 | T300: =F300-E300 -> 0 | U300: =T300*(1-I300-M300) -> 0 | V300: =(F300-E300)*0.2 -> 0 | W300: =F300-(E300+V300)-(F300*S300)-(F300*R300) -> 0 | X300: =IFERROR((F300-E300)/E300,"") | Y300: =IFERROR((Q300-H300)/Q300,"") | Z300: =IFERROR(W300/F300,"") | AH300: =IFERROR(AVERAGE(AE300:AG300),"") | AI300: =AE300+AF300+AG300 -> 0
H301: =((E301*N301)*(1+I301))*G301 -> 0 | I301: 0.035 | J301: =H301*(1-I301) -> 0 | K301: =H301-J301 -> 0 | L301: 0.001397 | M301: 0.0215 | N301: =L301*(1+M301) -> 0.0014270355 | O301: =(J301*M301)+15 -> 15 | P301: =(J301*N301)+M301 -> 0.0215 | Q301: =((F301*N301)*(1+I301))*G301 -> 0 | R301: 0.06 | T301: =F301-E301 -> 0 | U301: =T301*(1-I301-M301) -> 0 | V301: =(F301-E301)*0.2 -> 0 | W301: =F301-(E301+V301)-(F301*S301)-(F301*R301) -> 0 | X301: =IFERROR((F301-E301)/E301,"") | Y301: =IFERROR((Q301-H301)/Q301,"") | Z301: =IFERROR(W301/F301,"") | AH301: =IFERROR(AVERAGE(AE301:AG301),"") | AI301: =AE301+AF301+AG301 -> 0
H302: =((E302*N302)*(1+I302))*G302 -> 0 | I302: 0.035 | J302: =H302*(1-I302) -> 0 | K302: =H302-J302 -> 0 | L302: 0.001397 | M302: 0.0215 | N302: =L302*(1+M302) -> 0.0014270355 | O302: =(J302*M302)+15 -> 15 | P302: =(J302*N302)+M302 -> 0.0215 | Q302: =((F302*N302)*(1+I302))*G302 -> 0 | R302: 0.06 | T302: =F302-E302 -> 0 | U302: =T302*(1-I302-M302) -> 0 | V302: =(F302-E302)*0.2 -> 0 | W302: =F302-(E302+V302)-(F302*S302)-(F302*R302) -> 0 | X302: =IFERROR((F302-E302)/E302,"") | Y302: =IFERROR((Q302-H302)/Q302,"") | Z302: =IFERROR(W302/F302,"") | AH302: =IFERROR(AVERAGE(AE302:AG302),"") | AI302: =AE302+AF302+AG302 -> 0
H303: =((E303*N303)*(1+I303))*G303 -> 0 | I303: 0.035 | J303: =H303*(1-I303) -> 0 | K303: =H303-J303 -> 0 | L303: 0.001397 | M303: 0.0215 | N303: =L303*(1+M303) -> 0.0014270355 | O303: =(J303*M303)+15 -> 15 | P303: =(J303*N303)+M303 -> 0.0215 | Q303: =((F303*N303)*(1+I303))*G303 -> 0 | R303: 0.06 | T303: =F303-E303 -> 0 | U303: =T303*(1-I303-M303) -> 0 | V303: =(F303-E303)*0.2 -> 0 | W303: =F303-(E303+V303)-(F303*S303)-(F303*R303) -> 0 | X303: =IFERROR((F303-E303)/E303,"") | Y303: =IFERROR((Q303-H303)/Q303,"") | Z303: =IFERROR(W303/F303,"") | AH303: =IFERROR(AVERAGE(AE303:AG303),"") | AI303: =AE303+AF303+AG303 -> 0
H304: =((E304*N304)*(1+I304))*G304 -> 0 | I304: 0.035 | J304: =H304*(1-I304) -> 0 | K304: =H304-J304 -> 0 | L304: 0.001397 | M304: 0.0215 | N304: =L304*(1+M304) -> 0.0014270355 | O304: =(J304*M304)+15 -> 15 | P304: =(J304*N304)+M304 -> 0.0215 | Q304: =((F304*N304)*(1+I304))*G304 -> 0 | R304: 0.06 | T304: =F304-E304 -> 0 | U304: =T304*(1-I304-M304) -> 0 | V304: =(F304-E304)*0.2 -> 0 | W304: =F304-(E304+V304)-(F304*S304)-(F304*R304) -> 0 | X304: =IFERROR((F304-E304)/E304,"") | Y304: =IFERROR((Q304-H304)/Q304,"") | Z304: =IFERROR(W304/F304,"") | AH304: =IFERROR(AVERAGE(AE304:AG304),"") | AI304: =AE304+AF304+AG304 -> 0
H305: =((E305*N305)*(1+I305))*G305 -> 0 | I305: 0.035 | J305: =H305*(1-I305) -> 0 | K305: =H305-J305 -> 0 | L305: 0.001397 | M305: 0.0215 | N305: =L305*(1+M305) -> 0.0014270355 | O305: =(J305*M305)+15 -> 15 | P305: =(J305*N305)+M305 -> 0.0215 | Q305: =((F305*N305)*(1+I305))*G305 -> 0 | R305: 0.06 | T305: =F305-E305 -> 0 | U305: =T305*(1-I305-M305) -> 0 | V305: =(F305-E305)*0.2 -> 0 | W305: =F305-(E305+V305)-(F305*S305)-(F305*R305) -> 0 | X305: =IFERROR((F305-E305)/E305,"") | Y305: =IFERROR((Q305-H305)/Q305,"") | Z305: =IFERROR(W305/F305,"") | AH305: =IFERROR(AVERAGE(AE305:AG305),"") | AI305: =AE305+AF305+AG305 -> 0
H306: =((E306*N306)*(1+I306))*G306 -> 0 | I306: 0.035 | J306: =H306*(1-I306) -> 0 | K306: =H306-J306 -> 0 | L306: 0.001397 | M306: 0.0215 | N306: =L306*(1+M306) -> 0.0014270355 | O306: =(J306*M306)+15 -> 15 | P306: =(J306*N306)+M306 -> 0.0215 | Q306: =((F306*N306)*(1+I306))*G306 -> 0 | R306: 0.06 | T306: =F306-E306 -> 0 | U306: =T306*(1-I306-M306) -> 0 | V306: =(F306-E306)*0.2 -> 0 | W306: =F306-(E306+V306)-(F306*S306)-(F306*R306) -> 0 | X306: =IFERROR((F306-E306)/E306,"") | Y306: =IFERROR((Q306-H306)/Q306,"") | Z306: =IFERROR(W306/F306,"") | AH306: =IFERROR(AVERAGE(AE306:AG306),"") | AI306: =AE306+AF306+AG306 -> 0
H307: =((E307*N307)*(1+I307))*G307 -> 0 | I307: 0.035 | J307: =H307*(1-I307) -> 0 | K307: =H307-J307 -> 0 | L307: 0.001397 | M307: 0.0215 | N307: =L307*(1+M307) -> 0.0014270355 | O307: =(J307*M307)+15 -> 15 | P307: =(J307*N307)+M307 -> 0.0215 | Q307: =((F307*N307)*(1+I307))*G307 -> 0 | R307: 0.06 | T307: =F307-E307 -> 0 | U307: =T307*(1-I307-M307) -> 0 | V307: =(F307-E307)*0.2 -> 0 | W307: =F307-(E307+V307)-(F307*S307)-(F307*R307) -> 0 | X307: =IFERROR((F307-E307)/E307,"") | Y307: =IFERROR((Q307-H307)/Q307,"") | Z307: =IFERROR(W307/F307,"") | AH307: =IFERROR(AVERAGE(AE307:AG307),"") | AI307: =AE307+AF307+AG307 -> 0
H308: =((E308*N308)*(1+I308))*G308 -> 0 | I308: 0.035 | J308: =H308*(1-I308) -> 0 | K308: =H308-J308 -> 0 | L308: 0.001397 | M308: 0.0215 | N308: =L308*(1+M308) -> 0.0014270355 | O308: =(J308*M308)+15 -> 15 | P308: =(J308*N308)+M308 -> 0.0215 | Q308: =((F308*N308)*(1+I308))*G308 -> 0 | R308: 0.06 | T308: =F308-E308 -> 0 | U308: =T308*(1-I308-M308) -> 0 | V308: =(F308-E308)*0.2 -> 0 | W308: =F308-(E308+V308)-(F308*S308)-(F308*R308) -> 0 | X308: =IFERROR((F308-E308)/E308,"") | Y308: =IFERROR((Q308-H308)/Q308,"") | Z308: =IFERROR(W308/F308,"") | AH308: =IFERROR(AVERAGE(AE308:AG308),"") | AI308: =AE308+AF308+AG308 -> 0
H309: =((E309*N309)*(1+I309))*G309 -> 0 | I309: 0.035 | J309: =H309*(1-I309) -> 0 | K309: =H309-J309 -> 0 | L309: 0.001397 | M309: 0.0215 | N309: =L309*(1+M309) -> 0.0014270355 | O309: =(J309*M309)+15 -> 15 | P309: =(J309*N309)+M309 -> 0.0215 | Q309: =((F309*N309)*(1+I309))*G309 -> 0 | R309: 0.06 | T309: =F309-E309 -> 0 | U309: =T309*(1-I309-M309) -> 0 | V309: =(F309-E309)*0.2 -> 0 | W309: =F309-(E309+V309)-(F309*S309)-(F309*R309) -> 0 | X309: =IFERROR((F309-E309)/E309,"") | Y309: =IFERROR((Q309-H309)/Q309,"") | Z309: =IFERROR(W309/F309,"") | AH309: =IFERROR(AVERAGE(AE309:AG309),"") | AI309: =AE309+AF309+AG309 -> 0
... H315: =((E315*N315)*(1+I315))*G315 -> 0 | I315: 0.035 | J315: =H315*(1-I315) -> 0 | K315: =H315-J315 -> 0 | L315: 0.001397 | M315: 0.0215 | N315: =L315*(1+M315) -> 0.0014270355 | O315: =(J315*M315)+15 -> 15 | P315: =(J315*N315)+M315 -> 0.0215 | Q315: =((F315*N315)*(1+I315))*G315 -> 0 | R315: 0.06 | T315: =F315-E315 -> 0 | U315: =T315*(1-I315-M315) -> 0 | V315: =(F315-E315)*0.2 -> 0 | W315: =F315-(E315+V315)-(F315*S315)-(F315*R315) -> 0 | X315: =IFERROR((F315-E315)/E315,"") | Y315: =IFERROR((Q315-H315)/Q315,"") | Z315: =IFERROR(W315/F315,"") | AH315: =IFERROR(AVERAGE(AE315:AG315),"") | AI315: =AE315+AF315+AG315 -> 0
H316: =((E316*N316)*(1+I316))*G316 -> 0 | I316: 0.035 | J316: =H316*(1-I316) -> 0 | K316: =H316-J316 -> 0 | L316: 0.001397 | M316: 0.0215 | N316: =L316*(1+M316) -> 0.0014270355 | O316: =(J316*M316)+15 -> 15 | P316: =(J316*N316)+M316 -> 0.0215 | Q316: =((F316*N316)*(1+I316))*G316 -> 0 | R316: 0.06 | T316: =F316-E316 -> 0 | U316: =T316*(1-I316-M316) -> 0 | V316: =(F316-E316)*0.2 -> 0 | W316: =F316-(E316+V316)-(F316*S316)-(F316*R316) -> 0 | X316: =IFERROR((F316-E316)/E316,"") | Y316: =IFERROR((Q316-H316)/Q316,"") | Z316: =IFERROR(W316/F316,"")
H317: =((E317*N317)*(1+I317))*G317 -> 0 | I317: 0.035 | J317: =H317*(1-I317) -> 0 | K317: =H317-J317 -> 0 | L317: 0.001397 | M317: 0.0215 | N317: =L317*(1+M317) -> 0.0014270355 | O317: =(J317*M317)+15 -> 15 | P317: =(J317*N317)+M317 -> 0.0215 | Q317: =((F317*N317)*(1+I317))*G317 -> 0 | R317: 0.06 | T317: =F317-E317 -> 0 | U317: =T317*(1-I317-M317) -> 0 | V317: =(F317-E317)*0.2 -> 0 | W317: =F317-(E317+V317)-(F317*S317)-(F317*R317) -> 0 | X317: =IFERROR((F317-E317)/E317,"") | Y317: =IFERROR((Q317-H317)/Q317,"") | Z317: =IFERROR(W317/F317,"")
H318: =((E318*N318)*(1+I318))*G318 -> 0 | I318: 0.035 | J318: =H318*(1-I318) -> 0 | K318: =H318-J318 -> 0 | L318: 0.001397 | M318: 0.0215 | N318: =L318*(1+M318) -> 0.0014270355 | O318: =(J318*M318)+15 -> 15 | P318: =(J318*N318)+M318 -> 0.0215 | Q318: =((F318*N318)*(1+I318))*G318 -> 0 | R318: 0.06 | T318: =F318-E318 -> 0 | U318: =T318*(1-I318-M318) -> 0 | V318: =(F318-E318)*0.2 -> 0 | W318: =F318-(E318+V318)-(F318*S318)-(F318*R318) -> 0 | X318: =IFERROR((F318-E318)/E318,"") | Y318: =IFERROR((Q318-H318)/Q318,"") | Z318: =IFERROR(W318/F318,"")
H319: =((E319*N319)*(1+I319))*G319 -> 0 | I319: 0.035 | J319: =H319*(1-I319) -> 0 | K319: =H319-J319 -> 0 | L319: 0.001397 | M319: 0.0215 | N319: =L319*(1+M319) -> 0.0014270355 | O319: =(J319*M319)+15 -> 15 | P319: =(J319*N319)+M319 -> 0.0215 | Q319: =((F319*N319)*(1+I319))*G319 -> 0 | R319: 0.06 | T319: =F319-E319 -> 0 | U319: =T319*(1-I319-M319) -> 0 | V319: =(F319-E319)*0.2 -> 0 | W319: =F319-(E319+V319)-(F319*S319)-(F319*R319) -> 0 | X319: =IFERROR((F319-E319)/E319,"") | Y319: =IFERROR((Q319-H319)/Q319,"") | Z319: =IFERROR(W319/F319,"")
H320: =((E320*N320)*(1+I320))*G320 -> 0 | I320: 0.035 | J320: =H320*(1-I320) -> 0 | K320: =H320-J320 -> 0 | L320: 0.001397 | M320: 0.0215 | N320: =L320*(1+M320) -> 0.0014270355 | O320: =(J320*M320)+15 -> 15 | P320: =(J320*N320)+M320 -> 0.0215 | Q320: =((F320*N320)*(1+I320))*G320 -> 0 | R320: 0.06 | T320: =F320-E320 -> 0 | U320: =T320*(1-I320-M320) -> 0 | V320: =(F320-E320)*0.2 -> 0 | W320: =F320-(E320+V320)-(F320*S320)-(F320*R320) -> 0 | X320: =IFERROR((F320-E320)/E320,"") | Y320: =IFERROR((Q320-H320)/Q320,"") | Z320: =IFERROR(W320/F320,"")
H321: =((E321*N321)*(1+I321))*G321 -> 0 | I321: 0.035 | J321: =H321*(1-I321) -> 0 | K321: =H321-J321 -> 0 | L321: 0.001397 | M321: 0.0215 | N321: =L321*(1+M321) -> 0.0014270355 | O321: =(J321*M321)+15 -> 15 | P321: =(J321*N321)+M321 -> 0.0215 | Q321: =((F321*N321)*(1+I321))*G321 -> 0 | R321: 0.06 | T321: =F321-E321 -> 0 | U321: =T321*(1-I321-M321) -> 0 | V321: =(F321-E321)*0.2 -> 0 | W321: =F321-(E321+V321)-(F321*S321)-(F321*R321) -> 0 | X321: =IFERROR((F321-E321)/E321,"") | Y321: =IFERROR((Q321-H321)/Q321,"") | Z321: =IFERROR(W321/F321,"")
H322: =((E322*N322)*(1+I322))*G322 -> 0 | I322: 0.035 | J322: =H322*(1-I322) -> 0 | K322: =H322-J322 -> 0 | L322: 0.001397 | M322: 0.0215 | N322: =L322*(1+M322) -> 0.0014270355 | O322: =(J322*M322)+15 -> 15 | P322: =(J322*N322)+M322 -> 0.0215 | Q322: =((F322*N322)*(1+I322))*G322 -> 0 | R322: 0.06 | T322: =F322-E322 -> 0 | U322: =T322*(1-I322-M322) -> 0 | V322: =(F322-E322)*0.2 -> 0 | W322: =F322-(E322+V322)-(F322*S322)-(F322*R322) -> 0 | X322: =IFERROR((F322-E322)/E322,"") | Y322: =IFERROR((Q322-H322)/Q322,"") | Z322: =IFERROR(W322/F322,"")
H323: =((E323*N323)*(1+I323))*G323 -> 0 | I323: 0.035 | J323: =H323*(1-I323) -> 0 | K323: =H323-J323 -> 0 | L323: 0.001397 | M323: 0.0215 | N323: =L323*(1+M323) -> 0.0014270355 | O323: =(J323*M323)+15 -> 15 | P323: =(J323*N323)+M323 -> 0.0215 | Q323: =((F323*N323)*(1+I323))*G323 -> 0 | R323: 0.06 | T323: =F323-E323 -> 0 | U323: =T323*(1-I323-M323) -> 0 | V323: =(F323-E323)*0.2 -> 0 | W323: =F323-(E323+V323)-(F323*S323)-(F323*R323) -> 0 | X323: =IFERROR((F323-E323)/E323,"") | Y323: =IFERROR((Q323-H323)/Q323,"") | Z323: =IFERROR(W323/F323,"")
H324: =((E324*N324)*(1+I324))*G324 -> 0 | I324: 0.035 | J324: =H324*(1-I324) -> 0 | K324: =H324-J324 -> 0 | L324: 0.001397 | M324: 0.0215 | N324: =L324*(1+M324) -> 0.0014270355 | O324: =(J324*M324)+15 -> 15 | P324: =(J324*N324)+M324 -> 0.0215 | Q324: =((F324*N324)*(1+I324))*G324 -> 0 | R324: 0.06 | T324: =F324-E324 -> 0 | U324: =T324*(1-I324-M324) -> 0 | V324: =(F324-E324)*0.2 -> 0 | W324: =F324-(E324+V324)-(F324*S324)-(F324*R324) -> 0 | X324: =IFERROR((F324-E324)/E324,"") | Y324: =IFERROR((Q324-H324)/Q324,"") | Z324: =IFERROR(W324/F324,"")
L325: 0.001397 | T325: =F325-E325 -> 0 | U325: =T325*(1-I325-M325) -> 0 | V325: =(F325-E325)*0.2 -> 0 | W325: =F325-(E325+V325)-(F325*S325)-(F325*R325) -> 0 | X325: =IFERROR((F325-E325)/E325,"") | Z325: =IFERROR(W325/F325,"")
L326: 0.001397 | T326: =F326-E326 -> 0 | U326: =T326*(1-I326-M326) -> 0 | V326: =(F326-E326)*0.2 -> 0 | W326: =F326-(E326+V326)-(F326*S326)-(F326*R326) -> 0 | X326: =IFERROR((F326-E326)/E326,"") | Z326: =IFERROR(W326/F326,"")
L327: 0.001397 | T327: =F327-E327 -> 0 | U327: =T327*(1-I327-M327) -> 0 | V327: =(F327-E327)*0.2 -> 0 | W327: =F327-(E327+V327)-(F327*S327)-(F327*R327) -> 0 | X327: =IFERROR((F327-E327)/E327,"") | Z327: =IFERROR(W327/F327,"")
L328: 0.001397 | T328: =F328-E328 -> 0 | U328: =T328*(1-I328-M328) -> 0 | V328: =(F328-E328)*0.2 -> 0 | W328: =F328-(E328+V328)-(F328*S328)-(F328*R328) -> 0 | X328: =IFERROR((F328-E328)/E328,"") | Z328: =IFERROR(W328/F328,"")
L329: 0.001397 | T329: =F329-E329 -> 0 | U329: =T329*(1-I329-M329) -> 0 | V329: =(F329-E329)*0.2 -> 0 | W329: =F329-(E329+V329)-(F329*S329)-(F329*R329) -> 0 | Z329: =IFERROR(W329/F329,"")
L330: 0.001397 | T330: =F330-E330 -> 0 | U330: =T330*(1-I330-M330) -> 0 | V330: =(F330-E330)*0.2 -> 0 | W330: =F330-(E330+V330)-(F330*S330)-(F330*R330) -> 0 | Z330: =IFERROR(W330/F330,"")
L331: 0.001397 | T331: =F331-E331 -> 0 | U331: =T331*(1-I331-M331) -> 0 | V331: =(F331-E331)*0.2 -> 0 | W331: =F331-(E331+V331)-(F331*S331)-(F331*R331) -> 0 | Z331: =IFERROR(W331/F331,"")
L332: 0.001397 | T332: =F332-E332 -> 0 | U332: =T332*(1-I332-M332) -> 0 | V332: =(F332-E332)*0.2 -> 0 | W332: =F332-(E332+V332)-(F332*S332)-(F332*R332) -> 0 | Z332: =IFERROR(W332/F332,"")
...

Sheet Controle- Vendas e Comissões
A1: Data da Venda | B1: Data da Viagem | C1: Mês da Viagem | D1: Código da Cotação | E1: Cliente | F1: total entrada | G1: CUSTO (COP) | H1: TET (COP) | I1: Cotação COP | J1: IOF | K1: Valor após IOF | L1: Valor de IOF Bruto | M1: Spread | N1: Cotação Real | O1: Valor SPREAD BRUTO | P1: Custo Convertido (US) | Q1: TET (BRL) | R1: CUSTO (BRL) | S1: Devolução | T1: Simples Nacional (%) | U1: Outros custos diretos (%) | V1: Antes de comision | W1: Desconto | X1: Lucro Bruto | Y1: Cupom Afiliado | Z1: Comissão Afiliado | AA1: Lucro pós-comissão | AB1: Comissão Jadhe? | AC1: Comissão (R$) | AD1: Lucro Liquido | AE1: obs | AF1: Status | AG1: Nota Fiscal | AH1: Imposto
A2: 45937 | B2: 45937 | C2: =TEXT(B2,"mmm") -> out. | E2: Heloísa Delgado | G2: 500000 | H2: 700000 | I2: 0.0014045 | J2: 0.035 | K2: =R2*(1-J2) -> 716.46962 | L2: =R2-K2 -> 25.985945 | M2: 0.0215 | N2: =I2*(1+M2) -> 0.0014346968 | O2: =(K2*M2)+15 -> 30.404097 | P2: =(K2*N2)+M21 -> 1.0494166 | Q2: 351 | R2: =(G2*N2)*(1+J2) -> 742.45557 | T2: 0.06 | X2: =Q2-R2-S2-W2 -> -391.45557 | Y2: Sim | Z2: =IF(Y2="Sim",(X2)*0.1,"") -> -39.145557 | AA2: =IF(Y2="Sim",X2-Z2,X2) -> -352.31001 | AB2: Sim | AC2: =IF(AB2="Sim",AA2*0.2,"") -> -70.462002 | AD2: =IF(AB2="Sim",AA2-AC2,AA2) -> -281.84801 | AF2: OK | AG2: TRUE | AH2: =IF(AG2="VERDADEIRO",Q2*0.06,"") | AI2: Comissão Por Mês
A3: 45912 | B3: 45938 | C3: =TEXT(B3,"mmm") -> out. | E3: Ana Oliveira | I3: 0.0014045 | J3: 0.035 | K3: =R3*(1-J3) -> 579 | L3: =R3-K3 -> 21 | M3: 0.0215 | N3: =I3*(1+M3) -> 0.0014346968 | O3: =(K3*M3)+15 -> 27.4485 | P3: =(K3*N3)+M22 -> 0.85218942 | Q3: 1000 | R3: 600 | T3: =IF(Z3="Sim",(S3-W3)*0.1,"") | U3: =IF(AD3="Sim",(W3-T3)*0.1,"") | V3: =IF(AE3="Sim",(T3-U3)*0.1,"") | X3: =Q3-R3-S3-W3 -> 400 | Y3: Sim | Z3: =IF(Y3="Sim",(X3)*0.1,"") -> 40 | AA3: =IF(Y3="Sim",X3-Z3,X3) -> 360 | AB3: Sim | AC3: =IF(AB3="Sim",AA3*0.2,"") -> 72 | AD3: =IF(AB3="Sim",AA3-AC3,AA3) -> 288 | AF3: OK | AG3: FALSE | AI3: out. | AJ3: =SUMIFS($AC$2:$AC$962,$AB$2:$AB$962,"Sim",$C$2:$C$962,AI3) -> 3296.24 | AL3: Legenda
A4: 45942 | B4: 45939 | C4: =TEXT(B4,"mmm") -> out. | E4: Marcus Estrela | I4: 0.0014045 | J4: 0.035 | K4: =R4*(1-J4) -> 0 | L4: =R4-K4 -> 0 | M4: 0.0215 | N4: =I4*(1+M4) -> 0.0014346968 | O4: =(K4*M4)+15 -> 15 | P4: =(K4*N4)+M23 -> 0.0215 | Q4: 193.83 | R4: =(G4*N4)*(1+J4) -> 0 | T4: 0.06 | X4: =Q4-R4-S4-W4 -> 193.83 | Z4: =IF(Y4="Sim",(X4)*0.1,"") | AA4: =IF(Y4="Sim",X4-Z4,X4) -> 193.83 | AB4: Sim | AC4: =IF(AB4="Sim",AA4*0.2,"") -> 38.766 | AD4: =IF(AB4="Sim",AA4-AC4,AA4) -> 155.064 | AF4: OK | AG4: FALSE | AI4: nov. | AJ4: =SUMIFS($AC$2:$AC$962,$AB$2:$AB$962,"Sim",$C$2:$C$962,AI4) -> 8139.308 | AM4: Fechado
A5: 45934 | B5: 45941 | C5: =TEXT(B5,"mmm") -> out. | E5: Fabiana Castro | I5: 0.0014045 | J5: 0.035 | K5: =R5*(1-J5) -> 557.7507 | L5: =R5-K5 -> 20.2293 | M5: 0.0215 | N5: =I5*(1+M5) -> 0.0014346968 | O5: =(K5*M5)+15 -> 26.99164 | P5: =(K5*N5)+M24 -> 0.82170312 | Q5: 1117.23 | R5: 577.98 | T5: 0.06 | X5: =Q5-R5-S5-W5 -> 539.25 | Z5: =IF(Y5="Sim",(X5)*0.1,"") | AA5: =IF(Y5="Sim",X5-Z5,X5) -> 539.25 | AB5: Sim | AC5: =IF(AB5="Sim",AA5*0.2,"") -> 107.85 | AD5: =IF(AB5="Sim",AA5-AC5,AA5) -> 431.4 | AF5: OK | AG5: FALSE | AI5: dez. | AJ5: =SUMIFS($AC$2:$AC$962,$AB$2:$AB$962,"Sim",$C$2:$C$962,AI5) -> 18195.394 | AM5: Abater NETO
A6: 45932 | B6: 45941 | C6: =TEXT(B6,"mmm") -> out. | E6: Matheus Heck | I6: 0.0014045 | J6: 0.035 | K6: =R6*(1-J6) -> 0 | L6: =R6-K6 -> 0 | M6: 0.0215 | N6: =I6*(1+M6) -> 0.0014346968 | O6: =(K6*M6)+15 -> 15 | P6: =(K6*N6)+M25 -> 0.0215 | Q6: 911.05 | R6: =(G6*N6)*(1+J6) -> 0 | T6: 0.06 | X6: =Q6-R6-S6-W6 -> 911.05 | Z6: =IF(Y6="Sim",(X6)*0.1,"") | AA6: =IF(Y6="Sim",X6-Z6,X6) -> 911.05 | AB6: Sim | AC6: =IF(AB6="Sim",AA6*0.2,"") -> 182.21 | AD6: =IF(AB6="Sim",AA6-AC6,AA6) -> 728.84 | AF6: OK | AG6: FALSE | AI6: jan. | AJ6: =SUMIFS($AC$2:$AC$962,$AB$2:$AB$962,"Sim",$C$2:$C$962,AI6) -> 7298.8548 | AM6: PG tudo em COP
A7: 45933 | B7: 45944 | C7: =TEXT(B7,"mmm") -> out. | E7: Marina Nunes | I7: 0.0014045 | J7: 0.035 | K7: =R7*(1-J7) -> 714.9106 | L7: =R7-K7 -> 25.9294 | M7: 0.0215 | N7: =I7*(1+M7) -> 0.0014346968 | O7: =(K7*M7)+15 -> 30.370578 | P7: =(K7*N7)+M26 -> 1.0471799 | Q7: 3249 | R7: 740.84 | T7: 0.06 | X7: =Q7-R7-S7-W7 -> 2508.16 | Z7: =IF(Y7="Sim",(X7)*0.1,"") | AA7: =IF(Y7="Sim",X7-Z7,X7) -> 2508.16 | AB7: Sim | AC7: =IF(AB7="Sim",AA7*0.2,"") -> 501.632 | AD7: =IF(AB7="Sim",AA7-AC7,AA7) -> 2006.528 | AF7: OK | AG7: FALSE | AI7: fev. | AJ7: =SUMIFS($AC$2:$AC$962,$AB$2:$AB$962,"Sim",$C$2:$C$962,AI7) -> 9911.5534 | AM7: Vamos receber da GYG
A8: 45946 | B8: 45953 | C8: =TEXT(B8,"mmm") -> out. | E8: Magda Helena | I8: 0.0014045 | J8: 0.035 | K8: =R8*(1-J8) -> 0 | L8: =R8-K8 -> 0 | M8: 0.0215 | N8: =I8*(1+M8) -> 0.0014346968 | O8: =(K8*M8)+15 -> 15 | P8: =(K8*N8)+#REF! -> #REF! | Q8: 832.53 | R8: =(G8*N8)*(1+J8) -> 0 | T8: 0.06 | X8: =Q8-R8-S8-W8 -> 832.53 | Z8: =IF(Y8="Sim",(X8)*0.1,"") | AA8: =IF(Y8="Sim",X8-Z8,X8) -> 832.53 | AB8: Sim | AC8: =IF(AB8="Sim",AA8*0.2,"") -> 166.506 | AD8: =IF(AB8="Sim",AA8-AC8,AA8) -> 666.024 | AF8: OK | AG8: FALSE | AI8: mar. | AJ8: =SUMIFS($AC$2:$AC$962,$AB$2:$AB$962,"Sim",$C$2:$C$962,AI8) -> 3804.883 | AM8: Pax da Ju
A9: 45901 | B9: 45955 | C9: =TEXT(B9,"mmm") -> out. | E9: Caroline Sneider | I9: 0.0014045 | J9: 0.035 | K9: =R9*(1-J9) -> 0 | L9: =R9-K9 -> 0 | M9: 0.0215 | N9: =I9*(1+M9) -> 0.0014346968 | O9: =(K9*M9)+15 -> 15 | P9: =(K9*N9)+M27 -> 0.0215 | Q9: 431.26 | R9: 0 | T9: 0.06 | X9: =Q9-R9-S9-W9 -> 431.26 | Z9: =IF(Y9="Sim",(X9)*0.1,"") | AA9: =IF(Y9="Sim",X9-Z9,X9) -> 431.26 | AB9: Sim | AC9: =IF(AB9="Sim",AA9*0.2,"") -> 86.252 | AD9: =IF(AB9="Sim",AA9-AC9,AA9) -> 345.008 | AF9: OK | AG9: FALSE | AI9: abr. | AJ9: =SUMIFS($AC$2:$AC$962,$AB$2:$AB$962,"Sim",$C$2:$C$962,AI9) -> 153.8658 | AM9: Pago à Jadhe
A10: 45950 | B10: 45955 | C10: =TEXT(B10,"mmm") -> out. | E10: Delpho Sobrinho | I10: 0.0014045 | J10: 0.035 | K10: =R10*(1-J10) -> 0 | L10: =R10-K10 -> 0 | M10: 0.0215 | N10: =I10*(1+M10) -> 0.0014346968 | O10: =(K10*M10)+15 -> 15 | P10: =(K10*N10)+M28 -> 0.0215 | Q10: 914 | R10: =(G10*N10)*(1+J10) -> 0 | T10: 0.06 | X10: =Q10-R10-S10-W10 -> 914 | Z10: =IF(Y10="Sim",(X10)*0.1,"") | AA10: =IF(Y10="Sim",X10-Z10,X10) -> 914 | AB10: Sim | AC10: =IF(AB10="Sim",AA10*0.2,"") -> 182.8 | AD10: =IF(AB10="Sim",AA10-AC10,AA10) -> 731.2 | AF10: OK | AG10: FALSE | AI10: mai. | AJ10: =SUMIFS($AC$2:$AC$962,$AB$2:$AB$962,"Sim",$C$2:$C$962,AI10) -> 0 | AM10: Solicitar reserva
A11: 45950 | B11: 45955 | C11: =TEXT(B11,"mmm") -> out. | E11: Mauro Ferreira | I11: 0.0014045 | J11: 0.035 | K11: =R11*(1-J11) -> 0 | L11: =R11-K11 -> 0 | M11: 0.0215 | N11: =I11*(1+M11) -> 0.0014346968 | O11: =(K11*M11)+15 -> 15 | P11: =(K11*N11)+M29 -> 0.0215 | Q11: 441.3 | R11: =(G11*N11)*(1+J11) -> 0 | T11: 0.06 | X11: =Q11-R11-S11-W11 -> 441.3 | Z11: =IF(Y11="Sim",(X11)*0.1,"") | AA11: =IF(Y11="Sim",X11-Z11,X11) -> 441.3 | AB11: Sim | AC11: =IF(AB11="Sim",AA11*0.2,"") -> 88.26 | AD11: =IF(AB11="Sim",AA11-AC11,AA11) -> 353.04 | AF11: OK | AG11: FALSE | AI11: jun. | AJ11: =SUMIFS($AC$2:$AC$962,$AB$2:$AB$962,"Sim",$C$2:$C$962,AI11) -> 0 | AM11: Reserva enviada
A12: 45944 | B12: 45955 | C12: =TEXT(B12,"mmm") -> out. | E12: Sumaica Holanda | I12: 0.0014045 | J12: 0.035 | K12: =R12*(1-J12) -> 0 | L12: =R12-K12 -> 0 | M12: 0.0215 | N12: =I12*(1+M12) -> 0.0014346968 | O12: =(K12*M12)+15 -> 15 | P12: =(K12*N12)+#REF! -> #REF! | Q12: 766.89 | R12: =(G12*N12)*(1+J12) -> 0 | T12: 0.06 | X12: =Q12-R12-S12-W12 -> 766.89 | Z12: =IF(Y12="Sim",(X12)*0.1,"") | AA12: =IF(Y12="Sim",X12-Z12,X12) -> 766.89 | AB12: Sim | AC12: =IF(AB12="Sim",AA12*0.2,"") -> 153.378 | AD12: =IF(AB12="Sim",AA12-AC12,AA12) -> 613.512 | AF12: OK | AG12: FALSE
B13: 45956 | C13: =TEXT(B13,"mmm") -> out. | E13: Amanda Fagundes | I13: 0.0014045 | J13: 0.035 | K13: =R13*(1-J13) -> 10403.665 | L13: =R13-K13 -> 377.335 | M13: 0.0215 | N13: =I13*(1+M13) -> 0.0014346968 | O13: =(K13*M13)+15 -> 238.6788 | P13: =(K13*N13)+M30 -> 14.947604 | Q13: 16991 | R13: 10781 | T13: 0.06 | X13: =Q13-R13-S13-W13 -> 6210 | Z13: =IF(Y13="Sim",(X13)*0.1,"") | AA13: =IF(Y13="Sim",X13-Z13,X13) -> 6210 | AB13: Sim | AC13: =IF(AB13="Sim",AA13*0.2,"") -> 1242 | AD13: =IF(AB13="Sim",AA13-AC13,AA13) -> 4968 | AF13: OK | AG13: FALSE
A14: 45938 | B14: 45956 | C14: =TEXT(B14,"mmm") -> out. | E14: Danielle Sonego | I14: 0.0014045 | J14: 0.035 | K14: =R14*(1-J14) -> 712.7104 | L14: =R14-K14 -> 25.8496 | M14: 0.0215 | N14: =I14*(1+M14) -> 0.0014346968 | O14: =(K14*M14)+15 -> 30.323274 | P14: =(K14*N14)+M31 -> 1.0440233 | Q14: 2021.59 | R14: 738.56 | T14: 0.06 | X14: =Q14-R14-S14-W14 -> 1283.03 | Z14: =IF(Y14="Sim",(X14)*0.1,"") | AA14: =IF(Y14="Sim",X14-Z14,X14) -> 1283.03 | AB14: Sim | AC14: =IF(AB14="Sim",AA14*0.2,"") -> 256.606 | AD14: =IF(AB14="Sim",AA14-AC14,AA14) -> 1026.424 | AF14: OK | AG14: FALSE | AJ14: Empréstimo
A15: 45944 | B15: 45958 | C15: =TEXT(B15,"mmm") -> out. | E15: Liliana Coelho | I15: 0.0014045 | J15: 0.035 | K15: =R15*(1-J15) -> 0 | L15: =R15-K15 -> 0 | M15: 0.0215 | N15: =I15*(1+M15) -> 0.0014346968 | O15: =(K15*M15)+15 -> 15 | P15: =(K15*N15)+M32 -> 0.0215 | Q15: 1442.21 | R15: =(G15*N15)*(1+J15) -> 0 | T15: 0.06 | X15: =Q15-R15-S15-W15 -> 1442.21 | Z15: =IF(Y15="Sim",(X15)*0.1,"") | AA15: =IF(Y15="Sim",X15-Z15,X15) -> 1442.21 | AB15: Sim | AC15: =IF(AB15="Sim",AA15*0.2,"") -> 288.442 | AD15: =IF(AB15="Sim",AA15-AC15,AA15) -> 1153.768 | AF15: OK | AG15: FALSE | AJ15: Parcela 1 - R$1000 - Dezembro ✅ | AM15: jan
A16: 45963 | B16: 45964 | C16: =TEXT(B16,"mmm") -> nov. | E16: Michelle França | I16: 0.0014045 | J16: 0.035 | K16: =R16*(1-J16) -> 599.9212 | L16: =R16-K16 -> 21.7588 | M16: 0.0215 | N16: =I16*(1+M16) -> 0.0014346968 | O16: =(K16*M16)+15 -> 27.898306 | P16: =(K16*N16)+M33 -> 0.882205 | Q16: 2170.71 | R16: 621.68 | T16: 0.06 | X16: =Q16-R16-S16-W16 -> 1549.03 | Z16: =IF(Y16="Sim",(X16)*0.1,"") | AA16: =IF(Y16="Sim",X16-Z16,X16) -> 1549.03 | AB16: Sim | AC16: =IF(AB16="Sim",AA16*0.2,"") -> 309.806 | AD16: =IF(AB16="Sim",AA16-AC16,AA16) -> 1239.224 | AF16: OK | AG16: FALSE | AJ16: Parcela 2 - R$1000 - Janeiro ✅ | AM16: =AJ6 -> 7298.8548 | AN16: comissoes
A17: 45965 | B17: 45965 | C17: =TEXT(B17,"mmm") -> nov. | E17: Fabiana Soares | I17: 0.0014045 | J17: 0.035 | K17: =R17*(1-J17) -> 0 | L17: =R17-K17 -> 0 | M17: 0.0215 | N17: =I17*(1+M17) -> 0.0014346968 | O17: =(K17*M17)+15 -> 15 | P17: =(K17*N17)+M33 -> 0.0215 | Q17: 474.52 | R17: =(G17*N17)*(1+J17) -> 0 | T17: 0.06 | X17: =Q17-R17-S17-W17 -> 474.52 | Z17: =IF(Y17="Sim",(X17)*0.1,"") | AA17: =IF(Y17="Sim",X17-Z17,X17) -> 474.52 | AB17: Sim | AC17: =IF(AB17="Sim",AA17*0.2,"") -> 94.904 | AD17: =IF(AB17="Sim",AA17-AC17,AA17) -> 379.616 | AF17: OK | AG17: FALSE | AJ17: Parcela 3 - R$1000 - Fevereiro ✅ | AM17: 741.59 | AN17: extras
A18: 45937 | B18: 45966 | C18: =TEXT(B18,"mmm") -> nov. | E18: Luísa Moura | I18: 0.0014045 | J18: 0.035 | K18: =R18*(1-J18) -> 0 | L18: =R18-K18 -> 0 | M18: 0.0215 | N18: =I18*(1+M18) -> 0.0014346968 | O18: =(K18*M18)+15 -> 15 | P18: =(K18*N18)+M35 -> 0.0215 | Q18: 644.63 | R18: =(G18*N18)*(1+J18) -> 0 | T18: 0.06 | X18: =Q18-R18-S18-W18 -> 644.63 | Z18: =IF(Y18="Sim",(X18)*0.1,"") | AA18: =IF(Y18="Sim",X18-Z18,X18) -> 644.63 | AB18: Sim | AC18: =IF(AB18="Sim",AA18*0.2,"") -> 128.926 | AD18: =IF(AB18="Sim",AA18-AC18,AA18) -> 515.704 | AF18: OK | AG18: FALSE | AJ18: Parcela 4 - R$1000 - Março | AM18: 2000 | AN18: ajuda custo
A19: 45954 | B19: 45968 | C19: =TEXT(B19,"mmm") -> nov. | E19: Lohran Moraes | I19: 0.0014045 | J19: 0.035 | K19: =R19*(1-J19) -> 0 | L19: =R19-K19 -> 0 | M19: 0.0215 | N19: =I19*(1+M19) -> 0.0014346968 | O19: =(K19*M19)+15 -> 15 | P19: =(K19*N19)+M35 -> 0.0215 | Q19: 875.19 | R19: =(G19*N19)*(1+J19) -> 0 | T19: 0.06 | X19: =Q19-R19-S19-W19 -> 875.19 | Z19: =IF(Y19="Sim",(X19)*0.1,"") | AA19: =IF(Y19="Sim",X19-Z19,X19) -> 875.19 | AB19: Sim | AC19: =IF(AB19="Sim",AA19*0.2,"") -> 175.038 | AD19: =IF(AB19="Sim",AA19-AC19,AA19) -> 700.152 | AF19: OK | AG19: FALSE | AJ19: Parcela 5 - R$1000 - Abril | AM19: =SUM(AM16:AM18) -> 10040.445
A20: 45943 | B20: 45969 | C20: =TEXT(B20,"mmm") -> nov. | E20: Letícia Venâncio | I20: 0.0014045 | J20: 0.035 | K20: =R20*(1-J20) -> 574.2908 | L20: =R20-K20 -> 20.8292 | M20: 0.0215 | N20: =I20*(1+M20) -> 0.0014346968 | O20: =(K20*M20)+15 -> 27.347252 | P20: =(K20*N20)+M37 -> 0.84543314 | Q20: 1059.22 | R20: 595.12 | T20: 0.06 | X20: =Q20-R20-S20-W20 -> 464.1 | Z20: =IF(Y20="Sim",(X20)*0.1,"") | AA20: =IF(Y20="Sim",X20-Z20,X20) -> 464.1 | AB20: Sim | AC20: =IF(AB20="Sim",AA20*0.2,"") -> 92.82 | AD20: =IF(AB20="Sim",AA20-AC20,AA20) -> 371.28 | AF20: OK | AG20: FALSE | AM20: =AM19-1000 -> 9040.4448 | AN20: parcela fev
B21: 45969 | C21: =TEXT(B21,"mmm") -> nov. | E21: Lorena Costa | I21: 0.0014045 | J21: 0.035 | K21: =R21*(1-J21) -> 0 | L21: =R21-K21 -> 0 | M21: 0.0215 | N21: =I21*(1+M21) -> 0.0014346968 | O21: =(K21*M21)+15 -> 15 | P21: =(K21*N21)+M37 -> 0.0215 | Q21: 649.66 | R21: =(G21*N21)*(1+J21) -> 0 | T21: 0.06 | X21: =Q21-R21-S21-W21 -> 649.66 | Z21: =IF(Y21="Sim",(X21)*0.1,"") | AA21: =IF(Y21="Sim",X21-Z21,X21) -> 649.66 | AB21: Sim | AC21: =IF(AB21="Sim",AA21*0.2,"") -> 129.932 | AD21: =IF(AB21="Sim",AA21-AC21,AA21) -> 519.728 | AF21: OK | AG21: FALSE | AM21: =AM20-3000 -> 6040.4448 | AN21: enviar
A22: 45968 | B22: 45972 | C22: =TEXT(B22,"mmm") -> nov. | E22: Igor Faria | I22: 0.0014045 | J22: 0.035 | K22: =R22*(1-J22) -> 0 | L22: =R22-K22 -> 0 | M22: 0.0215 | N22: =I22*(1+M22) -> 0.0014346968 | O22: =(K22*M22)+15 -> 15 | P22: =(K22*N22)+M38 -> 0.0215 | Q22: 299.5 | R22: =(G22*N22)*(1+J22) -> 0 | T22: 0.06 | X22: =Q22-R22-S22-W22 -> 299.5 | Z22: =IF(Y22="Sim",(X22)*0.1,"") | AA22: =IF(Y22="Sim",X22-Z22,X22) -> 299.5 | AB22: Sim | AC22: =IF(AB22="Sim",AA22*0.2,"") -> 59.9 | AD22: =IF(AB22="Sim",AA22-AC22,AA22) -> 239.6 | AF22: OK | AG22: FALSE
A23: 45973 | B23: 45973 | C23: =TEXT(B23,"mmm") -> nov. | E23: Bruna Linshalm | I23: 0.0014045 | J23: 0.035 | K23: =R23*(1-J23) -> 0 | L23: =R23-K23 -> 0 | M23: 0.0215 | N23: =I23*(1+M23) -> 0.0014346968 | O23: =(K23*M23)+15 -> 15 | P23: =(K23*N23)+M39 -> 0.0215 | Q23: 563.04 | R23: =(G23*N23)*(1+J23) -> 0 | T23: 0.06 | X23: =Q23-R23-S23-W23 -> 563.04 | Z23: =IF(Y23="Sim",(X23)*0.1,"") | AA23: =IF(Y23="Sim",X23-Z23,X23) -> 563.04 | AB23: Sim | AC23: =IF(AB23="Sim",AA23*0.2,"") -> 112.608 | AD23: =IF(AB23="Sim",AA23-AC23,AA23) -> 450.432 | AF23: OK | AG23: FALSE
A24: 45943 | B24: 45973 | C24: =TEXT(B24,"mmm") -> nov. | E24: Valdineia Santos | I24: 0.0014045 | J24: 0.035 | K24: =R24*(1-J24) -> 0 | L24: =R24-K24 -> 0 | M24: 0.0215 | N24: =I24*(1+M24) -> 0.0014346968 | O24: =(K24*M24)+15 -> 15 | P24: =(K24*N24)+M41 -> 0.0215 | Q24: 1131.43 | R24: =(G24*N24)*(1+J24) -> 0 | T24: 0.06 | X24: =Q24-R24-S24-W24 -> 1131.43 | Z24: =IF(Y24="Sim",(X24)*0.1,"") | AA24: =IF(Y24="Sim",X24-Z24,X24) -> 1131.43 | AB24: Sim | AC24: =IF(AB24="Sim",AA24*0.2,"") -> 226.286 | AD24: =IF(AB24="Sim",AA24-AC24,AA24) -> 905.144 | AF24: OK | AG24: FALSE
A25: 45952 | B25: 45974 | C25: =TEXT(B25,"mmm") -> nov. | E25: Erika Lima | I25: 0.0014045 | J25: 0.035 | K25: =R25*(1-J25) -> 0 | L25: =R25-K25 -> 0 | M25: 0.0215 | N25: =I25*(1+M25) -> 0.0014346968 | O25: =(K25*M25)+15 -> 15 | P25: =(K25*N25)+M41 -> 0.0215 | Q25: 1758.62 | R25: =(G25*N25)*(1+J25) -> 0 | T25: 0.06 | X25: =Q25-R25-S25-W25 -> 1758.62 | Z25: =IF(Y25="Sim",(X25)*0.1,"") | AA25: =IF(Y25="Sim",X25-Z25,X25) -> 1758.62 | AB25: Sim | AC25: =IF(AB25="Sim",AA25*0.2,"") -> 351.724 | AD25: =IF(AB25="Sim",AA25-AC25,AA25) -> 1406.896 | AF25: OK | AG25: FALSE
A26: 45964 | B26: 45974 | C26: =TEXT(B26,"mmm") -> nov. | E26: Felipe Barbeta | I26: 0.0014045 | J26: 0.035 | K26: =R26*(1-J26) -> 0 | L26: =R26-K26 -> 0 | M26: 0.0215 | N26: =I26*(1+M26) -> 0.0014346968 | O26: =(K26*M26)+15 -> 15 | P26: =(K26*N26)+M42 -> 0.0215 | Q26: 854.94 | R26: =(G26*N26)*(1+J26) -> 0 | T26: 0.06 | X26: =Q26-R26-S26-W26 -> 854.94 | Z26: =IF(Y26="Sim",(X26)*0.1,"") | AA26: =IF(Y26="Sim",X26-Z26,X26) -> 854.94 | AB26: Sim | AC26: =IF(AB26="Sim",AA26*0.2,"") -> 170.988 | AD26: =IF(AB26="Sim",AA26-AC26,AA26) -> 683.952 | AF26: OK | AG26: FALSE
A27: 45910 | B27: 45975 | C27: =TEXT(B27,"mmm") -> nov. | E27: Danilo Santos | I27: 0.0014045 | J27: 0.035 | K27: =R27*(1-J27) -> 0 | L27: =R27-K27 -> 0 | M27: 0.0215 | N27: =I27*(1+M27) -> 0.0014346968 | O27: =(K27*M27)+15 -> 15 | P27: =(K27*N27)+M45 -> 0.0215 | Q27: 321.1 | R27: =(G27*N27)*(1+J27) -> 0 | T27: 0.06 | X27: =Q27-R27-S27-W27 -> 321.1 | Z27: =IF(Y27="Sim",(X27)*0.1,"") | AA27: =IF(Y27="Sim",X27-Z27,X27) -> 321.1 | AB27: Sim | AC27: =IF(AB27="Sim",AA27*0.2,"") -> 64.22 | AD27: =IF(AB27="Sim",AA27-AC27,AA27) -> 256.88 | AF27: OK | AG27: FALSE
A28: 45974 | B28: 45975 | C28: =TEXT(B28,"mmm") -> nov. | E28: Pedro Marcondes | I28: 0.0014045 | J28: 0.035 | K28: =R28*(1-J28) -> 1009.0716 | L28: =R28-K28 -> 36.59845 | M28: 0.0215 | N28: =I28*(1+M28) -> 0.0014346968 | O28: =(K28*M28)+15 -> 36.695038 | P28: =(K28*N28)+M45 -> 1.4692117 | Q28: 1468.61 | R28: 1045.67 | T28: 0.06 | X28: =Q28-R28-S28-W28 -> 422.94 | Z28: =IF(Y28="Sim",(X28)*0.1,"") | AA28: =IF(Y28="Sim",X28-Z28,X28) -> 422.94 | AB28: Sim | AC28: =IF(AB28="Sim",AA28*0.2,"") -> 84.588 | AD28: =IF(AB28="Sim",AA28-AC28,AA28) -> 338.352 | AF28: OK | AG28: FALSE
A29: 45946 | B29: 45976 | C29: =TEXT(B29,"mmm") -> nov. | E29: Natália Marinelli | I29: 0.0014045 | J29: 0.035 | K29: =R29*(1-J29) -> 0 | L29: =R29-K29 -> 0 | M29: 0.0215 | N29: =I29*(1+M29) -> 0.0014346968 | O29: =(K29*M29)+15 -> 15 | P29: =(K29*N29)+M47 -> 0.0215 | Q29: 952.46 | R29: =(G29*N29)*(1+J29) -> 0 | T29: 0.06 | X29: =Q29-R29-S29-W29 -> 952.46 | Z29: =IF(Y29="Sim",(X29)*0.1,"") | AA29: =IF(Y29="Sim",X29-Z29,X29) -> 952.46 | AB29: Sim | AC29: =IF(AB29="Sim",AA29*0.2,"") -> 190.492 | AD29: =IF(AB29="Sim",AA29-AC29,AA29) -> 761.968 | AF29: OK | AG29: FALSE
A30: 45944 | B30: 45977 | C30: =TEXT(B30,"mmm") -> nov. | E30: Akemi Kimura | I30: 0.0014045 | J30: 0.035 | K30: =R30*(1-J30) -> 84.92 | L30: =R30-K30 -> 3.08 | M30: 0.0215 | N30: =I30*(1+M30) -> 0.0014346968 | O30: =(K30*M30)+15 -> 16.82578 | P30: =(K30*N30)+M48 -> 0.14333445 | Q30: =2166 -> 2166 | R30: 88 | T30: 0.06 | X30: =Q30-R30-S30-W30 -> 2078 | Z30: =IF(Y30="Sim",(X30)*0.1,"") | AA30: =IF(Y30="Sim",X30-Z30,X30) -> 2078 | AB30: Sim | AC30: =IF(AB30="Sim",AA30*0.2,"") -> 415.6 | AD30: =IF(AB30="Sim",AA30-AC30,AA30) -> 1662.4 | AF30: OK | AG30: FALSE
A31: 45943 | B31: 45977 | C31: =TEXT(B31,"mmm") -> nov. | E31: Elson Silva | I31: 0.0014045 | J31: 0.035 | K31: =R31*(1-J31) -> 4631.2184 | L31: =R31-K31 -> 167.97165 | M31: 0.0215 | N31: =I31*(1+M31) -> 0.0014346968 | O31: =(K31*M31)+15 -> 114.57119 | P31: =(K31*N31)+M50 -> 6.6658939 | Q31: =3400+2945.08 -> 6345.08 | R31: =2185.34+1933.85+680 -> 4799.19 | T31: 0.06 | X31: =Q31-R31-S31-W31 -> 1545.89 | Z31: =IF(Y31="Sim",(X31)*0.1,"") | AA31: =IF(Y31="Sim",X31-Z31,X31) -> 1545.89 | AB31: Sim | AC31: =IF(AB31="Sim",AA31*0.2,"") -> 309.178 | AD31: =IF(AB31="Sim",AA31-AC31,AA31) -> 1236.712 | AF31: OK | AG31: FALSE
A32: 45954 | B32: 45977 | C32: =TEXT(B32,"mmm") -> nov. | E32: Flávia Ribeiro GYG | I32: 0.0014045 | J32: 0.035 | K32: =R32*(1-J32) -> 760.1884 | L32: =R32-K32 -> 27.5716 | M32: 0.0215 | N32: =I32*(1+M32) -> 0.0014346968 | O32: =(K32*M32)+15 -> 31.344051 | P32: =(K32*N32)+M51 -> 1.1121398 | Q32: 1153.6 | R32: 787.76 | T32: 0.06 | X32: =Q32-R32-S32-W32 -> 365.84 | Z32: =IF(Y32="Sim",(X32)*0.1,"") | AA32: =IF(Y32="Sim",X32-Z32,X32) -> 365.84 | AB32: Sim | AC32: =IF(AB32="Sim",AA32*0.2,"") -> 73.168 | AD32: =IF(AB32="Sim",AA32-AC32,AA32) -> 292.672 | AF32: OK | AG32: FALSE
A33: 45976 | B33: 45977 | C33: =TEXT(B33,"mmm") -> nov. | E33: Leonardo Martins | I33: 0.0014045 | J33: 0.035 | K33: =R33*(1-J33) -> 0 | L33: =R33-K33 -> 0 | M33: 0.0215 | N33: =I33*(1+M33) -> 0.0014346968 | O33: =(K33*M33)+15 -> 15 | P33: =(K33*N33)+M53 -> 0.0215 | Q33: 478.04 | R33: =(G33*N33)*(1+J33) -> 0 | T33: 0.06 | X33: =Q33-R33-S33-W33 -> 478.04 | Z33: =IF(Y33="Sim",(X33)*0.1,"") | AA33: =IF(Y33="Sim",X33-Z33,X33) -> 478.04 | AB33: Sim | AC33: =IF(AB33="Sim",AA33*0.2,"") -> 95.608 | AD33: =IF(AB33="Sim",AA33-AC33,AA33) -> 382.432 | AF33: OK | AG33: FALSE
A34: 45840 | B34: 45977 | C34: =TEXT(B34,"mmm") -> nov. | E34: Ronaldo Lopes | I34: 0.0014045 | Q34: 2267 | R34: 0 | T34: 0.06 | X34: =Q34-R34-S34-W34 -> 2267 | Z34: =IF(Y34="Sim",(X34)*0.1,"") | AA34: =IF(Y34="Sim",X34-Z34,X34) -> 2267 | AB34: Sim | AC34: =IF(AB34="Sim",AA34*0.2,"") -> 453.4 | AD34: =IF(AB34="Sim",AA34-AC34,AA34) -> 1813.6 | AF34: OK | AG34: FALSE
A35: 45946 | B35: 45978 | C35: =TEXT(B35,"mmm") -> nov. | E35: Giulia Morais | I35: 0.0014045 | J35: 0.035 | K35: =R35*(1-J35) -> 5043.8234 | L35: =R35-K35 -> 182.9366 | M35: 0.0215 | N35: =I35*(1+M35) -> 0.0014346968 | O35: =(K35*M35)+15 -> 123.4422 | P35: =(K35*N35)+M54 -> 7.257857 | Q35: 7351.15 | R35: 5226.76 | T35: 0.06 | X35: =Q35-R35-S35-W35 -> 2124.39 | Z35: =IF(Y35="Sim",(X35)*0.1,"") | AA35: =IF(Y35="Sim",X35-Z35,X35) -> 2124.39 | AB35: Sim | AC35: =IF(AB35="Sim",AA35*0.2,"") -> 424.878 | AD35: =IF(AB35="Sim",AA35-AC35,AA35) -> 1699.512 | AF35: OK | AG35: FALSE
A36: 45944 | B36: 45978 | C36: =TEXT(B36,"mmm") -> nov. | E36: Vivian Carvalho | I36: 0.0014045 | J36: 0.035 | K36: =R36*(1-J36) -> 0 | L36: =R36-K36 -> 0 | M36: 0.0215 | N36: =I36*(1+M36) -> 0.0014346968 | O36: =(K36*M36)+15 -> 15 | P36: =(K36*N36)+M55 -> 0.0215 | Q36: 180.92 | R36: =(G36*N36)*(1+J36) -> 0 | T36: 0.06 | X36: =Q36-R36-S36-W36 -> 180.92 | Z36: =IF(Y36="Sim",(X36)*0.1,"") | AA36: =IF(Y36="Sim",X36-Z36,X36) -> 180.92 | AB36: Sim | AC36: =IF(AB36="Sim",AA36*0.2,"") -> 36.184 | AD36: =IF(AB36="Sim",AA36-AC36,AA36) -> 144.736 | AF36: OK | AG36: FALSE
A37: 45973 | B37: 45980 | C37: =TEXT(B37,"mmm") -> nov. | E37: Ana Weber | I37: 0.0014045 | J37: 0.035 | K37: =R37*(1-J37) -> 0 | L37: =R37-K37 -> 0 | M37: 0.0215 | N37: =I37*(1+M37) -> 0.0014346968 | O37: =(K37*M37)+15 -> 15 | P37: =(K37*N37)+M56 -> 0.0215 | Q37: 1665 | R37: =(G37*N37)*(1+J37) -> 0 | T37: 0.06 | X37: =Q37-R37-S37-W37 -> 1665 | Z37: =IF(Y37="Sim",(X37)*0.1,"") | AA37: =IF(Y37="Sim",X37-Z37,X37) -> 1665 | AB37: Sim | AC37: =IF(AB37="Sim",AA37*0.2,"") -> 333 | AD37: =IF(AB37="Sim",AA37-AC37,AA37) -> 1332 | AF37: OK | AG37: FALSE
A38: 45971 | B38: 45980 | C38: =TEXT(B38,"mmm") -> nov. | E38: Fernanda Lago | I38: 0.0014045 | J38: 0.035 | K38: =R38*(1-J38) -> 0 | L38: =R38-K38 -> 0 | M38: 0.0215 | N38: =I38*(1+M38) -> 0.0014346968 | O38: =(K38*M38)+15 -> 15 | P38: =(K38*N38)+M57 -> 0.0215 | Q38: 479.44 | R38: =(G38*N38)*(1+J38) -> 0 | T38: 0.06 | X38: =Q38-R38-S38-W38 -> 479.44 | Z38: =IF(Y38="Sim",(X38)*0.1,"") | AA38: =IF(Y38="Sim",X38-Z38,X38) -> 479.44 | AB38: Sim | AC38: =IF(AB38="Sim",AA38*0.2,"") -> 95.888 | AD38: =IF(AB38="Sim",AA38-AC38,AA38) -> 383.552 | AF38: OK | AG38: FALSE
A39: 45946 | B39: 45980 | C39: =TEXT(B39,"mmm") -> nov. | E39: Valquíria Rodrigues | I39: 0.0014045 | J39: 0.035 | K39: =R39*(1-J39) -> 0 | L39: =R39-K39 -> 0 | M39: 0.0215 | N39: =I39*(1+M39) -> 0.0014346968 | O39: =(K39*M39)+15 -> 15 | P39: =(K39*N39)+M58 -> 0.0215 | Q39: 474.7 | R39: =(G39*N39)*(1+J39) -> 0 | T39: 0.06 | X39: =Q39-R39-S39-W39 -> 474.7 | Z39: =IF(Y39="Sim",(X39)*0.1,"") | AA39: =IF(Y39="Sim",X39-Z39,X39) -> 474.7 | AB39: Sim | AC39: =IF(AB39="Sim",AA39*0.2,"") -> 94.94 | AD39: =IF(AB39="Sim",AA39-AC39,AA39) -> 379.76 | AF39: OK | AG39: FALSE
A40: 45974 | B40: 45981 | C40: =TEXT(B40,"mmm") -> nov. | E40: Angélica Bezerra | I40: 0.0014045 | J40: 0.035 | K40: =R40*(1-J40) -> 160.962 | L40: =R40-K40 -> 5.838 | M40: 0.0215 | N40: =I40*(1+M40) -> 0.0014346968 | O40: =(K40*M40)+15 -> 18.460683 | P40: =(K40*N40)+M60 -> 0.25243166 | Q40: 2345.82 | R40: 166.8 | T40: 0.06 | X40: =Q40-R40-S40-W40 -> 2179.02 | Z40: =IF(Y40="Sim",(X40)*0.1,"") | AA40: =IF(Y40="Sim",X40-Z40,X40) -> 2179.02 | AB40: Sim | AC40: =IF(AB40="Sim",AA40*0.2,"") -> 435.804 | AD40: =IF(AB40="Sim",AA40-AC40,AA40) -> 1743.216 | AF40: OK | AG40: FALSE
A41: 45943 | B41: 45981 | C41: =TEXT(B41,"mmm") -> nov. | E41: Thamires Ferreira | I41: 0.0014045 | J41: 0.035 | K41: =R41*(1-J41) -> 0 | L41: =R41-K41 -> 0 | M41: 0.0215 | N41: =I41*(1+M41) -> 0.0014346968 | O41: =(K41*M41)+15 -> 15 | P41: =(K41*N41)+#REF! -> #REF! | Q41: 729 | R41: =(G41*N41)*(1+J41) -> 0 | T41: 0.06 | X41: =Q41-R41-S41-W41 -> 729 | Z41: =IF(Y41="Sim",(X41)*0.1,"") | AA41: =IF(Y41="Sim",X41-Z41,X41) -> 729 | AB41: Sim | AC41: =IF(AB41="Sim",AA41*0.2,"") -> 145.8 | AD41: =IF(AB41="Sim",AA41-AC41,AA41) -> 583.2 | AF41: OK | AG41: FALSE
A42: 45982 | B42: 45982 | C42: =TEXT(B42,"mmm") -> nov. | E42: Valquiria Rodrigues Paue | I42: 0.0014045 | J42: 0.035 | K42: =R42*(1-J42) -> 946.5878 | L42: =R42-K42 -> 34.3322 | M42: 0.0215 | N42: =I42*(1+M42) -> 0.0014346968 | O42: =(K42*M42)+15 -> 35.351638 | P42: =(K42*N42)+M62 -> 1.3795664 | Q42: 1475 | R42: 980.92 | T42: 0.06 | X42: =Q42-R42-S42-W42 -> 494.08 | Z42: =IF(Y42="Sim",(X42)*0.1,"") | AA42: =IF(Y42="Sim",X42-Z42,X42) -> 494.08 | AB42: Sim | AC42: =IF(AB42="Sim",AA42*0.2,"") -> 98.816 | AD42: =IF(AB42="Sim",AA42-AC42,AA42) -> 395.264 | AF42: OK | AG42: FALSE
A43: 45972 | B43: 45983 | C43: =TEXT(B43,"mmm") -> nov. | E43: Gisele Rodrigues | I43: 0.0014045 | J43: 0.035 | K43: =R43*(1-J43) -> 0 | L43: =R43-K43 -> 0 | M43: 0.0215 | N43: =I43*(1+M43) -> 0.0014346968 | O43: =(K43*M43)+15 -> 15 | P43: =(K43*N43)+M62 -> 0.0215 | Q43: 1066.82 | R43: =(G43*N43)*(1+J43) -> 0 | T43: 0.06 | X43: =Q43-R43-S43-W43 -> 1066.82 | Z43: =IF(Y43="Sim",(X43)*0.1,"") | AA43: =IF(Y43="Sim",X43-Z43,X43) -> 1066.82 | AB43: Sim | AC43: =IF(AB43="Sim",AA43*0.2,"") -> 213.364 | AD43: =IF(AB43="Sim",AA43-AC43,AA43) -> 853.456 | AF43: OK | AG43: FALSE
A44: 45902 | B44: 45984 | C44: =TEXT(B44,"mmm") -> nov. | E44: Giovana Lopes | I44: 0.0014045 | J44: 0.035 | K44: =R44*(1-J44) -> 0 | L44: =R44-K44 -> 0 | M44: 0.0215 | N44: =I44*(1+M44) -> 0.0014346968 | O44: =(K44*M44)+15 -> 15 | P44: =(K44*N44)+M64 -> 0.0215 | Q44: 1168.48 | R44: =(G44*N44)*(1+J44) -> 0 | T44: 0.06 | X44: =Q44-R44-S44-W44 -> 1168.48 | Z44: =IF(Y44="Sim",(X44)*0.1,"") | AA44: =IF(Y44="Sim",X44-Z44,X44) -> 1168.48 | AB44: Sim | AC44: =IF(AB44="Sim",AA44*0.2,"") -> 233.696 | AD44: =IF(AB44="Sim",AA44-AC44,AA44) -> 934.784 | AF44: OK | AG44: FALSE
A45: 45975 | B45: 45984 | C45: =TEXT(B45,"mmm") -> nov. | E45: Maurício Pereira | I45: 0.0014045 | J45: 0.035 | K45: =R45*(1-J45) -> 0 | L45: =R45-K45 -> 0 | M45: 0.0215 | N45: =I45*(1+M45) -> 0.0014346968 | O45: =(K45*M45)+15 -> 15 | P45: =(K45*N45)+M64 -> 0.0215 | Q45: 5895.57 | R45: =(G45*N45)*(1+J45) -> 0 | T45: 0.06 | X45: =Q45-R45-S45-W45 -> 5895.57 | Z45: =IF(Y45="Sim",(X45)*0.1,"") | AA45: =IF(Y45="Sim",X45-Z45,X45) -> 5895.57 | AB45: Sim | AC45: =IF(AB45="Sim",AA45*0.2,"") -> 1179.114 | AD45: =IF(AB45="Sim",AA45-AC45,AA45) -> 4716.456 | AF45: OK | AG45: FALSE
A46: 45889 | B46: 45984 | C46: =TEXT(B46,"mmm") -> nov. | E46: Mayara Urbano | I46: 0.0014045 | J46: 0.035 | K46: =R46*(1-J46) -> 0 | L46: =R46-K46 -> 0 | M46: 0.0215 | N46: =I46*(1+M46) -> 0.0014346968 | O46: =(K46*M46)+15 -> 15 | P46: =(K46*N46)+M66 -> 0.0215 | Q46: 658 | R46: =(G46*N46)*(1+J46) -> 0 | T46: 0.06 | X46: =Q46-R46-S46-W46 -> 658 | Z46: =IF(Y46="Sim",(X46)*0.1,"") | AA46: =IF(Y46="Sim",X46-Z46,X46) -> 658 | AB46: Sim | AC46: =IF(AB46="Sim",AA46*0.2,"") -> 131.6 | AD46: =IF(AB46="Sim",AA46-AC46,AA46) -> 526.4 | AF46: OK | AG46: FALSE
A47: 45988 | B47: 45985 | C47: =TEXT(B47,"mmm") -> nov. | E47: Ana Latto | I47: 0.0014045 | J47: 0.035 | K47: =R47*(1-J47) -> 0 | L47: =R47-K47 -> 0 | M47: 0.0215 | N47: =I47*(1+M47) -> 0.0014346968 | O47: =(K47*M47)+15 -> 15 | P47: =(K47*N47)+M67 -> 0.0215 | Q47: 485.05 | R47: =(G47*N47)*(1+J47) -> 0 | T47: 0.06 | X47: =Q47-R47-S47-W47 -> 485.05 | Z47: =IF(Y47="Sim",(X47)*0.1,"") | AA47: =IF(Y47="Sim",X47-Z47,X47) -> 485.05 | AB47: Sim | AC47: =IF(AB47="Sim",AA47*0.2,"") -> 97.01 | AD47: =IF(AB47="Sim",AA47-AC47,AA47) -> 388.04 | AF47: OK | AG47: FALSE
A48: 45945 | B48: 45985 | C48: =TEXT(B48,"mmm") -> nov. | E48: Homero Michelli | I48: 0.0014045 | J48: 0.035 | K48: =R48*(1-J48) -> 0 | L48: =R48-K48 -> 0 | M48: 0.0215 | N48: =I48*(1+M48) -> 0.0014346968 | O48: =(K48*M48)+15 -> 15 | P48: =(K48*N48)+M68 -> 0.0215 | Q48: 732.02 | R48: =(G48*N48)*(1+J48) -> 0 | T48: 0.06 | X48: =Q48-R48-S48-W48 -> 732.02 | Z48: =IF(Y48="Sim",(X48)*0.1,"") | AA48: =IF(Y48="Sim",X48-Z48,X48) -> 732.02 | AB48: Sim | AC48: =IF(AB48="Sim",AA48*0.2,"") -> 146.404 | AD48: =IF(AB48="Sim",AA48-AC48,AA48) -> 585.616 | AF48: OK | AG48: FALSE
A49: 45986 | B49: 45986 | C49: =TEXT(B49,"mmm") -> nov. | E49: Ana Paula Ferreira | I49: 0.0014045 | J49: 0.035 | K49: =R49*(1-J49) -> 542.70635 | L49: =R49-K49 -> 19.68365 | M49: 0.0215 | N49: =I49*(1+M49) -> 0.0014346968 | O49: =(K49*M49)+15 -> 26.668187 | P49: =(K49*N49)+M69 -> 0.80011904 | Q49: 987.19 | R49: 562.39 | T49: 0.06 | X49: =Q49-R49-S49-W49 -> 424.8 | Z49: =IF(Y49="Sim",(X49)*0.1,"") | AA49: =IF(Y49="Sim",X49-Z49,X49) -> 424.8 | AB49: Sim | AC49: =IF(AB49="Sim",AA49*0.2,"") -> 84.96 | AD49: =IF(AB49="Sim",AA49-AC49,AA49) -> 339.84 | AF49: OK | AG49: FALSE
